Workbook

Sheet Method
A1: Limerick Residential Pipeline – Method and Assumptions
A3: Assumptions (edit the yellow cells)
A4: Report date | B4: 46294 | C4: Date the register was queried. Used for staleness and expiry tests.
A5: Stale threshold (months) | B5: 24 | C5: A counted Permission Granted / Commencement Expected application with no CIS update for longer than this is reported as Constrained / uncertain until checked.
A6: Overlap search radius (m) | B6: 150 | C6: Used at build time to flag upstream records near another record. Changing it does not re-run the search.
A7: Location mismatch threshold (m) | B7: 500 | C7: Register point more than this far from the CIS point is flagged as a possible reference mismatch.
A10: Sources
A11: CIS granted/delivery export | B11: Granted/delivery records and their site grouping from the Existing Site Pipeline tab of Limerick_Residential_Pipeline_Full_Build.xlsx (226 records in 153 sites).
A12: CIS upstream export | B12: Export 20260923095518.xls as de-duplicated in the source workbook (55 records; 3 non-residential frameworks excluded).
A13: Planning register | B13: National Planning Applications dataset (Department of Housing, Local Government and Heritage), ArcGIS feature service IrishPlanningApplications, Limerick County Council records (12,835, received 2017 onwards). Queried 29/09/2026.
A14: An Coimisiún Pleanála | B14: SHD case pages at pleanala.ie/en-ie/case/<number>, read 29/09/2026 for the 6 records with ABP references.
A16: Counting (primacy)
A17: Counting unit | B17: The application. Each application gets a Relationship; only Primary, Additional phase, Additional application on site, Replaces earlier and Extension of duration (parent not in CIS) count. Sites group applications for review; site totals are sums of counted applications.
A18: Extension of duration | B18: Register EoD applications, or descriptions starting "extension of permission/duration", link to the parent file number in the description (or to the most similar earlier application on the site). Units stay on the parent; the parent expiry is extended.
A19: Replaces earlier | B19: A later application that (a) modifies a quoted earlier permission and restates at least half its units, (b) is consequent on a quoted outline permission, or (c) repeats an earlier live application nearby (description text match >= 85% with units within 25%, or units within 10% with text match >= 50%). The earlier application becomes Superseded.
A20: Amendment within parent | B20: Modifies a quoted earlier permission but covers less than half its units. Its units are treated as already counted in the parent.
A21: Additional phase | B21: Quotes an earlier permission without modification wording (e.g. phase 2, connecting to services of), or modifies a completed scheme or one with no unit count. Counted.
A22: Additional application on site | B22: Other live applications exist on the same site or within 100m, but no link could be found in the descriptions. Counted by default and marked Low confidence – these are the main remaining double-count risk and are in the Review Queue.
A23: Not live | B23: Refused, refused on appeal, withdrawn or invalid in the register. Not counted.
A24: Analyst override | B24: Set Analyst Relationship on the Applications tab to override the automatic relationship. Final Relationship and all totals update.
A26: Reporting tier and units
A27: Reporting Tier | B27: Per counted application. Analyst Status overrides. Otherwise Complete = Delivered; Permission Granted or Commencement Expected that is past expiry or stale = Constrained / uncertain; else the CIS tier.
A28: Units | B28: CIS units. Remaining = units less stated completions (completions recorded on the site are assigned to its largest Part Complete application). Delivered = units on Complete applications plus stated completions.
A29: Student accommodation | B29: Student units and bedspaces reported separately and never added to general dwellings.
A30: Expiry | B30: Register expiry date, replaced by a granted Extension of Duration expiry where one quotes the parent file number; ABP expiry = date signed + 5 (or 10) years; CIS decision date + 5 years as fallback.
A32: Bedroom mix
A33: Priority | B33: CIS / KPMG bedroom mix where present. Otherwise the register development description is parsed for "N no. X-bed ..." patterns.
A34: Acceptance rule | B34: A parsed mix is used only when the bedrooms found add up exactly to the stated unit total (description header, CIS units or register units). Partial parses are shown in Mix Note but not used.
A35: Coverage | B35: Mix Coverage on the Summary is the share of counted units with a known bedroom split. Descriptions that only say "N houses" carry no bedroom data; those need the planning drawings or schedule of accommodation.
A37: Limitations
A38: Part 8 and pre-2017 | B38: Part 8 references and applications before 2017 are not in the national dataset and stay unverified.
A39: Register unit counts | B39: NumResidentialUnits is blank or zero on many register records.
A40: Automatic relationships | B40: Rules read the text of descriptions. They cannot see drawings, so phase boundaries and repeat applications on different parts of a large landholding can be misread. Check Low and Medium confidence rows.
A41: Legal position | B41: Screening only. It does not confirm the legal status of any permission.
A42: Social housing report | B42: Social Housing Construction Projects Status Report Q1 2026 (Department of Housing, Limerick pages). The report has no planning references or coordinates; only schemes matched with confidence on name, address and units (and consistent dates) are shown in the Social Housing columns. Unmatched and uncertain rows are omitted.
A43: Contacts | B43: CIS project team names and emails are not carried into this file.

Sheet Summary
A1: Limerick Residential Pipeline – Summary
A2: ="Report date "&TEXT(Method!$B$4,"dd/mm/yyyy")&". Counted applications only (see Relationship). Delivered and Excluded kept out of pipeline totals." -> Report date 29/09/2026. Counted applications only (see Relationship). Delivered and Excluded kept out of pipeline totals.
A4: Headline pipeline
A5: Pipeline general dwellings (units remaining) | B5: =SUM(Applications!$AL$2:$AL$293) -> 8902
A6: Pipeline student units | B6: =SUM(Applications!$AM$2:$AM$293) -> 743
A7: Pipeline student bedspaces | B7: =SUM(Applications!$AN$2:$AN$293) -> 2142
A8: Of which firm (Committed, Committed Pre-Construction, Advanced Pre-Construction) | B8: =SUMIFS(Applications!$AL$2:$AL$293,Applications!$AG$2:$AG$293,"Committed")+SUMIFS(Applications!$AL$2:$AL$293,Applications!$AG$2:$AG$293,"Committed Pre-Construction")+SUMIFS(Applications!$AL$2:$AL$293,Applications!$AG$2:$AG$293,"Advanced Pre-Construction") -> 3655
A9: Delivered units (Complete applications + stated completions) | B9: =SUM(Applications!$AK$2:$AK$293) -> 1325
A10: Counted applications | B10: =COUNTIF(Applications!$Z$2:$Z$293,"Yes") -> 257
A11: Applications not counted (superseded, amendments, extensions, not live, excluded) | B11: =COUNTIF(Applications!$Z$2:$Z$293,"No") -> 35
A13: Reconciliation to the previous workbook
A14: Previous headline units (Pipeline Summary tab, application-level, all stages) | B14: 11402 | C14: Source: Pipeline Summary tab of Limerick_Residential_Pipeline_Full_Build.xlsx (sum of Units).
A15: Units on applications not counted (primacy / not live) | B15: =SUMIFS(Applications!$Q$2:$Q$293,Applications!$Z$2:$Z$293,"No",Applications!$N$2:$N$293,"Yes") -> 809
A16: Units on counted applications reported as Excluded by analyst | B16: =SUMIFS(Applications!$AI$2:$AI$293,Applications!$AG$2:$AG$293,"Excluded") -> 0
A17: New total: pipeline general + student units + delivered | B17: =B5+B6+B9 -> 10970
A18: Difference to previous headline | B18: =B17-B14 -> -432
A20: Pipeline by reporting tier
A21: Reporting Tier | B21: Applications | C21: General Dwellings | D21: Student Units | E21: Student Bedspaces | F21: Known Bedroom Mix | G21: Mix Coverage
A22: Committed | B22: =COUNTIFS(Applications!$AG$2:$AG$293,A22) -> 73 | C22: =SUMIFS(Applications!$AL$2:$AL$293,Applications!$AG$2:$AG$293,A22) -> 2879 | D22: =SUMIFS(Applications!$AM$2:$AM$293,Applications!$AG$2:$AG$293,A22) -> 26 | E22: =SUMIFS(Applications!$AN$2:$AN$293,Applications!$AG$2:$AG$293,A22) -> 202 | F22: =SUMIFS(Applications!$AV$2:$AV$293,Applications!$AG$2:$AG$293,A22,Applications!$P$2:$P$293,"General") -> 2428 | G22: =IF(SUMIFS(Applications!$AI$2:$AI$293,Applications!$AG$2:$AG$293,A22,Applications!$P$2:$P$293,"General")=0,"",MIN(1,F22/SUMIFS(Applications!$AI$2:$AI$293,Applications!$AG$2:$AG$293,A22,Applications!$P$2:$P$293,"General"))) -> 0.81531229
A23: Committed Pre-Construction | B23: =COUNTIFS(Applications!$AG$2:$AG$293,A23) -> 10 | C23: =SUMIFS(Applications!$AL$2:$AL$293,Applications!$AG$2:$AG$293,A23) -> 309 | D23: =SUMIFS(Applications!$AM$2:$AM$293,Applications!$AG$2:$AG$293,A23) -> 0 | E23: =SUMIFS(Applications!$AN$2:$AN$293,Applications!$AG$2:$AG$293,A23) -> 0 | F23: =SUMIFS(Applications!$AV$2:$AV$293,Applications!$AG$2:$AG$293,A23,Applications!$P$2:$P$293,"General") -> 225 | G23: =IF(SUMIFS(Applications!$AI$2:$AI$293,Applications!$AG$2:$AG$293,A23,Applications!$P$2:$P$293,"General")=0,"",MIN(1,F23/SUMIFS(Applications!$AI$2:$AI$293,Applications!$AG$2:$AG$293,A23,Applications!$P$2:$P$293,"General"))) -> 0.72815534
A24: Advanced Pre-Construction | B24: =COUNTIFS(Applications!$AG$2:$AG$293,A24) -> 13 | C24: =SUMIFS(Applications!$AL$2:$AL$293,Applications!$AG$2:$AG$293,A24) -> 467 | D24: =SUMIFS(Applications!$AM$2:$AM$293,Applications!$AG$2:$AG$293,A24) -> 0 | E24: =SUMIFS(Applications!$AN$2:$AN$293,Applications!$AG$2:$AG$293,A24) -> 0 | F24: =SUMIFS(Applications!$AV$2:$AV$293,Applications!$AG$2:$AG$293,A24,Applications!$P$2:$P$293,"General") -> 415 | G24: =IF(SUMIFS(Applications!$AI$2:$AI$293,Applications!$AG$2:$AG$293,A24,Applications!$P$2:$P$293,"General")=0,"",MIN(1,F24/SUMIFS(Applications!$AI$2:$AI$293,Applications!$AG$2:$AG$293,A24,Applications!$P$2:$P$293,"General"))) -> 0.88865096
A25: Likely | B25: =COUNTIFS(Applications!$AG$2:$AG$293,A25) -> 5 | C25: =SUMIFS(Applications!$AL$2:$AL$293,Applications!$AG$2:$AG$293,A25) -> 592 | D25: =SUMIFS(Applications!$AM$2:$AM$293,Applications!$AG$2:$AG$293,A25) -> 196 | E25: =SUMIFS(Applications!$AN$2:$AN$293,Applications!$AG$2:$AG$293,A25) -> 1400 | F25: =SUMIFS(Applications!$AV$2:$AV$293,Applications!$AG$2:$AG$293,A25,Applications!$P$2:$P$293,"General") -> 574 | G25: =IF(SUMIFS(Applications!$AI$2:$AI$293,Applications!$AG$2:$AG$293,A25,Applications!$P$2:$P$293,"General")=0,"",MIN(1,F25/SUMIFS(Applications!$AI$2:$AI$293,Applications!$AG$2:$AG$293,A25,Applications!$P$2:$P$293,"General"))) -> 0.96959459
A26: Potential | B26: =COUNTIFS(Applications!$AG$2:$AG$293,A26) -> 36 | C26: =SUMIFS(Applications!$AL$2:$AL$293,Applications!$AG$2:$AG$293,A26) -> 2803 | D26: =SUMIFS(Applications!$AM$2:$AM$293,Applications!$AG$2:$AG$293,A26) -> 465 | E26: =SUMIFS(Applications!$AN$2:$AN$293,Applications!$AG$2:$AG$293,A26) -> 424 | F26: =SUMIFS(Applications!$AV$2:$AV$293,Applications!$AG$2:$AG$293,A26,Applications!$P$2:$P$293,"General") -> 2669 | G26: =IF(SUMIFS(Applications!$AI$2:$AI$293,Applications!$AG$2:$AG$293,A26,Applications!$P$2:$P$293,"General")=0,"",MIN(1,F26/SUMIFS(Applications!$AI$2:$AI$293,Applications!$AG$2:$AG$293,A26,Applications!$P$2:$P$293,"General"))) -> 0.95219408
A27: Application Pipeline | B27: =COUNTIFS(Applications!$AG$2:$AG$293,A27) -> 15 | C27: =SUMIFS(Applications!$AL$2:$AL$293,Applications!$AG$2:$AG$293,A27) -> 263 | D27: =SUMIFS(Applications!$AM$2:$AM$293,Applications!$AG$2:$AG$293,A27) -> 0 | E27: =SUMIFS(Applications!$AN$2:$AN$293,Applications!$AG$2:$AG$293,A27) -> 0 | F27: =SUMIFS(Applications!$AV$2:$AV$293,Applications!$AG$2:$AG$293,A27,Applications!$P$2:$P$293,"General") -> 173 | G27: =IF(SUMIFS(Applications!$AI$2:$AI$293,Applications!$AG$2:$AG$293,A27,Applications!$P$2:$P$293,"General")=0,"",MIN(1,F27/SUMIFS(Applications!$AI$2:$AI$293,Applications!$AG$2:$AG$293,A27,Applications!$P$2:$P$293,"General"))) -> 0.65779468
A28: Constrained / uncertain | B28: =COUNTIFS(Applications!$AG$2:$AG$293,A28) -> 61 | C28: =SUMIFS(Applications!$AL$2:$AL$293,Applications!$AG$2:$AG$293,A28) -> 1589 | D28: =SUMIFS(Applications!$AM$2:$AM$293,Applications!$AG$2:$AG$293,A28) -> 56 | E28: =SUMIFS(Applications!$AN$2:$AN$293,Applications!$AG$2:$AG$293,A28) -> 116 | F28: =SUMIFS(Applications!$AV$2:$AV$293,Applications!$AG$2:$AG$293,A28,Applications!$P$2:$P$293,"General") -> 1043 | G28: =IF(SUMIFS(Applications!$AI$2:$AI$293,Applications!$AG$2:$AG$293,A28,Applications!$P$2:$P$293,"General")=0,"",MIN(1,F28/SUMIFS(Applications!$AI$2:$AI$293,Applications!$AG$2:$AG$293,A28,Applications!$P$2:$P$293,"General"))) -> 0.65638767
A29: Pipeline total | B29: =SUM(B22:B28) -> 213 | C29: =SUM(C22:C28) -> 8902 | D29: =SUM(D22:D28) -> 743 | E29: =SUM(E22:E28) -> 2142 | F29: =SUM(F22:F28) -> 7527 | G29: =IF(SUMIFS(Applications!$AI$2:$AI$293,Applications!$AG$2:$AG$293,A22,Applications!$P$2:$P$293,"General")+SUMIFS(Applications!$AI$2:$AI$293,Applications!$AG$2:$AG$293,A23,Applications!$P$2:$P$293,"General")+SUMIFS(Applications!$AI$2:$AI$293,Applications!$AG$2:$AG$293,A24,Applications!$P$2:$P$293,"General")+SUMIFS(Applications!$AI$2:$AI$293,Applications!$AG$2:$AG$293,A25,Applications!$P$2:$P$293,"General")+SUMIFS(Applications!$AI$2:$AI$293,Applications!$AG$2:$AG$293,A26,Applications!$P$2:$P$293,"General")+SUMIFS(Applications!$AI$2:$AI$293,Applications!$AG$2:$AG$293,A27,Applications!$P$2:$P$293,"General")+SUMIFS(Applications!$AI$2:$AI$293,Applications!$AG$2:$AG$293,A28,Applications!$P$2:$P$293,"General")=0,"",MIN(1,F29/(SUMIFS(Applications!$AI$2:$AI$293,Applications!$AG$2:$AG$293,A22,Applications!$P$2:$P$293,"General")+SUMIFS(Applications!$AI$2:$AI$293,Applications!$AG$2:$AG$293,A23,Applications!$P$2:$P$293,"General")+SUMIFS(Applications!$AI$2:$AI$293,Applications!$AG$2:$AG$293,A24,Applications!$P$2:$P$293,"General")+SUMIFS(Applications!$AI$2:$AI$293,Applications!$AG$2:$AG$293,A25,Applications!$P$2:$P$293,"General")+SUMIFS(Applications!$AI$2:$AI$293,Applications!$AG$2:$AG$293,A26,Applications!$P$2:$P$293,"General")+SUMIFS(Applications!$AI$2:$AI$293,Applications!$AG$2:$AG$293,A27,Applications!$P$2:$P$293,"General")+SUMIFS(Applications!$AI$2:$AI$293,Applications!$AG$2:$AG$293,A28,Applications!$P$2:$P$293,"General")))) -> 0.83624042
A30: Delivered | B30: =COUNTIFS(Applications!$AG$2:$AG$293,A30) -> 44 | C30: =SUMIFS(Applications!$AK$2:$AK$293,Applications!$AG$2:$AG$293,A30,Applications!$P$2:$P$293,"General") -> 1226
A31: Excluded | B31: =COUNTIFS(Applications!$AG$2:$AG$293,A31) -> 0 | C31: =SUMIFS(Applications!$AI$2:$AI$293,Applications!$AG$2:$AG$293,A31,Applications!$P$2:$P$293,"General") -> 0
A32: Mix coverage = counted general units with a known bedroom split, as a share of counted general units in the tier.
A34: Pipeline bedroom mix (general dwellings, counted applications with known mix)
A35: Bedrooms | B35: Units | C35: Share | D35: Of which from CIS / KPMG | E35: Of which from register description | F35: Of which from planning file documents
A36: Studio | B36: =SUMIFS(Applications!$AP$2:$AP$293,Applications!$AG$2:$AG$293,"<>Not counted",Applications!$AG$2:$AG$293,"<>Delivered",Applications!$AG$2:$AG$293,"<>Excluded",Applications!$P$2:$P$293,"General") -> 1 | C36: =IF($B$42=0,"",B36/$B$42) -> 0.00013285506 | D36: =SUMIFS(Applications!$AP$2:$AP$293,Applications!$AG$2:$AG$293,"<>Not counted",Applications!$AG$2:$AG$293,"<>Delivered",Applications!$AG$2:$AG$293,"<>Excluded",Applications!$P$2:$P$293,"General",Applications!$AO$2:$AO$293,"CIS / KPMG") -> 0 | E36: =SUMIFS(Applications!$AP$2:$AP$293,Applications!$AG$2:$AG$293,"<>Not counted",Applications!$AG$2:$AG$293,"<>Delivered",Applications!$AG$2:$AG$293,"<>Excluded",Applications!$P$2:$P$293,"General",Applications!$AO$2:$AO$293,"Register description") -> 1 | F36: =SUMIFS(Applications!$AP$2:$AP$293,Applications!$AG$2:$AG$293,"<>Not counted",Applications!$AG$2:$AG$293,"<>Delivered",Applications!$AG$2:$AG$293,"<>Excluded",Applications!$P$2:$P$293,"General",Applications!$AO$2:$AO$293,"Planning file documents") -> 0
A37: 1 Bed | B37: =SUMIFS(Applications!$AQ$2:$AQ$293,Applications!$AG$2:$AG$293,"<>Not counted",Applications!$AG$2:$AG$293,"<>Delivered",Applications!$AG$2:$AG$293,"<>Excluded",Applications!$P$2:$P$293,"General") -> 1726 | C37: =IF($B$42=0,"",B37/$B$42) -> 0.22930783 | D37: =SUMIFS(Applications!$AQ$2:$AQ$293,Applications!$AG$2:$AG$293,"<>Not counted",Applications!$AG$2:$AG$293,"<>Delivered",Applications!$AG$2:$AG$293,"<>Excluded",Applications!$P$2:$P$293,"General",Applications!$AO$2:$AO$293,"CIS / KPMG") -> 1084 | E37: =SUMIFS(Applications!$AQ$2:$AQ$293,Applications!$AG$2:$AG$293,"<>Not counted",Applications!$AG$2:$AG$293,"<>Delivered",Applications!$AG$2:$AG$293,"<>Excluded",Applications!$P$2:$P$293,"General",Applications!$AO$2:$AO$293,"Register description") -> 616 | F37: =SUMIFS(Applications!$AQ$2:$AQ$293,Applications!$AG$2:$AG$293,"<>Not counted",Applications!$AG$2:$AG$293,"<>Delivered",Applications!$AG$2:$AG$293,"<>Excluded",Applications!$P$2:$P$293,"General",Applications!$AO$2:$AO$293,"Planning file documents") -> 26
A38: 2 Bed | B38: =SUMIFS(Applications!$AR$2:$AR$293,Applications!$AG$2:$AG$293,"<>Not counted",Applications!$AG$2:$AG$293,"<>Delivered",Applications!$AG$2:$AG$293,"<>Excluded",Applications!$P$2:$P$293,"General") -> 2595 | C38: =IF($B$42=0,"",B38/$B$42) -> 0.34475887 | D38: =SUMIFS(Applications!$AR$2:$AR$293,Applications!$AG$2:$AG$293,"<>Not counted",Applications!$AG$2:$AG$293,"<>Delivered",Applications!$AG$2:$AG$293,"<>Excluded",Applications!$P$2:$P$293,"General",Applications!$AO$2:$AO$293,"CIS / KPMG") -> 1667 | E38: =SUMIFS(Applications!$AR$2:$AR$293,Applications!$AG$2:$AG$293,"<>Not counted",Applications!$AG$2:$AG$293,"<>Delivered",Applications!$AG$2:$AG$293,"<>Excluded",Applications!$P$2:$P$293,"General",Applications!$AO$2:$AO$293,"Register description") -> 823 | F38: =SUMIFS(Applications!$AR$2:$AR$293,Applications!$AG$2:$AG$293,"<>Not counted",Applications!$AG$2:$AG$293,"<>Delivered",Applications!$AG$2:$AG$293,"<>Excluded",Applications!$P$2:$P$293,"General",Applications!$AO$2:$AO$293,"Planning file documents") -> 105
A39: 3 Bed | B39: =SUMIFS(Applications!$AS$2:$AS$293,Applications!$AG$2:$AG$293,"<>Not counted",Applications!$AG$2:$AG$293,"<>Delivered",Applications!$AG$2:$AG$293,"<>Excluded",Applications!$P$2:$P$293,"General") -> 2502 | C39: =IF($B$42=0,"",B39/$B$42) -> 0.33240335 | D39: =SUMIFS(Applications!$AS$2:$AS$293,Applications!$AG$2:$AG$293,"<>Not counted",Applications!$AG$2:$AG$293,"<>Delivered",Applications!$AG$2:$AG$293,"<>Excluded",Applications!$P$2:$P$293,"General",Applications!$AO$2:$AO$293,"CIS / KPMG") -> 1298 | E39: =SUMIFS(Applications!$AS$2:$AS$293,Applications!$AG$2:$AG$293,"<>Not counted",Applications!$AG$2:$AG$293,"<>Delivered",Applications!$AG$2:$AG$293,"<>Excluded",Applications!$P$2:$P$293,"General",Applications!$AO$2:$AO$293,"Register description") -> 893 | F39: =SUMIFS(Applications!$AS$2:$AS$293,Applications!$AG$2:$AG$293,"<>Not counted",Applications!$AG$2:$AG$293,"<>Delivered",Applications!$AG$2:$AG$293,"<>Excluded",Applications!$P$2:$P$293,"General",Applications!$AO$2:$AO$293,"Planning file documents") -> 311
A40: 4 Bed | B40: =SUMIFS(Applications!$AT$2:$AT$293,Applications!$AG$2:$AG$293,"<>Not counted",Applications!$AG$2:$AG$293,"<>Delivered",Applications!$AG$2:$AG$293,"<>Excluded",Applications!$P$2:$P$293,"General") -> 664 | C40: =IF($B$42=0,"",B40/$B$42) -> 0.088215757 | D40: =SUMIFS(Applications!$AT$2:$AT$293,Applications!$AG$2:$AG$293,"<>Not counted",Applications!$AG$2:$AG$293,"<>Delivered",Applications!$AG$2:$AG$293,"<>Excluded",Applications!$P$2:$P$293,"General",Applications!$AO$2:$AO$293,"CIS / KPMG") -> 371 | E40: =SUMIFS(Applications!$AT$2:$AT$293,Applications!$AG$2:$AG$293,"<>Not counted",Applications!$AG$2:$AG$293,"<>Delivered",Applications!$AG$2:$AG$293,"<>Excluded",Applications!$P$2:$P$293,"General",Applications!$AO$2:$AO$293,"Register description") -> 261 | F40: =SUMIFS(Applications!$AT$2:$AT$293,Applications!$AG$2:$AG$293,"<>Not counted",Applications!$AG$2:$AG$293,"<>Delivered",Applications!$AG$2:$AG$293,"<>Excluded",Applications!$P$2:$P$293,"General",Applications!$AO$2:$AO$293,"Planning file documents") -> 32
A41: 5+ Bed | B41: =SUMIFS(Applications!$AU$2:$AU$293,Applications!$AG$2:$AG$293,"<>Not counted",Applications!$AG$2:$AG$293,"<>Delivered",Applications!$AG$2:$AG$293,"<>Excluded",Applications!$P$2:$P$293,"General") -> 39 | C41: =IF($B$42=0,"",B41/$B$42) -> 0.0051813472 | D41: =SUMIFS(Applications!$AU$2:$AU$293,Applications!$AG$2:$AG$293,"<>Not counted",Applications!$AG$2:$AG$293,"<>Delivered",Applications!$AG$2:$AG$293,"<>Excluded",Applications!$P$2:$P$293,"General",Applications!$AO$2:$AO$293,"CIS / KPMG") -> 33 | E41: =SUMIFS(Applications!$AU$2:$AU$293,Applications!$AG$2:$AG$293,"<>Not counted",Applications!$AG$2:$AG$293,"<>Delivered",Applications!$AG$2:$AG$293,"<>Excluded",Applications!$P$2:$P$293,"General",Applications!$AO$2:$AO$293,"Register description") -> 6 | F41: =SUMIFS(Applications!$AU$2:$AU$293,Applications!$AG$2:$AG$293,"<>Not counted",Applications!$AG$2:$AG$293,"<>Delivered",Applications!$AG$2:$AG$293,"<>Excluded",Applications!$P$2:$P$293,"General",Applications!$AO$2:$AO$293,"Planning file documents") -> 0
A42: Total with known mix | B42: =SUM(B36:B41) -> 7527 | D42: =SUM(D36:D41) -> 4453 | E42: =SUM(E36:E41) -> 2600 | F42: =SUM(F36:F41) -> 474
A43: Counted general units in pipeline (all, incl. unknown mix) | B43: =SUMIFS(Applications!$AI$2:$AI$293,Applications!$AG$2:$AG$293,"<>Not counted",Applications!$AG$2:$AG$293,"<>Delivered",Applications!$AG$2:$AG$293,"<>Excluded",Applications!$P$2:$P$293,"General") -> 9001
A44: Mix coverage | B44: =IF(B43=0,"",B42/B43) -> 0.83624042
A45: Shares describe permitted units on applications with a known mix, not the whole pipeline. Treat as indicative where coverage is low.
A47: Application relationships (primacy)
A48: Final Relationship | B48: Applications | C48: Units (CIS) | D48: Counted? | E48: Unreviewed Low / Medium confidence
A49: Primary | B49: =COUNTIF(Applications!$Y$2:$Y$293,A49) -> 170 | C49: =SUMIFS(Applications!$Q$2:$Q$293,Applications!$Y$2:$Y$293,A49) -> 7676 | D49: Yes | E49: =COUNTIFS(Applications!$Y$2:$Y$293,A49,Applications!$W$2:$W$293,"Low",Applications!$X$2:$X$293,"")+COUNTIFS(Applications!$Y$2:$Y$293,A49,Applications!$W$2:$W$293,"Medium",Applications!$X$2:$X$293,"") -> 0
A50: Additional phase | B50: =COUNTIF(Applications!$Y$2:$Y$293,A50) -> 6 | C50: =SUMIFS(Applications!$Q$2:$Q$293,Applications!$Y$2:$Y$293,A50) -> 280 | D50: Yes | E50: =COUNTIFS(Applications!$Y$2:$Y$293,A50,Applications!$W$2:$W$293,"Low",Applications!$X$2:$X$293,"")+COUNTIFS(Applications!$Y$2:$Y$293,A50,Applications!$W$2:$W$293,"Medium",Applications!$X$2:$X$293,"") -> 6
A51: Additional application on site | B51: =COUNTIF(Applications!$Y$2:$Y$293,A51) -> 70 | C51: =SUMIFS(Applications!$Q$2:$Q$293,Applications!$Y$2:$Y$293,A51) -> 2734 | D51: Yes | E51: =COUNTIFS(Applications!$Y$2:$Y$293,A51,Applications!$W$2:$W$293,"Low",Applications!$X$2:$X$293,"")+COUNTIFS(Applications!$Y$2:$Y$293,A51,Applications!$W$2:$W$293,"Medium",Applications!$X$2:$X$293,"") -> 70
A52: Replaces earlier | B52: =COUNTIF(Applications!$Y$2:$Y$293,A52) -> 3 | C52: =SUMIFS(Applications!$Q$2:$Q$293,Applications!$Y$2:$Y$293,A52) -> 89 | D52: Yes | E52: =COUNTIFS(Applications!$Y$2:$Y$293,A52,Applications!$W$2:$W$293,"Low",Applications!$X$2:$X$293,"")+COUNTIFS(Applications!$Y$2:$Y$293,A52,Applications!$W$2:$W$293,"Medium",Applications!$X$2:$X$293,"") -> 3
A53: Extension of duration (parent not in CIS) | B53: =COUNTIF(Applications!$Y$2:$Y$293,A53) -> 8 | C53: =SUMIFS(Applications!$Q$2:$Q$293,Applications!$Y$2:$Y$293,A53) -> 191 | D53: Yes | E53: =COUNTIFS(Applications!$Y$2:$Y$293,A53,Applications!$W$2:$W$293,"Low",Applications!$X$2:$X$293,"")+COUNTIFS(Applications!$Y$2:$Y$293,A53,Applications!$W$2:$W$293,"Medium",Applications!$X$2:$X$293,"") -> 8
A54: Superseded | B54: =COUNTIF(Applications!$Y$2:$Y$293,A54) -> 3 | C54: =SUMIFS(Applications!$Q$2:$Q$293,Applications!$Y$2:$Y$293,A54) -> 90 | D54: No | E54: =COUNTIFS(Applications!$Y$2:$Y$293,A54,Applications!$W$2:$W$293,"Low",Applications!$X$2:$X$293,"")+COUNTIFS(Applications!$Y$2:$Y$293,A54,Applications!$W$2:$W$293,"Medium",Applications!$X$2:$X$293,"") -> 2
A55: Amendment within parent | B55: =COUNTIF(Applications!$Y$2:$Y$293,A55) -> 3 | C55: =SUMIFS(Applications!$Q$2:$Q$293,Applications!$Y$2:$Y$293,A55) -> 73 | D55: No | E55: =COUNTIFS(Applications!$Y$2:$Y$293,A55,Applications!$W$2:$W$293,"Low",Applications!$X$2:$X$293,"")+COUNTIFS(Applications!$Y$2:$Y$293,A55,Applications!$W$2:$W$293,"Medium",Applications!$X$2:$X$293,"") -> 3
A56: Extension of duration | B56: =COUNTIF(Applications!$Y$2:$Y$293,A56) -> 6 | C56: =SUMIFS(Applications!$Q$2:$Q$293,Applications!$Y$2:$Y$293,A56) -> 16 | D56: No | E56: =COUNTIFS(Applications!$Y$2:$Y$293,A56,Applications!$W$2:$W$293,"Low",Applications!$X$2:$X$293,"")+COUNTIFS(Applications!$Y$2:$Y$293,A56,Applications!$W$2:$W$293,"Medium",Applications!$X$2:$X$293,"") -> 1
A57: Not live | B57: =COUNTIF(Applications!$Y$2:$Y$293,A57) -> 14 | C57: =SUMIFS(Applications!$Q$2:$Q$293,Applications!$Y$2:$Y$293,A57) -> 518 | D57: No | E57: =COUNTIFS(Applications!$Y$2:$Y$293,A57,Applications!$W$2:$W$293,"Low",Applications!$X$2:$X$293,"")+COUNTIFS(Applications!$Y$2:$Y$293,A57,Applications!$W$2:$W$293,"Medium",Applications!$X$2:$X$293,"") -> 0
A58: Duplicate | B58: =COUNTIF(Applications!$Y$2:$Y$293,A58) -> 6 | C58: =SUMIFS(Applications!$Q$2:$Q$293,Applications!$Y$2:$Y$293,A58) -> 112 | D58: No | E58: =COUNTIFS(Applications!$Y$2:$Y$293,A58,Applications!$W$2:$W$293,"Low",Applications!$X$2:$X$293,"")+COUNTIFS(Applications!$Y$2:$Y$293,A58,Applications!$W$2:$W$293,"Medium",Applications!$X$2:$X$293,"") -> 0
A59: Excluded | B59: =COUNTIF(Applications!$Y$2:$Y$293,A59) -> 3 | C59: =SUMIFS(Applications!$Q$2:$Q$293,Applications!$Y$2:$Y$293,A59) -> 0 | D59: No | E59: =COUNTIFS(Applications!$Y$2:$Y$293,A59,Applications!$W$2:$W$293,"Low",Applications!$X$2:$X$293,"")+COUNTIFS(Applications!$Y$2:$Y$293,A59,Applications!$W$2:$W$293,"Medium",Applications!$X$2:$X$293,"") -> 0
A61: Pipeline by settlement (general dwellings)
A62: Settlement | B62: Applications | C62: Firm | D62: Likely + Potential | E62: Application Pipeline | F62: Constrained / uncertain | G62: Total
A63: Abbeyfeale | B63: =COUNTIFS(Applications!$F$2:$F$293,A63,Applications!$AL$2:$AL$293,">0") -> 4 | C63: =SUMIFS(Applications!$AL$2:$AL$293,Applications!$F$2:$F$293,$A63,Applications!$AG$2:$AG$293,"Committed")+SUMIFS(Applications!$AL$2:$AL$293,Applications!$F$2:$F$293,$A63,Applications!$AG$2:$AG$293,"Committed Pre-Construction")+SUMIFS(Applications!$AL$2:$AL$293,Applications!$F$2:$F$293,$A63,Applications!$AG$2:$AG$293,"Advanced Pre-Construction") -> 80 | D63: =SUMIFS(Applications!$AL$2:$AL$293,Applications!$F$2:$F$293,$A63,Applications!$AG$2:$AG$293,"Likely")+SUMIFS(Applications!$AL$2:$AL$293,Applications!$F$2:$F$293,$A63,Applications!$AG$2:$AG$293,"Potential") -> 0 | E63: =SUMIFS(Applications!$AL$2:$AL$293,Applications!$F$2:$F$293,$A63,Applications!$AG$2:$AG$293,"Application Pipeline") -> 48 | F63: =SUMIFS(Applications!$AL$2:$AL$293,Applications!$F$2:$F$293,$A63,Applications!$AG$2:$AG$293,"Constrained / uncertain") -> 7 | G63: =SUM(C63:F63) -> 135
A64: Adare | B64: =COUNTIFS(Applications!$F$2:$F$293,A64,Applications!$AL$2:$AL$293,">0") -> 3 | C64: =SUMIFS(Applications!$AL$2:$AL$293,Applications!$F$2:$F$293,$A64,Applications!$AG$2:$AG$293,"Committed")+SUMIFS(Applications!$AL$2:$AL$293,Applications!$F$2:$F$293,$A64,Applications!$AG$2:$AG$293,"Committed Pre-Construction")+SUMIFS(Applications!$AL$2:$AL$293,Applications!$F$2:$F$293,$A64,Applications!$AG$2:$AG$293,"Advanced Pre-Construction") -> 11 | D64: =SUMIFS(Applications!$AL$2:$AL$293,Applications!$F$2:$F$293,$A64,Applications!$AG$2:$AG$293,"Likely")+SUMIFS(Applications!$AL$2:$AL$293,Applications!$F$2:$F$293,$A64,Applications!$AG$2:$AG$293,"Potential") -> 28 | E64: =SUMIFS(Applications!$AL$2:$AL$293,Applications!$F$2:$F$293,$A64,Applications!$AG$2:$AG$293,"Application Pipeline") -> 0 | F64: =SUMIFS(Applications!$AL$2:$AL$293,Applications!$F$2:$F$293,$A64,Applications!$AG$2:$AG$293,"Constrained / uncertain") -> 0 | G64: =SUM(C64:F64) -> 39
A65: Annacotty | B65: =COUNTIFS(Applications!$F$2:$F$293,A65,Applications!$AL$2:$AL$293,">0") -> 3 | C65: =SUMIFS(Applications!$AL$2:$AL$293,Applications!$F$2:$F$293,$A65,Applications!$AG$2:$AG$293,"Committed")+SUMIFS(Applications!$AL$2:$AL$293,Applications!$F$2:$F$293,$A65,Applications!$AG$2:$AG$293,"Committed Pre-Construction")+SUMIFS(Applications!$AL$2:$AL$293,Applications!$F$2:$F$293,$A65,Applications!$AG$2:$AG$293,"Advanced Pre-Construction") -> 6 | D65: =SUMIFS(Applications!$AL$2:$AL$293,Applications!$F$2:$F$293,$A65,Applications!$AG$2:$AG$293,"Likely")+SUMIFS(Applications!$AL$2:$AL$293,Applications!$F$2:$F$293,$A65,Applications!$AG$2:$AG$293,"Potential") -> 76 | E65: =SUMIFS(Applications!$AL$2:$AL$293,Applications!$F$2:$F$293,$A65,Applications!$AG$2:$AG$293,"Application Pipeline") -> 0 | F65: =SUMIFS(Applications!$AL$2:$AL$293,Applications!$F$2:$F$293,$A65,Applications!$AG$2:$AG$293,"Constrained / uncertain") -> 137 | G65: =SUM(C65:F65) -> 219
A66: Bruff | B66: =COUNTIFS(Applications!$F$2:$F$293,A66,Applications!$AL$2:$AL$293,">0") -> 3 | C66: =SUMIFS(Applications!$AL$2:$AL$293,Applications!$F$2:$F$293,$A66,Applications!$AG$2:$AG$293,"Committed")+SUMIFS(Applications!$AL$2:$AL$293,Applications!$F$2:$F$293,$A66,Applications!$AG$2:$AG$293,"Committed Pre-Construction")+SUMIFS(Applications!$AL$2:$AL$293,Applications!$F$2:$F$293,$A66,Applications!$AG$2:$AG$293,"Advanced Pre-Construction") -> 18 | D66: =SUMIFS(Applications!$AL$2:$AL$293,Applications!$F$2:$F$293,$A66,Applications!$AG$2:$AG$293,"Likely")+SUMIFS(Applications!$AL$2:$AL$293,Applications!$F$2:$F$293,$A66,Applications!$AG$2:$AG$293,"Potential") -> 8 | E66: =SUMIFS(Applications!$AL$2:$AL$293,Applications!$F$2:$F$293,$A66,Applications!$AG$2:$AG$293,"Application Pipeline") -> 0 | F66: =SUMIFS(Applications!$AL$2:$AL$293,Applications!$F$2:$F$293,$A66,Applications!$AG$2:$AG$293,"Constrained / uncertain") -> 74 | G66: =SUM(C66:F66) -> 100
A67: Caherconlish | B67: =COUNTIFS(Applications!$F$2:$F$293,A67,Applications!$AL$2:$AL$293,">0") -> 0 | C67: =SUMIFS(Applications!$AL$2:$AL$293,Applications!$F$2:$F$293,$A67,Applications!$AG$2:$AG$293,"Committed")+SUMIFS(Applications!$AL$2:$AL$293,Applications!$F$2:$F$293,$A67,Applications!$AG$2:$AG$293,"Committed Pre-Construction")+SUMIFS(Applications!$AL$2:$AL$293,Applications!$F$2:$F$293,$A67,Applications!$AG$2:$AG$293,"Advanced Pre-Construction") -> 0 | D67: =SUMIFS(Applications!$AL$2:$AL$293,Applications!$F$2:$F$293,$A67,Applications!$AG$2:$AG$293,"Likely")+SUMIFS(Applications!$AL$2:$AL$293,Applications!$F$2:$F$293,$A67,Applications!$AG$2:$AG$293,"Potential") -> 0 | E67: =SUMIFS(Applications!$AL$2:$AL$293,Applications!$F$2:$F$293,$A67,Applications!$AG$2:$AG$293,"Application Pipeline") -> 0 | F67: =SUMIFS(Applications!$AL$2:$AL$293,Applications!$F$2:$F$293,$A67,Applications!$AG$2:$AG$293,"Constrained / uncertain") -> 0 | G67: =SUM(C67:F67) -> 0
A68: Cappamore | B68: =COUNTIFS(Applications!$F$2:$F$293,A68,Applications!$AL$2:$AL$293,">0") -> 3 | C68: =SUMIFS(Applications!$AL$2:$AL$293,Applications!$F$2:$F$293,$A68,Applications!$AG$2:$AG$293,"Committed")+SUMIFS(Applications!$AL$2:$AL$293,Applications!$F$2:$F$293,$A68,Applications!$AG$2:$AG$293,"Committed Pre-Construction")+SUMIFS(Applications!$AL$2:$AL$293,Applications!$F$2:$F$293,$A68,Applications!$AG$2:$AG$293,"Advanced Pre-Construction") -> 32 | D68: =SUMIFS(Applications!$AL$2:$AL$293,Applications!$F$2:$F$293,$A68,Applications!$AG$2:$AG$293,"Likely")+SUMIFS(Applications!$AL$2:$AL$293,Applications!$F$2:$F$293,$A68,Applications!$AG$2:$AG$293,"Potential") -> 7 | E68: =SUMIFS(Applications!$AL$2:$AL$293,Applications!$F$2:$F$293,$A68,Applications!$AG$2:$AG$293,"Application Pipeline") -> 0 | F68: =SUMIFS(Applications!$AL$2:$AL$293,Applications!$F$2:$F$293,$A68,Applications!$AG$2:$AG$293,"Constrained / uncertain") -> 0 | G68: =SUM(C68:F68) -> 39
A69: Castleconnell | B69: =COUNTIFS(Applications!$F$2:$F$293,A69,Applications!$AL$2:$AL$293,">0") -> 4 | C69: =SUMIFS(Applications!$AL$2:$AL$293,Applications!$F$2:$F$293,$A69,Applications!$AG$2:$AG$293,"Committed")+SUMIFS(Applications!$AL$2:$AL$293,Applications!$F$2:$F$293,$A69,Applications!$AG$2:$AG$293,"Committed Pre-Construction")+SUMIFS(Applications!$AL$2:$AL$293,Applications!$F$2:$F$293,$A69,Applications!$AG$2:$AG$293,"Advanced Pre-Construction") -> 129 | D69: =SUMIFS(Applications!$AL$2:$AL$293,Applications!$F$2:$F$293,$A69,Applications!$AG$2:$AG$293,"Likely")+SUMIFS(Applications!$AL$2:$AL$293,Applications!$F$2:$F$293,$A69,Applications!$AG$2:$AG$293,"Potential") -> 14 | E69: =SUMIFS(Applications!$AL$2:$AL$293,Applications!$F$2:$F$293,$A69,Applications!$AG$2:$AG$293,"Application Pipeline") -> 0 | F69: =SUMIFS(Applications!$AL$2:$AL$293,Applications!$F$2:$F$293,$A69,Applications!$AG$2:$AG$293,"Constrained / uncertain") -> 0 | G69: =SUM(C69:F69) -> 143
A70: Kilmallock | B70: =COUNTIFS(Applications!$F$2:$F$293,A70,Applications!$AL$2:$AL$293,">0") -> 6 | C70: =SUMIFS(Applications!$AL$2:$AL$293,Applications!$F$2:$F$293,$A70,Applications!$AG$2:$AG$293,"Committed")+SUMIFS(Applications!$AL$2:$AL$293,Applications!$F$2:$F$293,$A70,Applications!$AG$2:$AG$293,"Committed Pre-Construction")+SUMIFS(Applications!$AL$2:$AL$293,Applications!$F$2:$F$293,$A70,Applications!$AG$2:$AG$293,"Advanced Pre-Construction") -> 92 | D70: =SUMIFS(Applications!$AL$2:$AL$293,Applications!$F$2:$F$293,$A70,Applications!$AG$2:$AG$293,"Likely")+SUMIFS(Applications!$AL$2:$AL$293,Applications!$F$2:$F$293,$A70,Applications!$AG$2:$AG$293,"Potential") -> 0 | E70: =SUMIFS(Applications!$AL$2:$AL$293,Applications!$F$2:$F$293,$A70,Applications!$AG$2:$AG$293,"Application Pipeline") -> 12 | F70: =SUMIFS(Applications!$AL$2:$AL$293,Applications!$F$2:$F$293,$A70,Applications!$AG$2:$AG$293,"Constrained / uncertain") -> 4 | G70: =SUM(C70:F70) -> 108
A71: Limerick City and Suburbs | B71: =COUNTIFS(Applications!$F$2:$F$293,A71,Applications!$AL$2:$AL$293,">0") -> 57 | C71: =SUMIFS(Applications!$AL$2:$AL$293,Applications!$F$2:$F$293,$A71,Applications!$AG$2:$AG$293,"Committed")+SUMIFS(Applications!$AL$2:$AL$293,Applications!$F$2:$F$293,$A71,Applications!$AG$2:$AG$293,"Committed Pre-Construction")+SUMIFS(Applications!$AL$2:$AL$293,Applications!$F$2:$F$293,$A71,Applications!$AG$2:$AG$293,"Advanced Pre-Construction") -> 1127 | D71: =SUMIFS(Applications!$AL$2:$AL$293,Applications!$F$2:$F$293,$A71,Applications!$AG$2:$AG$293,"Likely")+SUMIFS(Applications!$AL$2:$AL$293,Applications!$F$2:$F$293,$A71,Applications!$AG$2:$AG$293,"Potential") -> 1584 | E71: =SUMIFS(Applications!$AL$2:$AL$293,Applications!$F$2:$F$293,$A71,Applications!$AG$2:$AG$293,"Application Pipeline") -> 161 | F71: =SUMIFS(Applications!$AL$2:$AL$293,Applications!$F$2:$F$293,$A71,Applications!$AG$2:$AG$293,"Constrained / uncertain") -> 242 | G71: =SUM(C71:F71) -> 3114
A72: Mungret | B72: =COUNTIFS(Applications!$F$2:$F$293,A72,Applications!$AL$2:$AL$293,">0") -> 11 | C72: =SUMIFS(Applications!$AL$2:$AL$293,Applications!$F$2:$F$293,$A72,Applications!$AG$2:$AG$293,"Committed")+SUMIFS(Applications!$AL$2:$AL$293,Applications!$F$2:$F$293,$A72,Applications!$AG$2:$AG$293,"Committed Pre-Construction")+SUMIFS(Applications!$AL$2:$AL$293,Applications!$F$2:$F$293,$A72,Applications!$AG$2:$AG$293,"Advanced Pre-Construction") -> 581 | D72: =SUMIFS(Applications!$AL$2:$AL$293,Applications!$F$2:$F$293,$A72,Applications!$AG$2:$AG$293,"Likely")+SUMIFS(Applications!$AL$2:$AL$293,Applications!$F$2:$F$293,$A72,Applications!$AG$2:$AG$293,"Potential") -> 490 | E72: =SUMIFS(Applications!$AL$2:$AL$293,Applications!$F$2:$F$293,$A72,Applications!$AG$2:$AG$293,"Application Pipeline") -> 0 | F72: =SUMIFS(Applications!$AL$2:$AL$293,Applications!$F$2:$F$293,$A72,Applications!$AG$2:$AG$293,"Constrained / uncertain") -> 117 | G72: =SUM(C72:F72) -> 1188
A73: Newcastle West | B73: =COUNTIFS(Applications!$F$2:$F$293,A73,Applications!$AL$2:$AL$293,">0") -> 8 | C73: =SUMIFS(Applications!$AL$2:$AL$293,Applications!$F$2:$F$293,$A73,Applications!$AG$2:$AG$293,"Committed")+SUMIFS(Applications!$AL$2:$AL$293,Applications!$F$2:$F$293,$A73,Applications!$AG$2:$AG$293,"Committed Pre-Construction")+SUMIFS(Applications!$AL$2:$AL$293,Applications!$F$2:$F$293,$A73,Applications!$AG$2:$AG$293,"Advanced Pre-Construction") -> 108 | D73: =SUMIFS(Applications!$AL$2:$AL$293,Applications!$F$2:$F$293,$A73,Applications!$AG$2:$AG$293,"Likely")+SUMIFS(Applications!$AL$2:$AL$293,Applications!$F$2:$F$293,$A73,Applications!$AG$2:$AG$293,"Potential") -> 0 | E73: =SUMIFS(Applications!$AL$2:$AL$293,Applications!$F$2:$F$293,$A73,Applications!$AG$2:$AG$293,"Application Pipeline") -> 30 | F73: =SUMIFS(Applications!$AL$2:$AL$293,Applications!$F$2:$F$293,$A73,Applications!$AG$2:$AG$293,"Constrained / uncertain") -> 159 | G73: =SUM(C73:F73) -> 297
A74: Patrickswell | B74: =COUNTIFS(Applications!$F$2:$F$293,A74,Applications!$AL$2:$AL$293,">0") -> 14 | C74: =SUMIFS(Applications!$AL$2:$AL$293,Applications!$F$2:$F$293,$A74,Applications!$AG$2:$AG$293,"Committed")+SUMIFS(Applications!$AL$2:$AL$293,Applications!$F$2:$F$293,$A74,Applications!$AG$2:$AG$293,"Committed Pre-Construction")+SUMIFS(Applications!$AL$2:$AL$293,Applications!$F$2:$F$293,$A74,Applications!$AG$2:$AG$293,"Advanced Pre-Construction") -> 266 | D74: =SUMIFS(Applications!$AL$2:$AL$293,Applications!$F$2:$F$293,$A74,Applications!$AG$2:$AG$293,"Likely")+SUMIFS(Applications!$AL$2:$AL$293,Applications!$F$2:$F$293,$A74,Applications!$AG$2:$AG$293,"Potential") -> 69 | E74: =SUMIFS(Applications!$AL$2:$AL$293,Applications!$F$2:$F$293,$A74,Applications!$AG$2:$AG$293,"Application Pipeline") -> 0 | F74: =SUMIFS(Applications!$AL$2:$AL$293,Applications!$F$2:$F$293,$A74,Applications!$AG$2:$AG$293,"Constrained / uncertain") -> 149 | G74: =SUM(C74:F74) -> 484
... A76: Other County Limerick | B76: =COUNTIFS(Applications!$F$2:$F$293,A76,Applications!$AL$2:$AL$293,">0") -> 80 | C76: =SUMIFS(Applications!$AL$2:$AL$293,Applications!$F$2:$F$293,$A76,Applications!$AG$2:$AG$293,"Committed")+SUMIFS(Applications!$AL$2:$AL$293,Applications!$F$2:$F$293,$A76,Applications!$AG$2:$AG$293,"Committed Pre-Construction")+SUMIFS(Applications!$AL$2:$AL$293,Applications!$F$2:$F$293,$A76,Applications!$AG$2:$AG$293,"Advanced Pre-Construction") -> 1184 | D76: =SUMIFS(Applications!$AL$2:$AL$293,Applications!$F$2:$F$293,$A76,Applications!$AG$2:$AG$293,"Likely")+SUMIFS(Applications!$AL$2:$AL$293,Applications!$F$2:$F$293,$A76,Applications!$AG$2:$AG$293,"Potential") -> 992 | E76: =SUMIFS(Applications!$AL$2:$AL$293,Applications!$F$2:$F$293,$A76,Applications!$AG$2:$AG$293,"Application Pipeline") -> 12 | F76: =SUMIFS(Applications!$AL$2:$AL$293,Applications!$F$2:$F$293,$A76,Applications!$AG$2:$AG$293,"Constrained / uncertain") -> 644 | G76: =SUM(C76:F76) -> 2832
A77: Total | B77: =SUM(B63:B76) -> 202 | C77: =SUM(C63:C76) -> 3655 | D77: =SUM(D63:D76) -> 3395 | E77: =SUM(E63:E76) -> 263 | F77: =SUM(F63:F76) -> 1589 | G77: =SUM(G63:G76) -> 8902
A78: Settlement for upstream records is assigned from address text; check before using at settlement level.
A80: Register validation (applications)
A81: Check Result | B81: Applications
A82: Consistent | B82: =COUNTIF(Applications!$BR$2:$BR$293,A82) -> 211
A83: Consistent – decision date differs | B83: =COUNTIF(Applications!$BR$2:$BR$293,A83) -> 27
A84: Stage out of date – now granted | B84: =COUNTIF(Applications!$BR$2:$BR$293,A84) -> 0
A85: Check – register still pending | B85: =COUNTIF(Applications!$BR$2:$BR$293,A85) -> 2
A86: Check – location differs | B86: =COUNTIF(Applications!$BR$2:$BR$293,A86) -> 0
A87: Conflict – not live in register | B87: =COUNTIF(Applications!$BR$2:$BR$293,A87) -> 13
A88: Conflict – register not live but CIS says built | B88: =COUNTIF(Applications!$BR$2:$BR$293,A88) -> 1
A89: Unverified – not in register (Part 8 / other) | B89: =COUNTIF(Applications!$BR$2:$BR$293,A89) -> 29
A90: Unverified – no reference | B90: =COUNTIF(Applications!$BR$2:$BR$293,A90) -> 6
A91: Excluded (non-residential) | B91: =COUNTIF(Applications!$BR$2:$BR$293,A91) -> 3
A92: Total | B92: =SUM(B82:B91) -> 292
A94: Review status
A95: Sites needing review | B95: =COUNTIF(Sites!$T$2:$T$217,"Yes") -> 102
A96: Sites marked reviewed | B96: =COUNTIF(Sites!$T$2:$T$217,"Resolved") -> 0
A97: Counted units on sites needing review | B97: =SUMIFS(Sites!$K$2:$K$217,Sites!$T$2:$T$217,"Yes") -> 5609
A98: Unreviewed low-confidence counted applications | B98: =COUNTIFS(Applications!$W$2:$W$293,"Low",Applications!$Z$2:$Z$293,"Yes",Applications!$X$2:$X$293,"") -> 80

Sheet Sites
A1: Site ID | B1: Origin | C1: Site / Project Heading | D1: Address | E1: Settlement | F1: Latitude | G1: Longitude | H1: Most Advanced CIS Stage | I1: Applications | J1: Counted Applications | K1: Counted Units | L1: Pipeline General Dwellings | M1: Pipeline Student Units | N1: Delivered Units | O1: Not-Counted Applications | P1: Low-Confidence Links (unreviewed) | Q1: Stale / Expired (counted) | R1: Possible Overlap | S1: Low-Confidence Grouping | T1: Review Required | U1: Site Reviewed | V1: Site Note
A2: P-1432711 | B2: Granted/delivery export (grouped) | C2: €39m - Large Residential Development, Mungret | D2: Mungret Park Road, Caheranardrish, Mungret | E2: Mungret | F2: 52.631157 | G2: -8.6902988 | H2: Permission Granted | I2: =COUNTIF(Applications!$B$2:$B$293,A2) -> 1 | J2: =COUNTIFS(Applications!$B$2:$B$293,A2,Applications!$Z$2:$Z$293,"Yes") -> 1 | K2: =SUMIFS(Applications!$AI$2:$AI$293,Applications!$B$2:$B$293,A2) -> 182 | L2: =SUMIFS(Applications!$AL$2:$AL$293,Applications!$B$2:$B$293,A2) -> 182 | M2: =SUMIFS(Applications!$AM$2:$AM$293,Applications!$B$2:$B$293,A2) -> 0 | N2: =SUMIFS(Applications!$AK$2:$AK$293,Applications!$B$2:$B$293,A2) -> 0 | O2: =I2-J2 -> 0 | P2: =COUNTIFS(Applications!$B$2:$B$293,A2,Applications!$W$2:$W$293,"Low",Applications!$X$2:$X$293,"") -> 0 | Q2: =COUNTIFS(Applications!$B$2:$B$293,A2,Applications!$AH$2:$AH$293,"Past*")+COUNTIFS(Applications!$B$2:$B$293,A2,Applications!$AH$2:$AH$293,"No CIS*") -> 0 | S2: No | T2: =IF(OR(R2<>"",S2="Yes",P2>0,Q2>0),IF(U2="Yes","Resolved","Yes"),"No") -> No
A3: P-1446288 | B3: Granted/delivery export (grouped) | C3: €125.6m - Large Residential Development, Castletroy | D3: Lands at Monaleen Road, Castletroy | E3: Limerick City and Suburbs | F3: 52.664122 | G3: -8.5618067 | H3: Permission Granted | I3: =COUNTIF(Applications!$B$2:$B$293,A3) -> 1 | J3: =COUNTIFS(Applications!$B$2:$B$293,A3,Applications!$Z$2:$Z$293,"Yes") -> 1 | K3: =SUMIFS(Applications!$AI$2:$AI$293,Applications!$B$2:$B$293,A3) -> 523 | L3: =SUMIFS(Applications!$AL$2:$AL$293,Applications!$B$2:$B$293,A3) -> 523 | M3: =SUMIFS(Applications!$AM$2:$AM$293,Applications!$B$2:$B$293,A3) -> 0 | N3: =SUMIFS(Applications!$AK$2:$AK$293,Applications!$B$2:$B$293,A3) -> 0 | O3: =I3-J3 -> 0 | P3: =COUNTIFS(Applications!$B$2:$B$293,A3,Applications!$W$2:$W$293,"Low",Applications!$X$2:$X$293,"") -> 0 | Q3: =COUNTIFS(Applications!$B$2:$B$293,A3,Applications!$AH$2:$AH$293,"Past*")+COUNTIFS(Applications!$B$2:$B$293,A3,Applications!$AH$2:$AH$293,"No CIS*") -> 0 | S3: No | T3: =IF(OR(R3<>"",S3="Yes",P3>0,Q3>0),IF(U3="Yes","Resolved","Yes"),"No") -> No
A4: P-1350850 | B4: Granted/delivery export (grouped) | C4: €3.9m - Residential Development, Castlemahon | D4: Main Street, Castlemahon | E4: Other County Limerick | F4: 52.431087 | G4: -9.0108993 | H4: Commencement Expected | I4: =COUNTIF(Applications!$B$2:$B$293,A4) -> 1 | J4: =COUNTIFS(Applications!$B$2:$B$293,A4,Applications!$Z$2:$Z$293,"Yes") -> 1 | K4: =SUMIFS(Applications!$AI$2:$AI$293,Applications!$B$2:$B$293,A4) -> 18 | L4: =SUMIFS(Applications!$AL$2:$AL$293,Applications!$B$2:$B$293,A4) -> 18 | M4: =SUMIFS(Applications!$AM$2:$AM$293,Applications!$B$2:$B$293,A4) -> 0 | N4: =SUMIFS(Applications!$AK$2:$AK$293,Applications!$B$2:$B$293,A4) -> 0 | O4: =I4-J4 -> 0 | P4: =COUNTIFS(Applications!$B$2:$B$293,A4,Applications!$W$2:$W$293,"Low",Applications!$X$2:$X$293,"") -> 0 | Q4: =COUNTIFS(Applications!$B$2:$B$293,A4,Applications!$AH$2:$AH$293,"Past*")+COUNTIFS(Applications!$B$2:$B$293,A4,Applications!$AH$2:$AH$293,"No CIS*") -> 0 | S4: No | T4: =IF(OR(R4<>"",S4="Yes",P4>0,Q4>0),IF(U4="Yes","Resolved","Yes"),"No") -> No
A5: SG-004 | B5: Granted/delivery export (grouped) | C5: €6.3m - Residential Development, Patrickswell | D5: Barnakyle, Patrickswell | E5: Patrickswell | F5: 52.601353 | G5: -8.7051357 | H5: On Site | I5: =COUNTIF(Applications!$B$2:$B$293,A5) -> 10 | J5: =COUNTIFS(Applications!$B$2:$B$293,A5,Applications!$Z$2:$Z$293,"Yes") -> 10 | K5: =SUMIFS(Applications!$AI$2:$AI$293,Applications!$B$2:$B$293,A5) -> 314 | L5: =SUMIFS(Applications!$AL$2:$AL$293,Applications!$B$2:$B$293,A5) -> 305 | M5: =SUMIFS(Applications!$AM$2:$AM$293,Applications!$B$2:$B$293,A5) -> 0 | N5: =SUMIFS(Applications!$AK$2:$AK$293,Applications!$B$2:$B$293,A5) -> 9 | O5: =I5-J5 -> 0 | P5: =COUNTIFS(Applications!$B$2:$B$293,A5,Applications!$W$2:$W$293,"Low",Applications!$X$2:$X$293,"") -> 9 | Q5: =COUNTIFS(Applications!$B$2:$B$293,A5,Applications!$AH$2:$AH$293,"Past*")+COUNTIFS(Applications!$B$2:$B$293,A5,Applications!$AH$2:$AH$293,"No CIS*") -> 3 | S5: Yes | T5: =IF(OR(R5<>"",S5="Yes",P5>0,Q5>0),IF(U5="Yes","Resolved","Yes"),"No") -> Yes
A6: P-1444384 | B6: Granted/delivery export (grouped) | C6: €8.6m - Staff Accommodation/8Apartments, Adare | D6: Fitzgerald's Woodlands House Hotel, Knockanes, Adare | E6: Adare | F6: 52.561726 | G6: -8.7657741 | H6: Permission Granted | I6: =COUNTIF(Applications!$B$2:$B$293,A6) -> 1 | J6: =COUNTIFS(Applications!$B$2:$B$293,A6,Applications!$Z$2:$Z$293,"Yes") -> 1 | K6: =SUMIFS(Applications!$AI$2:$AI$293,Applications!$B$2:$B$293,A6) -> 28 | L6: =SUMIFS(Applications!$AL$2:$AL$293,Applications!$B$2:$B$293,A6) -> 28 | M6: =SUMIFS(Applications!$AM$2:$AM$293,Applications!$B$2:$B$293,A6) -> 0 | N6: =SUMIFS(Applications!$AK$2:$AK$293,Applications!$B$2:$B$293,A6) -> 0 | O6: =I6-J6 -> 0 | P6: =COUNTIFS(Applications!$B$2:$B$293,A6,Applications!$W$2:$W$293,"Low",Applications!$X$2:$X$293,"") -> 0 | Q6: =COUNTIFS(Applications!$B$2:$B$293,A6,Applications!$AH$2:$AH$293,"Past*")+COUNTIFS(Applications!$B$2:$B$293,A6,Applications!$AH$2:$AH$293,"No CIS*") -> 0 | S6: No | T6: =IF(OR(R6<>"",S6="Yes",P6>0,Q6>0),IF(U6="Yes","Resolved","Yes"),"No") -> No
A7: P-1414007 | B7: Granted/delivery export (grouped) | C7: €1m - 8 Houses, Bruff | D7: Ardykeohane, Bruff | E7: Bruff | F7: 52.476941 | G7: -8.5370467 | H7: Permission Granted | I7: =COUNTIF(Applications!$B$2:$B$293,A7) -> 1 | J7: =COUNTIFS(Applications!$B$2:$B$293,A7,Applications!$Z$2:$Z$293,"Yes") -> 1 | K7: =SUMIFS(Applications!$AI$2:$AI$293,Applications!$B$2:$B$293,A7) -> 8 | L7: =SUMIFS(Applications!$AL$2:$AL$293,Applications!$B$2:$B$293,A7) -> 8 | M7: =SUMIFS(Applications!$AM$2:$AM$293,Applications!$B$2:$B$293,A7) -> 0 | N7: =SUMIFS(Applications!$AK$2:$AK$293,Applications!$B$2:$B$293,A7) -> 0 | O7: =I7-J7 -> 0 | P7: =COUNTIFS(Applications!$B$2:$B$293,A7,Applications!$W$2:$W$293,"Low",Applications!$X$2:$X$293,"") -> 0 | Q7: =COUNTIFS(Applications!$B$2:$B$293,A7,Applications!$AH$2:$AH$293,"Past*")+COUNTIFS(Applications!$B$2:$B$293,A7,Applications!$AH$2:$AH$293,"No CIS*") -> 0 | S7: No | T7: =IF(OR(R7<>"",S7="Yes",P7>0,Q7>0),IF(U7="Yes","Resolved","Yes"),"No") -> No
A8: SG-023 | B8: Granted/delivery export (grouped) | C8: €4m - Residential Development | D8: Broadford | E8: Other County Limerick | F8: 52.344978 | G8: -8.9745614 | H8: Part Complete | I8: =COUNTIF(Applications!$B$2:$B$293,A8) -> 2 | J8: =COUNTIFS(Applications!$B$2:$B$293,A8,Applications!$Z$2:$Z$293,"Yes") -> 1 | K8: =SUMIFS(Applications!$AI$2:$AI$293,Applications!$B$2:$B$293,A8) -> 18 | L8: =SUMIFS(Applications!$AL$2:$AL$293,Applications!$B$2:$B$293,A8) -> 7 | M8: =SUMIFS(Applications!$AM$2:$AM$293,Applications!$B$2:$B$293,A8) -> 0 | N8: =SUMIFS(Applications!$AK$2:$AK$293,Applications!$B$2:$B$293,A8) -> 11 | O8: =I8-J8 -> 1 | P8: =COUNTIFS(Applications!$B$2:$B$293,A8,Applications!$W$2:$W$293,"Low",Applications!$X$2:$X$293,"") -> 1 | Q8: =COUNTIFS(Applications!$B$2:$B$293,A8,Applications!$AH$2:$AH$293,"Past*")+COUNTIFS(Applications!$B$2:$B$293,A8,Applications!$AH$2:$AH$293,"No CIS*") -> 0 | S8: Yes | T8: =IF(OR(R8<>"",S8="Yes",P8>0,Q8>0),IF(U8="Yes","Resolved","Yes"),"No") -> Yes
A9: SG-003 | B9: Granted/delivery export (grouped) | C9: €5.9m - Residential Development, Patrickswell | D9: Ballyanrahan East, Patrickswell | E9: Patrickswell | F9: 52.599095 | G9: -8.7091281 | H9: Part Complete | I9: =COUNTIF(Applications!$B$2:$B$293,A9) -> 7 | J9: =COUNTIFS(Applications!$B$2:$B$293,A9,Applications!$Z$2:$Z$293,"Yes") -> 3 | K9: =SUMIFS(Applications!$AI$2:$AI$293,Applications!$B$2:$B$293,A9) -> 112 | L9: =SUMIFS(Applications!$AL$2:$AL$293,Applications!$B$2:$B$293,A9) -> 86 | M9: =SUMIFS(Applications!$AM$2:$AM$293,Applications!$B$2:$B$293,A9) -> 0 | N9: =SUMIFS(Applications!$AK$2:$AK$293,Applications!$B$2:$B$293,A9) -> 26 | O9: =I9-J9 -> 4 | P9: =COUNTIFS(Applications!$B$2:$B$293,A9,Applications!$W$2:$W$293,"Low",Applications!$X$2:$X$293,"") -> 2 | Q9: =COUNTIFS(Applications!$B$2:$B$293,A9,Applications!$AH$2:$AH$293,"Past*")+COUNTIFS(Applications!$B$2:$B$293,A9,Applications!$AH$2:$AH$293,"No CIS*") -> 0 | S9: Yes | T9: =IF(OR(R9<>"",S9="Yes",P9>0,Q9>0),IF(U9="Yes","Resolved","Yes"),"No") -> Yes
A10: SG-019 | B10: Granted/delivery export (grouped) | C10: €44m - Residential Development, Castletroy | D10: Newcastle, Castletroy | E10: Limerick City and Suburbs | F10: 52.666952 | G10: -8.5497456 | H10: On Site | I10: =COUNTIF(Applications!$B$2:$B$293,A10) -> 3 | J10: =COUNTIFS(Applications!$B$2:$B$293,A10,Applications!$Z$2:$Z$293,"Yes") -> 3 | K10: =SUMIFS(Applications!$AI$2:$AI$293,Applications!$B$2:$B$293,A10) -> 227 | L10: =SUMIFS(Applications!$AL$2:$AL$293,Applications!$B$2:$B$293,A10) -> 27 | M10: =SUMIFS(Applications!$AM$2:$AM$293,Applications!$B$2:$B$293,A10) -> 0 | N10: =SUMIFS(Applications!$AK$2:$AK$293,Applications!$B$2:$B$293,A10) -> 200 | O10: =I10-J10 -> 0 | P10: =COUNTIFS(Applications!$B$2:$B$293,A10,Applications!$W$2:$W$293,"Low",Applications!$X$2:$X$293,"") -> 2 | Q10: =COUNTIFS(Applications!$B$2:$B$293,A10,Applications!$AH$2:$AH$293,"Past*")+COUNTIFS(Applications!$B$2:$B$293,A10,Applications!$AH$2:$AH$293,"No CIS*") -> 0 | S10: Yes | T10: =IF(OR(R10<>"",S10="Yes",P10>0,Q10>0),IF(U10="Yes","Resolved","Yes"),"No") -> Yes
A11: P-1437215 | B11: Granted/delivery export (grouped) | C11: €84m - Parkway Valley LRD, Singland | D11: Site known as "Parkway Valley", Dublin Road (R445), Singland | E11: Other County Limerick | F11: 52.660173 | G11: -8.5885499 | H11: Permission Granted | I11: =COUNTIF(Applications!$B$2:$B$293,A11) -> 1 | J11: =COUNTIFS(Applications!$B$2:$B$293,A11,Applications!$Z$2:$Z$293,"Yes") -> 1 | K11: =SUMIFS(Applications!$AI$2:$AI$293,Applications!$B$2:$B$293,A11) -> 403 | L11: =SUMIFS(Applications!$AL$2:$AL$293,Applications!$B$2:$B$293,A11) -> 403 | M11: =SUMIFS(Applications!$AM$2:$AM$293,Applications!$B$2:$B$293,A11) -> 0 | N11: =SUMIFS(Applications!$AK$2:$AK$293,Applications!$B$2:$B$293,A11) -> 0 | O11: =I11-J11 -> 0 | P11: =COUNTIFS(Applications!$B$2:$B$293,A11,Applications!$W$2:$W$293,"Low",Applications!$X$2:$X$293,"") -> 0 | Q11: =COUNTIFS(Applications!$B$2:$B$293,A11,Applications!$AH$2:$AH$293,"Past*")+COUNTIFS(Applications!$B$2:$B$293,A11,Applications!$AH$2:$AH$293,"No CIS*") -> 0 | S11: No | T11: =IF(OR(R11<>"",S11="Yes",P11>0,Q11>0),IF(U11="Yes","Resolved","Yes"),"No") -> No
A12: P-1428325 | B12: Granted/delivery export (grouped) | C12: €42m - Large Residential Development,Limerick | D12: Towlerton , Ballysimon, Limerick | E12: Limerick City and Suburbs | F12: 52.655611 | G12: -8.5815955 | H12: Permission Granted | I12: =COUNTIF(Applications!$B$2:$B$293,A12) -> 1 | J12: =COUNTIFS(Applications!$B$2:$B$293,A12,Applications!$Z$2:$Z$293,"Yes") -> 1 | K12: =SUMIFS(Applications!$AI$2:$AI$293,Applications!$B$2:$B$293,A12) -> 212 | L12: =SUMIFS(Applications!$AL$2:$AL$293,Applications!$B$2:$B$293,A12) -> 212 | M12: =SUMIFS(Applications!$AM$2:$AM$293,Applications!$B$2:$B$293,A12) -> 0 | N12: =SUMIFS(Applications!$AK$2:$AK$293,Applications!$B$2:$B$293,A12) -> 0 | O12: =I12-J12 -> 0 | P12: =COUNTIFS(Applications!$B$2:$B$293,A12,Applications!$W$2:$W$293,"Low",Applications!$X$2:$X$293,"") -> 0 | Q12: =COUNTIFS(Applications!$B$2:$B$293,A12,Applications!$AH$2:$AH$293,"Past*")+COUNTIFS(Applications!$B$2:$B$293,A12,Applications!$AH$2:$AH$293,"No CIS*") -> 0 | S12: No | T12: =IF(OR(R12<>"",S12="Yes",P12>0,Q12>0),IF(U12="Yes","Resolved","Yes"),"No") -> No
A13: SG-020 | B13: Granted/delivery export (grouped) | C13: €47m - The Mungret Project | D13: Dromdarrig, Mungret | E13: Mungret | F13: 52.629688 | G13: -8.6773868 | H13: On Site | I13: =COUNTIF(Applications!$B$2:$B$293,A13) -> 2 | J13: =COUNTIFS(Applications!$B$2:$B$293,A13,Applications!$Z$2:$Z$293,"Yes") -> 2 | K13: =SUMIFS(Applications!$AI$2:$AI$293,Applications!$B$2:$B$293,A13) -> 419 | L13: =SUMIFS(Applications!$AL$2:$AL$293,Applications!$B$2:$B$293,A13) -> 419 | M13: =SUMIFS(Applications!$AM$2:$AM$293,Applications!$B$2:$B$293,A13) -> 0 | N13: =SUMIFS(Applications!$AK$2:$AK$293,Applications!$B$2:$B$293,A13) -> 0 | O13: =I13-J13 -> 0 | P13: =COUNTIFS(Applications!$B$2:$B$293,A13,Applications!$W$2:$W$293,"Low",Applications!$X$2:$X$293,"") -> 1 | Q13: =COUNTIFS(Applications!$B$2:$B$293,A13,Applications!$AH$2:$AH$293,"Past*")+COUNTIFS(Applications!$B$2:$B$293,A13,Applications!$AH$2:$AH$293,"No CIS*") -> 0 | S13: Yes | T13: =IF(OR(R13<>"",S13="Yes",P13>0,Q13>0),IF(U13="Yes","Resolved","Yes"),"No") -> Yes
... A154: P-978022 | B154: Granted/delivery export (grouped) | C154: €3m - Mixed Use Development | D154: Ellen Street/Carr Street/Punch's Row | E154: Other County Limerick | F154: 52.664066 | G154: -8.6220618 | H154: Permission Granted | I154: =COUNTIF(Applications!$B$2:$B$293,A154) -> 1 | J154: =COUNTIFS(Applications!$B$2:$B$293,A154,Applications!$Z$2:$Z$293,"Yes") -> 1 | K154: =SUMIFS(Applications!$AI$2:$AI$293,Applications!$B$2:$B$293,A154) -> 8 | L154: =SUMIFS(Applications!$AL$2:$AL$293,Applications!$B$2:$B$293,A154) -> 8 | M154: =SUMIFS(Applications!$AM$2:$AM$293,Applications!$B$2:$B$293,A154) -> 0 | N154: =SUMIFS(Applications!$AK$2:$AK$293,Applications!$B$2:$B$293,A154) -> 0 | O154: =I154-J154 -> 0 | P154: =COUNTIFS(Applications!$B$2:$B$293,A154,Applications!$W$2:$W$293,"Low",Applications!$X$2:$X$293,"") -> 0 | Q154: =COUNTIFS(Applications!$B$2:$B$293,A154,Applications!$AH$2:$AH$293,"Past*")+COUNTIFS(Applications!$B$2:$B$293,A154,Applications!$AH$2:$AH$293,"No CIS*") -> 1 | S154: No | T154: =IF(OR(R154<>"",S154="Yes",P154>0,Q154>0),IF(U154="Yes","Resolved","Yes"),"No") -> Yes
A155: U-837963 | B155: Latest upstream export | C155: €588k - 3 Houses | D155: adjacent to the Soccer Club and accessed of The Grove, Garrane Beg, Pallasgreen | E155: Other County Limerick | F155: 52.564175 | G155: -8.3381718 | H155: Tender | I155: =COUNTIF(Applications!$B$2:$B$293,A155) -> 1 | J155: =COUNTIFS(Applications!$B$2:$B$293,A155,Applications!$Z$2:$Z$293,"Yes") -> 1 | K155: =SUMIFS(Applications!$AI$2:$AI$293,Applications!$B$2:$B$293,A155) -> 3 | L155: =SUMIFS(Applications!$AL$2:$AL$293,Applications!$B$2:$B$293,A155) -> 3 | M155: =SUMIFS(Applications!$AM$2:$AM$293,Applications!$B$2:$B$293,A155) -> 0 | N155: =SUMIFS(Applications!$AK$2:$AK$293,Applications!$B$2:$B$293,A155) -> 0 | O155: =I155-J155 -> 0 | P155: =COUNTIFS(Applications!$B$2:$B$293,A155,Applications!$W$2:$W$293,"Low",Applications!$X$2:$X$293,"") -> 0 | Q155: =COUNTIFS(Applications!$B$2:$B$293,A155,Applications!$AH$2:$AH$293,"Past*")+COUNTIFS(Applications!$B$2:$B$293,A155,Applications!$AH$2:$AH$293,"No CIS*") -> 0 | R155: P-1278179 (20m): €1.5m - 3 Community Houses, Complete, 3 units | S155: No | T155: =IF(OR(R155<>"",S155="Yes",P155>0,Q155>0),IF(U155="Yes","Resolved","Yes"),"No") -> Yes
A156: U-1034286 | B156: Latest upstream export | C156: €567k - Change of Use to Care Residential Units | D156: Sisters of Mercy Convent, Main Street, Doon | E156: Other County Limerick | F156: 52.603895 | G156: -8.244808 | H156: Tender | I156: =COUNTIF(Applications!$B$2:$B$293,A156) -> 1 | J156: =COUNTIFS(Applications!$B$2:$B$293,A156,Applications!$Z$2:$Z$293,"Yes") -> 1 | K156: =SUMIFS(Applications!$AI$2:$AI$293,Applications!$B$2:$B$293,A156) -> 21 | L156: =SUMIFS(Applications!$AL$2:$AL$293,Applications!$B$2:$B$293,A156) -> 21 | M156: =SUMIFS(Applications!$AM$2:$AM$293,Applications!$B$2:$B$293,A156) -> 0 | N156: =SUMIFS(Applications!$AK$2:$AK$293,Applications!$B$2:$B$293,A156) -> 0 | O156: =I156-J156 -> 0 | P156: =COUNTIFS(Applications!$B$2:$B$293,A156,Applications!$W$2:$W$293,"Low",Applications!$X$2:$X$293,"") -> 0 | Q156: =COUNTIFS(Applications!$B$2:$B$293,A156,Applications!$AH$2:$AH$293,"Past*")+COUNTIFS(Applications!$B$2:$B$293,A156,Applications!$AH$2:$AH$293,"No CIS*") -> 0 | S156: No | T156: =IF(OR(R156<>"",S156="Yes",P156>0,Q156>0),IF(U156="Yes","Resolved","Yes"),"No") -> No
A157: U-1033981 | B157: Latest upstream export | C157: €960k - Residential Development | D157: St. Patrick Villas, Castleconnel | E157: Castleconnell | F157: 52.704525 | G157: -8.5059194 | H157: Tender | I157: =COUNTIF(Applications!$B$2:$B$293,A157) -> 1 | J157: =COUNTIFS(Applications!$B$2:$B$293,A157,Applications!$Z$2:$Z$293,"Yes") -> 1 | K157: =SUMIFS(Applications!$AI$2:$AI$293,Applications!$B$2:$B$293,A157) -> 4 | L157: =SUMIFS(Applications!$AL$2:$AL$293,Applications!$B$2:$B$293,A157) -> 4 | M157: =SUMIFS(Applications!$AM$2:$AM$293,Applications!$B$2:$B$293,A157) -> 0 | N157: =SUMIFS(Applications!$AK$2:$AK$293,Applications!$B$2:$B$293,A157) -> 0 | O157: =I157-J157 -> 0 | P157: =COUNTIFS(Applications!$B$2:$B$293,A157,Applications!$W$2:$W$293,"Low",Applications!$X$2:$X$293,"") -> 0 | Q157: =COUNTIFS(Applications!$B$2:$B$293,A157,Applications!$AH$2:$AH$293,"Past*")+COUNTIFS(Applications!$B$2:$B$293,A157,Applications!$AH$2:$AH$293,"No CIS*") -> 0 | S157: No | T157: =IF(OR(R157<>"",S157="Yes",P157>0,Q157>0),IF(U157="Yes","Resolved","Yes"),"No") -> No
A158: U-1040199 | B158: Latest upstream export | C158: €2.6m - Apartments | D158: Ballygrennan Close, Moyross | E158: Limerick City and Suburbs | F158: 52.683828 | G158: -8.6494762 | H158: Tender | I158: =COUNTIF(Applications!$B$2:$B$293,A158) -> 1 | J158: =COUNTIFS(Applications!$B$2:$B$293,A158,Applications!$Z$2:$Z$293,"Yes") -> 1 | K158: =SUMIFS(Applications!$AI$2:$AI$293,Applications!$B$2:$B$293,A158) -> 12 | L158: =SUMIFS(Applications!$AL$2:$AL$293,Applications!$B$2:$B$293,A158) -> 12 | M158: =SUMIFS(Applications!$AM$2:$AM$293,Applications!$B$2:$B$293,A158) -> 0 | N158: =SUMIFS(Applications!$AK$2:$AK$293,Applications!$B$2:$B$293,A158) -> 0 | O158: =I158-J158 -> 0 | P158: =COUNTIFS(Applications!$B$2:$B$293,A158,Applications!$W$2:$W$293,"Low",Applications!$X$2:$X$293,"") -> 0 | Q158: =COUNTIFS(Applications!$B$2:$B$293,A158,Applications!$AH$2:$AH$293,"Past*")+COUNTIFS(Applications!$B$2:$B$293,A158,Applications!$AH$2:$AH$293,"No CIS*") -> 0 | S158: No | T158: =IF(OR(R158<>"",S158="Yes",P158>0,Q158>0),IF(U158="Yes","Resolved","Yes"),"No") -> No
A159: U-1157017 | B159: Latest upstream export | C159: €2.5m - Residential Development, Mungret | D159: Castlemungret, Mungret, Co. Limerick, Republic of Ireland, V94 339H | E159: Mungret | F159: 52.635932 | G159: -8.6902517 | H159: On Site | I159: =COUNTIF(Applications!$B$2:$B$293,A159) -> 1 | J159: =COUNTIFS(Applications!$B$2:$B$293,A159,Applications!$Z$2:$Z$293,"Yes") -> 1 | K159: =SUMIFS(Applications!$AI$2:$AI$293,Applications!$B$2:$B$293,A159) -> 12 | L159: =SUMIFS(Applications!$AL$2:$AL$293,Applications!$B$2:$B$293,A159) -> 12 | M159: =SUMIFS(Applications!$AM$2:$AM$293,Applications!$B$2:$B$293,A159) -> 0 | N159: =SUMIFS(Applications!$AK$2:$AK$293,Applications!$B$2:$B$293,A159) -> 0 | O159: =I159-J159 -> 0 | P159: =COUNTIFS(Applications!$B$2:$B$293,A159,Applications!$W$2:$W$293,"Low",Applications!$X$2:$X$293,"") -> 0 | Q159: =COUNTIFS(Applications!$B$2:$B$293,A159,Applications!$AH$2:$AH$293,"Past*")+COUNTIFS(Applications!$B$2:$B$293,A159,Applications!$AH$2:$AH$293,"No CIS*") -> 0 | S159: No | T159: =IF(OR(R159<>"",S159="Yes",P159>0,Q159>0),IF(U159="Yes","Resolved","Yes"),"No") -> No
A160: U-1164424 | B160: Latest upstream export | C160: €9.6m - Residential Development | D160: Hillcroft Close, St. Patricks Road, Singland, Limerick | E160: Limerick City and Suburbs | F160: 52.661374 | G160: -8.5993881 | H160: Contract Awarded | I160: =COUNTIF(Applications!$B$2:$B$293,A160) -> 1 | J160: =COUNTIFS(Applications!$B$2:$B$293,A160,Applications!$Z$2:$Z$293,"Yes") -> 1 | K160: =SUMIFS(Applications!$AI$2:$AI$293,Applications!$B$2:$B$293,A160) -> 55 | L160: =SUMIFS(Applications!$AL$2:$AL$293,Applications!$B$2:$B$293,A160) -> 55 | M160: =SUMIFS(Applications!$AM$2:$AM$293,Applications!$B$2:$B$293,A160) -> 0 | N160: =SUMIFS(Applications!$AK$2:$AK$293,Applications!$B$2:$B$293,A160) -> 0 | O160: =I160-J160 -> 0 | P160: =COUNTIFS(Applications!$B$2:$B$293,A160,Applications!$W$2:$W$293,"Low",Applications!$X$2:$X$293,"") -> 0 | Q160: =COUNTIFS(Applications!$B$2:$B$293,A160,Applications!$AH$2:$AH$293,"Past*")+COUNTIFS(Applications!$B$2:$B$293,A160,Applications!$AH$2:$AH$293,"No CIS*") -> 0 | S160: No | T160: =IF(OR(R160<>"",S160="Yes",P160>0,Q160>0),IF(U160="Yes","Resolved","Yes"),"No") -> No
A161: U-1165485 | B161: Latest upstream export | C161: €11.3m - Residential Development | D161: Saint Ita's Road, Abbeyfeale West, Abbeyfeale | E161: Abbeyfeale | F161: 52.382036 | G161: -9.2982956 | H161: Contract Awarded | I161: =COUNTIF(Applications!$B$2:$B$293,A161) -> 1 | J161: =COUNTIFS(Applications!$B$2:$B$293,A161,Applications!$Z$2:$Z$293,"Yes") -> 1 | K161: =SUMIFS(Applications!$AI$2:$AI$293,Applications!$B$2:$B$293,A161) -> 68 | L161: =SUMIFS(Applications!$AL$2:$AL$293,Applications!$B$2:$B$293,A161) -> 68 | M161: =SUMIFS(Applications!$AM$2:$AM$293,Applications!$B$2:$B$293,A161) -> 0 | N161: =SUMIFS(Applications!$AK$2:$AK$293,Applications!$B$2:$B$293,A161) -> 0 | O161: =I161-J161 -> 0 | P161: =COUNTIFS(Applications!$B$2:$B$293,A161,Applications!$W$2:$W$293,"Low",Applications!$X$2:$X$293,"") -> 0 | Q161: =COUNTIFS(Applications!$B$2:$B$293,A161,Applications!$AH$2:$AH$293,"Past*")+COUNTIFS(Applications!$B$2:$B$293,A161,Applications!$AH$2:$AH$293,"No CIS*") -> 0 | S161: No | T161: =IF(OR(R161<>"",S161="Yes",P161>0,Q161>0),IF(U161="Yes","Resolved","Yes"),"No") -> No
A162: U-1166991 | B162: Latest upstream export | C162: €10.8m - Residential Development, Croom | D162: Skagh, Croom, Croom | E162: Other County Limerick | F162: 52.525037 | G162: -8.7170903 | H162: Contract Awarded | I162: =COUNTIF(Applications!$B$2:$B$293,A162) -> 1 | J162: =COUNTIFS(Applications!$B$2:$B$293,A162,Applications!$Z$2:$Z$293,"Yes") -> 1 | K162: =SUMIFS(Applications!$AI$2:$AI$293,Applications!$B$2:$B$293,A162) -> 51 | L162: =SUMIFS(Applications!$AL$2:$AL$293,Applications!$B$2:$B$293,A162) -> 51 | M162: =SUMIFS(Applications!$AM$2:$AM$293,Applications!$B$2:$B$293,A162) -> 0 | N162: =SUMIFS(Applications!$AK$2:$AK$293,Applications!$B$2:$B$293,A162) -> 0 | O162: =I162-J162 -> 0 | P162: =COUNTIFS(Applications!$B$2:$B$293,A162,Applications!$W$2:$W$293,"Low",Applications!$X$2:$X$293,"") -> 0 | Q162: =COUNTIFS(Applications!$B$2:$B$293,A162,Applications!$AH$2:$AH$293,"Past*")+COUNTIFS(Applications!$B$2:$B$293,A162,Applications!$AH$2:$AH$293,"No CIS*") -> 0 | S162: No | T162: =IF(OR(R162<>"",S162="Yes",P162>0,Q162>0),IF(U162="Yes","Resolved","Yes"),"No") -> No
A163: U-1212017 | B163: Latest upstream export | C163: €1m - Residential Development, Ballylanders | D163: Church Glen, Glennahaglish, Ballylanders | E163: Other County Limerick | F163: 52.36881 | G163: -8.34341 | H163: Contract Awarded | I163: =COUNTIF(Applications!$B$2:$B$293,A163) -> 1 | J163: =COUNTIFS(Applications!$B$2:$B$293,A163,Applications!$Z$2:$Z$293,"Yes") -> 0 | K163: =SUMIFS(Applications!$AI$2:$AI$293,Applications!$B$2:$B$293,A163) -> 0 | L163: =SUMIFS(Applications!$AL$2:$AL$293,Applications!$B$2:$B$293,A163) -> 0 | M163: =SUMIFS(Applications!$AM$2:$AM$293,Applications!$B$2:$B$293,A163) -> 0 | N163: =SUMIFS(Applications!$AK$2:$AK$293,Applications!$B$2:$B$293,A163) -> 0 | O163: =I163-J163 -> 1 | P163: =COUNTIFS(Applications!$B$2:$B$293,A163,Applications!$W$2:$W$293,"Low",Applications!$X$2:$X$293,"") -> 0 | Q163: =COUNTIFS(Applications!$B$2:$B$293,A163,Applications!$AH$2:$AH$293,"Past*")+COUNTIFS(Applications!$B$2:$B$293,A163,Applications!$AH$2:$AH$293,"No CIS*") -> 0 | R163: P-1213266 (79m): €2.5m - 9 Houses, On Site, 9 units | S163: No | T163: =IF(OR(R163<>"",S163="Yes",P163>0,Q163>0),IF(U163="Yes","Resolved","Yes"),"No") -> Yes
A164: U-1227182 | B164: Latest upstream export | C164: €4.5m - Housing Development, Mungret | D164: Rathmale, Mungret, Co. Limerick, Republic of Ireland | E164: Mungret | F164: 52.632858 | G164: -8.6983485 | H164: Permission Granted | I164: =COUNTIF(Applications!$B$2:$B$293,A164) -> 1 | J164: =COUNTIFS(Applications!$B$2:$B$293,A164,Applications!$Z$2:$Z$293,"Yes") -> 1 | K164: =SUMIFS(Applications!$AI$2:$AI$293,Applications!$B$2:$B$293,A164) -> 21 | L164: =SUMIFS(Applications!$AL$2:$AL$293,Applications!$B$2:$B$293,A164) -> 21 | M164: =SUMIFS(Applications!$AM$2:$AM$293,Applications!$B$2:$B$293,A164) -> 0 | N164: =SUMIFS(Applications!$AK$2:$AK$293,Applications!$B$2:$B$293,A164) -> 0 | O164: =I164-J164 -> 0 | P164: =COUNTIFS(Applications!$B$2:$B$293,A164,Applications!$W$2:$W$293,"Low",Applications!$X$2:$X$293,"") -> 0 | Q164: =COUNTIFS(Applications!$B$2:$B$293,A164,Applications!$AH$2:$AH$293,"Past*")+COUNTIFS(Applications!$B$2:$B$293,A164,Applications!$AH$2:$AH$293,"No CIS*") -> 1 | S164: No | T164: =IF(OR(R164<>"",S164="Yes",P164>0,Q164>0),IF(U164="Yes","Resolved","Yes"),"No") -> Yes
A165: U-1241529 | B165: Latest upstream export | C165: €4.5m - Housing Development, Limerick City | D165: St. Anne's, Dublin Road, Limerick City | E165: Limerick City and Suburbs | F165: 52.66476 | G165: -8.6087547 | H165: Contract Awarded | I165: =COUNTIF(Applications!$B$2:$B$293,A165) -> 1 | J165: =COUNTIFS(Applications!$B$2:$B$293,A165,Applications!$Z$2:$Z$293,"Yes") -> 1 | K165: =SUMIFS(Applications!$AI$2:$AI$293,Applications!$B$2:$B$293,A165) -> 20 | L165: =SUMIFS(Applications!$AL$2:$AL$293,Applications!$B$2:$B$293,A165) -> 20 | M165: =SUMIFS(Applications!$AM$2:$AM$293,Applications!$B$2:$B$293,A165) -> 0 | N165: =SUMIFS(Applications!$AK$2:$AK$293,Applications!$B$2:$B$293,A165) -> 0 | O165: =I165-J165 -> 0 | P165: =COUNTIFS(Applications!$B$2:$B$293,A165,Applications!$W$2:$W$293,"Low",Applications!$X$2:$X$293,"") -> 0 | Q165: =COUNTIFS(Applications!$B$2:$B$293,A165,Applications!$AH$2:$AH$293,"Past*")+COUNTIFS(Applications!$B$2:$B$293,A165,Applications!$AH$2:$AH$293,"No CIS*") -> 0 | S165: No | T165: =IF(OR(R165<>"",S165="Yes",P165>0,Q165>0),IF(U165="Yes","Resolved","Yes"),"No") -> No
A166: U-1250272 | B166: Latest upstream export | C166: €6.5m - Apartment Development, Limerick | D166: Windmill Street and Cogan Street, Limerick, Co. Limerick, Republic of Ireland, V94 DNH7 | E166: Limerick City and Suburbs | F166: 52.659338 | G166: -8.6354307 | H166: Permission Granted | I166: =COUNTIF(Applications!$B$2:$B$293,A166) -> 1 | J166: =COUNTIFS(Applications!$B$2:$B$293,A166,Applications!$Z$2:$Z$293,"Yes") -> 1 | K166: =SUMIFS(Applications!$AI$2:$AI$293,Applications!$B$2:$B$293,A166) -> 29 | L166: =SUMIFS(Applications!$AL$2:$AL$293,Applications!$B$2:$B$293,A166) -> 29 | M166: =SUMIFS(Applications!$AM$2:$AM$293,Applications!$B$2:$B$293,A166) -> 0 | N166: =SUMIFS(Applications!$AK$2:$AK$293,Applications!$B$2:$B$293,A166) -> 0 | O166: =I166-J166 -> 0 | P166: =COUNTIFS(Applications!$B$2:$B$293,A166,Applications!$W$2:$W$293,"Low",Applications!$X$2:$X$293,"") -> 1 | Q166: =COUNTIFS(Applications!$B$2:$B$293,A166,Applications!$AH$2:$AH$293,"Past*")+COUNTIFS(Applications!$B$2:$B$293,A166,Applications!$AH$2:$AH$293,"No CIS*") -> 1 | R166: P-1195465 (44m): €2.1m - Apartment Development , Permission Granted, 14 units; P-980328 (106m): €2m - Apartment Development , Complete, 14 units | S166: No | T166: =IF(OR(R166<>"",S166="Yes",P166>0,Q166>0),IF(U166="Yes","Resolved","Yes"),"No") -> Yes
A167: U-1254537 | B167: Latest upstream export | C167: €5m - Apartment/Retail Development, Dooradoyle | D167: Shannonside Kitchens Site, St Nessans Road, Dooradoyle, Co. Limerick, Republic of Ireland, V94 XH99 | E167: Limerick City and Suburbs | F167: 52.639955 | G167: -8.6504621 | H167: Permission Granted | I167: =COUNTIF(Applications!$B$2:$B$293,A167) -> 1 | J167: =COUNTIFS(Applications!$B$2:$B$293,A167,Applications!$Z$2:$Z$293,"Yes") -> 1 | K167: =SUMIFS(Applications!$AI$2:$AI$293,Applications!$B$2:$B$293,A167) -> 30 | L167: =SUMIFS(Applications!$AL$2:$AL$293,Applications!$B$2:$B$293,A167) -> 30 | M167: =SUMIFS(Applications!$AM$2:$AM$293,Applications!$B$2:$B$293,A167) -> 0 | N167: =SUMIFS(Applications!$AK$2:$AK$293,Applications!$B$2:$B$293,A167) -> 0 | O167: =I167-J167 -> 0 | P167: =COUNTIFS(Applications!$B$2:$B$293,A167,Applications!$W$2:$W$293,"Low",Applications!$X$2:$X$293,"") -> 0 | Q167: =COUNTIFS(Applications!$B$2:$B$293,A167,Applications!$AH$2:$AH$293,"Past*")+COUNTIFS(Applications!$B$2:$B$293,A167,Applications!$AH$2:$AH$293,"No CIS*") -> 1 | S167: No | T167: =IF(OR(R167<>"",S167="Yes",P167>0,Q167>0),IF(U167="Yes","Resolved","Yes"),"No") -> Yes
A168: U-1277663 | B168: Latest upstream export | C168: €9m - Housing Development, Patrickswell | D168: Ballyanrahan East, Patrickswell | E168: Patrickswell | F168: 52.600921 | G168: -8.7117481 | H168: Contract Awarded | I168: =COUNTIF(Applications!$B$2:$B$293,A168) -> 1 | J168: =COUNTIFS(Applications!$B$2:$B$293,A168,Applications!$Z$2:$Z$293,"Yes") -> 1 | K168: =SUMIFS(Applications!$AI$2:$AI$293,Applications!$B$2:$B$293,A168) -> 41 | L168: =SUMIFS(Applications!$AL$2:$AL$293,Applications!$B$2:$B$293,A168) -> 41 | M168: =SUMIFS(Applications!$AM$2:$AM$293,Applications!$B$2:$B$293,A168) -> 0 | N168: =SUMIFS(Applications!$AK$2:$AK$293,Applications!$B$2:$B$293,A168) -> 0 | O168: =I168-J168 -> 0 | P168: =COUNTIFS(Applications!$B$2:$B$293,A168,Applications!$W$2:$W$293,"Low",Applications!$X$2:$X$293,"") -> 1 | Q168: =COUNTIFS(Applications!$B$2:$B$293,A168,Applications!$AH$2:$AH$293,"Past*")+COUNTIFS(Applications!$B$2:$B$293,A168,Applications!$AH$2:$AH$293,"No CIS*") -> 0 | R168: SG-003 (73m): €2.2m - Housing Development , On Site, 5 units; SG-003 (76m): €3.9m - EOD - Residential Development, Patric, On Site, 16 units | S168: No | T168: =IF(OR(R168<>"",S168="Yes",P168>0,Q168>0),IF(U168="Yes","Resolved","Yes"),"No") -> Yes
A169: U-1278374 | B169: Latest upstream export | C169: €3m - Apartment Development, Limerick | D169: 21 & 21A Barringon Street, Limerick, Co. Limerick, Republic of Ireland, V94 RX33 | E169: Limerick City and Suburbs | F169: 52.658031 | G169: -8.6314016 | H169: On Site | I169: =COUNTIF(Applications!$B$2:$B$293,A169) -> 1 | J169: =COUNTIFS(Applications!$B$2:$B$293,A169,Applications!$Z$2:$Z$293,"Yes") -> 1 | K169: =SUMIFS(Applications!$AI$2:$AI$293,Applications!$B$2:$B$293,A169) -> 24 | L169: =SUMIFS(Applications!$AL$2:$AL$293,Applications!$B$2:$B$293,A169) -> 24 | M169: =SUMIFS(Applications!$AM$2:$AM$293,Applications!$B$2:$B$293,A169) -> 0 | N169: =SUMIFS(Applications!$AK$2:$AK$293,Applications!$B$2:$B$293,A169) -> 0 | O169: =I169-J169 -> 0 | P169: =COUNTIFS(Applications!$B$2:$B$293,A169,Applications!$W$2:$W$293,"Low",Applications!$X$2:$X$293,"") -> 0 | Q169: =COUNTIFS(Applications!$B$2:$B$293,A169,Applications!$AH$2:$AH$293,"Past*")+COUNTIFS(Applications!$B$2:$B$293,A169,Applications!$AH$2:$AH$293,"No CIS*") -> 0 | S169: No | T169: =IF(OR(R169<>"",S169="Yes",P169>0,Q169>0),IF(U169="Yes","Resolved","Yes"),"No") -> No
A170: U-1302008 | B170: Latest upstream export | C170: €3.6m - Hosuing Development, Crossagalla | D170: Ros Mor Estate, Kilmallock Road, Crossagalla | E170: Kilmallock | F170: 52.644131 | G170: -8.5877005 | H170: Plans Submitted | I170: =COUNTIF(Applications!$B$2:$B$293,A170) -> 1 | J170: =COUNTIFS(Applications!$B$2:$B$293,A170,Applications!$Z$2:$Z$293,"Yes") -> 0 | K170: =SUMIFS(Applications!$AI$2:$AI$293,Applications!$B$2:$B$293,A170) -> 0 | L170: =SUMIFS(Applications!$AL$2:$AL$293,Applications!$B$2:$B$293,A170) -> 0 | M170: =SUMIFS(Applications!$AM$2:$AM$293,Applications!$B$2:$B$293,A170) -> 0 | N170: =SUMIFS(Applications!$AK$2:$AK$293,Applications!$B$2:$B$293,A170) -> 0 | O170: =I170-J170 -> 1 | P170: =COUNTIFS(Applications!$B$2:$B$293,A170,Applications!$W$2:$W$293,"Low",Applications!$X$2:$X$293,"") -> 0 | Q170: =COUNTIFS(Applications!$B$2:$B$293,A170,Applications!$AH$2:$AH$293,"Past*")+COUNTIFS(Applications!$B$2:$B$293,A170,Applications!$AH$2:$AH$293,"No CIS*") -> 0 | R170: SG-007 (14m): €3.6m - Housing/Creche Development, Crossagal, On Site, 12 units; SG-007 (48m): €529k - 4 Houses , Permission Granted, 4 units | S170: No | T170: =IF(OR(R170<>"",S170="Yes",P170>0,Q170>0),IF(U170="Yes","Resolved","Yes"),"No") -> Yes
A171: U-1310780 | B171: Latest upstream export | C171: €27m - Mixed Use Development, Dooradoyle | D171: Southcourt, Raheen, Dooradoyle | E171: Limerick City and Suburbs | F171: 52.628242 | G171: -8.6636361 | H171: Tender | I171: =COUNTIF(Applications!$B$2:$B$293,A171) -> 1 | J171: =COUNTIFS(Applications!$B$2:$B$293,A171,Applications!$Z$2:$Z$293,"Yes") -> 1 | K171: =SUMIFS(Applications!$AI$2:$AI$293,Applications!$B$2:$B$293,A171) -> 104 | L171: =SUMIFS(Applications!$AL$2:$AL$293,Applications!$B$2:$B$293,A171) -> 104 | M171: =SUMIFS(Applications!$AM$2:$AM$293,Applications!$B$2:$B$293,A171) -> 0 | N171: =SUMIFS(Applications!$AK$2:$AK$293,Applications!$B$2:$B$293,A171) -> 0 | O171: =I171-J171 -> 0 | P171: =COUNTIFS(Applications!$B$2:$B$293,A171,Applications!$W$2:$W$293,"Low",Applications!$X$2:$X$293,"") -> 0 | Q171: =COUNTIFS(Applications!$B$2:$B$293,A171,Applications!$AH$2:$AH$293,"Past*")+COUNTIFS(Applications!$B$2:$B$293,A171,Applications!$AH$2:$AH$293,"No CIS*") -> 0 | S171: No | T171: =IF(OR(R171<>"",S171="Yes",P171>0,Q171>0),IF(U171="Yes","Resolved","Yes"),"No") -> No
A172: U-1315592 | B172: Latest upstream export | C172: €12.6m - Residential Development, Patrickswell | D172: Barnakyle, Patrickswell | E172: Patrickswell | F172: 52.601042 | G172: -8.7045513 | H172: Plans Submitted | I172: =COUNTIF(Applications!$B$2:$B$293,A172) -> 1 | J172: =COUNTIFS(Applications!$B$2:$B$293,A172,Applications!$Z$2:$Z$293,"Yes") -> 0 | K172: =SUMIFS(Applications!$AI$2:$AI$293,Applications!$B$2:$B$293,A172) -> 0 | L172: =SUMIFS(Applications!$AL$2:$AL$293,Applications!$B$2:$B$293,A172) -> 0 | M172: =SUMIFS(Applications!$AM$2:$AM$293,Applications!$B$2:$B$293,A172) -> 0 | N172: =SUMIFS(Applications!$AK$2:$AK$293,Applications!$B$2:$B$293,A172) -> 0 | O172: =I172-J172 -> 1 | P172: =COUNTIFS(Applications!$B$2:$B$293,A172,Applications!$W$2:$W$293,"Low",Applications!$X$2:$X$293,"") -> 0 | Q172: =COUNTIFS(Applications!$B$2:$B$293,A172,Applications!$AH$2:$AH$293,"Past*")+COUNTIFS(Applications!$B$2:$B$293,A172,Applications!$AH$2:$AH$293,"No CIS*") -> 0 | R172: SG-004 (69m): €15.9m - Residential Development, Patrickswel, Permission Granted, 63 units; SG-004 (108m): €6.3m - Residential Development, Patrickswell, Permission Granted, 49 units | S172: No | T172: =IF(OR(R172<>"",S172="Yes",P172>0,Q172>0),IF(U172="Yes","Resolved","Yes"),"No") -> Yes
A173: U-1316160 | B173: Latest upstream export | C173: €705k - Radharc an Ghleanna Residential Development, Mountcollins | D173: Radharc an Ghleanna, Mountcollins | E173: Other County Limerick | F173: 52.318745 | G173: -9.2332914 | H173: Tender | I173: =COUNTIF(Applications!$B$2:$B$293,A173) -> 1 | J173: =COUNTIFS(Applications!$B$2:$B$293,A173,Applications!$Z$2:$Z$293,"Yes") -> 1 | K173: =SUMIFS(Applications!$AI$2:$AI$293,Applications!$B$2:$B$293,A173) -> 4 | L173: =SUMIFS(Applications!$AL$2:$AL$293,Applications!$B$2:$B$293,A173) -> 4 | M173: =SUMIFS(Applications!$AM$2:$AM$293,Applications!$B$2:$B$293,A173) -> 0 | N173: =SUMIFS(Applications!$AK$2:$AK$293,Applications!$B$2:$B$293,A173) -> 0 | O173: =I173-J173 -> 0 | P173: =COUNTIFS(Applications!$B$2:$B$293,A173,Applications!$W$2:$W$293,"Low",Applications!$X$2:$X$293,"") -> 0 | Q173: =COUNTIFS(Applications!$B$2:$B$293,A173,Applications!$AH$2:$AH$293,"Past*")+COUNTIFS(Applications!$B$2:$B$293,A173,Applications!$AH$2:$AH$293,"No CIS*") -> 0 | S173: No | T173: =IF(OR(R173<>"",S173="Yes",P173>0,Q173>0),IF(U173="Yes","Resolved","Yes"),"No") -> No
A174: U-1319159 | B174: Latest upstream export | C174: €22m - Golf Links Road LRD, Monaleen | D174: Golf Links Road, Newtown, Monaleen, Co. Limerick, Republic of Ireland, V94 P821 | E174: Limerick City and Suburbs | F174: 52.652714 | G174: -8.5604119 | H174: On Site | I174: =COUNTIF(Applications!$B$2:$B$293,A174) -> 1 | J174: =COUNTIFS(Applications!$B$2:$B$293,A174,Applications!$Z$2:$Z$293,"Yes") -> 1 | K174: =SUMIFS(Applications!$AI$2:$AI$293,Applications!$B$2:$B$293,A174) -> 122 | L174: =SUMIFS(Applications!$AL$2:$AL$293,Applications!$B$2:$B$293,A174) -> 122 | M174: =SUMIFS(Applications!$AM$2:$AM$293,Applications!$B$2:$B$293,A174) -> 0 | N174: =SUMIFS(Applications!$AK$2:$AK$293,Applications!$B$2:$B$293,A174) -> 0 | O174: =I174-J174 -> 0 | P174: =COUNTIFS(Applications!$B$2:$B$293,A174,Applications!$W$2:$W$293,"Low",Applications!$X$2:$X$293,"") -> 0 | Q174: =COUNTIFS(Applications!$B$2:$B$293,A174,Applications!$AH$2:$AH$293,"Past*")+COUNTIFS(Applications!$B$2:$B$293,A174,Applications!$AH$2:$AH$293,"No CIS*") -> 0 | S174: No | T174: =IF(OR(R174<>"",S174="Yes",P174>0,Q174>0),IF(U174="Yes","Resolved","Yes"),"No") -> No
A175: U-1327665 | B175: Latest upstream export | C175: €2.5m - Assisted Living Dwelling Units, Glin | D175: Cloverfield Killacolla (Baker), Glin | E175: Other County Limerick | F175: 52.5698 | G175: -9.2806095 | H175: Tender | I175: =COUNTIF(Applications!$B$2:$B$293,A175) -> 1 | J175: =COUNTIFS(Applications!$B$2:$B$293,A175,Applications!$Z$2:$Z$293,"Yes") -> 1 | K175: =SUMIFS(Applications!$AI$2:$AI$293,Applications!$B$2:$B$293,A175) -> 10 | L175: =SUMIFS(Applications!$AL$2:$AL$293,Applications!$B$2:$B$293,A175) -> 10 | M175: =SUMIFS(Applications!$AM$2:$AM$293,Applications!$B$2:$B$293,A175) -> 0 | N175: =SUMIFS(Applications!$AK$2:$AK$293,Applications!$B$2:$B$293,A175) -> 0 | O175: =I175-J175 -> 0 | P175: =COUNTIFS(Applications!$B$2:$B$293,A175,Applications!$W$2:$W$293,"Low",Applications!$X$2:$X$293,"") -> 0 | Q175: =COUNTIFS(Applications!$B$2:$B$293,A175,Applications!$AH$2:$AH$293,"Past*")+COUNTIFS(Applications!$B$2:$B$293,A175,Applications!$AH$2:$AH$293,"No CIS*") -> 0 | S175: No | T175: =IF(OR(R175<>"",S175="Yes",P175>0,Q175>0),IF(U175="Yes","Resolved","Yes"),"No") -> No
A176: U-1328561 | B176: Latest upstream export | C176: €2m - 7 Houses, Broadford | D176: Main Street, Broadford | E176: Other County Limerick | F176: 52.345862 | G176: -8.9744886 | H176: Tender | I176: =COUNTIF(Applications!$B$2:$B$293,A176) -> 1 | J176: =COUNTIFS(Applications!$B$2:$B$293,A176,Applications!$Z$2:$Z$293,"Yes") -> 1 | K176: =SUMIFS(Applications!$AI$2:$AI$293,Applications!$B$2:$B$293,A176) -> 7 | L176: =SUMIFS(Applications!$AL$2:$AL$293,Applications!$B$2:$B$293,A176) -> 7 | M176: =SUMIFS(Applications!$AM$2:$AM$293,Applications!$B$2:$B$293,A176) -> 0 | N176: =SUMIFS(Applications!$AK$2:$AK$293,Applications!$B$2:$B$293,A176) -> 0 | O176: =I176-J176 -> 0 | P176: =COUNTIFS(Applications!$B$2:$B$293,A176,Applications!$W$2:$W$293,"Low",Applications!$X$2:$X$293,"") -> 1 | Q176: =COUNTIFS(Applications!$B$2:$B$293,A176,Applications!$AH$2:$AH$293,"Past*")+COUNTIFS(Applications!$B$2:$B$293,A176,Applications!$AH$2:$AH$293,"No CIS*") -> 0 | R176: P-1201358 (58m): €2.4m - Residential Development, Broadford , Permission Granted, 18 units; SG-023 (98m): €4m - Residential Development, Permission Granted, 18 units | S176: No | T176: =IF(OR(R176<>"",S176="Yes",P176>0,Q176>0),IF(U176="Yes","Resolved","Yes"),"No") -> Yes
A177: U-1350169 | B177: Latest upstream export | C177: €2.2m - 6 Houses | D177: Barnakyle, Patrickswell | E177: Patrickswell | F177: 52.60031 | G177: -8.7065718 | H177: Plans Submitted | I177: =COUNTIF(Applications!$B$2:$B$293,A177) -> 1 | J177: =COUNTIFS(Applications!$B$2:$B$293,A177,Applications!$Z$2:$Z$293,"Yes") -> 0 | K177: =SUMIFS(Applications!$AI$2:$AI$293,Applications!$B$2:$B$293,A177) -> 0 | L177: =SUMIFS(Applications!$AL$2:$AL$293,Applications!$B$2:$B$293,A177) -> 0 | M177: =SUMIFS(Applications!$AM$2:$AM$293,Applications!$B$2:$B$293,A177) -> 0 | N177: =SUMIFS(Applications!$AK$2:$AK$293,Applications!$B$2:$B$293,A177) -> 0 | O177: =I177-J177 -> 1 | P177: =COUNTIFS(Applications!$B$2:$B$293,A177,Applications!$W$2:$W$293,"Low",Applications!$X$2:$X$293,"") -> 0 | Q177: =COUNTIFS(Applications!$B$2:$B$293,A177,Applications!$AH$2:$AH$293,"Past*")+COUNTIFS(Applications!$B$2:$B$293,A177,Applications!$AH$2:$AH$293,"No CIS*") -> 0 | R177: SG-004 (4m): €2.4m - 6 Houses, Permission Granted, 6 units; SG-004 (98m): €1.7 - 9 Houses, Patrickswell, Complete, 9 units | S177: No | T177: =IF(OR(R177<>"",S177="Yes",P177>0,Q177>0),IF(U177="Yes","Resolved","Yes"),"No") -> Yes
A178: U-1353358 | B178: Latest upstream export | C178: €2.7m - Residential Development, Limerick | D178: High Street, Limerick City, Co. Limerick, Republic of Ireland, V94 W8XF | E178: Limerick City and Suburbs | F178: 52.662564 | G178: -8.6221517 | H178: Permission Granted | I178: =COUNTIF(Applications!$B$2:$B$293,A178) -> 1 | J178: =COUNTIFS(Applications!$B$2:$B$293,A178,Applications!$Z$2:$Z$293,"Yes") -> 1 | K178: =SUMIFS(Applications!$AI$2:$AI$293,Applications!$B$2:$B$293,A178) -> 15 | L178: =SUMIFS(Applications!$AL$2:$AL$293,Applications!$B$2:$B$293,A178) -> 15 | M178: =SUMIFS(Applications!$AM$2:$AM$293,Applications!$B$2:$B$293,A178) -> 0 | N178: =SUMIFS(Applications!$AK$2:$AK$293,Applications!$B$2:$B$293,A178) -> 0 | O178: =I178-J178 -> 0 | P178: =COUNTIFS(Applications!$B$2:$B$293,A178,Applications!$W$2:$W$293,"Low",Applications!$X$2:$X$293,"") -> 0 | Q178: =COUNTIFS(Applications!$B$2:$B$293,A178,Applications!$AH$2:$AH$293,"Past*")+COUNTIFS(Applications!$B$2:$B$293,A178,Applications!$AH$2:$AH$293,"No CIS*") -> 0 | R178: SG-032 (126m): €5.45m - Apartment Development, Limerick, On Site, 13 units; SG-032 (131m): €2.1m - Infill Residential / Living Georgian , Permission Granted, 13 units | S178: No | T178: =IF(OR(R178<>"",S178="Yes",P178>0,Q178>0),IF(U178="Yes","Resolved","Yes"),"No") -> Yes
A179: U-1363929 | B179: Latest upstream export | C179: €4.2m - Residential Development | D179: Lower Park, Corbally, Co. Limerick, Republic of Ireland, V94 Y42A | E179: Limerick City and Suburbs | F179: 52.670681 | G179: -8.6045717 | H179: Permission Granted | I179: =COUNTIF(Applications!$B$2:$B$293,A179) -> 1 | J179: =COUNTIFS(Applications!$B$2:$B$293,A179,Applications!$Z$2:$Z$293,"Yes") -> 1 | K179: =SUMIFS(Applications!$AI$2:$AI$293,Applications!$B$2:$B$293,A179) -> 15 | L179: =SUMIFS(Applications!$AL$2:$AL$293,Applications!$B$2:$B$293,A179) -> 15 | M179: =SUMIFS(Applications!$AM$2:$AM$293,Applications!$B$2:$B$293,A179) -> 0 | N179: =SUMIFS(Applications!$AK$2:$AK$293,Applications!$B$2:$B$293,A179) -> 0 | O179: =I179-J179 -> 0 | P179: =COUNTIFS(Applications!$B$2:$B$293,A179,Applications!$W$2:$W$293,"Low",Applications!$X$2:$X$293,"") -> 0 | Q179: =COUNTIFS(Applications!$B$2:$B$293,A179,Applications!$AH$2:$AH$293,"Past*")+COUNTIFS(Applications!$B$2:$B$293,A179,Applications!$AH$2:$AH$293,"No CIS*") -> 1 | S179: No | T179: =IF(OR(R179<>"",S179="Yes",P179>0,Q179>0),IF(U179="Yes","Resolved","Yes"),"No") -> Yes
A180: U-1447625 | B180: Latest upstream export | C180: €1.4m - Part 8 - 2 Houses & 4 Apartments, Thomondghate | D180: 52 New Road, Thomondghate | E180: Limerick City and Suburbs | F180: 52.675636 | G180: -8.6336345 | H180: Plans Submitted | I180: =COUNTIF(Applications!$B$2:$B$293,A180) -> 1 | J180: =COUNTIFS(Applications!$B$2:$B$293,A180,Applications!$Z$2:$Z$293,"Yes") -> 1 | K180: =SUMIFS(Applications!$AI$2:$AI$293,Applications!$B$2:$B$293,A180) -> 6 | L180: =SUMIFS(Applications!$AL$2:$AL$293,Applications!$B$2:$B$293,A180) -> 6 | M180: =SUMIFS(Applications!$AM$2:$AM$293,Applications!$B$2:$B$293,A180) -> 0 | N180: =SUMIFS(Applications!$AK$2:$AK$293,Applications!$B$2:$B$293,A180) -> 0 | O180: =I180-J180 -> 0 | P180: =COUNTIFS(Applications!$B$2:$B$293,A180,Applications!$W$2:$W$293,"Low",Applications!$X$2:$X$293,"") -> 1 | Q180: =COUNTIFS(Applications!$B$2:$B$293,A180,Applications!$AH$2:$AH$293,"Past*")+COUNTIFS(Applications!$B$2:$B$293,A180,Applications!$AH$2:$AH$293,"No CIS*") -> 0 | R180: P-1265188 (84m): €10.4m - Residential Development, Thomondgate, Permission Granted, 46 units | S180: No | T180: =IF(OR(R180<>"",S180="Yes",P180>0,Q180>0),IF(U180="Yes","Resolved","Yes"),"No") -> Yes
A181: U-1364960 | B181: Latest upstream export | C181: €2m - 6 Apartments, Limerick | D181: 52 New Road, Thomondgate, Limerick | E181: Limerick City and Suburbs | F181: 52.675628 | G181: -8.6335879 | H181: Tender | I181: =COUNTIF(Applications!$B$2:$B$293,A181) -> 1 | J181: =COUNTIFS(Applications!$B$2:$B$293,A181,Applications!$Z$2:$Z$293,"Yes") -> 0 | K181: =SUMIFS(Applications!$AI$2:$AI$293,Applications!$B$2:$B$293,A181) -> 0 | L181: =SUMIFS(Applications!$AL$2:$AL$293,Applications!$B$2:$B$293,A181) -> 0 | M181: =SUMIFS(Applications!$AM$2:$AM$293,Applications!$B$2:$B$293,A181) -> 0 | N181: =SUMIFS(Applications!$AK$2:$AK$293,Applications!$B$2:$B$293,A181) -> 0 | O181: =I181-J181 -> 1 | P181: =COUNTIFS(Applications!$B$2:$B$293,A181,Applications!$W$2:$W$293,"Low",Applications!$X$2:$X$293,"") -> 0 | Q181: =COUNTIFS(Applications!$B$2:$B$293,A181,Applications!$AH$2:$AH$293,"Past*")+COUNTIFS(Applications!$B$2:$B$293,A181,Applications!$AH$2:$AH$293,"No CIS*") -> 0 | R181: P-1265188 (82m): €10.4m - Residential Development, Thomondgate, Permission Granted, 46 units; U-1447625 (3m): €1.4m - Part 8 - 2 Houses & 4 Apartments, Tho, Plans Submitted, 6 units | S181: No | T181: =IF(OR(R181<>"",S181="Yes",P181>0,Q181>0),IF(U181="Yes","Resolved","Yes"),"No") -> Yes
A182: U-1369195 | B182: Latest upstream export | C182: €15.4m - Residential Development, Patrickswell | D182: Barnakyle, Patrickswell | E182: Patrickswell | F182: 52.600593 | G182: -8.705249 | H182: Plans Submitted | I182: =COUNTIF(Applications!$B$2:$B$293,A182) -> 1 | J182: =COUNTIFS(Applications!$B$2:$B$293,A182,Applications!$Z$2:$Z$293,"Yes") -> 0 | K182: =SUMIFS(Applications!$AI$2:$AI$293,Applications!$B$2:$B$293,A182) -> 0 | L182: =SUMIFS(Applications!$AL$2:$AL$293,Applications!$B$2:$B$293,A182) -> 0 | M182: =SUMIFS(Applications!$AM$2:$AM$293,Applications!$B$2:$B$293,A182) -> 0 | N182: =SUMIFS(Applications!$AK$2:$AK$293,Applications!$B$2:$B$293,A182) -> 0 | O182: =I182-J182 -> 1 | P182: =COUNTIFS(Applications!$B$2:$B$293,A182,Applications!$W$2:$W$293,"Low",Applications!$X$2:$X$293,"") -> 0 | Q182: =COUNTIFS(Applications!$B$2:$B$293,A182,Applications!$AH$2:$AH$293,"Past*")+COUNTIFS(Applications!$B$2:$B$293,A182,Applications!$AH$2:$AH$293,"No CIS*") -> 0 | R182: SG-004 (9m): €15.9m - Residential Development, Patrickswel, Permission Granted, 63 units; SG-004 (98m): €2.4m - 6 Houses, Permission Granted, 6 units; U-1315592 (68m): €12.6m - Residential Development, Patrickswel, Plans Submitted, 61 units; U-1350169 (94m): €2.2m - 6 Houses , Plans Submitted, 6 units | S182: No | T182: =IF(OR(R182<>"",S182="Yes",P182>0,Q182>0),IF(U182="Yes","Resolved","Yes"),"No") -> Yes
A183: U-1376045 | B183: Latest upstream export | C183: €13.9m - Apartment Development, Raheen | D183: Baunacloka, Raheen | E183: Limerick City and Suburbs | F183: 52.625196 | G183: -8.6678663 | H183: Plans Submitted | I183: =COUNTIF(Applications!$B$2:$B$293,A183) -> 1 | J183: =COUNTIFS(Applications!$B$2:$B$293,A183,Applications!$Z$2:$Z$293,"Yes") -> 0 | K183: =SUMIFS(Applications!$AI$2:$AI$293,Applications!$B$2:$B$293,A183) -> 0 | L183: =SUMIFS(Applications!$AL$2:$AL$293,Applications!$B$2:$B$293,A183) -> 0 | M183: =SUMIFS(Applications!$AM$2:$AM$293,Applications!$B$2:$B$293,A183) -> 0 | N183: =SUMIFS(Applications!$AK$2:$AK$293,Applications!$B$2:$B$293,A183) -> 0 | O183: =I183-J183 -> 1 | P183: =COUNTIFS(Applications!$B$2:$B$293,A183,Applications!$W$2:$W$293,"Low",Applications!$X$2:$X$293,"") -> 0 | Q183: =COUNTIFS(Applications!$B$2:$B$293,A183,Applications!$AH$2:$AH$293,"Past*")+COUNTIFS(Applications!$B$2:$B$293,A183,Applications!$AH$2:$AH$293,"No CIS*") -> 0 | S183: No | T183: =IF(OR(R183<>"",S183="Yes",P183>0,Q183>0),IF(U183="Yes","Resolved","Yes"),"No") -> No
A184: U-1378081 | B184: Latest upstream export | C184: €879k - 4 Houses | D184: John Carew Park, Southill | E184: Limerick City and Suburbs | F184: 52.64472 | G184: -8.6173166 | H184: Plans Submitted | I184: =COUNTIF(Applications!$B$2:$B$293,A184) -> 1 | J184: =COUNTIFS(Applications!$B$2:$B$293,A184,Applications!$Z$2:$Z$293,"Yes") -> 1 | K184: =SUMIFS(Applications!$AI$2:$AI$293,Applications!$B$2:$B$293,A184) -> 4 | L184: =SUMIFS(Applications!$AL$2:$AL$293,Applications!$B$2:$B$293,A184) -> 4 | M184: =SUMIFS(Applications!$AM$2:$AM$293,Applications!$B$2:$B$293,A184) -> 0 | N184: =SUMIFS(Applications!$AK$2:$AK$293,Applications!$B$2:$B$293,A184) -> 0 | O184: =I184-J184 -> 0 | P184: =COUNTIFS(Applications!$B$2:$B$293,A184,Applications!$W$2:$W$293,"Low",Applications!$X$2:$X$293,"") -> 0 | Q184: =COUNTIFS(Applications!$B$2:$B$293,A184,Applications!$AH$2:$AH$293,"Past*")+COUNTIFS(Applications!$B$2:$B$293,A184,Applications!$AH$2:$AH$293,"No CIS*") -> 0 | R184: P-1363543 (135m): €4m - Housing Development, Complete, 14 units | S184: No | T184: =IF(OR(R184<>"",S184="Yes",P184>0,Q184>0),IF(U184="Yes","Resolved","Yes"),"No") -> Yes
A185: U-1378805 | B185: Latest upstream export | C185: €800k - Housing Development | D185: former Galbally Garda Station | E185: Other County Limerick | F185: 52.400183 | G185: -8.2967428 | H185: Plans Submitted | I185: =COUNTIF(Applications!$B$2:$B$293,A185) -> 1 | J185: =COUNTIFS(Applications!$B$2:$B$293,A185,Applications!$Z$2:$Z$293,"Yes") -> 1 | K185: =SUMIFS(Applications!$AI$2:$AI$293,Applications!$B$2:$B$293,A185) -> 4 | L185: =SUMIFS(Applications!$AL$2:$AL$293,Applications!$B$2:$B$293,A185) -> 4 | M185: =SUMIFS(Applications!$AM$2:$AM$293,Applications!$B$2:$B$293,A185) -> 0 | N185: =SUMIFS(Applications!$AK$2:$AK$293,Applications!$B$2:$B$293,A185) -> 0 | O185: =I185-J185 -> 0 | P185: =COUNTIFS(Applications!$B$2:$B$293,A185,Applications!$W$2:$W$293,"Low",Applications!$X$2:$X$293,"") -> 0 | Q185: =COUNTIFS(Applications!$B$2:$B$293,A185,Applications!$AH$2:$AH$293,"Past*")+COUNTIFS(Applications!$B$2:$B$293,A185,Applications!$AH$2:$AH$293,"No CIS*") -> 0 | S185: No | T185: =IF(OR(R185<>"",S185="Yes",P185>0,Q185>0),IF(U185="Yes","Resolved","Yes"),"No") -> No
A186: U-1391659 | B186: Latest upstream export | C186: €6.2m - Residential Development, Limerick | D186: Sandybrook House, Bloodmill Road, Limerick, Co. Limerick, Republic of Ireland, V94 YYH5 | E186: Limerick City and Suburbs | F186: 52.65693 | G186: -8.5895196 | H186: Contract Awarded | I186: =COUNTIF(Applications!$B$2:$B$293,A186) -> 1 | J186: =COUNTIFS(Applications!$B$2:$B$293,A186,Applications!$Z$2:$Z$293,"Yes") -> 1 | K186: =SUMIFS(Applications!$AI$2:$AI$293,Applications!$B$2:$B$293,A186) -> 31 | L186: =SUMIFS(Applications!$AL$2:$AL$293,Applications!$B$2:$B$293,A186) -> 31 | M186: =SUMIFS(Applications!$AM$2:$AM$293,Applications!$B$2:$B$293,A186) -> 0 | N186: =SUMIFS(Applications!$AK$2:$AK$293,Applications!$B$2:$B$293,A186) -> 0 | O186: =I186-J186 -> 0 | P186: =COUNTIFS(Applications!$B$2:$B$293,A186,Applications!$W$2:$W$293,"Low",Applications!$X$2:$X$293,"") -> 0 | Q186: =COUNTIFS(Applications!$B$2:$B$293,A186,Applications!$AH$2:$AH$293,"Past*")+COUNTIFS(Applications!$B$2:$B$293,A186,Applications!$AH$2:$AH$293,"No CIS*") -> 0 | R186: P-974045 (142m): €554k - 4 Houses , Complete, 4 units | S186: No | T186: =IF(OR(R186<>"",S186="Yes",P186>0,Q186>0),IF(U186="Yes","Resolved","Yes"),"No") -> Yes
A187: U-1393371 | B187: Latest upstream export | C187: €4.8m - Mixed Use Development, Limerick | D187: Corner of Old Clare Street and Saint Lelia Street, Limerick, Co. Limerick, Republic of Ireland, V94 RY10 | E187: Limerick City and Suburbs | F187: 52.66551 | G187: -8.6165296 | H187: Permission Granted | I187: =COUNTIF(Applications!$B$2:$B$293,A187) -> 1 | J187: =COUNTIFS(Applications!$B$2:$B$293,A187,Applications!$Z$2:$Z$293,"Yes") -> 1 | K187: =SUMIFS(Applications!$AI$2:$AI$293,Applications!$B$2:$B$293,A187) -> 30 | L187: =SUMIFS(Applications!$AL$2:$AL$293,Applications!$B$2:$B$293,A187) -> 30 | M187: =SUMIFS(Applications!$AM$2:$AM$293,Applications!$B$2:$B$293,A187) -> 0 | N187: =SUMIFS(Applications!$AK$2:$AK$293,Applications!$B$2:$B$293,A187) -> 0 | O187: =I187-J187 -> 0 | P187: =COUNTIFS(Applications!$B$2:$B$293,A187,Applications!$W$2:$W$293,"Low",Applications!$X$2:$X$293,"") -> 1 | Q187: =COUNTIFS(Applications!$B$2:$B$293,A187,Applications!$AH$2:$AH$293,"Past*")+COUNTIFS(Applications!$B$2:$B$293,A187,Applications!$AH$2:$AH$293,"No CIS*") -> 0 | R187: SG-025 (2m): €3.5m - Apartment Development, Limerick, Permission Granted, 14 units; SG-025 (145m): €1.4m - Retail Units/Apartments, Permission Granted, 8 units | S187: No | T187: =IF(OR(R187<>"",S187="Yes",P187>0,Q187>0),IF(U187="Yes","Resolved","Yes"),"No") -> Yes
A188: U-1402230 | B188: Latest upstream export | C188: €2.2m - 9 Residential Units | D188: Hazelhall, Castletroy | E188: Limerick City and Suburbs | F188: 52.662129 | G188: -8.5509414 | H188: Plans Submitted | I188: =COUNTIF(Applications!$B$2:$B$293,A188) -> 1 | J188: =COUNTIFS(Applications!$B$2:$B$293,A188,Applications!$Z$2:$Z$293,"Yes") -> 0 | K188: =SUMIFS(Applications!$AI$2:$AI$293,Applications!$B$2:$B$293,A188) -> 0 | L188: =SUMIFS(Applications!$AL$2:$AL$293,Applications!$B$2:$B$293,A188) -> 0 | M188: =SUMIFS(Applications!$AM$2:$AM$293,Applications!$B$2:$B$293,A188) -> 0 | N188: =SUMIFS(Applications!$AK$2:$AK$293,Applications!$B$2:$B$293,A188) -> 0 | O188: =I188-J188 -> 1 | P188: =COUNTIFS(Applications!$B$2:$B$293,A188,Applications!$W$2:$W$293,"Low",Applications!$X$2:$X$293,"") -> 0 | Q188: =COUNTIFS(Applications!$B$2:$B$293,A188,Applications!$AH$2:$AH$293,"Past*")+COUNTIFS(Applications!$B$2:$B$293,A188,Applications!$AH$2:$AH$293,"No CIS*") -> 0 | R188: SG-008 (103m): €4.6m - Residential Development , Complete, 38 units | S188: No | T188: =IF(OR(R188<>"",S188="Yes",P188>0,Q188>0),IF(U188="Yes","Resolved","Yes"),"No") -> Yes
A189: U-1408292 | B189: Latest upstream export | C189: €7m - Apartment Development, Limerick City | D189: Alphonsus Street, Saint Alphonsus Street, Limerick City, Co. Limerick, Republic of Ireland, V94 T3PD | E189: Limerick City and Suburbs | F189: 52.657511 | G189: -8.6355506 | H189: Permission Granted | I189: =COUNTIF(Applications!$B$2:$B$293,A189) -> 1 | J189: =COUNTIFS(Applications!$B$2:$B$293,A189,Applications!$Z$2:$Z$293,"Yes") -> 1 | K189: =SUMIFS(Applications!$AI$2:$AI$293,Applications!$B$2:$B$293,A189) -> 48 | L189: =SUMIFS(Applications!$AL$2:$AL$293,Applications!$B$2:$B$293,A189) -> 48 | M189: =SUMIFS(Applications!$AM$2:$AM$293,Applications!$B$2:$B$293,A189) -> 0 | N189: =SUMIFS(Applications!$AK$2:$AK$293,Applications!$B$2:$B$293,A189) -> 0 | O189: =I189-J189 -> 0 | P189: =COUNTIFS(Applications!$B$2:$B$293,A189,Applications!$W$2:$W$293,"Low",Applications!$X$2:$X$293,"") -> 0 | Q189: =COUNTIFS(Applications!$B$2:$B$293,A189,Applications!$AH$2:$AH$293,"Past*")+COUNTIFS(Applications!$B$2:$B$293,A189,Applications!$AH$2:$AH$293,"No CIS*") -> 0 | R189: P-1329797 (102m): €816k - 8 Apartment , Permission Granted, 8 units; P-1132789 (109m): €919k - Student Accommodation Development, Sa, Permission Granted, ? units | S189: No | T189: =IF(OR(R189<>"",S189="Yes",P189>0,Q189>0),IF(U189="Yes","Resolved","Yes"),"No") -> Yes
A190: U-1412368 | B190: Latest upstream export | C190: €1.5m - 5 Residential Units, Limerick | D190: Hazel Close, (Scout Hall), Bawnmore Road, Kennedy Park, Limerick | E190: Limerick City and Suburbs | F190: 52.651952 | G190: -8.6101618 | H190: Tender | I190: =COUNTIF(Applications!$B$2:$B$293,A190) -> 1 | J190: =COUNTIFS(Applications!$B$2:$B$293,A190,Applications!$Z$2:$Z$293,"Yes") -> 1 | K190: =SUMIFS(Applications!$AI$2:$AI$293,Applications!$B$2:$B$293,A190) -> 5 | L190: =SUMIFS(Applications!$AL$2:$AL$293,Applications!$B$2:$B$293,A190) -> 5 | M190: =SUMIFS(Applications!$AM$2:$AM$293,Applications!$B$2:$B$293,A190) -> 0 | N190: =SUMIFS(Applications!$AK$2:$AK$293,Applications!$B$2:$B$293,A190) -> 0 | O190: =I190-J190 -> 0 | P190: =COUNTIFS(Applications!$B$2:$B$293,A190,Applications!$W$2:$W$293,"Low",Applications!$X$2:$X$293,"") -> 0 | Q190: =COUNTIFS(Applications!$B$2:$B$293,A190,Applications!$AH$2:$AH$293,"Past*")+COUNTIFS(Applications!$B$2:$B$293,A190,Applications!$AH$2:$AH$293,"No CIS*") -> 0 | S190: No | T190: =IF(OR(R190<>"",S190="Yes",P190>0,Q190>0),IF(U190="Yes","Resolved","Yes"),"No") -> No
A191: U-1412002 | B191: Latest upstream export | C191: €95m - Dock Road LRD, Limerick | D191: The Former Limerick Gasworks Site, Dock Road, Limerick City | E191: Limerick City and Suburbs | F191: 52.658983 | G191: -8.6369766 | H191: Tender | I191: =COUNTIF(Applications!$B$2:$B$293,A191) -> 1 | J191: =COUNTIFS(Applications!$B$2:$B$293,A191,Applications!$Z$2:$Z$293,"Yes") -> 1 | K191: =SUMIFS(Applications!$AI$2:$AI$293,Applications!$B$2:$B$293,A191) -> 285 | L191: =SUMIFS(Applications!$AL$2:$AL$293,Applications!$B$2:$B$293,A191) -> 285 | M191: =SUMIFS(Applications!$AM$2:$AM$293,Applications!$B$2:$B$293,A191) -> 0 | N191: =SUMIFS(Applications!$AK$2:$AK$293,Applications!$B$2:$B$293,A191) -> 0 | O191: =I191-J191 -> 0 | P191: =COUNTIFS(Applications!$B$2:$B$293,A191,Applications!$W$2:$W$293,"Low",Applications!$X$2:$X$293,"") -> 0 | Q191: =COUNTIFS(Applications!$B$2:$B$293,A191,Applications!$AH$2:$AH$293,"Past*")+COUNTIFS(Applications!$B$2:$B$293,A191,Applications!$AH$2:$AH$293,"No CIS*") -> 0 | R191: U-1250272 (110m): €6.5m - Apartment Development, Limerick, Permission Granted, 29 units | S191: No | T191: =IF(OR(R191<>"",S191="Yes",P191>0,Q191>0),IF(U191="Yes","Resolved","Yes"),"No") -> Yes
A192: U-1412257 | B192: Latest upstream export | C192: €1.2m - 10 Houses, Crossagalla | D192: Old Cork Road - Kilmallock Road, Crossagalla | E192: Kilmallock | F192: 52.650319 | G192: -8.5996732 | H192: Contract Awarded | I192: =COUNTIF(Applications!$B$2:$B$293,A192) -> 1 | J192: =COUNTIFS(Applications!$B$2:$B$293,A192,Applications!$Z$2:$Z$293,"Yes") -> 1 | K192: =SUMIFS(Applications!$AI$2:$AI$293,Applications!$B$2:$B$293,A192) -> 10 | L192: =SUMIFS(Applications!$AL$2:$AL$293,Applications!$B$2:$B$293,A192) -> 10 | M192: =SUMIFS(Applications!$AM$2:$AM$293,Applications!$B$2:$B$293,A192) -> 0 | N192: =SUMIFS(Applications!$AK$2:$AK$293,Applications!$B$2:$B$293,A192) -> 0 | O192: =I192-J192 -> 0 | P192: =COUNTIFS(Applications!$B$2:$B$293,A192,Applications!$W$2:$W$293,"Low",Applications!$X$2:$X$293,"") -> 0 | Q192: =COUNTIFS(Applications!$B$2:$B$293,A192,Applications!$AH$2:$AH$293,"Past*")+COUNTIFS(Applications!$B$2:$B$293,A192,Applications!$AH$2:$AH$293,"No CIS*") -> 0 | S192: No | T192: =IF(OR(R192<>"",S192="Yes",P192>0,Q192>0),IF(U192="Yes","Resolved","Yes"),"No") -> No
A193: U-1412942 | B193: Latest upstream export | C193: €5.4m - Cosgrave Park Phase 2, Moyross | D193: Cosgrave Park, Sarsfield Gardens, Cosgrave Park and Moyross Road, Moyross, Limerick City | E193: Limerick City and Suburbs | F193: 52.680785 | G193: -8.6428096 | H193: Plans Submitted | I193: =COUNTIF(Applications!$B$2:$B$293,A193) -> 1 | J193: =COUNTIFS(Applications!$B$2:$B$293,A193,Applications!$Z$2:$Z$293,"Yes") -> 1 | K193: =SUMIFS(Applications!$AI$2:$AI$293,Applications!$B$2:$B$293,A193) -> 22 | L193: =SUMIFS(Applications!$AL$2:$AL$293,Applications!$B$2:$B$293,A193) -> 22 | M193: =SUMIFS(Applications!$AM$2:$AM$293,Applications!$B$2:$B$293,A193) -> 0 | N193: =SUMIFS(Applications!$AK$2:$AK$293,Applications!$B$2:$B$293,A193) -> 0 | O193: =I193-J193 -> 0 | P193: =COUNTIFS(Applications!$B$2:$B$293,A193,Applications!$W$2:$W$293,"Low",Applications!$X$2:$X$293,"") -> 0 | Q193: =COUNTIFS(Applications!$B$2:$B$293,A193,Applications!$AH$2:$AH$293,"Past*")+COUNTIFS(Applications!$B$2:$B$293,A193,Applications!$AH$2:$AH$293,"No CIS*") -> 0 | S193: No | T193: =IF(OR(R193<>"",S193="Yes",P193>0,Q193>0),IF(U193="Yes","Resolved","Yes"),"No") -> No
A194: U-1414882 | B194: Latest upstream export | C194: €4.5m - Residential Development, Abbeyfeale | D194: Cois Na Féile, Abbeyfeale East, Abbeyfeale | E194: Abbeyfeale | F194: 52.383015 | G194: -9.2835799 | H194: Tender | I194: =COUNTIF(Applications!$B$2:$B$293,A194) -> 1 | J194: =COUNTIFS(Applications!$B$2:$B$293,A194,Applications!$Z$2:$Z$293,"Yes") -> 1 | K194: =SUMIFS(Applications!$AI$2:$AI$293,Applications!$B$2:$B$293,A194) -> 12 | L194: =SUMIFS(Applications!$AL$2:$AL$293,Applications!$B$2:$B$293,A194) -> 12 | M194: =SUMIFS(Applications!$AM$2:$AM$293,Applications!$B$2:$B$293,A194) -> 0 | N194: =SUMIFS(Applications!$AK$2:$AK$293,Applications!$B$2:$B$293,A194) -> 0 | O194: =I194-J194 -> 0 | P194: =COUNTIFS(Applications!$B$2:$B$293,A194,Applications!$W$2:$W$293,"Low",Applications!$X$2:$X$293,"") -> 0 | Q194: =COUNTIFS(Applications!$B$2:$B$293,A194,Applications!$AH$2:$AH$293,"Past*")+COUNTIFS(Applications!$B$2:$B$293,A194,Applications!$AH$2:$AH$293,"No CIS*") -> 0 | S194: No | T194: =IF(OR(R194<>"",S194="Yes",P194>0,Q194>0),IF(U194="Yes","Resolved","Yes"),"No") -> No
A195: U-1416952 | B195: Latest upstream export | C195: €2.1m - Change of Use to Student Accommodation, Limerick | D195: Saint Philomena's, South Circular Road, Limerick | E195: Limerick City and Suburbs | F195: 52.654389 | G195: -8.6363475 | H195: Plans Submitted | I195: =COUNTIF(Applications!$B$2:$B$293,A195) -> 1 | J195: =COUNTIFS(Applications!$B$2:$B$293,A195,Applications!$Z$2:$Z$293,"Yes") -> 0 | K195: =SUMIFS(Applications!$AI$2:$AI$293,Applications!$B$2:$B$293,A195) -> 0 | L195: =SUMIFS(Applications!$AL$2:$AL$293,Applications!$B$2:$B$293,A195) -> 0 | M195: =SUMIFS(Applications!$AM$2:$AM$293,Applications!$B$2:$B$293,A195) -> 0 | N195: =SUMIFS(Applications!$AK$2:$AK$293,Applications!$B$2:$B$293,A195) -> 0 | O195: =I195-J195 -> 1 | P195: =COUNTIFS(Applications!$B$2:$B$293,A195,Applications!$W$2:$W$293,"Low",Applications!$X$2:$X$293,"") -> 0 | Q195: =COUNTIFS(Applications!$B$2:$B$293,A195,Applications!$AH$2:$AH$293,"Past*")+COUNTIFS(Applications!$B$2:$B$293,A195,Applications!$AH$2:$AH$293,"No CIS*") -> 0 | S195: No | T195: =IF(OR(R195<>"",S195="Yes",P195>0,Q195>0),IF(U195="Yes","Resolved","Yes"),"No") -> No
A196: U-1417331 | B196: Latest upstream export | C196: €1.8m - Residential Development, Newcastle West | D196: 11-12 Bishop Street, Gortboy, Newcastle West | E196: Newcastle West | F196: 52.452606 | G196: -9.0583768 | H196: Contract Awarded | I196: =COUNTIF(Applications!$B$2:$B$293,A196) -> 1 | J196: =COUNTIFS(Applications!$B$2:$B$293,A196,Applications!$Z$2:$Z$293,"Yes") -> 1 | K196: =SUMIFS(Applications!$AI$2:$AI$293,Applications!$B$2:$B$293,A196) -> 10 | L196: =SUMIFS(Applications!$AL$2:$AL$293,Applications!$B$2:$B$293,A196) -> 10 | M196: =SUMIFS(Applications!$AM$2:$AM$293,Applications!$B$2:$B$293,A196) -> 0 | N196: =SUMIFS(Applications!$AK$2:$AK$293,Applications!$B$2:$B$293,A196) -> 0 | O196: =I196-J196 -> 0 | P196: =COUNTIFS(Applications!$B$2:$B$293,A196,Applications!$W$2:$W$293,"Low",Applications!$X$2:$X$293,"") -> 0 | Q196: =COUNTIFS(Applications!$B$2:$B$293,A196,Applications!$AH$2:$AH$293,"Past*")+COUNTIFS(Applications!$B$2:$B$293,A196,Applications!$AH$2:$AH$293,"No CIS*") -> 0 | S196: No | T196: =IF(OR(R196<>"",S196="Yes",P196>0,Q196>0),IF(U196="Yes","Resolved","Yes"),"No") -> No
A197: U-1419385 | B197: Latest upstream export | C197: €3.9m - Part 8 Housing Scheme, Limerick | D197: 48 - 50 Mary Street, Limerick | E197: Limerick City and Suburbs | F197: 52.666756 | G197: -8.6204433 | H197: Plans Submitted | I197: =COUNTIF(Applications!$B$2:$B$293,A197) -> 1 | J197: =COUNTIFS(Applications!$B$2:$B$293,A197,Applications!$Z$2:$Z$293,"Yes") -> 0 | K197: =SUMIFS(Applications!$AI$2:$AI$293,Applications!$B$2:$B$293,A197) -> 0 | L197: =SUMIFS(Applications!$AL$2:$AL$293,Applications!$B$2:$B$293,A197) -> 0 | M197: =SUMIFS(Applications!$AM$2:$AM$293,Applications!$B$2:$B$293,A197) -> 0 | N197: =SUMIFS(Applications!$AK$2:$AK$293,Applications!$B$2:$B$293,A197) -> 0 | O197: =I197-J197 -> 1 | P197: =COUNTIFS(Applications!$B$2:$B$293,A197,Applications!$W$2:$W$293,"Low",Applications!$X$2:$X$293,"") -> 0 | Q197: =COUNTIFS(Applications!$B$2:$B$293,A197,Applications!$AH$2:$AH$293,"Past*")+COUNTIFS(Applications!$B$2:$B$293,A197,Applications!$AH$2:$AH$293,"No CIS*") -> 0 | R197: P-1202244 (121m): €3.8m - Residential Development, Curry Lane, Commencement Expected, 30 units | S197: No | T197: =IF(OR(R197<>"",S197="Yes",P197>0,Q197>0),IF(U197="Yes","Resolved","Yes"),"No") -> Yes
A198: U-1419614 | B198: Latest upstream export | C198: €4.8m - Apartment Development, Limerick | D198: 48-50 Mary Street, Limerick | E198: Limerick City and Suburbs | F198: 52.667053 | G198: -8.6203801 | H198: Plans Submitted | I198: =COUNTIF(Applications!$B$2:$B$293,A198) -> 1 | J198: =COUNTIFS(Applications!$B$2:$B$293,A198,Applications!$Z$2:$Z$293,"Yes") -> 1 | K198: =SUMIFS(Applications!$AI$2:$AI$293,Applications!$B$2:$B$293,A198) -> 30 | L198: =SUMIFS(Applications!$AL$2:$AL$293,Applications!$B$2:$B$293,A198) -> 30 | M198: =SUMIFS(Applications!$AM$2:$AM$293,Applications!$B$2:$B$293,A198) -> 0 | N198: =SUMIFS(Applications!$AK$2:$AK$293,Applications!$B$2:$B$293,A198) -> 0 | O198: =I198-J198 -> 0 | P198: =COUNTIFS(Applications!$B$2:$B$293,A198,Applications!$W$2:$W$293,"Low",Applications!$X$2:$X$293,"") -> 1 | Q198: =COUNTIFS(Applications!$B$2:$B$293,A198,Applications!$AH$2:$AH$293,"Past*")+COUNTIFS(Applications!$B$2:$B$293,A198,Applications!$AH$2:$AH$293,"No CIS*") -> 0 | R198: P-1202244 (147m): €3.8m - Residential Development, Curry Lane, Commencement Expected, 30 units; U-1419385 (33m): €3.9m - Part 8 Housing Scheme, Limerick, Plans Submitted, 30 units | S198: No | T198: =IF(OR(R198<>"",S198="Yes",P198>0,Q198>0),IF(U198="Yes","Resolved","Yes"),"No") -> Yes
A199: U-1419395 | B199: Latest upstream export | C199: €2.1m - Part 8 Residential Development, Limerick | D199: Ros Mor, Crossagalla, Kilmallock Road, Limerick | E199: Kilmallock | F199: 52.648907 | G199: -8.5979347 | H199: Plans Submitted | I199: =COUNTIF(Applications!$B$2:$B$293,A199) -> 1 | J199: =COUNTIFS(Applications!$B$2:$B$293,A199,Applications!$Z$2:$Z$293,"Yes") -> 1 | K199: =SUMIFS(Applications!$AI$2:$AI$293,Applications!$B$2:$B$293,A199) -> 12 | L199: =SUMIFS(Applications!$AL$2:$AL$293,Applications!$B$2:$B$293,A199) -> 12 | M199: =SUMIFS(Applications!$AM$2:$AM$293,Applications!$B$2:$B$293,A199) -> 0 | N199: =SUMIFS(Applications!$AK$2:$AK$293,Applications!$B$2:$B$293,A199) -> 0 | O199: =I199-J199 -> 0 | P199: =COUNTIFS(Applications!$B$2:$B$293,A199,Applications!$W$2:$W$293,"Low",Applications!$X$2:$X$293,"") -> 0 | Q199: =COUNTIFS(Applications!$B$2:$B$293,A199,Applications!$AH$2:$AH$293,"Past*")+COUNTIFS(Applications!$B$2:$B$293,A199,Applications!$AH$2:$AH$293,"No CIS*") -> 0 | S199: No | T199: =IF(OR(R199<>"",S199="Yes",P199>0,Q199>0),IF(U199="Yes","Resolved","Yes"),"No") -> No
A200: U-1425841 | B200: Latest upstream export | C200: €14m - Residential Development, Limerick | D200: Toppins Field between O'Donoghue Avenue, John Carew Road, Limerick | E200: Limerick City and Suburbs | F200: 52.647254 | G200: -8.6222003 | H200: Plans Submitted | I200: =COUNTIF(Applications!$B$2:$B$293,A200) -> 1 | J200: =COUNTIFS(Applications!$B$2:$B$293,A200,Applications!$Z$2:$Z$293,"Yes") -> 1 | K200: =SUMIFS(Applications!$AI$2:$AI$293,Applications!$B$2:$B$293,A200) -> 57 | L200: =SUMIFS(Applications!$AL$2:$AL$293,Applications!$B$2:$B$293,A200) -> 57 | M200: =SUMIFS(Applications!$AM$2:$AM$293,Applications!$B$2:$B$293,A200) -> 0 | N200: =SUMIFS(Applications!$AK$2:$AK$293,Applications!$B$2:$B$293,A200) -> 0 | O200: =I200-J200 -> 0 | P200: =COUNTIFS(Applications!$B$2:$B$293,A200,Applications!$W$2:$W$293,"Low",Applications!$X$2:$X$293,"") -> 0 | Q200: =COUNTIFS(Applications!$B$2:$B$293,A200,Applications!$AH$2:$AH$293,"Past*")+COUNTIFS(Applications!$B$2:$B$293,A200,Applications!$AH$2:$AH$293,"No CIS*") -> 0 | S200: No | T200: =IF(OR(R200<>"",S200="Yes",P200>0,Q200>0),IF(U200="Yes","Resolved","Yes"),"No") -> No
A201: U-1421134 | B201: Latest upstream export | C201: €31m - Large Residential Development, Newcastle West | D201: South of the Woodfield Manor development, and extending to Killeline to the west, Newcastle West | E201: Newcastle West | F201: 52.440627 | G201: -9.0479094 | H201: Plans Submitted | I201: =COUNTIF(Applications!$B$2:$B$293,A201) -> 1 | J201: =COUNTIFS(Applications!$B$2:$B$293,A201,Applications!$Z$2:$Z$293,"Yes") -> 0 | K201: =SUMIFS(Applications!$AI$2:$AI$293,Applications!$B$2:$B$293,A201) -> 0 | L201: =SUMIFS(Applications!$AL$2:$AL$293,Applications!$B$2:$B$293,A201) -> 0 | M201: =SUMIFS(Applications!$AM$2:$AM$293,Applications!$B$2:$B$293,A201) -> 0 | N201: =SUMIFS(Applications!$AK$2:$AK$293,Applications!$B$2:$B$293,A201) -> 0 | O201: =I201-J201 -> 1 | P201: =COUNTIFS(Applications!$B$2:$B$293,A201,Applications!$W$2:$W$293,"Low",Applications!$X$2:$X$293,"") -> 0 | Q201: =COUNTIFS(Applications!$B$2:$B$293,A201,Applications!$AH$2:$AH$293,"Past*")+COUNTIFS(Applications!$B$2:$B$293,A201,Applications!$AH$2:$AH$293,"No CIS*") -> 0 | S201: No | T201: =IF(OR(R201<>"",S201="Yes",P201>0,Q201>0),IF(U201="Yes","Resolved","Yes"),"No") -> No
A202: U-1422361 | B202: Latest upstream export | C202: €1.8m - 7 House/Apartment/Community Office, Feenagh | D202: Gortmore, Feenagh | E202: Other County Limerick | F202: 52.390146 | G202: -8.8795664 | H202: Plans Submitted | I202: =COUNTIF(Applications!$B$2:$B$293,A202) -> 1 | J202: =COUNTIFS(Applications!$B$2:$B$293,A202,Applications!$Z$2:$Z$293,"Yes") -> 1 | K202: =SUMIFS(Applications!$AI$2:$AI$293,Applications!$B$2:$B$293,A202) -> 8 | L202: =SUMIFS(Applications!$AL$2:$AL$293,Applications!$B$2:$B$293,A202) -> 8 | M202: =SUMIFS(Applications!$AM$2:$AM$293,Applications!$B$2:$B$293,A202) -> 0 | N202: =SUMIFS(Applications!$AK$2:$AK$293,Applications!$B$2:$B$293,A202) -> 0 | O202: =I202-J202 -> 0 | P202: =COUNTIFS(Applications!$B$2:$B$293,A202,Applications!$W$2:$W$293,"Low",Applications!$X$2:$X$293,"") -> 0 | Q202: =COUNTIFS(Applications!$B$2:$B$293,A202,Applications!$AH$2:$AH$293,"Past*")+COUNTIFS(Applications!$B$2:$B$293,A202,Applications!$AH$2:$AH$293,"No CIS*") -> 0 | S202: No | T202: =IF(OR(R202<>"",S202="Yes",P202>0,Q202>0),IF(U202="Yes","Resolved","Yes"),"No") -> No
A203: U-1424889 | B203: Latest upstream export | C203: €16m - Residential Development, Adare | D203: Barley Grove and the Adare Pitch and Putt Club, Rathkeale Road, Killarney Road, Graige, Adare | E203: Adare | F203: 52.556857 | G203: -8.7955011 | H203: Plans Submitted | I203: =COUNTIF(Applications!$B$2:$B$293,A203) -> 1 | J203: =COUNTIFS(Applications!$B$2:$B$293,A203,Applications!$Z$2:$Z$293,"Yes") -> 0 | K203: =SUMIFS(Applications!$AI$2:$AI$293,Applications!$B$2:$B$293,A203) -> 0 | L203: =SUMIFS(Applications!$AL$2:$AL$293,Applications!$B$2:$B$293,A203) -> 0 | M203: =SUMIFS(Applications!$AM$2:$AM$293,Applications!$B$2:$B$293,A203) -> 0 | N203: =SUMIFS(Applications!$AK$2:$AK$293,Applications!$B$2:$B$293,A203) -> 0 | O203: =I203-J203 -> 1 | P203: =COUNTIFS(Applications!$B$2:$B$293,A203,Applications!$W$2:$W$293,"Low",Applications!$X$2:$X$293,"") -> 0 | Q203: =COUNTIFS(Applications!$B$2:$B$293,A203,Applications!$AH$2:$AH$293,"Past*")+COUNTIFS(Applications!$B$2:$B$293,A203,Applications!$AH$2:$AH$293,"No CIS*") -> 0 | S203: No | T203: =IF(OR(R203<>"",S203="Yes",P203>0,Q203>0),IF(U203="Yes","Resolved","Yes"),"No") -> No
A204: U-1446285 | B204: Latest upstream export | C204: €7.8m - Residential Development, Abbeyfeale | D204: Saint Ita's Road, Abbeyfeale West, Abbeyfeale | E204: Abbeyfeale | F204: 52.382129 | G204: -9.2983841 | H204: Plans Submitted | I204: =COUNTIF(Applications!$B$2:$B$293,A204) -> 1 | J204: =COUNTIFS(Applications!$B$2:$B$293,A204,Applications!$Z$2:$Z$293,"Yes") -> 1 | K204: =SUMIFS(Applications!$AI$2:$AI$293,Applications!$B$2:$B$293,A204) -> 48 | L204: =SUMIFS(Applications!$AL$2:$AL$293,Applications!$B$2:$B$293,A204) -> 48 | M204: =SUMIFS(Applications!$AM$2:$AM$293,Applications!$B$2:$B$293,A204) -> 0 | N204: =SUMIFS(Applications!$AK$2:$AK$293,Applications!$B$2:$B$293,A204) -> 0 | O204: =I204-J204 -> 0 | P204: =COUNTIFS(Applications!$B$2:$B$293,A204,Applications!$W$2:$W$293,"Low",Applications!$X$2:$X$293,"") -> 1 | Q204: =COUNTIFS(Applications!$B$2:$B$293,A204,Applications!$AH$2:$AH$293,"Past*")+COUNTIFS(Applications!$B$2:$B$293,A204,Applications!$AH$2:$AH$293,"No CIS*") -> 0 | R204: U-1165485 (11m): €11.3m - Residential Development , Contract Awarded, 68 units | S204: No | T204: =IF(OR(R204<>"",S204="Yes",P204>0,Q204>0),IF(U204="Yes","Resolved","Yes"),"No") -> Yes
A205: U-1439022 | B205: Latest upstream export | C205: €1.4m - 6 Houses, Caherdavin | D205: Knockhil, Ferndale, Caherdavin | E205: Limerick City and Suburbs | F205: 52.673219 | G205: -8.6711213 | H205: Plans Submitted | I205: =COUNTIF(Applications!$B$2:$B$293,A205) -> 1 | J205: =COUNTIFS(Applications!$B$2:$B$293,A205,Applications!$Z$2:$Z$293,"Yes") -> 1 | K205: =SUMIFS(Applications!$AI$2:$AI$293,Applications!$B$2:$B$293,A205) -> 6 | L205: =SUMIFS(Applications!$AL$2:$AL$293,Applications!$B$2:$B$293,A205) -> 6 | M205: =SUMIFS(Applications!$AM$2:$AM$293,Applications!$B$2:$B$293,A205) -> 0 | N205: =SUMIFS(Applications!$AK$2:$AK$293,Applications!$B$2:$B$293,A205) -> 0 | O205: =I205-J205 -> 0 | P205: =COUNTIFS(Applications!$B$2:$B$293,A205,Applications!$W$2:$W$293,"Low",Applications!$X$2:$X$293,"") -> 0 | Q205: =COUNTIFS(Applications!$B$2:$B$293,A205,Applications!$AH$2:$AH$293,"Past*")+COUNTIFS(Applications!$B$2:$B$293,A205,Applications!$AH$2:$AH$293,"No CIS*") -> 0 | R205: SG-012 (141m): €16m - Residential Development, Ennis Road, Commencement Expected, 92 units; SG-012 (148m): €15m - EOD Residential Development, Permission Granted, 0 units | S205: No | T205: =IF(OR(R205<>"",S205="Yes",P205>0,Q205>0),IF(U205="Yes","Resolved","Yes"),"No") -> Yes
A206: U-1438136 | B206: Latest upstream export | C206: €883k - Part 8 - 6 Apartments, Corbally | D206: Meadow Brook, Mill Road, Corbally | E206: Limerick City and Suburbs | F206: 52.68509 | G206: -8.6231185 | H206: Plans Submitted | I206: =COUNTIF(Applications!$B$2:$B$293,A206) -> 1 | J206: =COUNTIFS(Applications!$B$2:$B$293,A206,Applications!$Z$2:$Z$293,"Yes") -> 1 | K206: =SUMIFS(Applications!$AI$2:$AI$293,Applications!$B$2:$B$293,A206) -> 6 | L206: =SUMIFS(Applications!$AL$2:$AL$293,Applications!$B$2:$B$293,A206) -> 6 | M206: =SUMIFS(Applications!$AM$2:$AM$293,Applications!$B$2:$B$293,A206) -> 0 | N206: =SUMIFS(Applications!$AK$2:$AK$293,Applications!$B$2:$B$293,A206) -> 0 | O206: =I206-J206 -> 0 | P206: =COUNTIFS(Applications!$B$2:$B$293,A206,Applications!$W$2:$W$293,"Low",Applications!$X$2:$X$293,"") -> 0 | Q206: =COUNTIFS(Applications!$B$2:$B$293,A206,Applications!$AH$2:$AH$293,"Past*")+COUNTIFS(Applications!$B$2:$B$293,A206,Applications!$AH$2:$AH$293,"No CIS*") -> 0 | S206: No | T206: =IF(OR(R206<>"",S206="Yes",P206>0,Q206>0),IF(U206="Yes","Resolved","Yes"),"No") -> No
A207: U-1431510 | B207: Latest upstream export | C207: €3.2m - Residential Development, Thomondgate | D207: The Rock, 40 Quarry Road, Thomondgate | E207: Limerick City and Suburbs | F207: 52.673609 | G207: -8.632195 | H207: Plans Submitted | I207: =COUNTIF(Applications!$B$2:$B$293,A207) -> 1 | J207: =COUNTIFS(Applications!$B$2:$B$293,A207,Applications!$Z$2:$Z$293,"Yes") -> 1 | K207: =SUMIFS(Applications!$AI$2:$AI$293,Applications!$B$2:$B$293,A207) -> 13 | L207: =SUMIFS(Applications!$AL$2:$AL$293,Applications!$B$2:$B$293,A207) -> 13 | M207: =SUMIFS(Applications!$AM$2:$AM$293,Applications!$B$2:$B$293,A207) -> 0 | N207: =SUMIFS(Applications!$AK$2:$AK$293,Applications!$B$2:$B$293,A207) -> 0 | O207: =I207-J207 -> 0 | P207: =COUNTIFS(Applications!$B$2:$B$293,A207,Applications!$W$2:$W$293,"Low",Applications!$X$2:$X$293,"") -> 0 | Q207: =COUNTIFS(Applications!$B$2:$B$293,A207,Applications!$AH$2:$AH$293,"Past*")+COUNTIFS(Applications!$B$2:$B$293,A207,Applications!$AH$2:$AH$293,"No CIS*") -> 0 | S207: No | T207: =IF(OR(R207<>"",S207="Yes",P207>0,Q207>0),IF(U207="Yes","Resolved","Yes"),"No") -> No
A208: U-1433772 | B208: Latest upstream export | C208: €3m - Part 8 Residential Development, Limerick | D208: Quarry Road, Thomondgate, Limerick City | E208: Limerick City and Suburbs | F208: 52.67203 | G208: -8.6307358 | H208: Plans Submitted | I208: =COUNTIF(Applications!$B$2:$B$293,A208) -> 1 | J208: =COUNTIFS(Applications!$B$2:$B$293,A208,Applications!$Z$2:$Z$293,"Yes") -> 1 | K208: =SUMIFS(Applications!$AI$2:$AI$293,Applications!$B$2:$B$293,A208) -> 13 | L208: =SUMIFS(Applications!$AL$2:$AL$293,Applications!$B$2:$B$293,A208) -> 13 | M208: =SUMIFS(Applications!$AM$2:$AM$293,Applications!$B$2:$B$293,A208) -> 0 | N208: =SUMIFS(Applications!$AK$2:$AK$293,Applications!$B$2:$B$293,A208) -> 0 | O208: =I208-J208 -> 0 | P208: =COUNTIFS(Applications!$B$2:$B$293,A208,Applications!$W$2:$W$293,"Low",Applications!$X$2:$X$293,"") -> 1 | Q208: =COUNTIFS(Applications!$B$2:$B$293,A208,Applications!$AH$2:$AH$293,"Past*")+COUNTIFS(Applications!$B$2:$B$293,A208,Applications!$AH$2:$AH$293,"No CIS*") -> 0 | R208: P-1384661 (38m): €1.3m - 6 Apartments, Thomondgate, On Site, 7 units | S208: No | T208: =IF(OR(R208<>"",S208="Yes",P208>0,Q208>0),IF(U208="Yes","Resolved","Yes"),"No") -> Yes
A209: U-1360912 | B209: Latest upstream export | C209: €4.3m - Apartment Development, Newcastle West | D209: Former Olympic Ballroom Site, Gortboy, Newcastle West | E209: Newcastle West | F209: 52.453465 | G209: -9.0541313 | H209: Plans Submitted | I209: =COUNTIF(Applications!$B$2:$B$293,A209) -> 1 | J209: =COUNTIFS(Applications!$B$2:$B$293,A209,Applications!$Z$2:$Z$293,"Yes") -> 1 | K209: =SUMIFS(Applications!$AI$2:$AI$293,Applications!$B$2:$B$293,A209) -> 30 | L209: =SUMIFS(Applications!$AL$2:$AL$293,Applications!$B$2:$B$293,A209) -> 30 | M209: =SUMIFS(Applications!$AM$2:$AM$293,Applications!$B$2:$B$293,A209) -> 0 | N209: =SUMIFS(Applications!$AK$2:$AK$293,Applications!$B$2:$B$293,A209) -> 0 | O209: =I209-J209 -> 0 | P209: =COUNTIFS(Applications!$B$2:$B$293,A209,Applications!$W$2:$W$293,"Low",Applications!$X$2:$X$293,"") -> 0 | Q209: =COUNTIFS(Applications!$B$2:$B$293,A209,Applications!$AH$2:$AH$293,"Past*")+COUNTIFS(Applications!$B$2:$B$293,A209,Applications!$AH$2:$AH$293,"No CIS*") -> 0 | S209: No | T209: =IF(OR(R209<>"",S209="Yes",P209>0,Q209>0),IF(U209="Yes","Resolved","Yes"),"No") -> No
A210: U-1438128 | B210: Latest upstream export | C210: €2.9m - 2 Transitional Houses/Extension, Bruree | D210: Bruree House, Garroose, Bruree | E210: Other County Limerick | F210: 52.416788 | G210: -8.6613033 | H210: Plans Submitted | I210: =COUNTIF(Applications!$B$2:$B$293,A210) -> 1 | J210: =COUNTIFS(Applications!$B$2:$B$293,A210,Applications!$Z$2:$Z$293,"Yes") -> 0 | K210: =SUMIFS(Applications!$AI$2:$AI$293,Applications!$B$2:$B$293,A210) -> 0 | L210: =SUMIFS(Applications!$AL$2:$AL$293,Applications!$B$2:$B$293,A210) -> 0 | M210: =SUMIFS(Applications!$AM$2:$AM$293,Applications!$B$2:$B$293,A210) -> 0 | N210: =SUMIFS(Applications!$AK$2:$AK$293,Applications!$B$2:$B$293,A210) -> 0 | O210: =I210-J210 -> 1 | P210: =COUNTIFS(Applications!$B$2:$B$293,A210,Applications!$W$2:$W$293,"Low",Applications!$X$2:$X$293,"") -> 0 | Q210: =COUNTIFS(Applications!$B$2:$B$293,A210,Applications!$AH$2:$AH$293,"Past*")+COUNTIFS(Applications!$B$2:$B$293,A210,Applications!$AH$2:$AH$293,"No CIS*") -> 0 | S210: No | T210: =IF(OR(R210<>"",S210="Yes",P210>0,Q210>0),IF(U210="Yes","Resolved","Yes"),"No") -> No
A211: U-1442414 | B211: Latest upstream export | C211: €540k - 4 Apartments, Limerick | D211: 1 - 4 Parnell Stree, Limerick | E211: Limerick City and Suburbs | F211: 52.660573 | G211: -8.6240409 | H211: Plans Submitted | I211: =COUNTIF(Applications!$B$2:$B$293,A211) -> 1 | J211: =COUNTIFS(Applications!$B$2:$B$293,A211,Applications!$Z$2:$Z$293,"Yes") -> 1 | K211: =SUMIFS(Applications!$AI$2:$AI$293,Applications!$B$2:$B$293,A211) -> 4 | L211: =SUMIFS(Applications!$AL$2:$AL$293,Applications!$B$2:$B$293,A211) -> 4 | M211: =SUMIFS(Applications!$AM$2:$AM$293,Applications!$B$2:$B$293,A211) -> 0 | N211: =SUMIFS(Applications!$AK$2:$AK$293,Applications!$B$2:$B$293,A211) -> 0 | O211: =I211-J211 -> 0 | P211: =COUNTIFS(Applications!$B$2:$B$293,A211,Applications!$W$2:$W$293,"Low",Applications!$X$2:$X$293,"") -> 0 | Q211: =COUNTIFS(Applications!$B$2:$B$293,A211,Applications!$AH$2:$AH$293,"Past*")+COUNTIFS(Applications!$B$2:$B$293,A211,Applications!$AH$2:$AH$293,"No CIS*") -> 0 | R211: SG-026 (113m): €5.8m - Apartment/Retail Development, Limeric, Permission Granted, 37 units; SG-026 (114m): €7m - Residential/Commercial Development, Lim, Permission Granted, 37 units | S211: No | T211: =IF(OR(R211<>"",S211="Yes",P211>0,Q211>0),IF(U211="Yes","Resolved","Yes"),"No") -> Yes
A212: U-1439374 | B212: Latest upstream export | C212: €14m - Large Residential Development, Castletroy | D212: Golf Links Road, Castletroy | E212: Limerick City and Suburbs | F212: 52.653023 | G212: -8.5604169 | H212: Plans Submitted | I212: =COUNTIF(Applications!$B$2:$B$293,A212) -> 1 | J212: =COUNTIFS(Applications!$B$2:$B$293,A212,Applications!$Z$2:$Z$293,"Yes") -> 0 | K212: =SUMIFS(Applications!$AI$2:$AI$293,Applications!$B$2:$B$293,A212) -> 0 | L212: =SUMIFS(Applications!$AL$2:$AL$293,Applications!$B$2:$B$293,A212) -> 0 | M212: =SUMIFS(Applications!$AM$2:$AM$293,Applications!$B$2:$B$293,A212) -> 0 | N212: =SUMIFS(Applications!$AK$2:$AK$293,Applications!$B$2:$B$293,A212) -> 0 | O212: =I212-J212 -> 1 | P212: =COUNTIFS(Applications!$B$2:$B$293,A212,Applications!$W$2:$W$293,"Low",Applications!$X$2:$X$293,"") -> 0 | Q212: =COUNTIFS(Applications!$B$2:$B$293,A212,Applications!$AH$2:$AH$293,"Past*")+COUNTIFS(Applications!$B$2:$B$293,A212,Applications!$AH$2:$AH$293,"No CIS*") -> 0 | R212: U-1319159 (34m): €22m - Golf Links Road LRD, Monaleen, On Site, 122 units | S212: No | T212: =IF(OR(R212<>"",S212="Yes",P212>0,Q212>0),IF(U212="Yes","Resolved","Yes"),"No") -> Yes
A213: U-1441321 | B213: Latest upstream export | C213: €3.2m - Change of Use to Apartment Development, Mungret | D213: The Old Girls' School, Baunacloka, Mungret | E213: Mungret | F213: 52.634882 | G213: -8.6779096 | H213: Plans Submitted | I213: =COUNTIF(Applications!$B$2:$B$293,A213) -> 1 | J213: =COUNTIFS(Applications!$B$2:$B$293,A213,Applications!$Z$2:$Z$293,"Yes") -> 0 | K213: =SUMIFS(Applications!$AI$2:$AI$293,Applications!$B$2:$B$293,A213) -> 0 | L213: =SUMIFS(Applications!$AL$2:$AL$293,Applications!$B$2:$B$293,A213) -> 0 | M213: =SUMIFS(Applications!$AM$2:$AM$293,Applications!$B$2:$B$293,A213) -> 0 | N213: =SUMIFS(Applications!$AK$2:$AK$293,Applications!$B$2:$B$293,A213) -> 0 | O213: =I213-J213 -> 1 | P213: =COUNTIFS(Applications!$B$2:$B$293,A213,Applications!$W$2:$W$293,"Low",Applications!$X$2:$X$293,"") -> 0 | Q213: =COUNTIFS(Applications!$B$2:$B$293,A213,Applications!$AH$2:$AH$293,"Past*")+COUNTIFS(Applications!$B$2:$B$293,A213,Applications!$AH$2:$AH$293,"No CIS*") -> 0 | R213: P-1306162 (122m): €11.3m - Housing Development, Mungret, On Site, 66 units; SG-001 (149m): €16.5m - Residential Development, Mungret, On Site, 96 units | S213: No | T213: =IF(OR(R213<>"",S213="Yes",P213>0,Q213>0),IF(U213="Yes","Resolved","Yes"),"No") -> Yes
A214: U-1417205 | B214: Latest upstream export | C214: €1.4m - Architect Led Integrated Design Team for College Avenue Infill Housing Scheme, Moyross | D214: College Avenue, Moyross | E214: Limerick City and Suburbs | F214: 52.680243 | G214: -8.6482002 | H214: Contract Awarded | I214: =COUNTIF(Applications!$B$2:$B$293,A214) -> 1 | J214: =COUNTIFS(Applications!$B$2:$B$293,A214,Applications!$Z$2:$Z$293,"Yes") -> 1 | K214: =SUMIFS(Applications!$AI$2:$AI$293,Applications!$B$2:$B$293,A214) -> 0 | L214: =SUMIFS(Applications!$AL$2:$AL$293,Applications!$B$2:$B$293,A214) -> 0 | M214: =SUMIFS(Applications!$AM$2:$AM$293,Applications!$B$2:$B$293,A214) -> 0 | N214: =SUMIFS(Applications!$AK$2:$AK$293,Applications!$B$2:$B$293,A214) -> 0 | O214: =I214-J214 -> 0 | P214: =COUNTIFS(Applications!$B$2:$B$293,A214,Applications!$W$2:$W$293,"Low",Applications!$X$2:$X$293,"") -> 0 | Q214: =COUNTIFS(Applications!$B$2:$B$293,A214,Applications!$AH$2:$AH$293,"Past*")+COUNTIFS(Applications!$B$2:$B$293,A214,Applications!$AH$2:$AH$293,"No CIS*") -> 0 | S214: No | T214: =IF(OR(R214<>"",S214="Yes",P214>0,Q214>0),IF(U214="Yes","Resolved","Yes"),"No") -> No
A215: U-1422145 | B215: Latest upstream export | C215: €719k - Architect Led Integrated Design Team Services for 23 Residential Units, Limerick | D215: St.Mary's Park, King's Island, Limerick | E215: Limerick City and Suburbs | F215: 52.671 | G215: -8.625 | H215: Contract Awarded | I215: =COUNTIF(Applications!$B$2:$B$293,A215) -> 1 | J215: =COUNTIFS(Applications!$B$2:$B$293,A215,Applications!$Z$2:$Z$293,"Yes") -> 1 | K215: =SUMIFS(Applications!$AI$2:$AI$293,Applications!$B$2:$B$293,A215) -> 23 | L215: =SUMIFS(Applications!$AL$2:$AL$293,Applications!$B$2:$B$293,A215) -> 23 | M215: =SUMIFS(Applications!$AM$2:$AM$293,Applications!$B$2:$B$293,A215) -> 0 | N215: =SUMIFS(Applications!$AK$2:$AK$293,Applications!$B$2:$B$293,A215) -> 0 | O215: =I215-J215 -> 0 | P215: =COUNTIFS(Applications!$B$2:$B$293,A215,Applications!$W$2:$W$293,"Low",Applications!$X$2:$X$293,"") -> 1 | Q215: =COUNTIFS(Applications!$B$2:$B$293,A215,Applications!$AH$2:$AH$293,"Past*")+COUNTIFS(Applications!$B$2:$B$293,A215,Applications!$AH$2:$AH$293,"No CIS*") -> 0 | R215: P-1054214 (45m): €6m - Residential Development, King's Island, Permission Granted, 27 units | S215: No | T215: =IF(OR(R215<>"",S215="Yes",P215>0,Q215>0),IF(U215="Yes","Resolved","Yes"),"No") -> Yes
A216: U-1424651 | B216: Latest upstream export | C216: €20m - Council Housing Programme 2026 - 2030, Limerick | D216: throughout Limerick City and Limerick County, Limerick | E216: Limerick City and Suburbs | H216: Tender | I216: =COUNTIF(Applications!$B$2:$B$293,A216) -> 1 | J216: =COUNTIFS(Applications!$B$2:$B$293,A216,Applications!$Z$2:$Z$293,"Yes") -> 1 | K216: =SUMIFS(Applications!$AI$2:$AI$293,Applications!$B$2:$B$293,A216) -> 0 | L216: =SUMIFS(Applications!$AL$2:$AL$293,Applications!$B$2:$B$293,A216) -> 0 | M216: =SUMIFS(Applications!$AM$2:$AM$293,Applications!$B$2:$B$293,A216) -> 0 | N216: =SUMIFS(Applications!$AK$2:$AK$293,Applications!$B$2:$B$293,A216) -> 0 | O216: =I216-J216 -> 0 | P216: =COUNTIFS(Applications!$B$2:$B$293,A216,Applications!$W$2:$W$293,"Low",Applications!$X$2:$X$293,"") -> 0 | Q216: =COUNTIFS(Applications!$B$2:$B$293,A216,Applications!$AH$2:$AH$293,"Past*")+COUNTIFS(Applications!$B$2:$B$293,A216,Applications!$AH$2:$AH$293,"No CIS*") -> 0 | S216: No | T216: =IF(OR(R216<>"",S216="Yes",P216>0,Q216>0),IF(U216="Yes","Resolved","Yes"),"No") -> No
A217: U-1438055 | B217: Latest upstream export | C217: €1.5m - Multi-Party Framework for Maintenance Repairs and Replacement of Heating Systems, Limerick | D217: Limerick City and County Council, Limerick | E217: Limerick City and Suburbs | H217: Tender | I217: =COUNTIF(Applications!$B$2:$B$293,A217) -> 1 | J217: =COUNTIFS(Applications!$B$2:$B$293,A217,Applications!$Z$2:$Z$293,"Yes") -> 1 | K217: =SUMIFS(Applications!$AI$2:$AI$293,Applications!$B$2:$B$293,A217) -> 0 | L217: =SUMIFS(Applications!$AL$2:$AL$293,Applications!$B$2:$B$293,A217) -> 0 | M217: =SUMIFS(Applications!$AM$2:$AM$293,Applications!$B$2:$B$293,A217) -> 0 | N217: =SUMIFS(Applications!$AK$2:$AK$293,Applications!$B$2:$B$293,A217) -> 0 | O217: =I217-J217 -> 0 | P217: =COUNTIFS(Applications!$B$2:$B$293,A217,Applications!$W$2:$W$293,"Low",Applications!$X$2:$X$293,"") -> 0 | Q217: =COUNTIFS(Applications!$B$2:$B$293,A217,Applications!$AH$2:$AH$293,"Past*")+COUNTIFS(Applications!$B$2:$B$293,A217,Applications!$AH$2:$AH$293,"No CIS*") -> 0 | S217: No | T217: =IF(OR(R217<>"",S217="Yes",P217>0,Q217>0),IF(U217="Yes","Resolved","Yes"),"No") -> No

Sheet Review Queue
A1: # | B1: Site ID | C1: Site / Project Heading | D1: Settlement | E1: Most Advanced Stage | F1: Counted Units (live) | G1: Issues (at build) | H1: Overlap Detail | I1: Review Status (live)
A2: 1 | B2: SG-008 | C2: €4.6m - Residential Development | D2: Limerick City and Suburbs | E2: Part Complete | F2: =IFERROR(INDEX(Sites!$K$2:$K$217,MATCH($B2,Sites!$A$2:$A$217,0)),"") -> 607 | G2: 6 low-confidence counted application(s): 181104 (Additional application on site, 99), 181105 (Additional application on site, 23), 19547 (Additional application on site, 90), 191236 (Additional application on site, 92), 211152 (Additional application on site, 105), 211400 (Additional application on site, 98) | Auto link to check: 20256 superseded 21350; 21350 replaces earlier 20256 | 19547 past expiry (27/05/2025) | Low-confidence grouping in source workbook | I2: =IFERROR(INDEX(Sites!$T$2:$T$217,MATCH($B2,Sites!$A$2:$A$217,0)),"") -> Yes
A3: 2 | B3: SG-020 | C3: €47m - The Mungret Project | D3: Mungret | E3: On Site | F3: =IFERROR(INDEX(Sites!$K$2:$K$217,MATCH($B3,Sites!$A$2:$A$217,0)),"") -> 419 | G3: 1 low-confidence counted application(s): 2561231 (Additional application on site, 169) | Low-confidence grouping in source workbook | I3: =IFERROR(INDEX(Sites!$T$2:$T$217,MATCH($B3,Sites!$A$2:$A$217,0)),"") -> Yes
A4: 3 | B4: SG-027 | C4: €21m - Residential Development, Old Cratloe Road | D4: Other County Limerick | E4: On Site | F4: =IFERROR(INDEX(Sites!$K$2:$K$217,MATCH($B4,Sites!$A$2:$A$217,0)),"") -> 362 | G4: 4 low-confidence counted application(s): 22917 (Additional application on site, 12), 22959 (Additional application on site, 98), 221114 (Additional application on site, 54), 2460032 (Additional application on site, 99) | 211800 no CIS update since 05/2024 | 22917 no CIS update since 08/2023 | Low-confidence grouping in source workbook | I4: =IFERROR(INDEX(Sites!$T$2:$T$217,MATCH($B4,Sites!$A$2:$A$217,0)),"") -> Yes
A5: 4 | B5: SG-004 | C5: €6.3m - Residential Development, Patrickswell | D5: Patrickswell | E5: On Site | F5: =IFERROR(INDEX(Sites!$K$2:$K$217,MATCH($B5,Sites!$A$2:$A$217,0)),"") -> 314 | G5: 9 low-confidence counted application(s): 19689 (Additional application on site, 9), 20281 (Additional application on site, 36), 21873 (Additional application on site, 9), 228017 (Additional application on site, 24), Part 8 - 1248404 (Additional application on site, 24), 2560156 (Additional application on site, 63), 2560633 (Additional application on site, 6), 2560653 (Additional application on site, 40), 2561228 (Additional application on site, 54) | 18346 past expiry (22/10/2023) | 20281 past expiry (01/12/2025) | Part 8 - 1248404 no CIS update since 03/2023 | Low-confidence grouping in source workbook | I5: =IFERROR(INDEX(Sites!$T$2:$T$217,MATCH($B5,Sites!$A$2:$A$217,0)),"") -> Yes
A6: 5 | B6: U-1412002 | C6: €95m - Dock Road LRD, Limerick | D6: Limerick City and Suburbs | E6: Tender | F6: =IFERROR(INDEX(Sites!$K$2:$K$217,MATCH($B6,Sites!$A$2:$A$217,0)),"") -> 285 | G6: Possible overlap with nearby record | H6: U-1250272 (110m): €6.5m - Apartment Development, Limerick, Permission Granted, 29 units | I6: =IFERROR(INDEX(Sites!$T$2:$T$217,MATCH($B6,Sites!$A$2:$A$217,0)),"") -> Yes
A7: 6 | B7: SG-013 | C7: €521k - 8 Houses | D7: Mungret | E7: Part Complete | F7: =IFERROR(INDEX(Sites!$K$2:$K$217,MATCH($B7,Sites!$A$2:$A$217,0)),"") -> 273 | G7: 4 low-confidence counted application(s): 201195 (Additional application on site, 66), 21532 (Additional application on site, 7), 211217 (Additional application on site, 101), 211216 (Additional application on site, 99) | Auto link to check: 2460578 amendment within parent 211217 | Low-confidence grouping in source workbook | I7: =IFERROR(INDEX(Sites!$T$2:$T$217,MATCH($B7,Sites!$A$2:$A$217,0)),"") -> Yes
A8: 7 | B8: SG-024 | C8: €3.7m - Ardhú Apartments Refurbishment, Ennis Road | D8: Other County Limerick | E8: On Site | F8: =IFERROR(INDEX(Sites!$K$2:$K$217,MATCH($B8,Sites!$A$2:$A$217,0)),"") -> 232 | G8: 1 low-confidence counted application(s): 217025 (Extension of duration (parent not in CIS), 65) | Auto link to check: 23557 additional phase 217025 | Low-confidence grouping in source workbook | I8: =IFERROR(INDEX(Sites!$T$2:$T$217,MATCH($B8,Sites!$A$2:$A$217,0)),"") -> Yes
A9: 8 | B9: SG-019 | C9: €44m - Residential Development, Castletroy | D9: Limerick City and Suburbs | E9: On Site | F9: =IFERROR(INDEX(Sites!$K$2:$K$217,MATCH($B9,Sites!$A$2:$A$217,0)),"") -> 227 | G9: 2 low-confidence counted application(s): 211475 (Additional application on site, 23), 2561323 (Additional application on site, 4) | Low-confidence grouping in source workbook | I9: =IFERROR(INDEX(Sites!$T$2:$T$217,MATCH($B9,Sites!$A$2:$A$217,0)),"") -> Yes
A10: 9 | B10: SG-001 | C10: €18.9m - Housing Development | D10: Mungret | E10: On Site | F10: =IFERROR(INDEX(Sites!$K$2:$K$217,MATCH($B10,Sites!$A$2:$A$217,0)),"") -> 192 | G10: 3 low-confidence counted application(s): 187001 (Extension of duration (parent not in CIS), 0), 201115 (Additional application on site, 96), 201114 (Additional application on site, 96) | 187001 no CIS update since 04/2018 | 201114 past expiry (26/05/2026) | Low-confidence grouping in source workbook | I10: =IFERROR(INDEX(Sites!$T$2:$T$217,MATCH($B10,Sites!$A$2:$A$217,0)),"") -> Yes
A11: 10 | B11: SG-015 | C11: €5m - Housing Development | D11: Rathkeale | E11: Permission Granted | F11: =IFERROR(INDEX(Sites!$K$2:$K$217,MATCH($B11,Sites!$A$2:$A$217,0)),"") -> 183 | G11: 1 low-confidence counted application(s): 22990 (Additional application on site, 99) | Auto link to check: 2360793 additional phase 22990; 2460304 additional phase 22990 | 198010 past expiry (27/01/2025) | 2460304 no CIS update since 06/2024 | Low-confidence grouping in source workbook | I11: =IFERROR(INDEX(Sites!$T$2:$T$217,MATCH($B11,Sites!$A$2:$A$217,0)),"") -> Yes
A12: 11 | B12: SG-005 | C12: €10m - Residential Development, Singland | D12: Other County Limerick | E12: On Site | F12: =IFERROR(INDEX(Sites!$K$2:$K$217,MATCH($B12,Sites!$A$2:$A$217,0)),"") -> 170 | G12: 1 low-confidence counted application(s): 181270 (Additional application on site, 37) | Low-confidence grouping in source workbook | I12: =IFERROR(INDEX(Sites!$T$2:$T$217,MATCH($B12,Sites!$A$2:$A$217,0)),"") -> Yes
A13: 12 | B13: SG-002 | C13: €4.8m - Residential Development, Castletroy | D13: Limerick City and Suburbs | E13: On Site | F13: =IFERROR(INDEX(Sites!$K$2:$K$217,MATCH($B13,Sites!$A$2:$A$217,0)),"") -> 151 | G13: 3 low-confidence counted application(s): 20361 (Additional application on site, 3), 21853 (Additional application on site, 2), 2560271 (Additional application on site, 114) | 1855 past expiry (03/07/2023) | 21853 no CIS update since 09/2023 | Low-confidence grouping in source workbook | Later application nearby: 20361 (06/05/2020, Granted, 3 units, in CIS) | I13: =IFERROR(INDEX(Sites!$T$2:$T$217,MATCH($B13,Sites!$A$2:$A$217,0)),"") -> Yes
A14: 13 | B14: P-1163033 | C14: €30m - Residential Development, Annacotty | D14: Annacotty | E14: Permission Granted | F14: =IFERROR(INDEX(Sites!$K$2:$K$217,MATCH($B14,Sites!$A$2:$A$217,0)),"") -> 137 | G14: ABPREF309999 past expiry (04/08/2026) | I14: =IFERROR(INDEX(Sites!$T$2:$T$217,MATCH($B14,Sites!$A$2:$A$217,0)),"") -> Yes
A15: 14 | B15: SG-003 | C15: €5.9m - Residential Development, Patrickswell | D15: Patrickswell | E15: Part Complete | F15: =IFERROR(INDEX(Sites!$K$2:$K$217,MATCH($B15,Sites!$A$2:$A$217,0)),"") -> 112 | G15: 2 low-confidence counted application(s): 181193 (Additional application on site, 58), 19444 (Additional application on site, 5) | Auto link to check: 257001 extension of duration 19444 | Low-confidence grouping in source workbook | I15: =IFERROR(INDEX(Sites!$T$2:$T$217,MATCH($B15,Sites!$A$2:$A$217,0)),"") -> Yes
A16: 15 | B16: SG-017 | C16: €8.9m - Mixed Use Development, 34-41 Catherine Street | D16: Other County Limerick | E16: Permission Granted | F16: =IFERROR(INDEX(Sites!$K$2:$K$217,MATCH($B16,Sites!$A$2:$A$217,0)),"") -> 100 | G16: 1 low-confidence counted application(s): 2561242 (Additional application on site, 76) | 20222 past expiry (05/01/2026) | Low-confidence grouping in source workbook | I16: =IFERROR(INDEX(Sites!$T$2:$T$217,MATCH($B16,Sites!$A$2:$A$217,0)),"") -> Yes
A17: 16 | B17: SG-012 | C17: €16m - Residential Development, Ennis Road | D17: Other County Limerick | E17: Commencement Expected | F17: =IFERROR(INDEX(Sites!$K$2:$K$217,MATCH($B17,Sites!$A$2:$A$217,0)),"") -> 92 | G17: Low-confidence grouping in source workbook | I17: =IFERROR(INDEX(Sites!$T$2:$T$217,MATCH($B17,Sites!$A$2:$A$217,0)),"") -> Yes
A18: 17 | B18: P-1242233 | C18: €11m - Residential Development, Limerick | D18: Other County Limerick | E18: Permission Granted | F18: =IFERROR(INDEX(Sites!$K$2:$K$217,MATCH($B18,Sites!$A$2:$A$217,0)),"") -> 86 | G18: 22817 no CIS update since 06/2023 | I18: =IFERROR(INDEX(Sites!$T$2:$T$217,MATCH($B18,Sites!$A$2:$A$217,0)),"") -> Yes
... A25: 24 | B25: SG-006 | C25: €3.4m - Residential Development, Mungret | D25: Mungret | E25: On Site | F25: =IFERROR(INDEX(Sites!$K$2:$K$217,MATCH($B25,Sites!$A$2:$A$217,0)),"") -> 54 | G25: 2 low-confidence counted application(s): 18465 (Additional phase, 25), 20467 (Additional phase, 29) | Low-confidence grouping in source workbook | I25: =IFERROR(INDEX(Sites!$T$2:$T$217,MATCH($B25,Sites!$A$2:$A$217,0)),"") -> Yes
A26: 25 | B26: U-1408292 | C26: €7m - Apartment Development, Limerick City | D26: Limerick City and Suburbs | E26: Permission Granted | F26: =IFERROR(INDEX(Sites!$K$2:$K$217,MATCH($B26,Sites!$A$2:$A$217,0)),"") -> 48 | G26: Possible overlap with nearby record | H26: P-1329797 (102m): €816k - 8 Apartment , Permission Granted, 8 units; P-1132789 (109m): €919k - Student Accommodation Development, Sa, Permission Granted, ? units | I26: =IFERROR(INDEX(Sites!$T$2:$T$217,MATCH($B26,Sites!$A$2:$A$217,0)),"") -> Yes
A27: 26 | B27: U-1446285 | C27: €7.8m - Residential Development, Abbeyfeale | D27: Abbeyfeale | E27: Plans Submitted | F27: =IFERROR(INDEX(Sites!$K$2:$K$217,MATCH($B27,Sites!$A$2:$A$217,0)),"") -> 48 | G27: 1 low-confidence counted application(s): 2660232 (Additional application on site, 48) | Possible overlap with nearby record | H27: U-1165485 (11m): €11.3m - Residential Development , Contract Awarded, 68 units | I27: =IFERROR(INDEX(Sites!$T$2:$T$217,MATCH($B27,Sites!$A$2:$A$217,0)),"") -> Yes
A28: 27 | B28: P-1265188 | C28: €10.4m - Residential Development, Thomondgate | D28: Other County Limerick | E28: Permission Granted | F28: =IFERROR(INDEX(Sites!$K$2:$K$217,MATCH($B28,Sites!$A$2:$A$217,0)),"") -> 46 | G28: 221400 no CIS update since 08/2024 | I28: =IFERROR(INDEX(Sites!$T$2:$T$217,MATCH($B28,Sites!$A$2:$A$217,0)),"") -> Yes
A29: 28 | B29: SG-035 | C29: €4.9m - Residential Development, Raheen | D29: Limerick City and Suburbs | E29: Permission Granted | F29: =IFERROR(INDEX(Sites!$K$2:$K$217,MATCH($B29,Sites!$A$2:$A$217,0)),"") -> 44 | G29: 1 low-confidence counted application(s): 2560425 (Additional application on site, 24) | Auto link to check: Part 8 - 1371977 replaces earlier 248161 | Low-confidence grouping in source workbook | I29: =IFERROR(INDEX(Sites!$T$2:$T$217,MATCH($B29,Sites!$A$2:$A$217,0)),"") -> Yes
A30: 29 | B30: U-1277663 | C30: €9m - Housing Development, Patrickswell | D30: Patrickswell | E30: Contract Awarded | F30: =IFERROR(INDEX(Sites!$K$2:$K$217,MATCH($B30,Sites!$A$2:$A$217,0)),"") -> 41 | G30: 1 low-confidence counted application(s): 2360144 (Additional application on site, 41) | Possible overlap with nearby record | H30: SG-003 (73m): €2.2m - Housing Development , On Site, 5 units; SG-003 (76m): €3.9m - EOD - Residential Development, Patric, On Site, 16 units | I30: =IFERROR(INDEX(Sites!$T$2:$T$217,MATCH($B30,Sites!$A$2:$A$217,0)),"") -> Yes
A31: 30 | B31: SG-029 | C31: €6m - Apartment Development, Limerick | D31: Other County Limerick | E31: On Site | F31: =IFERROR(INDEX(Sites!$K$2:$K$217,MATCH($B31,Sites!$A$2:$A$217,0)),"") -> 36 | G31: 1 low-confidence counted application(s): 228016 (Additional application on site, 36) | Low-confidence grouping in source workbook | I31: =IFERROR(INDEX(Sites!$T$2:$T$217,MATCH($B31,Sites!$A$2:$A$217,0)),"") -> Yes
A32: 31 | B32: SG-031 | C32: €5.2m - Residential Development, Limerick | D32: Other County Limerick | E32: Permission Granted | F32: =IFERROR(INDEX(Sites!$K$2:$K$217,MATCH($B32,Sites!$A$2:$A$217,0)),"") -> 32 | G32: 1 low-confidence counted application(s): Part 8 - 1264155 (Additional application on site, 8) | 221367 no CIS update since 08/2023 | Part 8 - 1264155 no CIS update since 12/2022 | Low-confidence grouping in source workbook | I32: =IFERROR(INDEX(Sites!$T$2:$T$217,MATCH($B32,Sites!$A$2:$A$217,0)),"") -> Yes
A33: 32 | B33: P-1225380 | C33: €18.8m - Nursing Home Development, Croom | D33: Other County Limerick | E33: Permission Granted | F33: =IFERROR(INDEX(Sites!$K$2:$K$217,MATCH($B33,Sites!$A$2:$A$217,0)),"") -> 32 | G33: 22410 no CIS update since 01/2023 | I33: =IFERROR(INDEX(Sites!$T$2:$T$217,MATCH($B33,Sites!$A$2:$A$217,0)),"") -> Yes
A34: 33 | B34: P-1258895 | C34: €4.9m - Residential Development, Newcastle West | D34: Newcastle West | E34: Permission Granted | F34: =IFERROR(INDEX(Sites!$K$2:$K$217,MATCH($B34,Sites!$A$2:$A$217,0)),"") -> 31 | G34: 228020 no CIS update since 02/2023 | I34: =IFERROR(INDEX(Sites!$T$2:$T$217,MATCH($B34,Sites!$A$2:$A$217,0)),"") -> Yes
A35: 34 | B35: U-1391659 | C35: €6.2m - Residential Development, Limerick | D35: Limerick City and Suburbs | E35: Contract Awarded | F35: =IFERROR(INDEX(Sites!$K$2:$K$217,MATCH($B35,Sites!$A$2:$A$217,0)),"") -> 31 | G35: Possible overlap with nearby record | H35: P-974045 (142m): €554k - 4 Houses , Complete, 4 units | I35: =IFERROR(INDEX(Sites!$T$2:$T$217,MATCH($B35,Sites!$A$2:$A$217,0)),"") -> Yes
A36: 35 | B36: P-1202244 | C36: €3.8m - Residential Development, Curry Lane | D36: Other County Limerick | E36: Commencement Expected | F36: =IFERROR(INDEX(Sites!$K$2:$K$217,MATCH($B36,Sites!$A$2:$A$217,0)),"") -> 30 | G36: 211640 no CIS update since 07/2024 | I36: =IFERROR(INDEX(Sites!$T$2:$T$217,MATCH($B36,Sites!$A$2:$A$217,0)),"") -> Yes
A37: 36 | B37: U-1254537 | C37: €5m - Apartment/Retail Development, Dooradoyle | D37: Limerick City and Suburbs | E37: Permission Granted | F37: =IFERROR(INDEX(Sites!$K$2:$K$217,MATCH($B37,Sites!$A$2:$A$217,0)),"") -> 30 | G37: 221107 no CIS update since 05/2023 | I37: =IFERROR(INDEX(Sites!$T$2:$T$217,MATCH($B37,Sites!$A$2:$A$217,0)),"") -> Yes
A38: 37 | B38: U-1393371 | C38: €4.8m - Mixed Use Development, Limerick | D38: Limerick City and Suburbs | E38: Permission Granted | F38: =IFERROR(INDEX(Sites!$K$2:$K$217,MATCH($B38,Sites!$A$2:$A$217,0)),"") -> 30 | G38: 1 low-confidence counted application(s): 2560169 (Additional application on site, 30) | Possible overlap with nearby record | H38: SG-025 (2m): €3.5m - Apartment Development, Limerick, Permission Granted, 14 units; SG-025 (145m): €1.4m - Retail Units/Apartments, Permission Granted, 8 units | I38: =IFERROR(INDEX(Sites!$T$2:$T$217,MATCH($B38,Sites!$A$2:$A$217,0)),"") -> Yes
A39: 38 | B39: U-1419614 | C39: €4.8m - Apartment Development, Limerick | D39: Limerick City and Suburbs | E39: Plans Submitted | F39: =IFERROR(INDEX(Sites!$K$2:$K$217,MATCH($B39,Sites!$A$2:$A$217,0)),"") -> 30 | G39: 1 low-confidence counted application(s): 258327 (Additional application on site, 30) | Possible overlap with nearby record | H39: P-1202244 (147m): €3.8m - Residential Development, Curry Lane, Commencement Expected, 30 units; U-1419385 (33m): €3.9m - Part 8 Housing Scheme, Limerick, Plans Submitted, 30 units | I39: =IFERROR(INDEX(Sites!$T$2:$T$217,MATCH($B39,Sites!$A$2:$A$217,0)),"") -> Yes
A40: 39 | B40: U-1250272 | C40: €6.5m - Apartment Development, Limerick | D40: Limerick City and Suburbs | E40: Permission Granted | F40: =IFERROR(INDEX(Sites!$K$2:$K$217,MATCH($B40,Sites!$A$2:$A$217,0)),"") -> 29 | G40: 1 low-confidence counted application(s): 221003 (Additional application on site, 29) | 221003 no CIS update since 06/2023 | Possible overlap with nearby record | H40: P-1195465 (44m): €2.1m - Apartment Development , Permission Granted, 14 units; P-980328 (106m): €2m - Apartment Development , Complete, 14 units | I40: =IFERROR(INDEX(Sites!$T$2:$T$217,MATCH($B40,Sites!$A$2:$A$217,0)),"") -> Yes
A41: 40 | B41: P-1054214 | C41: €6m - Residential Development, King's Island | D41: Other County Limerick | E41: Permission Granted | F41: =IFERROR(INDEX(Sites!$K$2:$K$217,MATCH($B41,Sites!$A$2:$A$217,0)),"") -> 27 | G41: 1 low-confidence counted application(s): 198004 (Additional application on site, 27) | 198004 past expiry (22/10/2025) | I41: =IFERROR(INDEX(Sites!$T$2:$T$217,MATCH($B41,Sites!$A$2:$A$217,0)),"") -> Yes
A42: 41 | B42: P-1022341 | C42: €5.7m - Residential Development, Rhebogue | D42: Other County Limerick | E42: Commencement Expected | F42: =IFERROR(INDEX(Sites!$K$2:$K$217,MATCH($B42,Sites!$A$2:$A$217,0)),"") -> 26 | G42: 1 low-confidence counted application(s): 187040 (Extension of duration (parent not in CIS), 26) | 187040 past expiry (30/12/2023) | I42: =IFERROR(INDEX(Sites!$T$2:$T$217,MATCH($B42,Sites!$A$2:$A$217,0)),"") -> Yes
A43: 42 | B43: P-1256924 | C43: €5.9m - Student Accommodation Development | D43: Other County Limerick | E43: Permission Granted | F43: =IFERROR(INDEX(Sites!$K$2:$K$217,MATCH($B43,Sites!$A$2:$A$217,0)),"") -> 25 | G43: 1 low-confidence counted application(s): 221172 (Additional application on site, 25) | 221172 no CIS update since 06/2024 | I43: =IFERROR(INDEX(Sites!$T$2:$T$217,MATCH($B43,Sites!$A$2:$A$217,0)),"") -> Yes
A44: 43 | B44: SG-030 | C44: €5.5m - Housing Development, Cappamore | D44: Cappamore | E44: Permission Granted | F44: =IFERROR(INDEX(Sites!$K$2:$K$217,MATCH($B44,Sites!$A$2:$A$217,0)),"") -> 24 | G44: Auto link to check: 2461101 replaces earlier 2260015 | Low-confidence grouping in source workbook | I44: =IFERROR(INDEX(Sites!$T$2:$T$217,MATCH($B44,Sites!$A$2:$A$217,0)),"") -> Yes
A45: 44 | B45: P-1005377 | C45: €1.9m - Housing Development | D45: Limerick City and Suburbs | E45: Complete | F45: =IFERROR(INDEX(Sites!$K$2:$K$217,MATCH($B45,Sites!$A$2:$A$217,0)),"") -> 24 | G45: 1 low-confidence counted application(s): 187029 (Extension of duration (parent not in CIS), 24) | I45: =IFERROR(INDEX(Sites!$T$2:$T$217,MATCH($B45,Sites!$A$2:$A$217,0)),"") -> Yes
A46: 45 | B46: U-1422145 | C46: €719k - Architect Led Integrated Design Team Services for 23 Residential Units, Limerick | D46: Limerick City and Suburbs | E46: Contract Awarded | F46: =IFERROR(INDEX(Sites!$K$2:$K$217,MATCH($B46,Sites!$A$2:$A$217,0)),"") -> 23 | G46: 1 low-confidence counted application(s): 1422145 (Additional application on site, 23) | Possible overlap with nearby record | H46: P-1054214 (45m): €6m - Residential Development, King's Island, Permission Granted, 27 units | I46: =IFERROR(INDEX(Sites!$T$2:$T$217,MATCH($B46,Sites!$A$2:$A$217,0)),"") -> Yes
A47: 46 | B47: P-1411773 | C47: €4.5m - Mixed Use Development | D47: Limerick City and Suburbs | E47: Permission Granted | F47: =IFERROR(INDEX(Sites!$K$2:$K$217,MATCH($B47,Sites!$A$2:$A$217,0)),"") -> 22 | G47: 1 low-confidence counted application(s): 2560771 (Additional application on site, 22) | I47: =IFERROR(INDEX(Sites!$T$2:$T$217,MATCH($B47,Sites!$A$2:$A$217,0)),"") -> Yes
A48: 47 | B48: SG-025 | C48: €3.5m - Apartment Development, Limerick | D48: Other County Limerick | E48: Permission Granted | F48: =IFERROR(INDEX(Sites!$K$2:$K$217,MATCH($B48,Sites!$A$2:$A$217,0)),"") -> 22 | G48: 1 low-confidence counted application(s): 2360759 (Additional application on site, 8) | 21835 no CIS update since 01/2022 | 2360759 no CIS update since 06/2024 | Low-confidence grouping in source workbook | I48: =IFERROR(INDEX(Sites!$T$2:$T$217,MATCH($B48,Sites!$A$2:$A$217,0)),"") -> Yes
A49: 48 | B49: SG-028 | C49: €4.2m - Apartment Development, Rosbrien | D49: Other County Limerick | E49: On Site | F49: =IFERROR(INDEX(Sites!$K$2:$K$217,MATCH($B49,Sites!$A$2:$A$217,0)),"") -> 21 | G49: Low-confidence grouping in source workbook | Later application nearby: 2360025 (26/01/2023, Granted on appeal, 21 units, in CIS) | I49: =IFERROR(INDEX(Sites!$T$2:$T$217,MATCH($B49,Sites!$A$2:$A$217,0)),"") -> Yes
A50: 49 | B50: P-1290708 | C50: €3.7m - Residential Development, Limerick City | D50: Limerick City and Suburbs | E50: Permission Granted | F50: =IFERROR(INDEX(Sites!$K$2:$K$217,MATCH($B50,Sites!$A$2:$A$217,0)),"") -> 21 | G50: 1 low-confidence counted application(s): 2360345 (Additional application on site, 21) | 2360345 no CIS update since 08/2023 | I50: =IFERROR(INDEX(Sites!$T$2:$T$217,MATCH($B50,Sites!$A$2:$A$217,0)),"") -> Yes
A51: 50 | B51: U-1227182 | C51: €4.5m - Housing Development, Mungret | D51: Mungret | E51: Permission Granted | F51: =IFERROR(INDEX(Sites!$K$2:$K$217,MATCH($B51,Sites!$A$2:$A$217,0)),"") -> 21 | G51: 22471 no CIS update since 01/2024 | I51: =IFERROR(INDEX(Sites!$T$2:$T$217,MATCH($B51,Sites!$A$2:$A$217,0)),"") -> Yes
A52: 51 | B52: SG-014 | C52: €2.3m - 8 Residential Units | D52: Limerick City and Suburbs | E52: On Site | F52: =IFERROR(INDEX(Sites!$K$2:$K$217,MATCH($B52,Sites!$A$2:$A$217,0)),"") -> 20 | G52: 1 low-confidence counted application(s): 197025 (Extension of duration (parent not in CIS), 12) | 197025 past expiry (01/12/2024) | Low-confidence grouping in source workbook | I52: =IFERROR(INDEX(Sites!$T$2:$T$217,MATCH($B52,Sites!$A$2:$A$217,0)),"") -> Yes
A53: 52 | B53: SG-032 | C53: €5.45m - Apartment Development, Limerick | D53: Other County Limerick | E53: On Site | F53: =IFERROR(INDEX(Sites!$K$2:$K$217,MATCH($B53,Sites!$A$2:$A$217,0)),"") -> 19 | G53: 1 low-confidence counted application(s): 2560595 (Additional application on site, 6) | Low-confidence grouping in source workbook | I53: =IFERROR(INDEX(Sites!$T$2:$T$217,MATCH($B53,Sites!$A$2:$A$217,0)),"") -> Yes
A54: 53 | B54: SG-023 | C54: €4m - Residential Development | D54: Other County Limerick | E54: Part Complete | F54: =IFERROR(INDEX(Sites!$K$2:$K$217,MATCH($B54,Sites!$A$2:$A$217,0)),"") -> 18 | G54: 1 low-confidence counted application(s): 218012 (Additional application on site, 18) | Low-confidence grouping in source workbook | I54: =IFERROR(INDEX(Sites!$T$2:$T$217,MATCH($B54,Sites!$A$2:$A$217,0)),"") -> Yes
A55: 54 | B55: P-1201358 | C55: €2.4m - Residential Development, Broadford | D55: Other County Limerick | E55: Permission Granted | F55: =IFERROR(INDEX(Sites!$K$2:$K$217,MATCH($B55,Sites!$A$2:$A$217,0)),"") -> 18 | G55: Part 8 - 1201358 no CIS update since 11/2021 | I55: =IFERROR(INDEX(Sites!$T$2:$T$217,MATCH($B55,Sites!$A$2:$A$217,0)),"") -> Yes
A56: 55 | B56: SG-018 | C56: €1.7m - 8 Apartments | D56: Other County Limerick | E56: Permission Granted | F56: =IFERROR(INDEX(Sites!$K$2:$K$217,MATCH($B56,Sites!$A$2:$A$217,0)),"") -> 17 | G56: 1 low-confidence counted application(s): 221381 (Additional application on site, 9) | 20466 past expiry (19/04/2026) | Low-confidence grouping in source workbook | I56: =IFERROR(INDEX(Sites!$T$2:$T$217,MATCH($B56,Sites!$A$2:$A$217,0)),"") -> Yes
A57: 56 | B57: P-1015929 | C57: €2m - Housing Development | D57: Other County Limerick | E57: Permission Granted | F57: =IFERROR(INDEX(Sites!$K$2:$K$217,MATCH($B57,Sites!$A$2:$A$217,0)),"") -> 17 | G57: past expiry (27/09/2024) | I57: =IFERROR(INDEX(Sites!$T$2:$T$217,MATCH($B57,Sites!$A$2:$A$217,0)),"") -> Yes
A58: 57 | B58: P-1401743 | C58: €2.4m - Apartment Development | D58: Other County Limerick | E58: Permission Granted | F58: =IFERROR(INDEX(Sites!$K$2:$K$217,MATCH($B58,Sites!$A$2:$A$217,0)),"") -> 16 | G58: 1 low-confidence counted application(s): 2560365 (Additional application on site, 16) | I58: =IFERROR(INDEX(Sites!$T$2:$T$217,MATCH($B58,Sites!$A$2:$A$217,0)),"") -> Yes
A59: 58 | B59: P-1112715 | C59: €3.2m - Change of Use to Apartment Development | D59: Other County Limerick | E59: Permission Granted | F59: =IFERROR(INDEX(Sites!$K$2:$K$217,MATCH($B59,Sites!$A$2:$A$217,0)),"") -> 15 | G59: 20622 past expiry (06/10/2025) | I59: =IFERROR(INDEX(Sites!$T$2:$T$217,MATCH($B59,Sites!$A$2:$A$217,0)),"") -> Yes
A60: 59 | B60: U-1353358 | C60: €2.7m - Residential Development, Limerick | D60: Limerick City and Suburbs | E60: Permission Granted | F60: =IFERROR(INDEX(Sites!$K$2:$K$217,MATCH($B60,Sites!$A$2:$A$217,0)),"") -> 15 | G60: Possible overlap with nearby record | H60: SG-032 (126m): €5.45m - Apartment Development, Limerick, On Site, 13 units; SG-032 (131m): €2.1m - Infill Residential / Living Georgian , Permission Granted, 13 units | I60: =IFERROR(INDEX(Sites!$T$2:$T$217,MATCH($B60,Sites!$A$2:$A$217,0)),"") -> Yes
A61: 60 | B61: U-1363929 | C61: €4.2m - Residential Development | D61: Limerick City and Suburbs | E61: Permission Granted | F61: =IFERROR(INDEX(Sites!$K$2:$K$217,MATCH($B61,Sites!$A$2:$A$217,0)),"") -> 15 | G61: 2460864 no CIS update since 09/2024 | I61: =IFERROR(INDEX(Sites!$T$2:$T$217,MATCH($B61,Sites!$A$2:$A$217,0)),"") -> Yes
A62: 61 | B62: P-1318536 | C62: €2.2m - Residential Development, Newcastle West | D62: Newcastle West | E62: Permission Granted | F62: =IFERROR(INDEX(Sites!$K$2:$K$217,MATCH($B62,Sites!$A$2:$A$217,0)),"") -> 14 | G62: 2360826 no CIS update since 04/2024 | I62: =IFERROR(INDEX(Sites!$T$2:$T$217,MATCH($B62,Sites!$A$2:$A$217,0)),"") -> Yes
A63: 62 | B63: P-1195465 | C63: €2.1m - Apartment Development | D63: Other County Limerick | E63: Permission Granted | F63: =IFERROR(INDEX(Sites!$K$2:$K$217,MATCH($B63,Sites!$A$2:$A$217,0)),"") -> 14 | G63: 211454 no CIS update since 08/2022 | I63: =IFERROR(INDEX(Sites!$T$2:$T$217,MATCH($B63,Sites!$A$2:$A$217,0)),"") -> Yes
A64: 63 | B64: P-1051821 | C64: €2m - Apartment Development | D64: Other County Limerick | E64: Permission Granted | F64: =IFERROR(INDEX(Sites!$K$2:$K$217,MATCH($B64,Sites!$A$2:$A$217,0)),"") -> 14 | G64: 19552 no CIS update since 11/2020 | I64: =IFERROR(INDEX(Sites!$T$2:$T$217,MATCH($B64,Sites!$A$2:$A$217,0)),"") -> Yes
A65: 64 | B65: SG-016 | C65: €790k - 5 Houses | D65: Other County Limerick | E65: Commencement Expected | F65: =IFERROR(INDEX(Sites!$K$2:$K$217,MATCH($B65,Sites!$A$2:$A$217,0)),"") -> 13 | G65: 2 low-confidence counted application(s): 191184 (Additional application on site, 5), 2360393 (Additional application on site, 8) | 191184 past expiry (27/07/2025) | Low-confidence grouping in source workbook | I65: =IFERROR(INDEX(Sites!$T$2:$T$217,MATCH($B65,Sites!$A$2:$A$217,0)),"") -> Yes
A66: 65 | B66: U-1433772 | C66: €3m - Part 8 Residential Development, Limerick | D66: Limerick City and Suburbs | E66: Plans Submitted | F66: =IFERROR(INDEX(Sites!$K$2:$K$217,MATCH($B66,Sites!$A$2:$A$217,0)),"") -> 13 | G66: 1 low-confidence counted application(s): Part 8- 26255726 (Additional application on site, 13) | Possible overlap with nearby record | H66: P-1384661 (38m): €1.3m - 6 Apartments, Thomondgate, On Site, 7 units | I66: =IFERROR(INDEX(Sites!$T$2:$T$217,MATCH($B66,Sites!$A$2:$A$217,0)),"") -> Yes
A67: 66 | B67: P-1071780 | C67: €1.8m - Housing Development | D67: Other County Limerick | E67: Permission Granted | F67: =IFERROR(INDEX(Sites!$K$2:$K$217,MATCH($B67,Sites!$A$2:$A$217,0)),"") -> 12 | G67: 198009 past expiry (08/12/2024) | I67: =IFERROR(INDEX(Sites!$T$2:$T$217,MATCH($B67,Sites!$A$2:$A$217,0)),"") -> Yes
A68: 67 | B68: SG-034 | C68: €755k - Change of Use to 3 Apartments | D68: Other County Limerick | E68: On Site | F68: =IFERROR(INDEX(Sites!$K$2:$K$217,MATCH($B68,Sites!$A$2:$A$217,0)),"") -> 11 | G68: 1 low-confidence counted application(s): 2460020 (Additional application on site, 8) | Low-confidence grouping in source workbook | I68: =IFERROR(INDEX(Sites!$T$2:$T$217,MATCH($B68,Sites!$A$2:$A$217,0)),"") -> Yes
A69: 68 | B69: SG-021 | C69: €1.4m - Housing Development | D69: Limerick City and Suburbs | E69: Permission Granted | F69: =IFERROR(INDEX(Sites!$K$2:$K$217,MATCH($B69,Sites!$A$2:$A$217,0)),"") -> 11 | G69: Auto link to check: 22524 amendment within parent 21147 | 21147 no CIS update since 01/2022 | Low-confidence grouping in source workbook | I69: =IFERROR(INDEX(Sites!$T$2:$T$217,MATCH($B69,Sites!$A$2:$A$217,0)),"") -> Yes
A70: 69 | B70: SG-033 | C70: €686k - 4 Dwellings | D70: Other County Limerick | E70: On Site | F70: =IFERROR(INDEX(Sites!$K$2:$K$217,MATCH($B70,Sites!$A$2:$A$217,0)),"") -> 10 | G70: Auto link to check: 2360798 additional phase 2360546 | Low-confidence grouping in source workbook | I70: =IFERROR(INDEX(Sites!$T$2:$T$217,MATCH($B70,Sites!$A$2:$A$217,0)),"") -> Yes
A71: 70 | B71: P-1213266 | C71: €2.5m - 9 Houses | D71: Other County Limerick | E71: On Site | F71: =IFERROR(INDEX(Sites!$K$2:$K$217,MATCH($B71,Sites!$A$2:$A$217,0)),"") -> 9 | G71: 1 low-confidence counted application(s): 228000 (Additional application on site, 9) | I71: =IFERROR(INDEX(Sites!$T$2:$T$217,MATCH($B71,Sites!$A$2:$A$217,0)),"") -> Yes
A72: 71 | B72: P-1329797 | C72: €816k - 8 Apartment | D72: Other County Limerick | E72: Permission Granted | F72: =IFERROR(INDEX(Sites!$K$2:$K$217,MATCH($B72,Sites!$A$2:$A$217,0)),"") -> 8 | G72: 1 low-confidence counted application(s): 2460075 (Additional application on site, 8) | 2460075 no CIS update since 06/2024 | I72: =IFERROR(INDEX(Sites!$T$2:$T$217,MATCH($B72,Sites!$A$2:$A$217,0)),"") -> Yes
A73: 72 | B73: P-978022 | C73: €3m - Mixed Use Development | D73: Other County Limerick | E73: Permission Granted | F73: =IFERROR(INDEX(Sites!$K$2:$K$217,MATCH($B73,Sites!$A$2:$A$217,0)),"") -> 8 | G73: 18168 past expiry (18/07/2023) | I73: =IFERROR(INDEX(Sites!$T$2:$T$217,MATCH($B73,Sites!$A$2:$A$217,0)),"") -> Yes
A74: 73 | B74: P-1333345 | C74: €1.6m - Change of Use to 7 Apartments, Limerick | D74: Limerick City and Suburbs | E74: On Site | F74: =IFERROR(INDEX(Sites!$K$2:$K$217,MATCH($B74,Sites!$A$2:$A$217,0)),"") -> 7 | G74: 1 low-confidence counted application(s): 2460151 (Additional application on site, 7) | I74: =IFERROR(INDEX(Sites!$T$2:$T$217,MATCH($B74,Sites!$A$2:$A$217,0)),"") -> Yes
A75: 74 | B75: P-1007351 | C75: €701k - 7 Houses | D75: Abbeyfeale | E75: Permission Granted | F75: =IFERROR(INDEX(Sites!$K$2:$K$217,MATCH($B75,Sites!$A$2:$A$217,0)),"") -> 7 | G75: 188013 past expiry (25/09/2023) | I75: =IFERROR(INDEX(Sites!$T$2:$T$217,MATCH($B75,Sites!$A$2:$A$217,0)),"") -> Yes
A76: 75 | B76: U-1328561 | C76: €2m - 7 Houses, Broadford | D76: Other County Limerick | E76: Tender | F76: =IFERROR(INDEX(Sites!$K$2:$K$217,MATCH($B76,Sites!$A$2:$A$217,0)),"") -> 7 | G76: 1 low-confidence counted application(s): 2460046 (Additional application on site, 7) | Possible overlap with nearby record | H76: P-1201358 (58m): €2.4m - Residential Development, Broadford , Permission Granted, 18 units; SG-023 (98m): €4m - Residential Development, Permission Granted, 18 units | I76: =IFERROR(INDEX(Sites!$T$2:$T$217,MATCH($B76,Sites!$A$2:$A$217,0)),"") -> Yes
A77: 76 | B77: P-997576 | C77: €1m - Residential Development | D77: Limerick City and Suburbs | E77: Complete | F77: =IFERROR(INDEX(Sites!$K$2:$K$217,MATCH($B77,Sites!$A$2:$A$217,0)),"") -> 6 | G77: 1 low-confidence counted application(s): 187020 (Extension of duration (parent not in CIS), 6) | I77: =IFERROR(INDEX(Sites!$T$2:$T$217,MATCH($B77,Sites!$A$2:$A$217,0)),"") -> Yes
A78: 77 | B78: U-1447625 | C78: €1.4m - Part 8 - 2 Houses & 4 Apartments, Thomondghate | D78: Limerick City and Suburbs | E78: Plans Submitted | F78: =IFERROR(INDEX(Sites!$K$2:$K$217,MATCH($B78,Sites!$A$2:$A$217,0)),"") -> 6 | G78: 1 low-confidence counted application(s): 248153 (Additional application on site, 6) | Possible overlap with nearby record | H78: P-1265188 (84m): €10.4m - Residential Development, Thomondgate, Permission Granted, 46 units | I78: =IFERROR(INDEX(Sites!$T$2:$T$217,MATCH($B78,Sites!$A$2:$A$217,0)),"") -> Yes
A79: 78 | B79: U-1439022 | C79: €1.4m - 6 Houses, Caherdavin | D79: Limerick City and Suburbs | E79: Plans Submitted | F79: =IFERROR(INDEX(Sites!$K$2:$K$217,MATCH($B79,Sites!$A$2:$A$217,0)),"") -> 6 | G79: Possible overlap with nearby record | H79: SG-012 (141m): €16m - Residential Development, Ennis Road, Commencement Expected, 92 units; SG-012 (148m): €15m - EOD Residential Development, Permission Granted, 0 units | I79: =IFERROR(INDEX(Sites!$T$2:$T$217,MATCH($B79,Sites!$A$2:$A$217,0)),"") -> Yes
A80: 79 | B80: SG-011 | C80: €782k - Apartment Change of Use, Henry Street | D80: Other County Limerick | E80: On Site | F80: =IFERROR(INDEX(Sites!$K$2:$K$217,MATCH($B80,Sites!$A$2:$A$217,0)),"") -> 5 | G80: Low-confidence grouping in source workbook | I80: =IFERROR(INDEX(Sites!$T$2:$T$217,MATCH($B80,Sites!$A$2:$A$217,0)),"") -> Yes
A81: 80 | B81: P-1292276 | C81: €907k - Change of Use to 4 Apartments | D81: Other County Limerick | E81: Permission Granted | F81: =IFERROR(INDEX(Sites!$K$2:$K$217,MATCH($B81,Sites!$A$2:$A$217,0)),"") -> 4 | G81: 23283 no CIS update since 07/2023 | I81: =IFERROR(INDEX(Sites!$T$2:$T$217,MATCH($B81,Sites!$A$2:$A$217,0)),"") -> Yes
A82: 81 | B82: P-1053166 | C82: €800k - Residential Development, Ballingarry | D82: Other County Limerick | E82: On Site | F82: =IFERROR(INDEX(Sites!$K$2:$K$217,MATCH($B82,Sites!$A$2:$A$217,0)),"") -> 4 | G82: 1 low-confidence counted application(s): 197016 (Extension of duration (parent not in CIS), 4) | I82: =IFERROR(INDEX(Sites!$T$2:$T$217,MATCH($B82,Sites!$A$2:$A$217,0)),"") -> Yes
A83: 82 | B83: P-1120093 | C83: €864k - 4 Houses | D83: Other County Limerick | E83: Permission Granted | F83: =IFERROR(INDEX(Sites!$K$2:$K$217,MATCH($B83,Sites!$A$2:$A$217,0)),"") -> 4 | G83: 20827 past expiry (25/08/2026) | I83: =IFERROR(INDEX(Sites!$T$2:$T$217,MATCH($B83,Sites!$A$2:$A$217,0)),"") -> Yes
A84: 83 | B84: U-1378081 | C84: €879k - 4 Houses | D84: Limerick City and Suburbs | E84: Plans Submitted | F84: =IFERROR(INDEX(Sites!$K$2:$K$217,MATCH($B84,Sites!$A$2:$A$217,0)),"") -> 4 | G84: Possible overlap with nearby record | H84: P-1363543 (135m): €4m - Housing Development, Complete, 14 units | I84: =IFERROR(INDEX(Sites!$T$2:$T$217,MATCH($B84,Sites!$A$2:$A$217,0)),"") -> Yes
A85: 84 | B85: U-1442414 | C85: €540k - 4 Apartments, Limerick | D85: Limerick City and Suburbs | E85: Plans Submitted | F85: =IFERROR(INDEX(Sites!$K$2:$K$217,MATCH($B85,Sites!$A$2:$A$217,0)),"") -> 4 | G85: Possible overlap with nearby record | H85: SG-026 (113m): €5.8m - Apartment/Retail Development, Limeric, Permission Granted, 37 units; SG-026 (114m): €7m - Residential/Commercial Development, Lim, Permission Granted, 37 units | I85: =IFERROR(INDEX(Sites!$T$2:$T$217,MATCH($B85,Sites!$A$2:$A$217,0)),"") -> Yes
A86: 85 | B86: P-1278179 | C86: €1.5m - 3 Community Houses | D86: Other County Limerick | E86: Complete | F86: =IFERROR(INDEX(Sites!$K$2:$K$217,MATCH($B86,Sites!$A$2:$A$217,0)),"") -> 3 | G86: 1 low-confidence counted application(s): 2360148 (Additional application on site, 3) | I86: =IFERROR(INDEX(Sites!$T$2:$T$217,MATCH($B86,Sites!$A$2:$A$217,0)),"") -> Yes
A87: 86 | B87: P-1339954 | C87: €884k - 3 Houses | D87: Other County Limerick | E87: Permission Granted | F87: =IFERROR(INDEX(Sites!$K$2:$K$217,MATCH($B87,Sites!$A$2:$A$217,0)),"") -> 3 | G87: 2460299 no CIS update since 05/2024 | I87: =IFERROR(INDEX(Sites!$T$2:$T$217,MATCH($B87,Sites!$A$2:$A$217,0)),"") -> Yes
A88: 87 | B88: P-1299520 | C88: €1.4m - 3 Houses | D88: Other County Limerick | E88: Commencement Expected | F88: =IFERROR(INDEX(Sites!$K$2:$K$217,MATCH($B88,Sites!$A$2:$A$217,0)),"") -> 3 | G88: 2360493 no CIS update since 04/2024 | I88: =IFERROR(INDEX(Sites!$T$2:$T$217,MATCH($B88,Sites!$A$2:$A$217,0)),"") -> Yes
A89: 88 | B89: P-1283723 | C89: €680k - 3 Houses | D89: Other County Limerick | E89: Permission Granted | F89: =IFERROR(INDEX(Sites!$K$2:$K$217,MATCH($B89,Sites!$A$2:$A$217,0)),"") -> 3 | G89: 2360207 past expiry (17/09/2026) | I89: =IFERROR(INDEX(Sites!$T$2:$T$217,MATCH($B89,Sites!$A$2:$A$217,0)),"") -> Yes
A90: 89 | B90: U-837963 | C90: €588k - 3 Houses | D90: Other County Limerick | E90: Tender | F90: =IFERROR(INDEX(Sites!$K$2:$K$217,MATCH($B90,Sites!$A$2:$A$217,0)),"") -> 3 | G90: Possible overlap with nearby record | H90: P-1278179 (20m): €1.5m - 3 Community Houses, Complete, 3 units | I90: =IFERROR(INDEX(Sites!$T$2:$T$217,MATCH($B90,Sites!$A$2:$A$217,0)),"") -> Yes
A91: 90 | B91: P-1121263 | C91: €543k - 2 Houses | D91: Other County Limerick | E91: Commencement Expected | F91: =IFERROR(INDEX(Sites!$K$2:$K$217,MATCH($B91,Sites!$A$2:$A$217,0)),"") -> 2 | G91: 20857 past expiry (24/11/2025) | I91: =IFERROR(INDEX(Sites!$T$2:$T$217,MATCH($B91,Sites!$A$2:$A$217,0)),"") -> Yes
A92: 91 | B92: P-1099323 | C92: €574k - Extension to Pub | D92: Other County Limerick | E92: Permission Granted | F92: =IFERROR(INDEX(Sites!$K$2:$K$217,MATCH($B92,Sites!$A$2:$A$217,0)),"") -> 1 | G92: 20341 past expiry (23/09/2025) | I92: =IFERROR(INDEX(Sites!$T$2:$T$217,MATCH($B92,Sites!$A$2:$A$217,0)),"") -> Yes
A93: 92 | B93: P-1132789 | C93: €919k - Student Accommodation Development, Saint Gerard Street | D93: Other County Limerick | E93: Permission Granted | F93: =IFERROR(INDEX(Sites!$K$2:$K$217,MATCH($B93,Sites!$A$2:$A$217,0)),"") -> 0 | G93: 201142 past expiry (20/09/2026) | I93: =IFERROR(INDEX(Sites!$T$2:$T$217,MATCH($B93,Sites!$A$2:$A$217,0)),"") -> Yes
A94: 93 | B94: U-1212017 | C94: €1m - Residential Development, Ballylanders | D94: Other County Limerick | E94: Contract Awarded | F94: =IFERROR(INDEX(Sites!$K$2:$K$217,MATCH($B94,Sites!$A$2:$A$217,0)),"") -> 0 | G94: Possible overlap with nearby record | H94: P-1213266 (79m): €2.5m - 9 Houses, On Site, 9 units | I94: =IFERROR(INDEX(Sites!$T$2:$T$217,MATCH($B94,Sites!$A$2:$A$217,0)),"") -> Yes
A95: 94 | B95: U-1302008 | C95: €3.6m - Hosuing Development, Crossagalla | D95: Kilmallock | E95: Plans Submitted | F95: =IFERROR(INDEX(Sites!$K$2:$K$217,MATCH($B95,Sites!$A$2:$A$217,0)),"") -> 0 | G95: Possible overlap with nearby record | Later application nearby: 2460468 (17/05/2024, Granted, 12 units, in CIS) | H95: SG-007 (14m): €3.6m - Housing/Creche Development, Crossagal, On Site, 12 units; SG-007 (48m): €529k - 4 Houses , Permission Granted, 4 units | I95: =IFERROR(INDEX(Sites!$T$2:$T$217,MATCH($B95,Sites!$A$2:$A$217,0)),"") -> Yes
A96: 95 | B96: U-1315592 | C96: €12.6m - Residential Development, Patrickswell | D96: Patrickswell | E96: Plans Submitted | F96: =IFERROR(INDEX(Sites!$K$2:$K$217,MATCH($B96,Sites!$A$2:$A$217,0)),"") -> 0 | G96: Possible overlap with nearby record | Later application nearby: 2560156 (25/02/2025, Granted on appeal, 63 units, in CIS) | H96: SG-004 (69m): €15.9m - Residential Development, Patrickswel, Permission Granted, 63 units; SG-004 (108m): €6.3m - Residential Development, Patrickswell, Permission Granted, 49 units | I96: =IFERROR(INDEX(Sites!$T$2:$T$217,MATCH($B96,Sites!$A$2:$A$217,0)),"") -> Yes
A97: 96 | B97: U-1350169 | C97: €2.2m - 6 Houses | D97: Patrickswell | E97: Plans Submitted | F97: =IFERROR(INDEX(Sites!$K$2:$K$217,MATCH($B97,Sites!$A$2:$A$217,0)),"") -> 0 | G97: Possible overlap with nearby record | Later application nearby: 2560156 (25/02/2025, Granted on appeal, 63 units, in CIS) | H97: SG-004 (4m): €2.4m - 6 Houses, Permission Granted, 6 units; SG-004 (98m): €1.7 - 9 Houses, Patrickswell, Complete, 9 units | I97: =IFERROR(INDEX(Sites!$T$2:$T$217,MATCH($B97,Sites!$A$2:$A$217,0)),"") -> Yes
A98: 97 | B98: U-1364960 | C98: €2m - 6 Apartments, Limerick | D98: Limerick City and Suburbs | E98: Tender | F98: =IFERROR(INDEX(Sites!$K$2:$K$217,MATCH($B98,Sites!$A$2:$A$217,0)),"") -> 0 | G98: Possible overlap with nearby record | H98: P-1265188 (82m): €10.4m - Residential Development, Thomondgate, Permission Granted, 46 units; U-1447625 (3m): €1.4m - Part 8 - 2 Houses & 4 Apartments, Tho, Plans Submitted, 6 units | I98: =IFERROR(INDEX(Sites!$T$2:$T$217,MATCH($B98,Sites!$A$2:$A$217,0)),"") -> Yes
A99: 98 | B99: U-1369195 | C99: €15.4m - Residential Development, Patrickswell | D99: Patrickswell | E99: Plans Submitted | F99: =IFERROR(INDEX(Sites!$K$2:$K$217,MATCH($B99,Sites!$A$2:$A$217,0)),"") -> 0 | G99: Possible overlap with nearby record | Later application nearby: 2560156 (25/02/2025, Granted on appeal, 63 units, in CIS) | H99: SG-004 (9m): €15.9m - Residential Development, Patrickswel, Permission Granted, 63 units; SG-004 (98m): €2.4m - 6 Houses, Permission Granted, 6 units; U-1315592 (68m): €12.6m - Residential Development, Patrickswel, Plans Submitted, 61 units; U-1350169 (94m): €2.2m - 6 Houses , Plans Submitted, 6 units | I99: =IFERROR(INDEX(Sites!$T$2:$T$217,MATCH($B99,Sites!$A$2:$A$217,0)),"") -> Yes
A100: 99 | B100: U-1402230 | C100: €2.2m - 9 Residential Units | D100: Limerick City and Suburbs | E100: Plans Submitted | F100: =IFERROR(INDEX(Sites!$K$2:$K$217,MATCH($B100,Sites!$A$2:$A$217,0)),"") -> 0 | G100: Possible overlap with nearby record | H100: SG-008 (103m): €4.6m - Residential Development , Complete, 38 units | I100: =IFERROR(INDEX(Sites!$T$2:$T$217,MATCH($B100,Sites!$A$2:$A$217,0)),"") -> Yes
A101: 100 | B101: U-1419385 | C101: €3.9m - Part 8 Housing Scheme, Limerick | D101: Limerick City and Suburbs | E101: Plans Submitted | F101: =IFERROR(INDEX(Sites!$K$2:$K$217,MATCH($B101,Sites!$A$2:$A$217,0)),"") -> 0 | G101: Possible overlap with nearby record | H101: P-1202244 (121m): €3.8m - Residential Development, Curry Lane, Commencement Expected, 30 units | I101: =IFERROR(INDEX(Sites!$T$2:$T$217,MATCH($B101,Sites!$A$2:$A$217,0)),"") -> Yes
A102: 101 | B102: U-1424889 | C102: €16m - Residential Development, Adare | D102: Adare | E102: Plans Submitted | F102: =IFERROR(INDEX(Sites!$K$2:$K$217,MATCH($B102,Sites!$A$2:$A$217,0)),"") -> 0 | G102: Later application nearby: 2661011 (02/09/2026, Pending, 67 units, NOT in CIS) | I102: =IFERROR(INDEX(Sites!$T$2:$T$217,MATCH($B102,Sites!$A$2:$A$217,0)),"") -> No
A103: 102 | B103: U-1439374 | C103: €14m - Large Residential Development, Castletroy | D103: Limerick City and Suburbs | E103: Plans Submitted | F103: =IFERROR(INDEX(Sites!$K$2:$K$217,MATCH($B103,Sites!$A$2:$A$217,0)),"") -> 0 | G103: Auto link to check: 2660675 amendment within parent 2360842 | Possible overlap with nearby record | H103: U-1319159 (34m): €22m - Golf Links Road LRD, Monaleen, On Site, 122 units | I103: =IFERROR(INDEX(Sites!$T$2:$T$217,MATCH($B103,Sites!$A$2:$A$217,0)),"") -> Yes
A104: 103 | B104: U-1441321 | C104: €3.2m - Change of Use to Apartment Development, Mungret | D104: Mungret | E104: Plans Submitted | F104: =IFERROR(INDEX(Sites!$K$2:$K$217,MATCH($B104,Sites!$A$2:$A$217,0)),"") -> 0 | G104: Possible overlap with nearby record | H104: P-1306162 (122m): €11.3m - Housing Development, Mungret, On Site, 66 units; SG-001 (149m): €16.5m - Residential Development, Mungret, On Site, 96 units | I104: =IFERROR(INDEX(Sites!$T$2:$T$217,MATCH($B104,Sites!$A$2:$A$217,0)),"") -> Yes

Sheet Applications
A1: Project Id | B1: Site ID | C1: CIS Reference | D1: Project Heading | E1: Address | F1: Settlement | G1: CIS Stage | H1: Planning Stage | I1: Contract Stage | J1: Application Date | K1: CIS Decision Date | L1: Last Updated | M1: Source Dataset | N1: Included in Pipeline | O1: Exclusion Reason | P1: Dwelling Type | Q1: Units | R1: Units in Description | S1: Student Bedspaces | T1: Auto Relationship | U1: Related Ref | V1: Relationship Basis | W1: Confidence | X1: Analyst Relationship | Y1: Final Relationship | Z1: Counts? | AA1: Units Completed (stated) | AB1: Months Since Update | AC1: Stale? | AD1: Expiry Used | AE1: Past Expiry? | AF1: Analyst Status | AG1: Reporting Tier | AH1: Tier Reason | AI1: Counted Units | AJ1: Remaining Units | AK1: Delivered Units | AL1: Pipeline General Dwellings | AM1: Pipeline Student Units | AN1: Pipeline Student Bedspaces | AO1: Mix Source | AP1: Studio | AQ1: 1 Bed | AR1: 2 Bed | AS1: 3 Bed | AT1: 4 Bed | AU1: 5+ Bed | AV1: Mix Total | AW1: Houses | AX1: Apartments | AY1: Type Unknown | AZ1: Mix Note | BA1: Register Source | BB1: Register Ref | BC1: Register Status | BD1: Register Decision | BE1: Appeal Decision | BF1: Register Outcome | BG1: Register Decision Date | BH1: Register Expiry | BI1: Extension of Duration | BJ1: Expiry incl. EoD | BK1: Register Units | BL1: Location Diff (m) | BM1: Later Application Nearby | BN1: Register Description | BO1: Register Link | BP1: Decision Date Diff (days) | BQ1: Units Check | BR1: Check Result | BS1: Social Housing Project No. | BT1: Social Housing Programme | BU1: Social Housing AHB | BV1: Social Housing Stage | BW1: Social Housing Stage Quarter | BX1: Public Delivery
A2: 1005377 | B2: P-1005377 | C2: 187029 | D2: €1.9m - Housing Development | E2: Laurelville, Mill Road, Corbally | F2: Limerick City and Suburbs | G2: Complete | H2: Plans Granted | I2: Completed | J2: 43325 | K2: 43377 | L2: 45838.473 | M2: Granted/delivery CIS export | N2: Yes | P2: General | Q2: 24 | R2: 18 | T2: Extension of duration (parent not in CIS) | U2: 08770120 | V2: Parent permission not in CIS; CIS units counted here | W2: Low | Y2: =IF(X2<>"",X2,T2) -> Extension of duration (parent not in CIS) | Z2: =IF(OR(Y2="Primary",Y2="Additional phase",Y2="Additional application on site",Y2="Replaces earlier",Y2="Extension of duration (parent not in CIS)"),"Yes","No") -> Yes | AB2: =IF(L2="","",ROUND((Method!$B$4-L2)/30.44,0)) -> 15 | AC2: =IF(AB2="","No",IF(AB2>Method!$B$5,"Yes","No")) -> No | AD2: =IF(BJ2<>"",BJ2,IF(K2<>"",EDATE(K2,60),"")) -> 44561 | AE2: =IF(AND(AD2<>"",OR(G2="Permission Granted",G2="Commencement Expected",G2="Stalled or Suspended")),IF(AD2<Method!$B$4,"Yes","No"),"No") -> No | AG2: =IF(Z2="No","Not counted",IF(AF2="Lapsed or dead","Excluded",IF(AF2="Constrained","Constrained / uncertain",IF(AF2="Confirmed live",IF(G2="On Site","Committed",IF(G2="Part Complete","Committed",IF(G2="Contract Awarded","Committed Pre-Construction",IF(G2="Tender","Advanced Pre-Construction",IF(G2="Commencement Expected","Likely",IF(G2="Permission Granted","Potential",IF(G2="Stalled or Suspended","Constrained / uncertain",IF(G2="Complete","Delivered","Application Pipeline")))))))),IF(G2="Complete","Delivered",IF(AND(OR(G2="Permission Granted",G2="Commencement Expected"),OR(AC2="Yes",AE2="Yes")),"Constrained / uncertain",IF(G2="On Site","Committed",IF(G2="Part Complete","Committed",IF(G2="Contract Awarded","Committed Pre-Construction",IF(G2="Tender","Advanced Pre-Construction",IF(G2="Commencement Expected","Likely",IF(G2="Permission Granted","Potential",IF(G2="Stalled or Suspended","Constrained / uncertain",IF(G2="Complete","Delivered","Application Pipeline")))))))))))))) -> Delivered | AH2: =IF(Z2="No","Relationship: "&Y2,IF(AF2<>"","Analyst: "&AF2,IF(G2="Complete","Complete",IF(AND(OR(G2="Permission Granted",G2="Commencement Expected"),AE2="Yes"),"Past expiry",IF(AND(OR(G2="Permission Granted",G2="Commencement Expected"),AC2="Yes"),"No CIS update in "&AB2&" months","As CIS"))))) -> Complete | AI2: =IF(Z2="Yes",N(Q2),0) -> 24 | AJ2: =IF(OR(Z2="No",G2="Complete"),0,MAX(N(Q2)-N(AA2),0)) -> 0 | AK2: =IF(Z2="No",0,IF(G2="Complete",N(Q2),MIN(N(AA2),N(Q2)))) -> 24 | AL2: =IF(OR(OR(AG2="Not counted",AG2="Excluded",AG2="Delivered"),P2="Student accommodation"),0,AJ2) -> 0 | AM2: =IF(OR(OR(AG2="Not counted",AG2="Excluded",AG2="Delivered"),P2<>"Student accommodation"),0,AJ2) -> 0 | AN2: =IF(OR(AG2="Not counted",AG2="Excluded",AG2="Delivered"),0,N(S2)) -> 0 | AO2: Not available (no bedroom detail in register text) | AV2: =N(AP2)+N(AQ2)+N(AR2)+N(AS2)+N(AT2)+N(AU2) -> 0 | BA2: Council register | BB2: 187029 | BC2: APPLICATION FINALISED | BD2: CONDITIONAL | BF2: Granted | BG2: 43377 | BH2: 44561 | BJ2: 44561 | BL2: 0 | BN2: Extension of Permission on Planning File Ref. No. 08/770120, previously extended under Planning Ref. No. PE771311 : construction of 18 no. residential dwellings, modification and realignment of boundary of existing dwelling, construction of new vehicular and pedestrian entrance/egress onto Mill Road | BO2: https://eplanning.ie/LimerickCCC/AppFileRefDetails/187029/0 | BP2: =IF(OR(K2="",BG2=""),"",ROUND(BG2-K2,0)) -> 0 | BQ2: =IF(OR(N(BK2)=0,Q2=""),"Not recorded",IF(BK2=Q2,"Match","Differs")) -> Not recorded | BR2: =IF(N2="No","Excluded (non-residential)",IF(BF2="No reference","Unverified – no reference",IF(BF2="Not in council register","Unverified – not in register (Part 8 / other)",IF(OR(BF2="Refused",BF2="Refused on appeal",BF2="Withdrawn",BF2="Invalid",BF2="Quashed"),IF(OR(G2="Complete",G2="On Site",G2="Part Complete"),"Conflict – register not live but CIS says built","Conflict – not live in register"),IF(AND(G2="Plans Submitted",OR(BF2="Granted",BF2="Granted on appeal")),"Stage out of date – now granted",IF(AND(G2<>"Plans Submitted",OR(BF2="Pending",BF2="Under appeal")),"Check – register still pending",IF(N(BL2)>Method!$B$7,"Check – location differs",IF(AND(BP2<>"",ABS(N(BP2))>60),"Consistent – decision date differs","Consistent")))))))) -> Consistent
A3: 1007351 | B3: P-1007351 | C3: 188013 | D3: €701k - 7 Houses | E3: Colbert Terrace, Abbeyfeale | F3: Abbeyfeale | G3: Permission Granted | H3: Plans Granted | J3: 43339 | K3: 43368 | L3: 43346.621 | M3: Granted/delivery CIS export | N3: Yes | P3: General | Q3: 7 | T3: Primary | V3: Only live application on site | W3: High | Y3: =IF(X3<>"",X3,T3) -> Primary | Z3: =IF(OR(Y3="Primary",Y3="Additional phase",Y3="Additional application on site",Y3="Replaces earlier",Y3="Extension of duration (parent not in CIS)"),"Yes","No") -> Yes | AB3: =IF(L3="","",ROUND((Method!$B$4-L3)/30.44,0)) -> 97 | AC3: =IF(AB3="","No",IF(AB3>Method!$B$5,"Yes","No")) -> Yes | AD3: =IF(BJ3<>"",BJ3,IF(K3<>"",EDATE(K3,60),"")) -> 45194 | AE3: =IF(AND(AD3<>"",OR(G3="Permission Granted",G3="Commencement Expected",G3="Stalled or Suspended")),IF(AD3<Method!$B$4,"Yes","No"),"No") -> Yes | AG3: =IF(Z3="No","Not counted",IF(AF3="Lapsed or dead","Excluded",IF(AF3="Constrained","Constrained / uncertain",IF(AF3="Confirmed live",IF(G3="On Site","Committed",IF(G3="Part Complete","Committed",IF(G3="Contract Awarded","Committed Pre-Construction",IF(G3="Tender","Advanced Pre-Construction",IF(G3="Commencement Expected","Likely",IF(G3="Permission Granted","Potential",IF(G3="Stalled or Suspended","Constrained / uncertain",IF(G3="Complete","Delivered","Application Pipeline")))))))),IF(G3="Complete","Delivered",IF(AND(OR(G3="Permission Granted",G3="Commencement Expected"),OR(AC3="Yes",AE3="Yes")),"Constrained / uncertain",IF(G3="On Site","Committed",IF(G3="Part Complete","Committed",IF(G3="Contract Awarded","Committed Pre-Construction",IF(G3="Tender","Advanced Pre-Construction",IF(G3="Commencement Expected","Likely",IF(G3="Permission Granted","Potential",IF(G3="Stalled or Suspended","Constrained / uncertain",IF(G3="Complete","Delivered","Application Pipeline")))))))))))))) -> Constrained / uncertain | AH3: =IF(Z3="No","Relationship: "&Y3,IF(AF3<>"","Analyst: "&AF3,IF(G3="Complete","Complete",IF(AND(OR(G3="Permission Granted",G3="Commencement Expected"),AE3="Yes"),"Past expiry",IF(AND(OR(G3="Permission Granted",G3="Commencement Expected"),AC3="Yes"),"No CIS update in "&AB3&" months","As CIS"))))) -> Past expiry | AI3: =IF(Z3="Yes",N(Q3),0) -> 7 | AJ3: =IF(OR(Z3="No",G3="Complete"),0,MAX(N(Q3)-N(AA3),0)) -> 7 | AK3: =IF(Z3="No",0,IF(G3="Complete",N(Q3),MIN(N(AA3),N(Q3)))) -> 0 | AL3: =IF(OR(OR(AG3="Not counted",AG3="Excluded",AG3="Delivered"),P3="Student accommodation"),0,AJ3) -> 7 | AM3: =IF(OR(OR(AG3="Not counted",AG3="Excluded",AG3="Delivered"),P3<>"Student accommodation"),0,AJ3) -> 0 | AN3: =IF(OR(AG3="Not counted",AG3="Excluded",AG3="Delivered"),0,N(S3)) -> 0 | AO3: Register description | AR3: 7 | AV3: =N(AP3)+N(AQ3)+N(AR3)+N(AS3)+N(AT3)+N(AU3) -> 7 | AY3: 7 | BA3: Council register | BB3: 188013 | BC3: NEW APPLICATION | BD3: N/A | BF3: Pending | BK3: 7 | BL3: 0 | BN3: (a) provision of 7 no. two storey two-bed residential housing units, (b) hard landscaping including; bin stores, front and rear gardens, and boundary walls and railings; (c) soft landscaping including; planting; (d) construction of and/or remedial works to boundaries with adjacent sites; (e) demolit | BO3: https://eplanning.ie/LimerickCCC/AppFileRefDetails/188013/0 | BP3: =IF(OR(K3="",BG3=""),"",ROUND(BG3-K3,0)) | BQ3: =IF(OR(N(BK3)=0,Q3=""),"Not recorded",IF(BK3=Q3,"Match","Differs")) -> Match | BR3: =IF(N3="No","Excluded (non-residential)",IF(BF3="No reference","Unverified – no reference",IF(BF3="Not in council register","Unverified – not in register (Part 8 / other)",IF(OR(BF3="Refused",BF3="Refused on appeal",BF3="Withdrawn",BF3="Invalid",BF3="Quashed"),IF(OR(G3="Complete",G3="On Site",G3="Part Complete"),"Conflict – register not live but CIS says built","Conflict – not live in register"),IF(AND(G3="Plans Submitted",OR(BF3="Granted",BF3="Granted on appeal")),"Stage out of date – now granted",IF(AND(G3<>"Plans Submitted",OR(BF3="Pending",BF3="Under appeal")),"Check – register still pending",IF(N(BL3)>Method!$B$7,"Check – location differs",IF(AND(BP3<>"",ABS(N(BP3))>60),"Consistent – decision date differs","Consistent")))))))) -> Check – register still pending
A4: 1009370 | B4: P-1009370 | C4: 18892 | D4: €870k - Apartments | E4: Scott's Bar, Courtbrack Avenue, South Circular Road | F4: Other County Limerick | G4: On Site | H4: Plans Granted | I4: On Site | J4: 43356 | K4: 43487 | L4: 43698.445 | M4: Granted/delivery CIS export | N4: Yes | P4: General | Q4: 6 | T4: Primary | V4: Only live application on site | W4: High | Y4: =IF(X4<>"",X4,T4) -> Primary | Z4: =IF(OR(Y4="Primary",Y4="Additional phase",Y4="Additional application on site",Y4="Replaces earlier",Y4="Extension of duration (parent not in CIS)"),"Yes","No") -> Yes | AB4: =IF(L4="","",ROUND((Method!$B$4-L4)/30.44,0)) -> 85 | AC4: =IF(AB4="","No",IF(AB4>Method!$B$5,"Yes","No")) -> Yes | AD4: =IF(BJ4<>"",BJ4,IF(K4<>"",EDATE(K4,60),"")) -> 45347 | AE4: =IF(AND(AD4<>"",OR(G4="Permission Granted",G4="Commencement Expected",G4="Stalled or Suspended")),IF(AD4<Method!$B$4,"Yes","No"),"No") -> No | AG4: =IF(Z4="No","Not counted",IF(AF4="Lapsed or dead","Excluded",IF(AF4="Constrained","Constrained / uncertain",IF(AF4="Confirmed live",IF(G4="On Site","Committed",IF(G4="Part Complete","Committed",IF(G4="Contract Awarded","Committed Pre-Construction",IF(G4="Tender","Advanced Pre-Construction",IF(G4="Commencement Expected","Likely",IF(G4="Permission Granted","Potential",IF(G4="Stalled or Suspended","Constrained / uncertain",IF(G4="Complete","Delivered","Application Pipeline")))))))),IF(G4="Complete","Delivered",IF(AND(OR(G4="Permission Granted",G4="Commencement Expected"),OR(AC4="Yes",AE4="Yes")),"Constrained / uncertain",IF(G4="On Site","Committed",IF(G4="Part Complete","Committed",IF(G4="Contract Awarded","Committed Pre-Construction",IF(G4="Tender","Advanced Pre-Construction",IF(G4="Commencement Expected","Likely",IF(G4="Permission Granted","Potential",IF(G4="Stalled or Suspended","Constrained / uncertain",IF(G4="Complete","Delivered","Application Pipeline")))))))))))))) -> Committed | AH4: =IF(Z4="No","Relationship: "&Y4,IF(AF4<>"","Analyst: "&AF4,IF(G4="Complete","Complete",IF(AND(OR(G4="Permission Granted",G4="Commencement Expected"),AE4="Yes"),"Past expiry",IF(AND(OR(G4="Permission Granted",G4="Commencement Expected"),AC4="Yes"),"No CIS update in "&AB4&" months","As CIS"))))) -> As CIS | AI4: =IF(Z4="Yes",N(Q4),0) -> 6 | AJ4: =IF(OR(Z4="No",G4="Complete"),0,MAX(N(Q4)-N(AA4),0)) -> 6 | AK4: =IF(Z4="No",0,IF(G4="Complete",N(Q4),MIN(N(AA4),N(Q4)))) -> 0 | AL4: =IF(OR(OR(AG4="Not counted",AG4="Excluded",AG4="Delivered"),P4="Student accommodation"),0,AJ4) -> 6 | AM4: =IF(OR(OR(AG4="Not counted",AG4="Excluded",AG4="Delivered"),P4<>"Student accommodation"),0,AJ4) -> 0 | AN4: =IF(OR(AG4="Not counted",AG4="Excluded",AG4="Delivered"),0,N(S4)) -> 0 | AO4: Register description | AQ4: 6 | AV4: =N(AP4)+N(AQ4)+N(AR4)+N(AS4)+N(AT4)+N(AU4) -> 6 | AX4: 6 | BA4: Council register | BB4: 18892 | BC4: APPLICATION FINALISED | BD4: CONDITIONAL | BF4: Granted | BG4: 43487 | BH4: 45347 | BJ4: 45347 | BL4: 0 | BN4: the subdivision and change of use of the existing first floor restaurant to 6 no. 1 bedroom apartments and all associated site works | BO4: https://eplanning.ie/LimerickCCC/AppFileRefDetails/18892/0 | BP4: =IF(OR(K4="",BG4=""),"",ROUND(BG4-K4,0)) -> 0 | BQ4: =IF(OR(N(BK4)=0,Q4=""),"Not recorded",IF(BK4=Q4,"Match","Differs")) -> Not recorded | BR4: =IF(N4="No","Excluded (non-residential)",IF(BF4="No reference","Unverified – no reference",IF(BF4="Not in council register","Unverified – not in register (Part 8 / other)",IF(OR(BF4="Refused",BF4="Refused on appeal",BF4="Withdrawn",BF4="Invalid",BF4="Quashed"),IF(OR(G4="Complete",G4="On Site",G4="Part Complete"),"Conflict – register not live but CIS says built","Conflict – not live in register"),IF(AND(G4="Plans Submitted",OR(BF4="Granted",BF4="Granted on appeal")),"Stage out of date – now granted",IF(AND(G4<>"Plans Submitted",OR(BF4="Pending",BF4="Under appeal")),"Check – register still pending",IF(N(BL4)>Method!$B$7,"Check – location differs",IF(AND(BP4<>"",ABS(N(BP4))>60),"Consistent – decision date differs","Consistent")))))))) -> Consistent
A5: 1014706 | B5: P-1014706 | C5: 18994 | D5: €553k - 6 Houses | E5: Daar River Walk, Newcastle West | F5: Newcastle West | G5: Complete | H5: Plans Granted | I5: Completed | J5: 43385 | K5: 43748 | L5: 46170.621 | M5: Granted/delivery CIS export | N5: Yes | P5: General | Q5: 6 | T5: Primary | V5: Only live application on site | W5: High | Y5: =IF(X5<>"",X5,T5) -> Primary | Z5: =IF(OR(Y5="Primary",Y5="Additional phase",Y5="Additional application on site",Y5="Replaces earlier",Y5="Extension of duration (parent not in CIS)"),"Yes","No") -> Yes | AB5: =IF(L5="","",ROUND((Method!$B$4-L5)/30.44,0)) -> 4 | AC5: =IF(AB5="","No",IF(AB5>Method!$B$5,"Yes","No")) -> No | AD5: =IF(BJ5<>"",BJ5,IF(K5<>"",EDATE(K5,60),"")) -> 45608 | AE5: =IF(AND(AD5<>"",OR(G5="Permission Granted",G5="Commencement Expected",G5="Stalled or Suspended")),IF(AD5<Method!$B$4,"Yes","No"),"No") -> No | AG5: =IF(Z5="No","Not counted",IF(AF5="Lapsed or dead","Excluded",IF(AF5="Constrained","Constrained / uncertain",IF(AF5="Confirmed live",IF(G5="On Site","Committed",IF(G5="Part Complete","Committed",IF(G5="Contract Awarded","Committed Pre-Construction",IF(G5="Tender","Advanced Pre-Construction",IF(G5="Commencement Expected","Likely",IF(G5="Permission Granted","Potential",IF(G5="Stalled or Suspended","Constrained / uncertain",IF(G5="Complete","Delivered","Application Pipeline")))))))),IF(G5="Complete","Delivered",IF(AND(OR(G5="Permission Granted",G5="Commencement Expected"),OR(AC5="Yes",AE5="Yes")),"Constrained / uncertain",IF(G5="On Site","Committed",IF(G5="Part Complete","Committed",IF(G5="Contract Awarded","Committed Pre-Construction",IF(G5="Tender","Advanced Pre-Construction",IF(G5="Commencement Expected","Likely",IF(G5="Permission Granted","Potential",IF(G5="Stalled or Suspended","Constrained / uncertain",IF(G5="Complete","Delivered","Application Pipeline")))))))))))))) -> Delivered | AH5: =IF(Z5="No","Relationship: "&Y5,IF(AF5<>"","Analyst: "&AF5,IF(G5="Complete","Complete",IF(AND(OR(G5="Permission Granted",G5="Commencement Expected"),AE5="Yes"),"Past expiry",IF(AND(OR(G5="Permission Granted",G5="Commencement Expected"),AC5="Yes"),"No CIS update in "&AB5&" months","As CIS"))))) -> Complete | AI5: =IF(Z5="Yes",N(Q5),0) -> 6 | AJ5: =IF(OR(Z5="No",G5="Complete"),0,MAX(N(Q5)-N(AA5),0)) -> 0 | AK5: =IF(Z5="No",0,IF(G5="Complete",N(Q5),MIN(N(AA5),N(Q5)))) -> 6 | AL5: =IF(OR(OR(AG5="Not counted",AG5="Excluded",AG5="Delivered"),P5="Student accommodation"),0,AJ5) -> 0 | AM5: =IF(OR(OR(AG5="Not counted",AG5="Excluded",AG5="Delivered"),P5<>"Student accommodation"),0,AJ5) -> 0 | AN5: =IF(OR(AG5="Not counted",AG5="Excluded",AG5="Delivered"),0,N(S5)) -> 0 | AO5: Not available (no bedroom detail in register text) | AV5: =N(AP5)+N(AQ5)+N(AR5)+N(AS5)+N(AT5)+N(AU5) -> 0 | BA5: Council register | BB5: 18994 | BC5: APPLICATION FINALISED | BD5: CONDITIONAL | BF5: Granted | BG5: 43748 | BH5: 45608 | BJ5: 45608 | BK5: 6 | BL5: 0 | BN5: the construction of six semi-detached dwelling houses and associated site works | BO5: https://eplanning.ie/LimerickCCC/AppFileRefDetails/18994/0 | BP5: =IF(OR(K5="",BG5=""),"",ROUND(BG5-K5,0)) -> 0 | BQ5: =IF(OR(N(BK5)=0,Q5=""),"Not recorded",IF(BK5=Q5,"Match","Differs")) -> Match | BR5: =IF(N5="No","Excluded (non-residential)",IF(BF5="No reference","Unverified – no reference",IF(BF5="Not in council register","Unverified – not in register (Part 8 / other)",IF(OR(BF5="Refused",BF5="Refused on appeal",BF5="Withdrawn",BF5="Invalid",BF5="Quashed"),IF(OR(G5="Complete",G5="On Site",G5="Part Complete"),"Conflict – register not live but CIS says built","Conflict – not live in register"),IF(AND(G5="Plans Submitted",OR(BF5="Granted",BF5="Granted on appeal")),"Stage out of date – now granted",IF(AND(G5<>"Plans Submitted",OR(BF5="Pending",BF5="Under appeal")),"Check – register still pending",IF(N(BL5)>Method!$B$7,"Check – location differs",IF(AND(BP5<>"",ABS(N(BP5))>60),"Consistent – decision date differs","Consistent")))))))) -> Consistent
A6: 1015929 | B6: P-1015929 | D6: €2m - Housing Development | E6: Cuairt na hAbhann, Clarina Village | F6: Other County Limerick | G6: Permission Granted | H6: Plans Granted | J6: 43398 | K6: 43735 | L6: 43403.503 | M6: Granted/delivery CIS export | N6: Yes | P6: General | Q6: 17 | T6: Primary | V6: Only live application on site | W6: High | Y6: =IF(X6<>"",X6,T6) -> Primary | Z6: =IF(OR(Y6="Primary",Y6="Additional phase",Y6="Additional application on site",Y6="Replaces earlier",Y6="Extension of duration (parent not in CIS)"),"Yes","No") -> Yes | AB6: =IF(L6="","",ROUND((Method!$B$4-L6)/30.44,0)) -> 95 | AC6: =IF(AB6="","No",IF(AB6>Method!$B$5,"Yes","No")) -> Yes | AD6: =IF(BJ6<>"",BJ6,IF(K6<>"",EDATE(K6,60),"")) -> 45562 | AE6: =IF(AND(AD6<>"",OR(G6="Permission Granted",G6="Commencement Expected",G6="Stalled or Suspended")),IF(AD6<Method!$B$4,"Yes","No"),"No") -> Yes | AG6: =IF(Z6="No","Not counted",IF(AF6="Lapsed or dead","Excluded",IF(AF6="Constrained","Constrained / uncertain",IF(AF6="Confirmed live",IF(G6="On Site","Committed",IF(G6="Part Complete","Committed",IF(G6="Contract Awarded","Committed Pre-Construction",IF(G6="Tender","Advanced Pre-Construction",IF(G6="Commencement Expected","Likely",IF(G6="Permission Granted","Potential",IF(G6="Stalled or Suspended","Constrained / uncertain",IF(G6="Complete","Delivered","Application Pipeline")))))))),IF(G6="Complete","Delivered",IF(AND(OR(G6="Permission Granted",G6="Commencement Expected"),OR(AC6="Yes",AE6="Yes")),"Constrained / uncertain",IF(G6="On Site","Committed",IF(G6="Part Complete","Committed",IF(G6="Contract Awarded","Committed Pre-Construction",IF(G6="Tender","Advanced Pre-Construction",IF(G6="Commencement Expected","Likely",IF(G6="Permission Granted","Potential",IF(G6="Stalled or Suspended","Constrained / uncertain",IF(G6="Complete","Delivered","Application Pipeline")))))))))))))) -> Constrained / uncertain | AH6: =IF(Z6="No","Relationship: "&Y6,IF(AF6<>"","Analyst: "&AF6,IF(G6="Complete","Complete",IF(AND(OR(G6="Permission Granted",G6="Commencement Expected"),AE6="Yes"),"Past expiry",IF(AND(OR(G6="Permission Granted",G6="Commencement Expected"),AC6="Yes"),"No CIS update in "&AB6&" months","As CIS"))))) -> Past expiry | AI6: =IF(Z6="Yes",N(Q6),0) -> 17 | AJ6: =IF(OR(Z6="No",G6="Complete"),0,MAX(N(Q6)-N(AA6),0)) -> 17 | AK6: =IF(Z6="No",0,IF(G6="Complete",N(Q6),MIN(N(AA6),N(Q6)))) -> 0 | AL6: =IF(OR(OR(AG6="Not counted",AG6="Excluded",AG6="Delivered"),P6="Student accommodation"),0,AJ6) -> 17 | AM6: =IF(OR(OR(AG6="Not counted",AG6="Excluded",AG6="Delivered"),P6<>"Student accommodation"),0,AJ6) -> 0 | AN6: =IF(OR(AG6="Not counted",AG6="Excluded",AG6="Delivered"),0,N(S6)) -> 0 | AO6: Not available (not in register) | AV6: =N(AP6)+N(AQ6)+N(AR6)+N(AS6)+N(AT6)+N(AU6) -> 0 | BA6: No reference | BF6: No reference | BP6: =IF(OR(K6="",BG6=""),"",ROUND(BG6-K6,0)) | BQ6: =IF(OR(N(BK6)=0,Q6=""),"Not recorded",IF(BK6=Q6,"Match","Differs")) -> Not recorded | BR6: =IF(N6="No","Excluded (non-residential)",IF(BF6="No reference","Unverified – no reference",IF(BF6="Not in council register","Unverified – not in register (Part 8 / other)",IF(OR(BF6="Refused",BF6="Refused on appeal",BF6="Withdrawn",BF6="Invalid",BF6="Quashed"),IF(OR(G6="Complete",G6="On Site",G6="Part Complete"),"Conflict – register not live but CIS says built","Conflict – not live in register"),IF(AND(G6="Plans Submitted",OR(BF6="Granted",BF6="Granted on appeal")),"Stage out of date – now granted",IF(AND(G6<>"Plans Submitted",OR(BF6="Pending",BF6="Under appeal")),"Check – register still pending",IF(N(BL6)>Method!$B$7,"Check – location differs",IF(AND(BP6<>"",ABS(N(BP6))>60),"Consistent – decision date differs","Consistent")))))))) -> Unverified – no reference
A7: 1015932 | B7: P-1015932 | C7: 188014 | D7: €1.7m - Residential Development, Rosbrien Road | E7: Gough Place, Rosbrien Road | F7: Other County Limerick | G7: Complete | H7: Plans Granted | I7: Completed | J7: 43395 | K7: 43451 | L7: 45014.634 | M7: Granted/delivery CIS export | N7: Yes | P7: General | Q7: 17 | R7: 17 | T7: Primary | V7: Only live application on site | W7: High | Y7: =IF(X7<>"",X7,T7) -> Primary | Z7: =IF(OR(Y7="Primary",Y7="Additional phase",Y7="Additional application on site",Y7="Replaces earlier",Y7="Extension of duration (parent not in CIS)"),"Yes","No") -> Yes | AB7: =IF(L7="","",ROUND((Method!$B$4-L7)/30.44,0)) -> 42 | AC7: =IF(AB7="","No",IF(AB7>Method!$B$5,"Yes","No")) -> Yes | AD7: =IF(BJ7<>"",BJ7,IF(K7<>"",EDATE(K7,60),"")) -> 45277 | AE7: =IF(AND(AD7<>"",OR(G7="Permission Granted",G7="Commencement Expected",G7="Stalled or Suspended")),IF(AD7<Method!$B$4,"Yes","No"),"No") -> No | AG7: =IF(Z7="No","Not counted",IF(AF7="Lapsed or dead","Excluded",IF(AF7="Constrained","Constrained / uncertain",IF(AF7="Confirmed live",IF(G7="On Site","Committed",IF(G7="Part Complete","Committed",IF(G7="Contract Awarded","Committed Pre-Construction",IF(G7="Tender","Advanced Pre-Construction",IF(G7="Commencement Expected","Likely",IF(G7="Permission Granted","Potential",IF(G7="Stalled or Suspended","Constrained / uncertain",IF(G7="Complete","Delivered","Application Pipeline")))))))),IF(G7="Complete","Delivered",IF(AND(OR(G7="Permission Granted",G7="Commencement Expected"),OR(AC7="Yes",AE7="Yes")),"Constrained / uncertain",IF(G7="On Site","Committed",IF(G7="Part Complete","Committed",IF(G7="Contract Awarded","Committed Pre-Construction",IF(G7="Tender","Advanced Pre-Construction",IF(G7="Commencement Expected","Likely",IF(G7="Permission Granted","Potential",IF(G7="Stalled or Suspended","Constrained / uncertain",IF(G7="Complete","Delivered","Application Pipeline")))))))))))))) -> Delivered | AH7: =IF(Z7="No","Relationship: "&Y7,IF(AF7<>"","Analyst: "&AF7,IF(G7="Complete","Complete",IF(AND(OR(G7="Permission Granted",G7="Commencement Expected"),AE7="Yes"),"Past expiry",IF(AND(OR(G7="Permission Granted",G7="Commencement Expected"),AC7="Yes"),"No CIS update in "&AB7&" months","As CIS"))))) -> Complete | AI7: =IF(Z7="Yes",N(Q7),0) -> 17 | AJ7: =IF(OR(Z7="No",G7="Complete"),0,MAX(N(Q7)-N(AA7),0)) -> 0 | AK7: =IF(Z7="No",0,IF(G7="Complete",N(Q7),MIN(N(AA7),N(Q7)))) -> 17 | AL7: =IF(OR(OR(AG7="Not counted",AG7="Excluded",AG7="Delivered"),P7="Student accommodation"),0,AJ7) -> 0 | AM7: =IF(OR(OR(AG7="Not counted",AG7="Excluded",AG7="Delivered"),P7<>"Student accommodation"),0,AJ7) -> 0 | AN7: =IF(OR(AG7="Not counted",AG7="Excluded",AG7="Delivered"),0,N(S7)) -> 0 | AO7: Register description | AQ7: 2 | AR7: 4 | AS7: 11 | AV7: =N(AP7)+N(AQ7)+N(AR7)+N(AS7)+N(AT7)+N(AU7) -> 17 | AW7: 5 | AX7: 12 | BA7: Council register | BB7: 188014 | BC7: DECISION MADE | BD7: CONDITIONAL | BF7: Granted | BG7: 43445 | BK7: 17 | BL7: 0 | BN7: (a) provision of 17 no. residential units comprising; 5 no. two storey 3 bedroom dwellings; 2 no. 1 bedroom apartments, 4 no. 2 bedroom apartments and 6 no. 3 bedrooms duplex apartments; (b) relocation of existing pitch including new fencing, floodlights and retaining walls; (c) provision of new exi | BO7: https://eplanning.ie/LimerickCCC/AppFileRefDetails/188014/0 | BP7: =IF(OR(K7="",BG7=""),"",ROUND(BG7-K7,0)) -> -6 | BQ7: =IF(OR(N(BK7)=0,Q7=""),"Not recorded",IF(BK7=Q7,"Match","Differs")) -> Match | BR7: =IF(N7="No","Excluded (non-residential)",IF(BF7="No reference","Unverified – no reference",IF(BF7="Not in council register","Unverified – not in register (Part 8 / other)",IF(OR(BF7="Refused",BF7="Refused on appeal",BF7="Withdrawn",BF7="Invalid",BF7="Quashed"),IF(OR(G7="Complete",G7="On Site",G7="Part Complete"),"Conflict – register not live but CIS says built","Conflict – not live in register"),IF(AND(G7="Plans Submitted",OR(BF7="Granted",BF7="Granted on appeal")),"Stage out of date – now granted",IF(AND(G7<>"Plans Submitted",OR(BF7="Pending",BF7="Under appeal")),"Check – register still pending",IF(N(BL7)>Method!$B$7,"Check – location differs",IF(AND(BP7<>"",ABS(N(BP7))>60),"Consistent – decision date differs","Consistent")))))))) -> Consistent | BS7: 1816 | BT7: SHIP LA Construction | BU7: *N/A | BV7: Completed | BW7: Q4-2022 | BX7: Local authority (construction)
