Workbook

Sheet Summary
A1: Limerick housing land register
A2: Council audit parcels plus parcels for residential consents outside the audit. Every permission is linked to one parcel; totals are calculated from the Permissions sheet.
A4: By parcel source
B5: Parcels | C5: Developable ha | D5: Consented | E5: Built to date | F5: Unconsented capacity | G5: Total supply | H5: Future supply
A6: Council audit | B6: =COUNTIFS(Parcels!$B$2:$B$3000,$A6) -> 131 | C6: =SUMIFS(Parcels!$P$2:$P$3000,Parcels!$B$2:$B$3000,$A6) -> 313.164 | D6: =SUMIFS(Parcels!$AM$2:$AM$3000,Parcels!$B$2:$B$3000,$A6) -> 5225 | E6: =SUMIFS(Parcels!$AR$2:$AR$3000,Parcels!$B$2:$B$3000,$A6) -> 227 | F6: =SUMIFS(Parcels!$AP$2:$AP$3000,Parcels!$B$2:$B$3000,$A6) -> 10104 | G6: =SUMIFS(Parcels!$AQ$2:$AQ$3000,Parcels!$B$2:$B$3000,$A6) -> 15329 | H6: =SUMIFS(Parcels!$AS$2:$AS$3000,Parcels!$B$2:$B$3000,$A6) -> 15102
A7: Council audit – reinstated | B7: =COUNTIFS(Parcels!$B$2:$B$3000,$A7) -> 3 | C7: =SUMIFS(Parcels!$P$2:$P$3000,Parcels!$B$2:$B$3000,$A7) -> 3.993 | D7: =SUMIFS(Parcels!$AM$2:$AM$3000,Parcels!$B$2:$B$3000,$A7) -> 27 | E7: =SUMIFS(Parcels!$AR$2:$AR$3000,Parcels!$B$2:$B$3000,$A7) -> 0 | F7: =SUMIFS(Parcels!$AP$2:$AP$3000,Parcels!$B$2:$B$3000,$A7) -> 138 | G7: =SUMIFS(Parcels!$AQ$2:$AQ$3000,Parcels!$B$2:$B$3000,$A7) -> 165 | H7: =SUMIFS(Parcels!$AS$2:$AS$3000,Parcels!$B$2:$B$3000,$A7) -> 165
A8: Planning consent – not in council audit | B8: =COUNTIFS(Parcels!$B$2:$B$3000,$A8) -> 184 | C8: =SUMIFS(Parcels!$P$2:$P$3000,Parcels!$B$2:$B$3000,$A8) -> 216.101 | D8: =SUMIFS(Parcels!$AM$2:$AM$3000,Parcels!$B$2:$B$3000,$A8) -> 5204 | E8: =SUMIFS(Parcels!$AR$2:$AR$3000,Parcels!$B$2:$B$3000,$A8) -> 1999 | F8: =SUMIFS(Parcels!$AP$2:$AP$3000,Parcels!$B$2:$B$3000,$A8) -> 195 | G8: =SUMIFS(Parcels!$AQ$2:$AQ$3000,Parcels!$B$2:$B$3000,$A8) -> 5399 | H8: =SUMIFS(Parcels!$AS$2:$AS$3000,Parcels!$B$2:$B$3000,$A8) -> 3400
A9: Zoned land – no consent (estimate) | B9: =COUNTIFS(Parcels!$B$2:$B$3000,$A9) -> 88 | C9: =SUMIFS(Parcels!$P$2:$P$3000,Parcels!$B$2:$B$3000,$A9) -> 118.343 | D9: =SUMIFS(Parcels!$AM$2:$AM$3000,Parcels!$B$2:$B$3000,$A9) -> 0 | E9: =SUMIFS(Parcels!$AR$2:$AR$3000,Parcels!$B$2:$B$3000,$A9) -> 0 | F9: =SUMIFS(Parcels!$AP$2:$AP$3000,Parcels!$B$2:$B$3000,$A9) -> 2805 | G9: =SUMIFS(Parcels!$AQ$2:$AQ$3000,Parcels!$B$2:$B$3000,$A9) -> 2805 | H9: =SUMIFS(Parcels!$AS$2:$AS$3000,Parcels!$B$2:$B$3000,$A9) -> 2805
A10: Total | B10: =SUM(B6:B9) -> 406 | C10: =SUM(C6:C9) -> 651.601 | D10: =SUM(D6:D9) -> 10456 | E10: =SUM(E6:E9) -> 2226 | F10: =SUM(F6:F9) -> 13242 | G10: =SUM(G6:G9) -> 23698 | H10: =SUM(H6:H9) -> 21472
A12: By scope
B13: Parcels | C13: Developable ha | D13: Consented | E13: Built to date | F13: Unconsented capacity | G13: Total supply | H13: Future supply
A14: City | B14: =COUNTIFS(Parcels!$C$2:$C$3000,$A14) -> 241 | C14: =SUMIFS(Parcels!$P$2:$P$3000,Parcels!$C$2:$C$3000,$A14) -> 420.728 | D14: =SUMIFS(Parcels!$AM$2:$AM$3000,Parcels!$C$2:$C$3000,$A14) -> 8543 | E14: =SUMIFS(Parcels!$AR$2:$AR$3000,Parcels!$C$2:$C$3000,$A14) -> 1878 | F14: =SUMIFS(Parcels!$AP$2:$AP$3000,Parcels!$C$2:$C$3000,$A14) -> 10400 | G14: =SUMIFS(Parcels!$AQ$2:$AQ$3000,Parcels!$C$2:$C$3000,$A14) -> 18943 | H14: =SUMIFS(Parcels!$AS$2:$AS$3000,Parcels!$C$2:$C$3000,$A14) -> 17065
A15: County | B15: =COUNTIFS(Parcels!$C$2:$C$3000,$A15) -> 206 | C15: =SUMIFS(Parcels!$P$2:$P$3000,Parcels!$C$2:$C$3000,$A15) -> 272.358 | D15: =SUMIFS(Parcels!$AM$2:$AM$3000,Parcels!$C$2:$C$3000,$A15) -> 1951 | E15: =SUMIFS(Parcels!$AR$2:$AR$3000,Parcels!$C$2:$C$3000,$A15) -> 354 | F15: =SUMIFS(Parcels!$AP$2:$AP$3000,Parcels!$C$2:$C$3000,$A15) -> 3532 | G15: =SUMIFS(Parcels!$AQ$2:$AQ$3000,Parcels!$C$2:$C$3000,$A15) -> 5483 | H15: =SUMIFS(Parcels!$AS$2:$AS$3000,Parcels!$C$2:$C$3000,$A15) -> 5129
A16: Total | B16: =SUM(B14:B15) -> 447 | C16: =SUM(C14:C15) -> 693.086 | D16: =SUM(D14:D15) -> 10494 | E16: =SUM(E14:E15) -> 2232 | F16: =SUM(F14:F15) -> 13932 | G16: =SUM(G14:G15) -> 24426 | H16: =SUM(H14:H15) -> 22194
A18: By catchment type
B19: Parcels | C19: Developable ha | D19: Consented | E19: Built to date | F19: Unconsented capacity | G19: Total supply | H19: Future supply
A20: City neighbourhood | B20: =COUNTIFS(Parcels!$E$2:$E$3000,$A20) -> 241 | C20: =SUMIFS(Parcels!$P$2:$P$3000,Parcels!$E$2:$E$3000,$A20) -> 420.728 | D20: =SUMIFS(Parcels!$AM$2:$AM$3000,Parcels!$E$2:$E$3000,$A20) -> 8543 | E20: =SUMIFS(Parcels!$AR$2:$AR$3000,Parcels!$E$2:$E$3000,$A20) -> 1878 | F20: =SUMIFS(Parcels!$AP$2:$AP$3000,Parcels!$E$2:$E$3000,$A20) -> 10400 | G20: =SUMIFS(Parcels!$AQ$2:$AQ$3000,Parcels!$E$2:$E$3000,$A20) -> 18943 | H20: =SUMIFS(Parcels!$AS$2:$AS$3000,Parcels!$E$2:$E$3000,$A20) -> 17065
A21: Key town | B21: =COUNTIFS(Parcels!$E$2:$E$3000,$A21) -> 80 | C21: =SUMIFS(Parcels!$P$2:$P$3000,Parcels!$E$2:$E$3000,$A21) -> 125.614 | D21: =SUMIFS(Parcels!$AM$2:$AM$3000,Parcels!$E$2:$E$3000,$A21) -> 618 | E21: =SUMIFS(Parcels!$AR$2:$AR$3000,Parcels!$E$2:$E$3000,$A21) -> 118 | F21: =SUMIFS(Parcels!$AP$2:$AP$3000,Parcels!$E$2:$E$3000,$A21) -> 2327 | G21: =SUMIFS(Parcels!$AQ$2:$AQ$3000,Parcels!$E$2:$E$3000,$A21) -> 2945 | H21: =SUMIFS(Parcels!$AS$2:$AS$3000,Parcels!$E$2:$E$3000,$A21) -> 2827
A22: Large village | B22: =COUNTIFS(Parcels!$E$2:$E$3000,$A22) -> 80 | C22: =SUMIFS(Parcels!$P$2:$P$3000,Parcels!$E$2:$E$3000,$A22) -> 104.484 | D22: =SUMIFS(Parcels!$AM$2:$AM$3000,Parcels!$E$2:$E$3000,$A22) -> 1120 | E22: =SUMIFS(Parcels!$AR$2:$AR$3000,Parcels!$E$2:$E$3000,$A22) -> 189 | F22: =SUMIFS(Parcels!$AP$2:$AP$3000,Parcels!$E$2:$E$3000,$A22) -> 789 | G22: =SUMIFS(Parcels!$AQ$2:$AQ$3000,Parcels!$E$2:$E$3000,$A22) -> 1909 | H22: =SUMIFS(Parcels!$AS$2:$AS$3000,Parcels!$E$2:$E$3000,$A22) -> 1720
A23: Rest of county | B23: =COUNTIFS(Parcels!$E$2:$E$3000,$A23) -> 46 | C23: =SUMIFS(Parcels!$P$2:$P$3000,Parcels!$E$2:$E$3000,$A23) -> 42.26 | D23: =SUMIFS(Parcels!$AM$2:$AM$3000,Parcels!$E$2:$E$3000,$A23) -> 213 | E23: =SUMIFS(Parcels!$AR$2:$AR$3000,Parcels!$E$2:$E$3000,$A23) -> 47 | F23: =SUMIFS(Parcels!$AP$2:$AP$3000,Parcels!$E$2:$E$3000,$A23) -> 416 | G23: =SUMIFS(Parcels!$AQ$2:$AQ$3000,Parcels!$E$2:$E$3000,$A23) -> 629 | H23: =SUMIFS(Parcels!$AS$2:$AS$3000,Parcels!$E$2:$E$3000,$A23) -> 582
A24: Total | B24: =SUM(B20:B23) -> 447 | C24: =SUM(C20:C23) -> 693.086 | D24: =SUM(D20:D23) -> 10494 | E24: =SUM(E20:E23) -> 2232 | F24: =SUM(F20:F23) -> 13932 | G24: =SUM(G20:G23) -> 24426 | H24: =SUM(H20:H23) -> 22194
A26: By parcel status
B27: Parcels | C27: Developable ha | D27: Consented | E27: Built to date | F27: Unconsented capacity | G27: Total supply | H27: Future supply
A28: Finished | B28: =COUNTIFS(Parcels!$BC$2:$BC$3000,$A28) -> 50 | C28: =SUMIFS(Parcels!$P$2:$P$3000,Parcels!$BC$2:$BC$3000,$A28) -> 59.406 | D28: =SUMIFS(Parcels!$AM$2:$AM$3000,Parcels!$BC$2:$BC$3000,$A28) -> 1196 | E28: =SUMIFS(Parcels!$AR$2:$AR$3000,Parcels!$BC$2:$BC$3000,$A28) -> 1196 | F28: =SUMIFS(Parcels!$AP$2:$AP$3000,Parcels!$BC$2:$BC$3000,$A28) -> 0 | G28: =SUMIFS(Parcels!$AQ$2:$AQ$3000,Parcels!$BC$2:$BC$3000,$A28) -> 1196 | H28: =SUMIFS(Parcels!$AS$2:$AS$3000,Parcels!$BC$2:$BC$3000,$A28) -> 0
A29: Partly built | B29: =COUNTIFS(Parcels!$BC$2:$BC$3000,$A29) -> 23 | C29: =SUMIFS(Parcels!$P$2:$P$3000,Parcels!$BC$2:$BC$3000,$A29) -> 128.138 | D29: =SUMIFS(Parcels!$AM$2:$AM$3000,Parcels!$BC$2:$BC$3000,$A29) -> 2209 | E29: =SUMIFS(Parcels!$AR$2:$AR$3000,Parcels!$BC$2:$BC$3000,$A29) -> 1036 | F29: =SUMIFS(Parcels!$AP$2:$AP$3000,Parcels!$BC$2:$BC$3000,$A29) -> 2625 | G29: =SUMIFS(Parcels!$AQ$2:$AQ$3000,Parcels!$BC$2:$BC$3000,$A29) -> 4834 | H29: =SUMIFS(Parcels!$AS$2:$AS$3000,Parcels!$BC$2:$BC$3000,$A29) -> 3798
A30: Consented – not built | B30: =COUNTIFS(Parcels!$BC$2:$BC$3000,$A30) -> 130 | C30: =SUMIFS(Parcels!$P$2:$P$3000,Parcels!$BC$2:$BC$3000,$A30) -> 210.641 | D30: =SUMIFS(Parcels!$AM$2:$AM$3000,Parcels!$BC$2:$BC$3000,$A30) -> 7089 | E30: =SUMIFS(Parcels!$AR$2:$AR$3000,Parcels!$BC$2:$BC$3000,$A30) -> 0 | F30: =SUMIFS(Parcels!$AP$2:$AP$3000,Parcels!$BC$2:$BC$3000,$A30) -> 1660 | G30: =SUMIFS(Parcels!$AQ$2:$AQ$3000,Parcels!$BC$2:$BC$3000,$A30) -> 8749 | H30: =SUMIFS(Parcels!$AS$2:$AS$3000,Parcels!$BC$2:$BC$3000,$A30) -> 8749
A31: No consent | B31: =COUNTIFS(Parcels!$BC$2:$BC$3000,$A31) -> 244 | C31: =SUMIFS(Parcels!$P$2:$P$3000,Parcels!$BC$2:$BC$3000,$A31) -> 294.901 | D31: =SUMIFS(Parcels!$AM$2:$AM$3000,Parcels!$BC$2:$BC$3000,$A31) -> 0 | E31: =SUMIFS(Parcels!$AR$2:$AR$3000,Parcels!$BC$2:$BC$3000,$A31) -> 0 | F31: =SUMIFS(Parcels!$AP$2:$AP$3000,Parcels!$BC$2:$BC$3000,$A31) -> 9647 | G31: =SUMIFS(Parcels!$AQ$2:$AQ$3000,Parcels!$BC$2:$BC$3000,$A31) -> 9647 | H31: =SUMIFS(Parcels!$AS$2:$AS$3000,Parcels!$BC$2:$BC$3000,$A31) -> 9647
A32: Total | B32: =SUM(B28:B31) -> 447 | C32: =SUM(C28:C31) -> 693.086 | D32: =SUM(D28:D31) -> 10494 | E32: =SUM(E28:E31) -> 2232 | F32: =SUM(F28:F31) -> 13932 | G32: =SUM(G28:G31) -> 24426 | H32: =SUM(H28:H31) -> 22194
A34: Expected completions (consented schemes; estimates)
B35: Q4 2026 | C35: 2027 | D35: 2028 | E35: 2029 | F35: 2030 | G35: 2031+
A36: All parcels | B36: =SUM(Parcels!$AT$2:$AT$3000) -> 506.2 | C36: =SUM(Parcels!$AU$2:$AU$3000) -> 2084.7 | D36: =SUM(Parcels!$AV$2:$AV$3000) -> 1725.2 | E36: =SUM(Parcels!$AW$2:$AW$3000) -> 1954.7 | F36: =SUM(Parcels!$AX$2:$AX$3000) -> 851 | G36: =SUM(Parcels!$AY$2:$AY$3000) -> 1573.2
A38: Checks (all should be zero)
A39: Permissions with a problem (see check column) | B39: =COUNTIF(Permissions!$AT$2:$AT$3000,"?*") -> 0
A40: Parcels with a flag | B40: =COUNTIF(Parcels!$BD$2:$BD$3000,"?*")-COUNTIF(Parcels!$BD$2:$BD$3000,"Consented above capacity") -> 0
A41: Units on Permissions not reaching a parcel | B41: =SUMIFS(Permissions!$G$2:$G$3000,Permissions!$R$2:$R$3000,"Yes")-SUM(Parcels!$AM$2:$AM$3000)-SUM(Parcels!$AN$2:$AN$3000)-SUM(Parcels!$AO$2:$AO$3000) -> 0
A42: Permissions with no parcel_id | B42: =COUNTIFS(Permissions!$A$2:$A$3000,"?*",Permissions!$B$2:$B$3000,"") -> 0
A43: Parcels consented above council capacity (review capacity) | B43: =COUNTIF(Parcels!$BD$2:$BD$3000,"Consented above capacity") -> 14
A45: Blue-grey columns are calculated. Edit only the white columns. capacity_units (council estimate on audit parcels, zoning estimate on zoned-land parcels) is the only unit figure typed on the Parcels sheet.

Sheet Catchments
A1: Supply by study catchment
A2: Each parcel is assigned to the catchment it overlaps most. Parcels just outside a key town or village are added to it when zoned in its LAP, within 500 m, or named in the scheme and within 2 km (catchment_basis on Parcels). Live formulas on the Parcels sheet.
A4: Catchment type | B4: Catchment | C4: Parcels | D4: Developable ha | E4: Consented | F4: Complete | G4: Under construction | H4: Permitted, not started | I4: Unconsented capacity | J4: Total supply | K4: Future supply | L4: Q4 2026 | M4: 2027 | N4: 2028 | O4: 2029 | P4: 2030 | Q4: 2031+
A5: City neighbourhood | B5: Ballinacurra | C5: =COUNTIFS(Parcels!$D$2:$D$3000,$B5) -> 9 | D5: =SUMIFS(Parcels!$P$2:$P$3000,Parcels!$D$2:$D$3000,$B5) -> 5.562 | E5: =SUMIFS(Parcels!$AM$2:$AM$3000,Parcels!$D$2:$D$3000,$B5) -> 415 | F5: =SUMIFS(Parcels!$AI$2:$AI$3000,Parcels!$D$2:$D$3000,$B5) -> 17 | G5: =SUMIFS(Parcels!$AJ$2:$AJ$3000,Parcels!$D$2:$D$3000,$B5) -> 398 | H5: =SUMIFS(Parcels!$AK$2:$AK$3000,Parcels!$D$2:$D$3000,$B5) -> 0 | I5: =SUMIFS(Parcels!$AP$2:$AP$3000,Parcels!$D$2:$D$3000,$B5) -> 153 | J5: =SUMIFS(Parcels!$AQ$2:$AQ$3000,Parcels!$D$2:$D$3000,$B5) -> 568 | K5: =SUMIFS(Parcels!$AS$2:$AS$3000,Parcels!$D$2:$D$3000,$B5) -> 430 | L5: =SUMIFS(Parcels!$AT$2:$AT$3000,Parcels!$D$2:$D$3000,$B5) -> 24.7 | M5: =SUMIFS(Parcels!$AU$2:$AU$3000,Parcels!$D$2:$D$3000,$B5) -> 107 | N5: =SUMIFS(Parcels!$AV$2:$AV$3000,Parcels!$D$2:$D$3000,$B5) -> 93 | O5: =SUMIFS(Parcels!$AW$2:$AW$3000,Parcels!$D$2:$D$3000,$B5) -> 88.5 | P5: =SUMIFS(Parcels!$AX$2:$AX$3000,Parcels!$D$2:$D$3000,$B5) -> 84.9 | Q5: =SUMIFS(Parcels!$AY$2:$AY$3000,Parcels!$D$2:$D$3000,$B5) -> -0.1
A6: City neighbourhood | B6: Caherdavin | C6: =COUNTIFS(Parcels!$D$2:$D$3000,$B6) -> 33 | D6: =SUMIFS(Parcels!$P$2:$P$3000,Parcels!$D$2:$D$3000,$B6) -> 64.726 | E6: =SUMIFS(Parcels!$AM$2:$AM$3000,Parcels!$D$2:$D$3000,$B6) -> 1298 | F6: =SUMIFS(Parcels!$AI$2:$AI$3000,Parcels!$D$2:$D$3000,$B6) -> 152 | G6: =SUMIFS(Parcels!$AJ$2:$AJ$3000,Parcels!$D$2:$D$3000,$B6) -> 539 | H6: =SUMIFS(Parcels!$AK$2:$AK$3000,Parcels!$D$2:$D$3000,$B6) -> 576 | I6: =SUMIFS(Parcels!$AP$2:$AP$3000,Parcels!$D$2:$D$3000,$B6) -> 985 | J6: =SUMIFS(Parcels!$AQ$2:$AQ$3000,Parcels!$D$2:$D$3000,$B6) -> 2283 | K6: =SUMIFS(Parcels!$AS$2:$AS$3000,Parcels!$D$2:$D$3000,$B6) -> 2083 | L6: =SUMIFS(Parcels!$AT$2:$AT$3000,Parcels!$D$2:$D$3000,$B6) -> 64.5 | M6: =SUMIFS(Parcels!$AU$2:$AU$3000,Parcels!$D$2:$D$3000,$B6) -> 306.2 | N6: =SUMIFS(Parcels!$AV$2:$AV$3000,Parcels!$D$2:$D$3000,$B6) -> 337.3 | O6: =SUMIFS(Parcels!$AW$2:$AW$3000,Parcels!$D$2:$D$3000,$B6) -> 304.1 | P6: =SUMIFS(Parcels!$AX$2:$AX$3000,Parcels!$D$2:$D$3000,$B6) -> 102.8 | Q6: =SUMIFS(Parcels!$AY$2:$AY$3000,Parcels!$D$2:$D$3000,$B6) -> 0.1
A7: City neighbourhood | B7: Castletroy/Annacotty | C7: =COUNTIFS(Parcels!$D$2:$D$3000,$B7) -> 32 | D7: =SUMIFS(Parcels!$P$2:$P$3000,Parcels!$D$2:$D$3000,$B7) -> 99.594 | E7: =SUMIFS(Parcels!$AM$2:$AM$3000,Parcels!$D$2:$D$3000,$B7) -> 2822 | F7: =SUMIFS(Parcels!$AI$2:$AI$3000,Parcels!$D$2:$D$3000,$B7) -> 628 | G7: =SUMIFS(Parcels!$AJ$2:$AJ$3000,Parcels!$D$2:$D$3000,$B7) -> 604 | H7: =SUMIFS(Parcels!$AK$2:$AK$3000,Parcels!$D$2:$D$3000,$B7) -> 1590 | I7: =SUMIFS(Parcels!$AP$2:$AP$3000,Parcels!$D$2:$D$3000,$B7) -> 1193 | J7: =SUMIFS(Parcels!$AQ$2:$AQ$3000,Parcels!$D$2:$D$3000,$B7) -> 4015 | K7: =SUMIFS(Parcels!$AS$2:$AS$3000,Parcels!$D$2:$D$3000,$B7) -> 3219 | L7: =SUMIFS(Parcels!$AT$2:$AT$3000,Parcels!$D$2:$D$3000,$B7) -> 139.5 | M7: =SUMIFS(Parcels!$AU$2:$AU$3000,Parcels!$D$2:$D$3000,$B7) -> 463.2 | N7: =SUMIFS(Parcels!$AV$2:$AV$3000,Parcels!$D$2:$D$3000,$B7) -> 23.4 | O7: =SUMIFS(Parcels!$AW$2:$AW$3000,Parcels!$D$2:$D$3000,$B7) -> 473.6 | P7: =SUMIFS(Parcels!$AX$2:$AX$3000,Parcels!$D$2:$D$3000,$B7) -> 202.6 | Q7: =SUMIFS(Parcels!$AY$2:$AY$3000,Parcels!$D$2:$D$3000,$B7) -> 891.7
A8: City neighbourhood | B8: City Centre | C8: =COUNTIFS(Parcels!$D$2:$D$3000,$B8) -> 55 | D8: =SUMIFS(Parcels!$P$2:$P$3000,Parcels!$D$2:$D$3000,$B8) -> 81.522 | E8: =SUMIFS(Parcels!$AM$2:$AM$3000,Parcels!$D$2:$D$3000,$B8) -> 925 | F8: =SUMIFS(Parcels!$AI$2:$AI$3000,Parcels!$D$2:$D$3000,$B8) -> 99 | G8: =SUMIFS(Parcels!$AJ$2:$AJ$3000,Parcels!$D$2:$D$3000,$B8) -> 111 | H8: =SUMIFS(Parcels!$AK$2:$AK$3000,Parcels!$D$2:$D$3000,$B8) -> 715 | I8: =SUMIFS(Parcels!$AP$2:$AP$3000,Parcels!$D$2:$D$3000,$B8) -> 3412 | J8: =SUMIFS(Parcels!$AQ$2:$AQ$3000,Parcels!$D$2:$D$3000,$B8) -> 4337 | K8: =SUMIFS(Parcels!$AS$2:$AS$3000,Parcels!$D$2:$D$3000,$B8) -> 4238 | L8: =SUMIFS(Parcels!$AT$2:$AT$3000,Parcels!$D$2:$D$3000,$B8) -> 13.8 | M8: =SUMIFS(Parcels!$AU$2:$AU$3000,Parcels!$D$2:$D$3000,$B8) -> 85.5 | N8: =SUMIFS(Parcels!$AV$2:$AV$3000,Parcels!$D$2:$D$3000,$B8) -> 242.4 | O8: =SUMIFS(Parcels!$AW$2:$AW$3000,Parcels!$D$2:$D$3000,$B8) -> 258.9 | P8: =SUMIFS(Parcels!$AX$2:$AX$3000,Parcels!$D$2:$D$3000,$B8) -> 72.7 | Q8: =SUMIFS(Parcels!$AY$2:$AY$3000,Parcels!$D$2:$D$3000,$B8) -> 152.7
A9: City neighbourhood | B9: Corbally/Grove Island | C9: =COUNTIFS(Parcels!$D$2:$D$3000,$B9) -> 12 | D9: =SUMIFS(Parcels!$P$2:$P$3000,Parcels!$D$2:$D$3000,$B9) -> 19.019 | E9: =SUMIFS(Parcels!$AM$2:$AM$3000,Parcels!$D$2:$D$3000,$B9) -> 90 | F9: =SUMIFS(Parcels!$AI$2:$AI$3000,Parcels!$D$2:$D$3000,$B9) -> 24 | G9: =SUMIFS(Parcels!$AJ$2:$AJ$3000,Parcels!$D$2:$D$3000,$B9) -> 26 | H9: =SUMIFS(Parcels!$AK$2:$AK$3000,Parcels!$D$2:$D$3000,$B9) -> 40 | I9: =SUMIFS(Parcels!$AP$2:$AP$3000,Parcels!$D$2:$D$3000,$B9) -> 605 | J9: =SUMIFS(Parcels!$AQ$2:$AQ$3000,Parcels!$D$2:$D$3000,$B9) -> 695 | K9: =SUMIFS(Parcels!$AS$2:$AS$3000,Parcels!$D$2:$D$3000,$B9) -> 671 | L9: =SUMIFS(Parcels!$AT$2:$AT$3000,Parcels!$D$2:$D$3000,$B9) -> 6.1 | M9: =SUMIFS(Parcels!$AU$2:$AU$3000,Parcels!$D$2:$D$3000,$B9) -> 19.9 | N9: =SUMIFS(Parcels!$AV$2:$AV$3000,Parcels!$D$2:$D$3000,$B9) -> 23.5 | O9: =SUMIFS(Parcels!$AW$2:$AW$3000,Parcels!$D$2:$D$3000,$B9) -> 16.5 | P9: =SUMIFS(Parcels!$AX$2:$AX$3000,Parcels!$D$2:$D$3000,$B9) -> 0 | Q9: =SUMIFS(Parcels!$AY$2:$AY$3000,Parcels!$D$2:$D$3000,$B9) -> 0
A10: City neighbourhood | B10: Dooradoyle | C10: =COUNTIFS(Parcels!$D$2:$D$3000,$B10) -> 36 | D10: =SUMIFS(Parcels!$P$2:$P$3000,Parcels!$D$2:$D$3000,$B10) -> 103.808 | E10: =SUMIFS(Parcels!$AM$2:$AM$3000,Parcels!$D$2:$D$3000,$B10) -> 1920 | F10: =SUMIFS(Parcels!$AI$2:$AI$3000,Parcels!$D$2:$D$3000,$B10) -> 110 | G10: =SUMIFS(Parcels!$AJ$2:$AJ$3000,Parcels!$D$2:$D$3000,$B10) -> 1121 | H10: =SUMIFS(Parcels!$AK$2:$AK$3000,Parcels!$D$2:$D$3000,$B10) -> 689 | I10: =SUMIFS(Parcels!$AP$2:$AP$3000,Parcels!$D$2:$D$3000,$B10) -> 2811 | J10: =SUMIFS(Parcels!$AQ$2:$AQ$3000,Parcels!$D$2:$D$3000,$B10) -> 4731 | K10: =SUMIFS(Parcels!$AS$2:$AS$3000,Parcels!$D$2:$D$3000,$B10) -> 4454 | L10: =SUMIFS(Parcels!$AT$2:$AT$3000,Parcels!$D$2:$D$3000,$B10) -> 108.4 | M10: =SUMIFS(Parcels!$AU$2:$AU$3000,Parcels!$D$2:$D$3000,$B10) -> 439.7 | N10: =SUMIFS(Parcels!$AV$2:$AV$3000,Parcels!$D$2:$D$3000,$B10) -> 343.6 | O10: =SUMIFS(Parcels!$AW$2:$AW$3000,Parcels!$D$2:$D$3000,$B10) -> 391.1 | P10: =SUMIFS(Parcels!$AX$2:$AX$3000,Parcels!$D$2:$D$3000,$B10) -> 302.4 | Q10: =SUMIFS(Parcels!$AY$2:$AY$3000,Parcels!$D$2:$D$3000,$B10) -> 224.8
A11: City neighbourhood | B11: Kings Island | C11: =COUNTIFS(Parcels!$D$2:$D$3000,$B11) -> 5 | D11: =SUMIFS(Parcels!$P$2:$P$3000,Parcels!$D$2:$D$3000,$B11) -> 0.906 | E11: =SUMIFS(Parcels!$AM$2:$AM$3000,Parcels!$D$2:$D$3000,$B11) -> 50 | F11: =SUMIFS(Parcels!$AI$2:$AI$3000,Parcels!$D$2:$D$3000,$B11) -> 0 | G11: =SUMIFS(Parcels!$AJ$2:$AJ$3000,Parcels!$D$2:$D$3000,$B11) -> 0 | H11: =SUMIFS(Parcels!$AK$2:$AK$3000,Parcels!$D$2:$D$3000,$B11) -> 50 | I11: =SUMIFS(Parcels!$AP$2:$AP$3000,Parcels!$D$2:$D$3000,$B11) -> 25 | J11: =SUMIFS(Parcels!$AQ$2:$AQ$3000,Parcels!$D$2:$D$3000,$B11) -> 75 | K11: =SUMIFS(Parcels!$AS$2:$AS$3000,Parcels!$D$2:$D$3000,$B11) -> 75 | L11: =SUMIFS(Parcels!$AT$2:$AT$3000,Parcels!$D$2:$D$3000,$B11) -> 0 | M11: =SUMIFS(Parcels!$AU$2:$AU$3000,Parcels!$D$2:$D$3000,$B11) -> 0 | N11: =SUMIFS(Parcels!$AV$2:$AV$3000,Parcels!$D$2:$D$3000,$B11) -> 30.1 | O11: =SUMIFS(Parcels!$AW$2:$AW$3000,Parcels!$D$2:$D$3000,$B11) -> 19.6 | P11: =SUMIFS(Parcels!$AX$2:$AX$3000,Parcels!$D$2:$D$3000,$B11) -> 0.3 | Q11: =SUMIFS(Parcels!$AY$2:$AY$3000,Parcels!$D$2:$D$3000,$B11) -> 0
A12: City neighbourhood | B12: Singland/Garryowen | C12: =COUNTIFS(Parcels!$D$2:$D$3000,$B12) -> 28 | D12: =SUMIFS(Parcels!$P$2:$P$3000,Parcels!$D$2:$D$3000,$B12) -> 15.732 | E12: =SUMIFS(Parcels!$AM$2:$AM$3000,Parcels!$D$2:$D$3000,$B12) -> 269 | F12: =SUMIFS(Parcels!$AI$2:$AI$3000,Parcels!$D$2:$D$3000,$B12) -> 29 | G12: =SUMIFS(Parcels!$AJ$2:$AJ$3000,Parcels!$D$2:$D$3000,$B12) -> 108 | H12: =SUMIFS(Parcels!$AK$2:$AK$3000,Parcels!$D$2:$D$3000,$B12) -> 132 | I12: =SUMIFS(Parcels!$AP$2:$AP$3000,Parcels!$D$2:$D$3000,$B12) -> 517 | J12: =SUMIFS(Parcels!$AQ$2:$AQ$3000,Parcels!$D$2:$D$3000,$B12) -> 786 | K12: =SUMIFS(Parcels!$AS$2:$AS$3000,Parcels!$D$2:$D$3000,$B12) -> 734 | L12: =SUMIFS(Parcels!$AT$2:$AT$3000,Parcels!$D$2:$D$3000,$B12) -> 18 | M12: =SUMIFS(Parcels!$AU$2:$AU$3000,Parcels!$D$2:$D$3000,$B12) -> 91.4 | N12: =SUMIFS(Parcels!$AV$2:$AV$3000,Parcels!$D$2:$D$3000,$B12) -> 104.5 | O12: =SUMIFS(Parcels!$AW$2:$AW$3000,Parcels!$D$2:$D$3000,$B12) -> 26.1 | P12: =SUMIFS(Parcels!$AX$2:$AX$3000,Parcels!$D$2:$D$3000,$B12) -> 0 | Q12: =SUMIFS(Parcels!$AY$2:$AY$3000,Parcels!$D$2:$D$3000,$B12) -> 0
A13: City neighbourhood | B13: Southhill | C13: =COUNTIFS(Parcels!$D$2:$D$3000,$B13) -> 31 | D13: =SUMIFS(Parcels!$P$2:$P$3000,Parcels!$D$2:$D$3000,$B13) -> 29.859 | E13: =SUMIFS(Parcels!$AM$2:$AM$3000,Parcels!$D$2:$D$3000,$B13) -> 754 | F13: =SUMIFS(Parcels!$AI$2:$AI$3000,Parcels!$D$2:$D$3000,$B13) -> 289 | G13: =SUMIFS(Parcels!$AJ$2:$AJ$3000,Parcels!$D$2:$D$3000,$B13) -> 47 | H13: =SUMIFS(Parcels!$AK$2:$AK$3000,Parcels!$D$2:$D$3000,$B13) -> 418 | I13: =SUMIFS(Parcels!$AP$2:$AP$3000,Parcels!$D$2:$D$3000,$B13) -> 699 | J13: =SUMIFS(Parcels!$AQ$2:$AQ$3000,Parcels!$D$2:$D$3000,$B13) -> 1453 | K13: =SUMIFS(Parcels!$AS$2:$AS$3000,Parcels!$D$2:$D$3000,$B13) -> 1161 | L13: =SUMIFS(Parcels!$AT$2:$AT$3000,Parcels!$D$2:$D$3000,$B13) -> 3.7 | M13: =SUMIFS(Parcels!$AU$2:$AU$3000,Parcels!$D$2:$D$3000,$B13) -> 40.8 | N13: =SUMIFS(Parcels!$AV$2:$AV$3000,Parcels!$D$2:$D$3000,$B13) -> 15.3 | O13: =SUMIFS(Parcels!$AW$2:$AW$3000,Parcels!$D$2:$D$3000,$B13) -> 43.8 | P13: =SUMIFS(Parcels!$AX$2:$AX$3000,Parcels!$D$2:$D$3000,$B13) -> 57.4 | Q13: =SUMIFS(Parcels!$AY$2:$AY$3000,Parcels!$D$2:$D$3000,$B13) -> 304
A14: City neighbourhood total | C14: =SUM(C5:C13) -> 241 | D14: =SUM(D5:D13) -> 420.728 | E14: =SUM(E5:E13) -> 8543 | F14: =SUM(F5:F13) -> 1348 | G14: =SUM(G5:G13) -> 2954 | H14: =SUM(H5:H13) -> 4210 | I14: =SUM(I5:I13) -> 10400 | J14: =SUM(J5:J13) -> 18943 | ... Q14: =SUM(Q5:Q13) -> 1573.2
A16: Key town | B16: Abbeyfeale | C16: =COUNTIFS(Parcels!$D$2:$D$3000,$B16) -> 10 | D16: =SUMIFS(Parcels!$P$2:$P$3000,Parcels!$D$2:$D$3000,$B16) -> 11.181 | E16: =SUMIFS(Parcels!$AM$2:$AM$3000,Parcels!$D$2:$D$3000,$B16) -> 87 | F16: =SUMIFS(Parcels!$AI$2:$AI$3000,Parcels!$D$2:$D$3000,$B16) -> 0 | G16: =SUMIFS(Parcels!$AJ$2:$AJ$3000,Parcels!$D$2:$D$3000,$B16) -> 0 | H16: =SUMIFS(Parcels!$AK$2:$AK$3000,Parcels!$D$2:$D$3000,$B16) -> 87 | I16: =SUMIFS(Parcels!$AP$2:$AP$3000,Parcels!$D$2:$D$3000,$B16) -> 176 | J16: =SUMIFS(Parcels!$AQ$2:$AQ$3000,Parcels!$D$2:$D$3000,$B16) -> 263 | K16: =SUMIFS(Parcels!$AS$2:$AS$3000,Parcels!$D$2:$D$3000,$B16) -> 263 | L16: =SUMIFS(Parcels!$AT$2:$AT$3000,Parcels!$D$2:$D$3000,$B16) -> 0 | M16: =SUMIFS(Parcels!$AU$2:$AU$3000,Parcels!$D$2:$D$3000,$B16) -> 0 | N16: =SUMIFS(Parcels!$AV$2:$AV$3000,Parcels!$D$2:$D$3000,$B16) -> 57.4 | O16: =SUMIFS(Parcels!$AW$2:$AW$3000,Parcels!$D$2:$D$3000,$B16) -> 28.9 | P16: =SUMIFS(Parcels!$AX$2:$AX$3000,Parcels!$D$2:$D$3000,$B16) -> 0.7 | Q16: =SUMIFS(Parcels!$AY$2:$AY$3000,Parcels!$D$2:$D$3000,$B16) -> 0
A17: Key town | B17: Caherconlish | C17: =COUNTIFS(Parcels!$D$2:$D$3000,$B17) -> 7 | D17: =SUMIFS(Parcels!$P$2:$P$3000,Parcels!$D$2:$D$3000,$B17) -> 8.214 | E17: =SUMIFS(Parcels!$AM$2:$AM$3000,Parcels!$D$2:$D$3000,$B17) -> 9 | F17: =SUMIFS(Parcels!$AI$2:$AI$3000,Parcels!$D$2:$D$3000,$B17) -> 9 | G17: =SUMIFS(Parcels!$AJ$2:$AJ$3000,Parcels!$D$2:$D$3000,$B17) -> 0 | H17: =SUMIFS(Parcels!$AK$2:$AK$3000,Parcels!$D$2:$D$3000,$B17) -> 0 | I17: =SUMIFS(Parcels!$AP$2:$AP$3000,Parcels!$D$2:$D$3000,$B17) -> 190 | J17: =SUMIFS(Parcels!$AQ$2:$AQ$3000,Parcels!$D$2:$D$3000,$B17) -> 199 | K17: =SUMIFS(Parcels!$AS$2:$AS$3000,Parcels!$D$2:$D$3000,$B17) -> 190 | L17: =SUMIFS(Parcels!$AT$2:$AT$3000,Parcels!$D$2:$D$3000,$B17) -> 0 | M17: =SUMIFS(Parcels!$AU$2:$AU$3000,Parcels!$D$2:$D$3000,$B17) -> 0 | N17: =SUMIFS(Parcels!$AV$2:$AV$3000,Parcels!$D$2:$D$3000,$B17) -> 0 | O17: =SUMIFS(Parcels!$AW$2:$AW$3000,Parcels!$D$2:$D$3000,$B17) -> 0 | P17: =SUMIFS(Parcels!$AX$2:$AX$3000,Parcels!$D$2:$D$3000,$B17) -> 0 | Q17: =SUMIFS(Parcels!$AY$2:$AY$3000,Parcels!$D$2:$D$3000,$B17) -> 0
A18: Key town | B18: Castleconnell | C18: =COUNTIFS(Parcels!$D$2:$D$3000,$B18) -> 13 | D18: =SUMIFS(Parcels!$P$2:$P$3000,Parcels!$D$2:$D$3000,$B18) -> 20.846 | E18: =SUMIFS(Parcels!$AM$2:$AM$3000,Parcels!$D$2:$D$3000,$B18) -> 156 | F18: =SUMIFS(Parcels!$AI$2:$AI$3000,Parcels!$D$2:$D$3000,$B18) -> 68 | G18: =SUMIFS(Parcels!$AJ$2:$AJ$3000,Parcels!$D$2:$D$3000,$B18) -> 74 | H18: =SUMIFS(Parcels!$AK$2:$AK$3000,Parcels!$D$2:$D$3000,$B18) -> 14 | I18: =SUMIFS(Parcels!$AP$2:$AP$3000,Parcels!$D$2:$D$3000,$B18) -> 208 | J18: =SUMIFS(Parcels!$AQ$2:$AQ$3000,Parcels!$D$2:$D$3000,$B18) -> 364 | K18: =SUMIFS(Parcels!$AS$2:$AS$3000,Parcels!$D$2:$D$3000,$B18) -> 296 | L18: =SUMIFS(Parcels!$AT$2:$AT$3000,Parcels!$D$2:$D$3000,$B18) -> 17.2 | M18: =SUMIFS(Parcels!$AU$2:$AU$3000,Parcels!$D$2:$D$3000,$B18) -> 56.8 | N18: =SUMIFS(Parcels!$AV$2:$AV$3000,Parcels!$D$2:$D$3000,$B18) -> 8.2 | O18: =SUMIFS(Parcels!$AW$2:$AW$3000,Parcels!$D$2:$D$3000,$B18) -> 5.8 | P18: =SUMIFS(Parcels!$AX$2:$AX$3000,Parcels!$D$2:$D$3000,$B18) -> 0 | Q18: =SUMIFS(Parcels!$AY$2:$AY$3000,Parcels!$D$2:$D$3000,$B18) -> 0
A19: Key town | B19: Kilmallock | C19: =COUNTIFS(Parcels!$D$2:$D$3000,$B19) -> 12 | D19: =SUMIFS(Parcels!$P$2:$P$3000,Parcels!$D$2:$D$3000,$B19) -> 18.914 | E19: =SUMIFS(Parcels!$AM$2:$AM$3000,Parcels!$D$2:$D$3000,$B19) -> 75 | F19: =SUMIFS(Parcels!$AI$2:$AI$3000,Parcels!$D$2:$D$3000,$B19) -> 5 | G19: =SUMIFS(Parcels!$AJ$2:$AJ$3000,Parcels!$D$2:$D$3000,$B19) -> 70 | H19: =SUMIFS(Parcels!$AK$2:$AK$3000,Parcels!$D$2:$D$3000,$B19) -> 0 | I19: =SUMIFS(Parcels!$AP$2:$AP$3000,Parcels!$D$2:$D$3000,$B19) -> 355 | J19: =SUMIFS(Parcels!$AQ$2:$AQ$3000,Parcels!$D$2:$D$3000,$B19) -> 430 | K19: =SUMIFS(Parcels!$AS$2:$AS$3000,Parcels!$D$2:$D$3000,$B19) -> 425 | L19: =SUMIFS(Parcels!$AT$2:$AT$3000,Parcels!$D$2:$D$3000,$B19) -> 1.2 | M19: =SUMIFS(Parcels!$AU$2:$AU$3000,Parcels!$D$2:$D$3000,$B19) -> 58.8 | N19: =SUMIFS(Parcels!$AV$2:$AV$3000,Parcels!$D$2:$D$3000,$B19) -> 10 | O19: =SUMIFS(Parcels!$AW$2:$AW$3000,Parcels!$D$2:$D$3000,$B19) -> 0 | P19: =SUMIFS(Parcels!$AX$2:$AX$3000,Parcels!$D$2:$D$3000,$B19) -> 0 | Q19: =SUMIFS(Parcels!$AY$2:$AY$3000,Parcels!$D$2:$D$3000,$B19) -> 0
A20: Key town | B20: Newcastle West | C20: =COUNTIFS(Parcels!$D$2:$D$3000,$B20) -> 27 | D20: =SUMIFS(Parcels!$P$2:$P$3000,Parcels!$D$2:$D$3000,$B20) -> 58.216 | E20: =SUMIFS(Parcels!$AM$2:$AM$3000,Parcels!$D$2:$D$3000,$B20) -> 280 | F20: =SUMIFS(Parcels!$AI$2:$AI$3000,Parcels!$D$2:$D$3000,$B20) -> 6 | G20: =SUMIFS(Parcels!$AJ$2:$AJ$3000,Parcels!$D$2:$D$3000,$B20) -> 166 | H20: =SUMIFS(Parcels!$AK$2:$AK$3000,Parcels!$D$2:$D$3000,$B20) -> 55 | I20: =SUMIFS(Parcels!$AP$2:$AP$3000,Parcels!$D$2:$D$3000,$B20) -> 1209 | J20: =SUMIFS(Parcels!$AQ$2:$AQ$3000,Parcels!$D$2:$D$3000,$B20) -> 1489 | K20: =SUMIFS(Parcels!$AS$2:$AS$3000,Parcels!$D$2:$D$3000,$B20) -> 1453 | L20: =SUMIFS(Parcels!$AT$2:$AT$3000,Parcels!$D$2:$D$3000,$B20) -> 38.7 | M20: =SUMIFS(Parcels!$AU$2:$AU$3000,Parcels!$D$2:$D$3000,$B20) -> 127.3 | N20: =SUMIFS(Parcels!$AV$2:$AV$3000,Parcels!$D$2:$D$3000,$B20) -> 40.2 | O20: =SUMIFS(Parcels!$AW$2:$AW$3000,Parcels!$D$2:$D$3000,$B20) -> 14.8 | P20: =SUMIFS(Parcels!$AX$2:$AX$3000,Parcels!$D$2:$D$3000,$B20) -> 0 | Q20: =SUMIFS(Parcels!$AY$2:$AY$3000,Parcels!$D$2:$D$3000,$B20) -> 0
A21: Key town | B21: Rathkeale | C21: =COUNTIFS(Parcels!$D$2:$D$3000,$B21) -> 11 | D21: =SUMIFS(Parcels!$P$2:$P$3000,Parcels!$D$2:$D$3000,$B21) -> 8.243 | E21: =SUMIFS(Parcels!$AM$2:$AM$3000,Parcels!$D$2:$D$3000,$B21) -> 11 | F21: =SUMIFS(Parcels!$AI$2:$AI$3000,Parcels!$D$2:$D$3000,$B21) -> 0 | G21: =SUMIFS(Parcels!$AJ$2:$AJ$3000,Parcels!$D$2:$D$3000,$B21) -> 11 | H21: =SUMIFS(Parcels!$AK$2:$AK$3000,Parcels!$D$2:$D$3000,$B21) -> 0 | I21: =SUMIFS(Parcels!$AP$2:$AP$3000,Parcels!$D$2:$D$3000,$B21) -> 189 | J21: =SUMIFS(Parcels!$AQ$2:$AQ$3000,Parcels!$D$2:$D$3000,$B21) -> 200 | K21: =SUMIFS(Parcels!$AS$2:$AS$3000,Parcels!$D$2:$D$3000,$B21) -> 200 | L21: =SUMIFS(Parcels!$AT$2:$AT$3000,Parcels!$D$2:$D$3000,$B21) -> 2.6 | M21: =SUMIFS(Parcels!$AU$2:$AU$3000,Parcels!$D$2:$D$3000,$B21) -> 8.4 | N21: =SUMIFS(Parcels!$AV$2:$AV$3000,Parcels!$D$2:$D$3000,$B21) -> 0 | O21: =SUMIFS(Parcels!$AW$2:$AW$3000,Parcels!$D$2:$D$3000,$B21) -> 0 | P21: =SUMIFS(Parcels!$AX$2:$AX$3000,Parcels!$D$2:$D$3000,$B21) -> 0 | Q21: =SUMIFS(Parcels!$AY$2:$AY$3000,Parcels!$D$2:$D$3000,$B21) -> 0
A22: Key town total | C22: =SUM(C16:C21) -> 80 | D22: =SUM(D16:D21) -> 125.614 | E22: =SUM(E16:E21) -> 618 | F22: =SUM(F16:F21) -> 88 | G22: =SUM(G16:G21) -> 321 | H22: =SUM(H16:H21) -> 156 | I22: =SUM(I16:I21) -> 2327 | J22: =SUM(J16:J21) -> 2945 | ... Q22: =SUM(Q16:Q21) -> 0
A24: Large village | B24: Adare | C24: =COUNTIFS(Parcels!$D$2:$D$3000,$B24) -> 13 | D24: =SUMIFS(Parcels!$P$2:$P$3000,Parcels!$D$2:$D$3000,$B24) -> 34.555 | E24: =SUMIFS(Parcels!$AM$2:$AM$3000,Parcels!$D$2:$D$3000,$B24) -> 226 | F24: =SUMIFS(Parcels!$AI$2:$AI$3000,Parcels!$D$2:$D$3000,$B24) -> 0 | G24: =SUMIFS(Parcels!$AJ$2:$AJ$3000,Parcels!$D$2:$D$3000,$B24) -> 15 | H24: =SUMIFS(Parcels!$AK$2:$AK$3000,Parcels!$D$2:$D$3000,$B24) -> 211 | I24: =SUMIFS(Parcels!$AP$2:$AP$3000,Parcels!$D$2:$D$3000,$B24) -> 191 | J24: =SUMIFS(Parcels!$AQ$2:$AQ$3000,Parcels!$D$2:$D$3000,$B24) -> 417 | K24: =SUMIFS(Parcels!$AS$2:$AS$3000,Parcels!$D$2:$D$3000,$B24) -> 415 | L24: =SUMIFS(Parcels!$AT$2:$AT$3000,Parcels!$D$2:$D$3000,$B24) -> 1.2 | M24: =SUMIFS(Parcels!$AU$2:$AU$3000,Parcels!$D$2:$D$3000,$B24) -> 10.7 | N24: =SUMIFS(Parcels!$AV$2:$AV$3000,Parcels!$D$2:$D$3000,$B24) -> 92.1 | O24: =SUMIFS(Parcels!$AW$2:$AW$3000,Parcels!$D$2:$D$3000,$B24) -> 99.8 | P24: =SUMIFS(Parcels!$AX$2:$AX$3000,Parcels!$D$2:$D$3000,$B24) -> 22.2 | Q24: =SUMIFS(Parcels!$AY$2:$AY$3000,Parcels!$D$2:$D$3000,$B24) -> 0
A25: Large village | B25: Bruff | C25: =COUNTIFS(Parcels!$D$2:$D$3000,$B25) -> 8 | D25: =SUMIFS(Parcels!$P$2:$P$3000,Parcels!$D$2:$D$3000,$B25) -> 6.843 | E25: =SUMIFS(Parcels!$AM$2:$AM$3000,Parcels!$D$2:$D$3000,$B25) -> 102 | F25: =SUMIFS(Parcels!$AI$2:$AI$3000,Parcels!$D$2:$D$3000,$B25) -> 2 | G25: =SUMIFS(Parcels!$AJ$2:$AJ$3000,Parcels!$D$2:$D$3000,$B25) -> 18 | H25: =SUMIFS(Parcels!$AK$2:$AK$3000,Parcels!$D$2:$D$3000,$B25) -> 82 | I25: =SUMIFS(Parcels!$AP$2:$AP$3000,Parcels!$D$2:$D$3000,$B25) -> 41 | J25: =SUMIFS(Parcels!$AQ$2:$AQ$3000,Parcels!$D$2:$D$3000,$B25) -> 143 | K25: =SUMIFS(Parcels!$AS$2:$AS$3000,Parcels!$D$2:$D$3000,$B25) -> 141 | L25: =SUMIFS(Parcels!$AT$2:$AT$3000,Parcels!$D$2:$D$3000,$B25) -> 0 | M25: =SUMIFS(Parcels!$AU$2:$AU$3000,Parcels!$D$2:$D$3000,$B25) -> 10.2 | N25: =SUMIFS(Parcels!$AV$2:$AV$3000,Parcels!$D$2:$D$3000,$B25) -> 36.7 | O25: =SUMIFS(Parcels!$AW$2:$AW$3000,Parcels!$D$2:$D$3000,$B25) -> 53.1 | P25: =SUMIFS(Parcels!$AX$2:$AX$3000,Parcels!$D$2:$D$3000,$B25) -> 0 | Q25: =SUMIFS(Parcels!$AY$2:$AY$3000,Parcels!$D$2:$D$3000,$B25) -> 0
A26: Large village | B26: Cappamore | C26: =COUNTIFS(Parcels!$D$2:$D$3000,$B26) -> 7 | D26: =SUMIFS(Parcels!$P$2:$P$3000,Parcels!$D$2:$D$3000,$B26) -> 3.724 | E26: =SUMIFS(Parcels!$AM$2:$AM$3000,Parcels!$D$2:$D$3000,$B26) -> 56 | F26: =SUMIFS(Parcels!$AI$2:$AI$3000,Parcels!$D$2:$D$3000,$B26) -> 27 | G26: =SUMIFS(Parcels!$AJ$2:$AJ$3000,Parcels!$D$2:$D$3000,$B26) -> 22 | H26: =SUMIFS(Parcels!$AK$2:$AK$3000,Parcels!$D$2:$D$3000,$B26) -> 7 | I26: =SUMIFS(Parcels!$AP$2:$AP$3000,Parcels!$D$2:$D$3000,$B26) -> 20 | J26: =SUMIFS(Parcels!$AQ$2:$AQ$3000,Parcels!$D$2:$D$3000,$B26) -> 76 | K26: =SUMIFS(Parcels!$AS$2:$AS$3000,Parcels!$D$2:$D$3000,$B26) -> 49 | L26: =SUMIFS(Parcels!$AT$2:$AT$3000,Parcels!$D$2:$D$3000,$B26) -> 3.1 | M26: =SUMIFS(Parcels!$AU$2:$AU$3000,Parcels!$D$2:$D$3000,$B26) -> 13.5 | N26: =SUMIFS(Parcels!$AV$2:$AV$3000,Parcels!$D$2:$D$3000,$B26) -> 9.8 | O26: =SUMIFS(Parcels!$AW$2:$AW$3000,Parcels!$D$2:$D$3000,$B26) -> 2.6 | P26: =SUMIFS(Parcels!$AX$2:$AX$3000,Parcels!$D$2:$D$3000,$B26) -> 0 | Q26: =SUMIFS(Parcels!$AY$2:$AY$3000,Parcels!$D$2:$D$3000,$B26) -> 0
A27: Large village | B27: Croom | C27: =COUNTIFS(Parcels!$D$2:$D$3000,$B27) -> 13 | D27: =SUMIFS(Parcels!$P$2:$P$3000,Parcels!$D$2:$D$3000,$B27) -> 13.627 | E27: =SUMIFS(Parcels!$AM$2:$AM$3000,Parcels!$D$2:$D$3000,$B27) -> 137 | F27: =SUMIFS(Parcels!$AI$2:$AI$3000,Parcels!$D$2:$D$3000,$B27) -> 16 | G27: =SUMIFS(Parcels!$AJ$2:$AJ$3000,Parcels!$D$2:$D$3000,$B27) -> 0 | H27: =SUMIFS(Parcels!$AK$2:$AK$3000,Parcels!$D$2:$D$3000,$B27) -> 121 | I27: =SUMIFS(Parcels!$AP$2:$AP$3000,Parcels!$D$2:$D$3000,$B27) -> 192 | J27: =SUMIFS(Parcels!$AQ$2:$AQ$3000,Parcels!$D$2:$D$3000,$B27) -> 329 | K27: =SUMIFS(Parcels!$AS$2:$AS$3000,Parcels!$D$2:$D$3000,$B27) -> 313 | L27: =SUMIFS(Parcels!$AT$2:$AT$3000,Parcels!$D$2:$D$3000,$B27) -> 0 | M27: =SUMIFS(Parcels!$AU$2:$AU$3000,Parcels!$D$2:$D$3000,$B27) -> 0 | N27: =SUMIFS(Parcels!$AV$2:$AV$3000,Parcels!$D$2:$D$3000,$B27) -> 85.7 | O27: =SUMIFS(Parcels!$AW$2:$AW$3000,Parcels!$D$2:$D$3000,$B27) -> 35.3 | P27: =SUMIFS(Parcels!$AX$2:$AX$3000,Parcels!$D$2:$D$3000,$B27) -> 0 | Q27: =SUMIFS(Parcels!$AY$2:$AY$3000,Parcels!$D$2:$D$3000,$B27) -> 0
A28: Large village | B28: Hospital | C28: =COUNTIFS(Parcels!$D$2:$D$3000,$B28) -> 6 | D28: =SUMIFS(Parcels!$P$2:$P$3000,Parcels!$D$2:$D$3000,$B28) -> 7.019 | E28: =SUMIFS(Parcels!$AM$2:$AM$3000,Parcels!$D$2:$D$3000,$B28) -> 20 | F28: =SUMIFS(Parcels!$AI$2:$AI$3000,Parcels!$D$2:$D$3000,$B28) -> 20 | G28: =SUMIFS(Parcels!$AJ$2:$AJ$3000,Parcels!$D$2:$D$3000,$B28) -> 0 | H28: =SUMIFS(Parcels!$AK$2:$AK$3000,Parcels!$D$2:$D$3000,$B28) -> 0 | I28: =SUMIFS(Parcels!$AP$2:$AP$3000,Parcels!$D$2:$D$3000,$B28) -> 128 | J28: =SUMIFS(Parcels!$AQ$2:$AQ$3000,Parcels!$D$2:$D$3000,$B28) -> 148 | K28: =SUMIFS(Parcels!$AS$2:$AS$3000,Parcels!$D$2:$D$3000,$B28) -> 128 | L28: =SUMIFS(Parcels!$AT$2:$AT$3000,Parcels!$D$2:$D$3000,$B28) -> 0 | M28: =SUMIFS(Parcels!$AU$2:$AU$3000,Parcels!$D$2:$D$3000,$B28) -> 0 | N28: =SUMIFS(Parcels!$AV$2:$AV$3000,Parcels!$D$2:$D$3000,$B28) -> 0 | O28: =SUMIFS(Parcels!$AW$2:$AW$3000,Parcels!$D$2:$D$3000,$B28) -> 0 | P28: =SUMIFS(Parcels!$AX$2:$AX$3000,Parcels!$D$2:$D$3000,$B28) -> 0 | Q28: =SUMIFS(Parcels!$AY$2:$AY$3000,Parcels!$D$2:$D$3000,$B28) -> 0
A29: Large village | B29: Kilfinnane | C29: =COUNTIFS(Parcels!$D$2:$D$3000,$B29) -> 8 | D29: =SUMIFS(Parcels!$P$2:$P$3000,Parcels!$D$2:$D$3000,$B29) -> 4.521 | E29: =SUMIFS(Parcels!$AM$2:$AM$3000,Parcels!$D$2:$D$3000,$B29) -> 33 | F29: =SUMIFS(Parcels!$AI$2:$AI$3000,Parcels!$D$2:$D$3000,$B29) -> 19 | G29: =SUMIFS(Parcels!$AJ$2:$AJ$3000,Parcels!$D$2:$D$3000,$B29) -> 14 | H29: =SUMIFS(Parcels!$AK$2:$AK$3000,Parcels!$D$2:$D$3000,$B29) -> 0 | I29: =SUMIFS(Parcels!$AP$2:$AP$3000,Parcels!$D$2:$D$3000,$B29) -> 58 | J29: =SUMIFS(Parcels!$AQ$2:$AQ$3000,Parcels!$D$2:$D$3000,$B29) -> 91 | K29: =SUMIFS(Parcels!$AS$2:$AS$3000,Parcels!$D$2:$D$3000,$B29) -> 72 | L29: =SUMIFS(Parcels!$AT$2:$AT$3000,Parcels!$D$2:$D$3000,$B29) -> 3.3 | M29: =SUMIFS(Parcels!$AU$2:$AU$3000,Parcels!$D$2:$D$3000,$B29) -> 10.7 | N29: =SUMIFS(Parcels!$AV$2:$AV$3000,Parcels!$D$2:$D$3000,$B29) -> 0 | O29: =SUMIFS(Parcels!$AW$2:$AW$3000,Parcels!$D$2:$D$3000,$B29) -> 0 | P29: =SUMIFS(Parcels!$AX$2:$AX$3000,Parcels!$D$2:$D$3000,$B29) -> 0 | Q29: =SUMIFS(Parcels!$AY$2:$AY$3000,Parcels!$D$2:$D$3000,$B29) -> 0
A30: Large village | B30: Moroe | C30: =COUNTIFS(Parcels!$D$2:$D$3000,$B30) -> 5 | D30: =SUMIFS(Parcels!$P$2:$P$3000,Parcels!$D$2:$D$3000,$B30) -> 6.409 | E30: =SUMIFS(Parcels!$AM$2:$AM$3000,Parcels!$D$2:$D$3000,$B30) -> 36 | F30: =SUMIFS(Parcels!$AI$2:$AI$3000,Parcels!$D$2:$D$3000,$B30) -> 0 | G30: =SUMIFS(Parcels!$AJ$2:$AJ$3000,Parcels!$D$2:$D$3000,$B30) -> 4 | H30: =SUMIFS(Parcels!$AK$2:$AK$3000,Parcels!$D$2:$D$3000,$B30) -> 0 | I30: =SUMIFS(Parcels!$AP$2:$AP$3000,Parcels!$D$2:$D$3000,$B30) -> 81 | J30: =SUMIFS(Parcels!$AQ$2:$AQ$3000,Parcels!$D$2:$D$3000,$B30) -> 117 | K30: =SUMIFS(Parcels!$AS$2:$AS$3000,Parcels!$D$2:$D$3000,$B30) -> 117 | L30: =SUMIFS(Parcels!$AT$2:$AT$3000,Parcels!$D$2:$D$3000,$B30) -> 0 | M30: =SUMIFS(Parcels!$AU$2:$AU$3000,Parcels!$D$2:$D$3000,$B30) -> 3.7 | N30: =SUMIFS(Parcels!$AV$2:$AV$3000,Parcels!$D$2:$D$3000,$B30) -> 0.3 | O30: =SUMIFS(Parcels!$AW$2:$AW$3000,Parcels!$D$2:$D$3000,$B30) -> 0 | P30: =SUMIFS(Parcels!$AX$2:$AX$3000,Parcels!$D$2:$D$3000,$B30) -> 0 | Q30: =SUMIFS(Parcels!$AY$2:$AY$3000,Parcels!$D$2:$D$3000,$B30) -> 0
A31: Large village | B31: Patrickswell | C31: =COUNTIFS(Parcels!$D$2:$D$3000,$B31) -> 20 | D31: =SUMIFS(Parcels!$P$2:$P$3000,Parcels!$D$2:$D$3000,$B31) -> 27.786 | E31: =SUMIFS(Parcels!$AM$2:$AM$3000,Parcels!$D$2:$D$3000,$B31) -> 510 | F31: =SUMIFS(Parcels!$AI$2:$AI$3000,Parcels!$D$2:$D$3000,$B31) -> 79 | G31: =SUMIFS(Parcels!$AJ$2:$AJ$3000,Parcels!$D$2:$D$3000,$B31) -> 257 | H31: =SUMIFS(Parcels!$AK$2:$AK$3000,Parcels!$D$2:$D$3000,$B31) -> 134 | I31: =SUMIFS(Parcels!$AP$2:$AP$3000,Parcels!$D$2:$D$3000,$B31) -> 78 | J31: =SUMIFS(Parcels!$AQ$2:$AQ$3000,Parcels!$D$2:$D$3000,$B31) -> 588 | K31: =SUMIFS(Parcels!$AS$2:$AS$3000,Parcels!$D$2:$D$3000,$B31) -> 485 | L31: =SUMIFS(Parcels!$AT$2:$AT$3000,Parcels!$D$2:$D$3000,$B31) -> 36.1 | M31: =SUMIFS(Parcels!$AU$2:$AU$3000,Parcels!$D$2:$D$3000,$B31) -> 149 | N31: =SUMIFS(Parcels!$AV$2:$AV$3000,Parcels!$D$2:$D$3000,$B31) -> 133.4 | O31: =SUMIFS(Parcels!$AW$2:$AW$3000,Parcels!$D$2:$D$3000,$B31) -> 67.5 | P31: =SUMIFS(Parcels!$AX$2:$AX$3000,Parcels!$D$2:$D$3000,$B31) -> 5 | Q31: =SUMIFS(Parcels!$AY$2:$AY$3000,Parcels!$D$2:$D$3000,$B31) -> 0
A32: Large village total | C32: =SUM(C24:C31) -> 80 | D32: =SUM(D24:D31) -> 104.484 | E32: =SUM(E24:E31) -> 1120 | F32: =SUM(F24:F31) -> 163 | G32: =SUM(G24:G31) -> 330 | H32: =SUM(H24:H31) -> 555 | I32: =SUM(I24:I31) -> 789 | J32: =SUM(J24:J31) -> 1909 | ... Q32: =SUM(Q24:Q31) -> 0
A34: Rest of county | B34: Rest of county | C34: =COUNTIFS(Parcels!$D$2:$D$3000,$B34) -> 46 | D34: =SUMIFS(Parcels!$P$2:$P$3000,Parcels!$D$2:$D$3000,$B34) -> 42.26 | E34: =SUMIFS(Parcels!$AM$2:$AM$3000,Parcels!$D$2:$D$3000,$B34) -> 213 | F34: =SUMIFS(Parcels!$AI$2:$AI$3000,Parcels!$D$2:$D$3000,$B34) -> 44 | G34: =SUMIFS(Parcels!$AJ$2:$AJ$3000,Parcels!$D$2:$D$3000,$B34) -> 106 | H34: =SUMIFS(Parcels!$AK$2:$AK$3000,Parcels!$D$2:$D$3000,$B34) -> 63 | I34: =SUMIFS(Parcels!$AP$2:$AP$3000,Parcels!$D$2:$D$3000,$B34) -> 416 | J34: =SUMIFS(Parcels!$AQ$2:$AQ$3000,Parcels!$D$2:$D$3000,$B34) -> 629 | K34: =SUMIFS(Parcels!$AS$2:$AS$3000,Parcels!$D$2:$D$3000,$B34) -> 582 | L34: =SUMIFS(Parcels!$AT$2:$AT$3000,Parcels!$D$2:$D$3000,$B34) -> 24.1 | M34: =SUMIFS(Parcels!$AU$2:$AU$3000,Parcels!$D$2:$D$3000,$B34) -> 81.9 | N34: =SUMIFS(Parcels!$AV$2:$AV$3000,Parcels!$D$2:$D$3000,$B34) -> 38.3 | O34: =SUMIFS(Parcels!$AW$2:$AW$3000,Parcels!$D$2:$D$3000,$B34) -> 24.7 | P34: =SUMIFS(Parcels!$AX$2:$AX$3000,Parcels!$D$2:$D$3000,$B34) -> 0 | Q34: =SUMIFS(Parcels!$AY$2:$AY$3000,Parcels!$D$2:$D$3000,$B34) -> 0
A35: Rest of county total | C35: =SUM(C34:C34) -> 46 | D35: =SUM(D34:D34) -> 42.26 | E35: =SUM(E34:E34) -> 213 | F35: =SUM(F34:F34) -> 44 | G35: =SUM(G34:G34) -> 106 | H35: =SUM(H34:H34) -> 63 | I35: =SUM(I34:I34) -> 416 | J35: =SUM(J34:J34) -> 629 | ... Q35: =SUM(Q34:Q34) -> 0

Sheet How to update
A1: The rule | B1: One permission, one parcel. Units live only on the Permissions sheet. Parcel totals add them up, so a home cannot be counted twice. Parcels do not overlap.
A2: New permission on an existing parcel | B2: Add a row to Permissions with a new perm_id, pick the parcel_id from the list, enter units and status, counts_toward_totals = Yes. The parcel totals update.
A3: New permission on new land | B3: Draw a parcel in the GeoPackage from the planning boundary (clip out any existing parcel), id PC-<planning ref without slashes>, parcel_source = Planning consent – not in council audit. Add the same parcel row here, then the permission row.
A4: Amendment, repeat or extension of duration | B4: Add the row with counts_toward_totals = No unless it replaces the counted permission. If it replaces it (e.g. a new scheme on the same land), set the old row to No and the new row to Yes.
A5: Status changes | B5: Change status on the Permissions row (Permitted – not started → Under construction → Complete). Use building control commencement and completion notices as the source; note it in notes and update last_updated.
A6: Expired permissions | B6: Set status to Expired – not started. The units drop out of consented supply; on an audit parcel the council capacity becomes unconsented capacity again.
A7: Capacity | B7: Audit parcels: council estimate. Zoned-land parcels: zoned area x developable share x density (see density_basis). If a permission shows the capacity was wrong, update capacity_units and say why in notes. Consent parcels have no capacity figure: their supply is the consented units.
A8: Zoned land (interim) | B8: Zoned-land parcels are estimates from new residential zoning not in any other parcel and not built on. When a permission is granted on one, draw the consent parcel and cut it out of the zoned parcel. When the county audit arrives, replace them.
A9: County audit | B9: Add county audit parcels with parcel_source = Council audit – county and scope = County. Move county permissions onto them by changing parcel_id, then retire any consent parcel left empty (flag: Consent parcel with no permission).
A10: GeoDirectory | B10: Each quarter, rerun the build with the new GeoDirectory extract. A scheme whose new built addresses reach 95% of its units moves to Complete (status_source says so); other differences are listed on the GeoDirectory checks sheet for a person to confirm.
A11: Retiring a parcel | B11: Do not delete. parcel_status turns to Finished when every counted home is complete and no council capacity is left; filter Finished parcels off the map. Their homes stay in the delivery record.
A12: Checks | B12: Summary sheet checks must all be zero before figures are reported. Red cells on Permissions (check column) and Parcels (flag) show what to fix.

Sheet Parcels
A1: parcel_id | B1: parcel_source | C1: scope | D1: catchment | E1: catchment_type | F1: catchment_share | G1: catchment_basis | H1: rsca | I1: neighbourhood | J1: lea | K1: local_name | L1: landowner | M1: zoning | N1: site_type | O1: density_band | P1: developable_area_ha | Q1: mapped_area_ha | R1: capacity_units | S1: capacity_basis | T1: density_estimate_units | U1: plan_name | V1: zone_gzt | W1: phase | X1: density_tier | Y1: density_dph | Z1: density_basis | AA1: rzlt_2027_share | AB1: geod_addresses_now | AC1: geod_new_since_2019 | AD1: register_status | AE1: notes | AF1: last_reviewed | AG1: reviewed_by | AH1: capacity_used | AI1: complete_units | AJ1: under_construction_units | AK1: permitted_not_started_units | AL1: stalled_units | AM1: consented_units | AN1: expired_units | AO1: in_planning_units | AP1: unconsented_capacity | AQ1: total_supply_units | AR1: built_units | AS1: future_supply_units | AT1: est_q4_2026 | AU1: est_2027 | AV1: est_2028 | AW1: est_2029 | AX1: est_2030 | AY1: est_2031_plus | AZ1: permissions | BA1: geod_new_built | BB1: geod_new_vacant | BC1: parcel_status | BD1: flag
A2: CITY-129 | B2: Council audit | C2: City | D2: Ballinacurra | E2: City neighbourhood | F2: 1 | G2: Inside catchment | H2: 129 | I2: Ballinacurra | J2: LIMERICK CITY WEST LEA-7 | K2: City Centre | L2: Council | M2: New Resi | N2: Brownfield | O2: 45+ | P2: 2.208 | Q2: 2.208 | R2: 99 | S2: Council estimate (area × density band) | T2: 75 | X2: City suburbs | Y2: 34 | Z2: 34 homes/ha = median of 39 permitted Limerick schemes of 10+ homes in city suburbs; applied to developable for density_estimate_units only | AB2: 0 | AC2: 0 | AD2: Undeveloped/Permission Sought | AE2: Unchanged | AF2: 2026-10-11 | AH2: =IF(R2="",AM2,R2) -> 99 | AI2: =SUMIFS(Permissions!$G$2:$G$3000,Permissions!$B$2:$B$3000,$A2,Permissions!$I$2:$I$3000,"Complete",Permissions!$R$2:$R$3000,"Yes") -> 0 | AJ2: =SUMIFS(Permissions!$G$2:$G$3000,Permissions!$B$2:$B$3000,$A2,Permissions!$I$2:$I$3000,"Under construction",Permissions!$R$2:$R$3000,"Yes") -> 0 | AK2: =SUMIFS(Permissions!$G$2:$G$3000,Permissions!$B$2:$B$3000,$A2,Permissions!$I$2:$I$3000,"Permitted – not started",Permissions!$R$2:$R$3000,"Yes") -> 0 | AL2: =SUMIFS(Permissions!$G$2:$G$3000,Permissions!$B$2:$B$3000,$A2,Permissions!$I$2:$I$3000,"Stalled",Permissions!$R$2:$R$3000,"Yes") -> 0 | AM2: =AI2+AJ2+AK2+AL2 -> 0 | AN2: =SUMIFS(Permissions!$G$2:$G$3000,Permissions!$B$2:$B$3000,$A2,Permissions!$I$2:$I$3000,"Expired – not started",Permissions!$R$2:$R$3000,"Yes") -> 0 | AO2: =SUMIFS(Permissions!$G$2:$G$3000,Permissions!$B$2:$B$3000,$A2,Permissions!$I$2:$I$3000,"In planning",Permissions!$R$2:$R$3000,"Yes") -> 0 | AP2: =IF(R2="",0,MAX(R2-AM2,0)) -> 99 | AQ2: =AM2+AP2 -> 99 | AR2: =SUMIFS(Permissions!$L$2:$L$3000,Permissions!$B$2:$B$3000,$A2,Permissions!$R$2:$R$3000,"Yes",Permissions!$I$2:$I$3000,"<>Expired – not started",Permissions!$I$2:$I$3000,"<>In planning") -> 0 | AS2: =AQ2-AR2 -> 99 | AT2: =SUMIFS(Permissions!$AJ$2:$AJ$3000,Permissions!$B$2:$B$3000,$A2,Permissions!$R$2:$R$3000,"Yes") -> 0 | AU2: =SUMIFS(Permissions!$AK$2:$AK$3000,Permissions!$B$2:$B$3000,$A2,Permissions!$R$2:$R$3000,"Yes") -> 0 | AV2: =SUMIFS(Permissions!$AL$2:$AL$3000,Permissions!$B$2:$B$3000,$A2,Permissions!$R$2:$R$3000,"Yes") -> 0 | AW2: =SUMIFS(Permissions!$AM$2:$AM$3000,Permissions!$B$2:$B$3000,$A2,Permissions!$R$2:$R$3000,"Yes") -> 0 | AX2: =SUMIFS(Permissions!$AN$2:$AN$3000,Permissions!$B$2:$B$3000,$A2,Permissions!$R$2:$R$3000,"Yes") -> 0 | AY2: =SUMIFS(Permissions!$AO$2:$AO$3000,Permissions!$B$2:$B$3000,$A2,Permissions!$R$2:$R$3000,"Yes") -> 0 | AZ2: =COUNTIFS(Permissions!$B$2:$B$3000,$A2,Permissions!$R$2:$R$3000,"Yes") -> 0 | BA2: =SUMIFS(Permissions!$M$2:$M$3000,Permissions!$B$2:$B$3000,$A2,Permissions!$R$2:$R$3000,"Yes") -> 0 | BB2: =SUMIFS(Permissions!$O$2:$O$3000,Permissions!$B$2:$B$3000,$A2,Permissions!$R$2:$R$3000,"Yes") -> 0 | BC2: =IF(AND(AM2>0,AR2>=AM2,AP2=0),"Finished",IF(AR2>0,"Partly built",IF(AM2>0,"Consented – not built","No consent"))) -> No consent | BD2: =IF(AND(R2<>"",AM2>1.1*R2),"Consented above capacity",IF(AND(LEFT(B2,8)="Planning",AZ2=0),"Consent parcel with no permission",IF(COUNTIF($A$2:$A$3000,$A2)>1,"Duplicate parcel_id","")))
A3: CITY-130 | B3: Council audit | C3: City | D3: Ballinacurra | E3: City neighbourhood | F3: 1 | G3: Inside catchment | H3: 130 | I3: Ballinacurra | J3: LIMERICK CITY WEST LEA-7 | K3: City Centre | L3: Council | M3: Exist Resi | N3: Infill | O3: 45+ | P3: 0.144 | Q3: 0.144 | R3: 6 | S3: Council estimate (area × density band) | T3: 5 | X3: City suburbs | Y3: 34 | Z3: 34 homes/ha = median of 39 permitted Limerick schemes of 10+ homes in city suburbs; applied to developable for density_estimate_units only | AB3: 0 | AC3: 0 | AD3: Undeveloped/Permission Sought | AE3: Unchanged | AF3: 2026-10-11 | AH3: =IF(R3="",AM3,R3) -> 6 | AI3: =SUMIFS(Permissions!$G$2:$G$3000,Permissions!$B$2:$B$3000,$A3,Permissions!$I$2:$I$3000,"Complete",Permissions!$R$2:$R$3000,"Yes") -> 0 | AJ3: =SUMIFS(Permissions!$G$2:$G$3000,Permissions!$B$2:$B$3000,$A3,Permissions!$I$2:$I$3000,"Under construction",Permissions!$R$2:$R$3000,"Yes") -> 0 | AK3: =SUMIFS(Permissions!$G$2:$G$3000,Permissions!$B$2:$B$3000,$A3,Permissions!$I$2:$I$3000,"Permitted – not started",Permissions!$R$2:$R$3000,"Yes") -> 0 | AL3: =SUMIFS(Permissions!$G$2:$G$3000,Permissions!$B$2:$B$3000,$A3,Permissions!$I$2:$I$3000,"Stalled",Permissions!$R$2:$R$3000,"Yes") -> 0 | AM3: =AI3+AJ3+AK3+AL3 -> 0 | AN3: =SUMIFS(Permissions!$G$2:$G$3000,Permissions!$B$2:$B$3000,$A3,Permissions!$I$2:$I$3000,"Expired – not started",Permissions!$R$2:$R$3000,"Yes") -> 0 | AO3: =SUMIFS(Permissions!$G$2:$G$3000,Permissions!$B$2:$B$3000,$A3,Permissions!$I$2:$I$3000,"In planning",Permissions!$R$2:$R$3000,"Yes") -> 0 | AP3: =IF(R3="",0,MAX(R3-AM3,0)) -> 6 | AQ3: =AM3+AP3 -> 6 | AR3: =SUMIFS(Permissions!$L$2:$L$3000,Permissions!$B$2:$B$3000,$A3,Permissions!$R$2:$R$3000,"Yes",Permissions!$I$2:$I$3000,"<>Expired – not started",Permissions!$I$2:$I$3000,"<>In planning") -> 0 | AS3: =AQ3-AR3 -> 6 | AT3: =SUMIFS(Permissions!$AJ$2:$AJ$3000,Permissions!$B$2:$B$3000,$A3,Permissions!$R$2:$R$3000,"Yes") -> 0 | AU3: =SUMIFS(Permissions!$AK$2:$AK$3000,Permissions!$B$2:$B$3000,$A3,Permissions!$R$2:$R$3000,"Yes") -> 0 | AV3: =SUMIFS(Permissions!$AL$2:$AL$3000,Permissions!$B$2:$B$3000,$A3,Permissions!$R$2:$R$3000,"Yes") -> 0 | AW3: =SUMIFS(Permissions!$AM$2:$AM$3000,Permissions!$B$2:$B$3000,$A3,Permissions!$R$2:$R$3000,"Yes") -> 0 | AX3: =SUMIFS(Permissions!$AN$2:$AN$3000,Permissions!$B$2:$B$3000,$A3,Permissions!$R$2:$R$3000,"Yes") -> 0 | AY3: =SUMIFS(Permissions!$AO$2:$AO$3000,Permissions!$B$2:$B$3000,$A3,Permissions!$R$2:$R$3000,"Yes") -> 0 | AZ3: =COUNTIFS(Permissions!$B$2:$B$3000,$A3,Permissions!$R$2:$R$3000,"Yes") -> 0 | BA3: =SUMIFS(Permissions!$M$2:$M$3000,Permissions!$B$2:$B$3000,$A3,Permissions!$R$2:$R$3000,"Yes") -> 0 | BB3: =SUMIFS(Permissions!$O$2:$O$3000,Permissions!$B$2:$B$3000,$A3,Permissions!$R$2:$R$3000,"Yes") -> 0 | BC3: =IF(AND(AM3>0,AR3>=AM3,AP3=0),"Finished",IF(AR3>0,"Partly built",IF(AM3>0,"Consented – not built","No consent"))) -> No consent | BD3: =IF(AND(R3<>"",AM3>1.1*R3),"Consented above capacity",IF(AND(LEFT(B3,8)="Planning",AZ3=0),"Consent parcel with no permission",IF(COUNTIF($A$2:$A$3000,$A3)>1,"Duplicate parcel_id","")))
A4: CITY-131 | B4: Council audit | C4: City | D4: Ballinacurra | E4: City neighbourhood | F4: 1 | G4: Inside catchment | H4: 131 | I4: Ballinacurra | J4: LIMERICK CITY WEST LEA-7 | K4: City Centre | L4: Council | M4: New Resi | N4: Infill | O4: 45+ | P4: 0.252 | Q4: 0.252 | R4: 11 | S4: Council estimate (area × density band) | T4: 9 | X4: City suburbs | Y4: 34 | Z4: 34 homes/ha = median of 39 permitted Limerick schemes of 10+ homes in city suburbs; applied to developable for density_estimate_units only | AB4: 0 | AC4: 0 | AD4: Undeveloped/Permission Sought | AE4: Unchanged | AF4: 2026-10-11 | AH4: =IF(R4="",AM4,R4) -> 11 | AI4: =SUMIFS(Permissions!$G$2:$G$3000,Permissions!$B$2:$B$3000,$A4,Permissions!$I$2:$I$3000,"Complete",Permissions!$R$2:$R$3000,"Yes") -> 0 | AJ4: =SUMIFS(Permissions!$G$2:$G$3000,Permissions!$B$2:$B$3000,$A4,Permissions!$I$2:$I$3000,"Under construction",Permissions!$R$2:$R$3000,"Yes") -> 0 | AK4: =SUMIFS(Permissions!$G$2:$G$3000,Permissions!$B$2:$B$3000,$A4,Permissions!$I$2:$I$3000,"Permitted – not started",Permissions!$R$2:$R$3000,"Yes") -> 0 | AL4: =SUMIFS(Permissions!$G$2:$G$3000,Permissions!$B$2:$B$3000,$A4,Permissions!$I$2:$I$3000,"Stalled",Permissions!$R$2:$R$3000,"Yes") -> 0 | AM4: =AI4+AJ4+AK4+AL4 -> 0 | AN4: =SUMIFS(Permissions!$G$2:$G$3000,Permissions!$B$2:$B$3000,$A4,Permissions!$I$2:$I$3000,"Expired – not started",Permissions!$R$2:$R$3000,"Yes") -> 0 | AO4: =SUMIFS(Permissions!$G$2:$G$3000,Permissions!$B$2:$B$3000,$A4,Permissions!$I$2:$I$3000,"In planning",Permissions!$R$2:$R$3000,"Yes") -> 0 | AP4: =IF(R4="",0,MAX(R4-AM4,0)) -> 11 | AQ4: =AM4+AP4 -> 11 | AR4: =SUMIFS(Permissions!$L$2:$L$3000,Permissions!$B$2:$B$3000,$A4,Permissions!$R$2:$R$3000,"Yes",Permissions!$I$2:$I$3000,"<>Expired – not started",Permissions!$I$2:$I$3000,"<>In planning") -> 0 | AS4: =AQ4-AR4 -> 11 | AT4: =SUMIFS(Permissions!$AJ$2:$AJ$3000,Permissions!$B$2:$B$3000,$A4,Permissions!$R$2:$R$3000,"Yes") -> 0 | AU4: =SUMIFS(Permissions!$AK$2:$AK$3000,Permissions!$B$2:$B$3000,$A4,Permissions!$R$2:$R$3000,"Yes") -> 0 | AV4: =SUMIFS(Permissions!$AL$2:$AL$3000,Permissions!$B$2:$B$3000,$A4,Permissions!$R$2:$R$3000,"Yes") -> 0 | AW4: =SUMIFS(Permissions!$AM$2:$AM$3000,Permissions!$B$2:$B$3000,$A4,Permissions!$R$2:$R$3000,"Yes") -> 0 | AX4: =SUMIFS(Permissions!$AN$2:$AN$3000,Permissions!$B$2:$B$3000,$A4,Permissions!$R$2:$R$3000,"Yes") -> 0 | AY4: =SUMIFS(Permissions!$AO$2:$AO$3000,Permissions!$B$2:$B$3000,$A4,Permissions!$R$2:$R$3000,"Yes") -> 0 | AZ4: =COUNTIFS(Permissions!$B$2:$B$3000,$A4,Permissions!$R$2:$R$3000,"Yes") -> 0 | BA4: =SUMIFS(Permissions!$M$2:$M$3000,Permissions!$B$2:$B$3000,$A4,Permissions!$R$2:$R$3000,"Yes") -> 0 | BB4: =SUMIFS(Permissions!$O$2:$O$3000,Permissions!$B$2:$B$3000,$A4,Permissions!$R$2:$R$3000,"Yes") -> 0 | BC4: =IF(AND(AM4>0,AR4>=AM4,AP4=0),"Finished",IF(AR4>0,"Partly built",IF(AM4>0,"Consented – not built","No consent"))) -> No consent | BD4: =IF(AND(R4<>"",AM4>1.1*R4),"Consented above capacity",IF(AND(LEFT(B4,8)="Planning",AZ4=0),"Consent parcel with no permission",IF(COUNTIF($A$2:$A$3000,$A4)>1,"Duplicate parcel_id","")))
A5: CITY-132 | B5: Council audit | C5: City | D5: Ballinacurra | E5: City neighbourhood | F5: 1 | G5: Inside catchment | H5: 132 | I5: Ballinacurra | J5: LIMERICK CITY WEST LEA-7 | K5: Dock Rd | L5: Private | M5: Exist Resi | N5: Brownfield | O5: 45+ | P5: 0.706 | Q5: 0.706 | R5: 32 | S5: Council estimate (area × density band) | T5: 24 | X5: City suburbs | Y5: 34 | Z5: 34 homes/ha = median of 39 permitted Limerick schemes of 10+ homes in city suburbs; applied to developable for density_estimate_units only | AB5: 0 | AC5: 0 | AD5: Undeveloped/Permission Sought | AE5: Unchanged | AF5: 2026-10-11 | AH5: =IF(R5="",AM5,R5) -> 32 | AI5: =SUMIFS(Permissions!$G$2:$G$3000,Permissions!$B$2:$B$3000,$A5,Permissions!$I$2:$I$3000,"Complete",Permissions!$R$2:$R$3000,"Yes") -> 0 | AJ5: =SUMIFS(Permissions!$G$2:$G$3000,Permissions!$B$2:$B$3000,$A5,Permissions!$I$2:$I$3000,"Under construction",Permissions!$R$2:$R$3000,"Yes") -> 0 | AK5: =SUMIFS(Permissions!$G$2:$G$3000,Permissions!$B$2:$B$3000,$A5,Permissions!$I$2:$I$3000,"Permitted – not started",Permissions!$R$2:$R$3000,"Yes") -> 0 | AL5: =SUMIFS(Permissions!$G$2:$G$3000,Permissions!$B$2:$B$3000,$A5,Permissions!$I$2:$I$3000,"Stalled",Permissions!$R$2:$R$3000,"Yes") -> 0 | AM5: =AI5+AJ5+AK5+AL5 -> 0 | AN5: =SUMIFS(Permissions!$G$2:$G$3000,Permissions!$B$2:$B$3000,$A5,Permissions!$I$2:$I$3000,"Expired – not started",Permissions!$R$2:$R$3000,"Yes") -> 0 | AO5: =SUMIFS(Permissions!$G$2:$G$3000,Permissions!$B$2:$B$3000,$A5,Permissions!$I$2:$I$3000,"In planning",Permissions!$R$2:$R$3000,"Yes") -> 0 | AP5: =IF(R5="",0,MAX(R5-AM5,0)) -> 32 | AQ5: =AM5+AP5 -> 32 | AR5: =SUMIFS(Permissions!$L$2:$L$3000,Permissions!$B$2:$B$3000,$A5,Permissions!$R$2:$R$3000,"Yes",Permissions!$I$2:$I$3000,"<>Expired – not started",Permissions!$I$2:$I$3000,"<>In planning") -> 0 | AS5: =AQ5-AR5 -> 32 | AT5: =SUMIFS(Permissions!$AJ$2:$AJ$3000,Permissions!$B$2:$B$3000,$A5,Permissions!$R$2:$R$3000,"Yes") -> 0 | AU5: =SUMIFS(Permissions!$AK$2:$AK$3000,Permissions!$B$2:$B$3000,$A5,Permissions!$R$2:$R$3000,"Yes") -> 0 | AV5: =SUMIFS(Permissions!$AL$2:$AL$3000,Permissions!$B$2:$B$3000,$A5,Permissions!$R$2:$R$3000,"Yes") -> 0 | AW5: =SUMIFS(Permissions!$AM$2:$AM$3000,Permissions!$B$2:$B$3000,$A5,Permissions!$R$2:$R$3000,"Yes") -> 0 | AX5: =SUMIFS(Permissions!$AN$2:$AN$3000,Permissions!$B$2:$B$3000,$A5,Permissions!$R$2:$R$3000,"Yes") -> 0 | AY5: =SUMIFS(Permissions!$AO$2:$AO$3000,Permissions!$B$2:$B$3000,$A5,Permissions!$R$2:$R$3000,"Yes") -> 0 | AZ5: =COUNTIFS(Permissions!$B$2:$B$3000,$A5,Permissions!$R$2:$R$3000,"Yes") -> 0 | BA5: =SUMIFS(Permissions!$M$2:$M$3000,Permissions!$B$2:$B$3000,$A5,Permissions!$R$2:$R$3000,"Yes") -> 0 | BB5: =SUMIFS(Permissions!$O$2:$O$3000,Permissions!$B$2:$B$3000,$A5,Permissions!$R$2:$R$3000,"Yes") -> 0 | BC5: =IF(AND(AM5>0,AR5>=AM5,AP5=0),"Finished",IF(AR5>0,"Partly built",IF(AM5>0,"Consented – not built","No consent"))) -> No consent | BD5: =IF(AND(R5<>"",AM5>1.1*R5),"Consented above capacity",IF(AND(LEFT(B5,8)="Planning",AZ5=0),"Consent parcel with no permission",IF(COUNTIF($A$2:$A$3000,$A5)>1,"Duplicate parcel_id","")))
A6: CITY-133 | B6: Council audit | C6: City | D6: Ballinacurra | E6: City neighbourhood | F6: 1 | G6: Inside catchment | H6: 133 | I6: Ballinacurra | J6: LIMERICK CITY WEST LEA-7 | K6: Dock Rd | L6: Private | M6: New Resi | N6: Infill | O6: 6.659 in 45+ 2.284 in 35+ | P6: 1.22 | Q6: 9.479 | R6: 55 | S6: Council estimate (area × density band) | T6: 41 | X6: City suburbs | Y6: 34 | Z6: 34 homes/ha = median of 39 permitted Limerick schemes of 10+ homes in city suburbs; applied to developable for density_estimate_units only | AB6: 310 | AC6: 310 | AD6: Complete/Commenced | AE6: Reduced Area | AF6: 2026-10-11 | AH6: =IF(R6="",AM6,R6) -> 55 | AI6: =SUMIFS(Permissions!$G$2:$G$3000,Permissions!$B$2:$B$3000,$A6,Permissions!$I$2:$I$3000,"Complete",Permissions!$R$2:$R$3000,"Yes") -> 0 | AJ6: =SUMIFS(Permissions!$G$2:$G$3000,Permissions!$B$2:$B$3000,$A6,Permissions!$I$2:$I$3000,"Under construction",Permissions!$R$2:$R$3000,"Yes") -> 371 | AK6: =SUMIFS(Permissions!$G$2:$G$3000,Permissions!$B$2:$B$3000,$A6,Permissions!$I$2:$I$3000,"Permitted – not started",Permissions!$R$2:$R$3000,"Yes") -> 0 | AL6: =SUMIFS(Permissions!$G$2:$G$3000,Permissions!$B$2:$B$3000,$A6,Permissions!$I$2:$I$3000,"Stalled",Permissions!$R$2:$R$3000,"Yes") -> 0 | AM6: =AI6+AJ6+AK6+AL6 -> 371 | AN6: =SUMIFS(Permissions!$G$2:$G$3000,Permissions!$B$2:$B$3000,$A6,Permissions!$I$2:$I$3000,"Expired – not started",Permissions!$R$2:$R$3000,"Yes") -> 0 | AO6: =SUMIFS(Permissions!$G$2:$G$3000,Permissions!$B$2:$B$3000,$A6,Permissions!$I$2:$I$3000,"In planning",Permissions!$R$2:$R$3000,"Yes") -> 0 | AP6: =IF(R6="",0,MAX(R6-AM6,0)) -> 0 | AQ6: =AM6+AP6 -> 371 | AR6: =SUMIFS(Permissions!$L$2:$L$3000,Permissions!$B$2:$B$3000,$A6,Permissions!$R$2:$R$3000,"Yes",Permissions!$I$2:$I$3000,"<>Expired – not started",Permissions!$I$2:$I$3000,"<>In planning") -> 121 | AS6: =AQ6-AR6 -> 250 | AT6: =SUMIFS(Permissions!$AJ$2:$AJ$3000,Permissions!$B$2:$B$3000,$A6,Permissions!$R$2:$R$3000,"Yes") -> 20.6 | AU6: =SUMIFS(Permissions!$AK$2:$AK$3000,Permissions!$B$2:$B$3000,$A6,Permissions!$R$2:$R$3000,"Yes") -> 88.5 | AV6: =SUMIFS(Permissions!$AL$2:$AL$3000,Permissions!$B$2:$B$3000,$A6,Permissions!$R$2:$R$3000,"Yes") -> 88.5 | AW6: =SUMIFS(Permissions!$AM$2:$AM$3000,Permissions!$B$2:$B$3000,$A6,Permissions!$R$2:$R$3000,"Yes") -> 88.5 | AX6: =SUMIFS(Permissions!$AN$2:$AN$3000,Permissions!$B$2:$B$3000,$A6,Permissions!$R$2:$R$3000,"Yes") -> 84.9 | AY6: =SUMIFS(Permissions!$AO$2:$AO$3000,Permissions!$B$2:$B$3000,$A6,Permissions!$R$2:$R$3000,"Yes") -> 0 | AZ6: =COUNTIFS(Permissions!$B$2:$B$3000,$A6,Permissions!$R$2:$R$3000,"Yes") -> 1 | BA6: =SUMIFS(Permissions!$M$2:$M$3000,Permissions!$B$2:$B$3000,$A6,Permissions!$R$2:$R$3000,"Yes") -> 121 | BB6: =SUMIFS(Permissions!$O$2:$O$3000,Permissions!$B$2:$B$3000,$A6,Permissions!$R$2:$R$3000,"Yes") -> 4 | BC6: =IF(AND(AM6>0,AR6>=AM6,AP6=0),"Finished",IF(AR6>0,"Partly built",IF(AM6>0,"Consented – not built","No consent"))) -> Partly built | BD6: =IF(AND(R6<>"",AM6>1.1*R6),"Consented above capacity",IF(AND(LEFT(B6,8)="Planning",AZ6=0),"Consent parcel with no permission",IF(COUNTIF($A$2:$A$3000,$A6)>1,"Duplicate parcel_id",""))) -> Consented above capacity
A7: CITY-1 | B7: Council audit | C7: City | D7: Caherdavin | E7: City neighbourhood | F7: 1 | G7: Inside catchment | H7: 1 | I7: Caherdavin | J7: LIMERICK CITY NORTH LEA-7 | K7: Northside | L7: Private | M7: New Resi | N7: Greenfield | O7: 35+ | P7: 2.408 | Q7: 2.4 | R7: 165 | S7: Council estimate (area × density band) | T7: 82 | X7: City suburbs | Y7: 34 | Z7: 34 homes/ha = median of 39 permitted Limerick schemes of 10+ homes in city suburbs; applied to developable for density_estimate_units only | AB7: 0 | AC7: 0 | AD7: Permission Granted | AE7: Unchanged | AF7: 2026-10-11 | AH7: =IF(R7="",AM7,R7) -> 165 | AI7: =SUMIFS(Permissions!$G$2:$G$3000,Permissions!$B$2:$B$3000,$A7,Permissions!$I$2:$I$3000,"Complete",Permissions!$R$2:$R$3000,"Yes") -> 0 | AJ7: =SUMIFS(Permissions!$G$2:$G$3000,Permissions!$B$2:$B$3000,$A7,Permissions!$I$2:$I$3000,"Under construction",Permissions!$R$2:$R$3000,"Yes") -> 0 | AK7: =SUMIFS(Permissions!$G$2:$G$3000,Permissions!$B$2:$B$3000,$A7,Permissions!$I$2:$I$3000,"Permitted – not started",Permissions!$R$2:$R$3000,"Yes") -> 165 | AL7: =SUMIFS(Permissions!$G$2:$G$3000,Permissions!$B$2:$B$3000,$A7,Permissions!$I$2:$I$3000,"Stalled",Permissions!$R$2:$R$3000,"Yes") -> 0 | AM7: =AI7+AJ7+AK7+AL7 -> 165 | AN7: =SUMIFS(Permissions!$G$2:$G$3000,Permissions!$B$2:$B$3000,$A7,Permissions!$I$2:$I$3000,"Expired – not started",Permissions!$R$2:$R$3000,"Yes") -> 0 | AO7: =SUMIFS(Permissions!$G$2:$G$3000,Permissions!$B$2:$B$3000,$A7,Permissions!$I$2:$I$3000,"In planning",Permissions!$R$2:$R$3000,"Yes") -> 0 | AP7: =IF(R7="",0,MAX(R7-AM7,0)) -> 0 | AQ7: =AM7+AP7 -> 165 | AR7: =SUMIFS(Permissions!$L$2:$L$3000,Permissions!$B$2:$B$3000,$A7,Permissions!$R$2:$R$3000,"Yes",Permissions!$I$2:$I$3000,"<>Expired – not started",Permissions!$I$2:$I$3000,"<>In planning") -> 0 | AS7: =AQ7-AR7 -> 165 | AT7: =SUMIFS(Permissions!$AJ$2:$AJ$3000,Permissions!$B$2:$B$3000,$A7,Permissions!$R$2:$R$3000,"Yes") -> 0 | AU7: =SUMIFS(Permissions!$AK$2:$AK$3000,Permissions!$B$2:$B$3000,$A7,Permissions!$R$2:$R$3000,"Yes") -> 0 | AV7: =SUMIFS(Permissions!$AL$2:$AL$3000,Permissions!$B$2:$B$3000,$A7,Permissions!$R$2:$R$3000,"Yes") -> 34.9 | AW7: =SUMIFS(Permissions!$AM$2:$AM$3000,Permissions!$B$2:$B$3000,$A7,Permissions!$R$2:$R$3000,"Yes") -> 72.3 | AX7: =SUMIFS(Permissions!$AN$2:$AN$3000,Permissions!$B$2:$B$3000,$A7,Permissions!$R$2:$R$3000,"Yes") -> 57.8 | AY7: =SUMIFS(Permissions!$AO$2:$AO$3000,Permissions!$B$2:$B$3000,$A7,Permissions!$R$2:$R$3000,"Yes") -> 0 | AZ7: =COUNTIFS(Permissions!$B$2:$B$3000,$A7,Permissions!$R$2:$R$3000,"Yes") -> 1 | BA7: =SUMIFS(Permissions!$M$2:$M$3000,Permissions!$B$2:$B$3000,$A7,Permissions!$R$2:$R$3000,"Yes") -> 0 | BB7: =SUMIFS(Permissions!$O$2:$O$3000,Permissions!$B$2:$B$3000,$A7,Permissions!$R$2:$R$3000,"Yes") -> 0 | BC7: =IF(AND(AM7>0,AR7>=AM7,AP7=0),"Finished",IF(AR7>0,"Partly built",IF(AM7>0,"Consented – not built","No consent"))) -> Consented – not built | BD7: =IF(AND(R7<>"",AM7>1.1*R7),"Consented above capacity",IF(AND(LEFT(B7,8)="Planning",AZ7=0),"Consent parcel with no permission",IF(COUNTIF($A$2:$A$3000,$A7)>1,"Duplicate parcel_id","")))
A8: CITY-10 | B8: Council audit | C8: City | D8: Caherdavin | E8: City neighbourhood | F8: 1 | G8: Inside catchment | H8: 10 | I8: Caherdavin | J8: LIMERICK CITY NORTH LEA-7 | K8: Northside | L8: Council | M8: Exist Resi | N8: Infill | O8: 45+ | P8: 1.991 | Q8: 1.991 | R8: 90 | S8: Council estimate (area × density band) | T8: 68 | X8: City suburbs | Y8: 34 | Z8: 34 homes/ha = median of 39 permitted Limerick schemes of 10+ homes in city suburbs; applied to developable for density_estimate_units only | AB8: 0 | AC8: 0 | AD8: Undeveloped/Permission Sought | AE8: Unchanged | AF8: 2026-10-11 | AH8: =IF(R8="",AM8,R8) -> 90 | AI8: =SUMIFS(Permissions!$G$2:$G$3000,Permissions!$B$2:$B$3000,$A8,Permissions!$I$2:$I$3000,"Complete",Permissions!$R$2:$R$3000,"Yes") -> 0 | AJ8: =SUMIFS(Permissions!$G$2:$G$3000,Permissions!$B$2:$B$3000,$A8,Permissions!$I$2:$I$3000,"Under construction",Permissions!$R$2:$R$3000,"Yes") -> 0 | AK8: =SUMIFS(Permissions!$G$2:$G$3000,Permissions!$B$2:$B$3000,$A8,Permissions!$I$2:$I$3000,"Permitted – not started",Permissions!$R$2:$R$3000,"Yes") -> 0 | AL8: =SUMIFS(Permissions!$G$2:$G$3000,Permissions!$B$2:$B$3000,$A8,Permissions!$I$2:$I$3000,"Stalled",Permissions!$R$2:$R$3000,"Yes") -> 0 | AM8: =AI8+AJ8+AK8+AL8 -> 0 | AN8: =SUMIFS(Permissions!$G$2:$G$3000,Permissions!$B$2:$B$3000,$A8,Permissions!$I$2:$I$3000,"Expired – not started",Permissions!$R$2:$R$3000,"Yes") -> 0 | AO8: =SUMIFS(Permissions!$G$2:$G$3000,Permissions!$B$2:$B$3000,$A8,Permissions!$I$2:$I$3000,"In planning",Permissions!$R$2:$R$3000,"Yes") -> 0 | AP8: =IF(R8="",0,MAX(R8-AM8,0)) -> 90 | AQ8: =AM8+AP8 -> 90 | AR8: =SUMIFS(Permissions!$L$2:$L$3000,Permissions!$B$2:$B$3000,$A8,Permissions!$R$2:$R$3000,"Yes",Permissions!$I$2:$I$3000,"<>Expired – not started",Permissions!$I$2:$I$3000,"<>In planning") -> 0 | AS8: =AQ8-AR8 -> 90 | AT8: =SUMIFS(Permissions!$AJ$2:$AJ$3000,Permissions!$B$2:$B$3000,$A8,Permissions!$R$2:$R$3000,"Yes") -> 0 | AU8: =SUMIFS(Permissions!$AK$2:$AK$3000,Permissions!$B$2:$B$3000,$A8,Permissions!$R$2:$R$3000,"Yes") -> 0 | AV8: =SUMIFS(Permissions!$AL$2:$AL$3000,Permissions!$B$2:$B$3000,$A8,Permissions!$R$2:$R$3000,"Yes") -> 0 | AW8: =SUMIFS(Permissions!$AM$2:$AM$3000,Permissions!$B$2:$B$3000,$A8,Permissions!$R$2:$R$3000,"Yes") -> 0 | AX8: =SUMIFS(Permissions!$AN$2:$AN$3000,Permissions!$B$2:$B$3000,$A8,Permissions!$R$2:$R$3000,"Yes") -> 0 | AY8: =SUMIFS(Permissions!$AO$2:$AO$3000,Permissions!$B$2:$B$3000,$A8,Permissions!$R$2:$R$3000,"Yes") -> 0 | AZ8: =COUNTIFS(Permissions!$B$2:$B$3000,$A8,Permissions!$R$2:$R$3000,"Yes") -> 0 | BA8: =SUMIFS(Permissions!$M$2:$M$3000,Permissions!$B$2:$B$3000,$A8,Permissions!$R$2:$R$3000,"Yes") -> 0 | BB8: =SUMIFS(Permissions!$O$2:$O$3000,Permissions!$B$2:$B$3000,$A8,Permissions!$R$2:$R$3000,"Yes") -> 0 | BC8: =IF(AND(AM8>0,AR8>=AM8,AP8=0),"Finished",IF(AR8>0,"Partly built",IF(AM8>0,"Consented – not built","No consent"))) -> No consent | BD8: =IF(AND(R8<>"",AM8>1.1*R8),"Consented above capacity",IF(AND(LEFT(B8,8)="Planning",AZ8=0),"Consent parcel with no permission",IF(COUNTIF($A$2:$A$3000,$A8)>1,"Duplicate parcel_id","")))
A9: CITY-12 | B9: Council audit | C9: City | D9: Caherdavin | E9: City neighbourhood | F9: 1 | G9: Inside catchment | H9: 12 | I9: Caherdavin | J9: LIMERICK CITY NORTH LEA-7 | K9: Northside | L9: Unknown | M9: Mixed Use | N9: Greenfield | O9: 6.207 in 45+ 3.224 in 35+ | P9: 9.431 | Q9: 9.427 | R9: 73 | S9: Council estimate (area × density band) | T9: 321 | X9: City suburbs | Y9: 34 | Z9: 34 homes/ha = median of 39 permitted Limerick schemes of 10+ homes in city suburbs; applied to developable for density_estimate_units only | AB9: 0 | AC9: 0 | AD9: Permission Granted | AE9: Unchanged (council file landowner "EOI", owner not stated: shown as Unknown) | AF9: 2026-10-11 | AH9: =IF(R9="",AM9,R9) -> 73 | AI9: =SUMIFS(Permissions!$G$2:$G$3000,Permissions!$B$2:$B$3000,$A9,Permissions!$I$2:$I$3000,"Complete",Permissions!$R$2:$R$3000,"Yes") -> 0 | AJ9: =SUMIFS(Permissions!$G$2:$G$3000,Permissions!$B$2:$B$3000,$A9,Permissions!$I$2:$I$3000,"Under construction",Permissions!$R$2:$R$3000,"Yes") -> 115 | AK9: =SUMIFS(Permissions!$G$2:$G$3000,Permissions!$B$2:$B$3000,$A9,Permissions!$I$2:$I$3000,"Permitted – not started",Permissions!$R$2:$R$3000,"Yes") -> 0 | AL9: =SUMIFS(Permissions!$G$2:$G$3000,Permissions!$B$2:$B$3000,$A9,Permissions!$I$2:$I$3000,"Stalled",Permissions!$R$2:$R$3000,"Yes") -> 0 | AM9: =AI9+AJ9+AK9+AL9 -> 115 | AN9: =SUMIFS(Permissions!$G$2:$G$3000,Permissions!$B$2:$B$3000,$A9,Permissions!$I$2:$I$3000,"Expired – not started",Permissions!$R$2:$R$3000,"Yes") -> 0 | AO9: =SUMIFS(Permissions!$G$2:$G$3000,Permissions!$B$2:$B$3000,$A9,Permissions!$I$2:$I$3000,"In planning",Permissions!$R$2:$R$3000,"Yes") -> 0 | AP9: =IF(R9="",0,MAX(R9-AM9,0)) -> 0 | AQ9: =AM9+AP9 -> 115 | AR9: =SUMIFS(Permissions!$L$2:$L$3000,Permissions!$B$2:$B$3000,$A9,Permissions!$R$2:$R$3000,"Yes",Permissions!$I$2:$I$3000,"<>Expired – not started",Permissions!$I$2:$I$3000,"<>In planning") -> 0 | AS9: =AQ9-AR9 -> 115 | AT9: =SUMIFS(Permissions!$AJ$2:$AJ$3000,Permissions!$B$2:$B$3000,$A9,Permissions!$R$2:$R$3000,"Yes") -> 0 | AU9: =SUMIFS(Permissions!$AK$2:$AK$3000,Permissions!$B$2:$B$3000,$A9,Permissions!$R$2:$R$3000,"Yes") -> 51.6 | AV9: =SUMIFS(Permissions!$AL$2:$AL$3000,Permissions!$B$2:$B$3000,$A9,Permissions!$R$2:$R$3000,"Yes") -> 63.4 | AW9: =SUMIFS(Permissions!$AM$2:$AM$3000,Permissions!$B$2:$B$3000,$A9,Permissions!$R$2:$R$3000,"Yes") -> 0 | AX9: =SUMIFS(Permissions!$AN$2:$AN$3000,Permissions!$B$2:$B$3000,$A9,Permissions!$R$2:$R$3000,"Yes") -> 0 | AY9: =SUMIFS(Permissions!$AO$2:$AO$3000,Permissions!$B$2:$B$3000,$A9,Permissions!$R$2:$R$3000,"Yes") -> 0 | AZ9: =COUNTIFS(Permissions!$B$2:$B$3000,$A9,Permissions!$R$2:$R$3000,"Yes") -> 1 | BA9: =SUMIFS(Permissions!$M$2:$M$3000,Permissions!$B$2:$B$3000,$A9,Permissions!$R$2:$R$3000,"Yes") -> 0 | BB9: =SUMIFS(Permissions!$O$2:$O$3000,Permissions!$B$2:$B$3000,$A9,Permissions!$R$2:$R$3000,"Yes") -> 0 | BC9: =IF(AND(AM9>0,AR9>=AM9,AP9=0),"Finished",IF(AR9>0,"Partly built",IF(AM9>0,"Consented – not built","No consent"))) -> Consented – not built | BD9: =IF(AND(R9<>"",AM9>1.1*R9),"Consented above capacity",IF(AND(LEFT(B9,8)="Planning",AZ9=0),"Consent parcel with no permission",IF(COUNTIF($A$2:$A$3000,$A9)>1,"Duplicate parcel_id",""))) -> Consented above capacity
A10: CITY-13 | B10: Council audit | C10: City | D10: Caherdavin | E10: City neighbourhood | F10: 1 | G10: Inside catchment | H10: 13 | I10: Caherdavin | J10: LIMERICK CITY NORTH LEA-7 | K10: Northside | L10: Council | M10: Exist Resi | N10: Infill | O10: 45+ | P10: 0.899 | Q10: 0.899 | R10: 40 | S10: Council estimate (area × density band) | T10: 31 | X10: City suburbs | Y10: 34 | Z10: 34 homes/ha = median of 39 permitted Limerick schemes of 10+ homes in city suburbs; applied to developable for density_estimate_units only | AB10: 0 | AC10: 0 | AD10: Undeveloped/Permission Sought | AE10: Unchanged | AF10: 2026-10-11 | AH10: =IF(R10="",AM10,R10) -> 40 | AI10: =SUMIFS(Permissions!$G$2:$G$3000,Permissions!$B$2:$B$3000,$A10,Permissions!$I$2:$I$3000,"Complete",Permissions!$R$2:$R$3000,"Yes") -> 0 | AJ10: =SUMIFS(Permissions!$G$2:$G$3000,Permissions!$B$2:$B$3000,$A10,Permissions!$I$2:$I$3000,"Under construction",Permissions!$R$2:$R$3000,"Yes") -> 0 | AK10: =SUMIFS(Permissions!$G$2:$G$3000,Permissions!$B$2:$B$3000,$A10,Permissions!$I$2:$I$3000,"Permitted – not started",Permissions!$R$2:$R$3000,"Yes") -> 0 | AL10: =SUMIFS(Permissions!$G$2:$G$3000,Permissions!$B$2:$B$3000,$A10,Permissions!$I$2:$I$3000,"Stalled",Permissions!$R$2:$R$3000,"Yes") -> 0 | AM10: =AI10+AJ10+AK10+AL10 -> 0 | AN10: =SUMIFS(Permissions!$G$2:$G$3000,Permissions!$B$2:$B$3000,$A10,Permissions!$I$2:$I$3000,"Expired – not started",Permissions!$R$2:$R$3000,"Yes") -> 0 | AO10: =SUMIFS(Permissions!$G$2:$G$3000,Permissions!$B$2:$B$3000,$A10,Permissions!$I$2:$I$3000,"In planning",Permissions!$R$2:$R$3000,"Yes") -> 0 | AP10: =IF(R10="",0,MAX(R10-AM10,0)) -> 40 | AQ10: =AM10+AP10 -> 40 | AR10: =SUMIFS(Permissions!$L$2:$L$3000,Permissions!$B$2:$B$3000,$A10,Permissions!$R$2:$R$3000,"Yes",Permissions!$I$2:$I$3000,"<>Expired – not started",Permissions!$I$2:$I$3000,"<>In planning") -> 0 | AS10: =AQ10-AR10 -> 40 | AT10: =SUMIFS(Permissions!$AJ$2:$AJ$3000,Permissions!$B$2:$B$3000,$A10,Permissions!$R$2:$R$3000,"Yes") -> 0 | AU10: =SUMIFS(Permissions!$AK$2:$AK$3000,Permissions!$B$2:$B$3000,$A10,Permissions!$R$2:$R$3000,"Yes") -> 0 | AV10: =SUMIFS(Permissions!$AL$2:$AL$3000,Permissions!$B$2:$B$3000,$A10,Permissions!$R$2:$R$3000,"Yes") -> 0 | AW10: =SUMIFS(Permissions!$AM$2:$AM$3000,Permissions!$B$2:$B$3000,$A10,Permissions!$R$2:$R$3000,"Yes") -> 0 | AX10: =SUMIFS(Permissions!$AN$2:$AN$3000,Permissions!$B$2:$B$3000,$A10,Permissions!$R$2:$R$3000,"Yes") -> 0 | AY10: =SUMIFS(Permissions!$AO$2:$AO$3000,Permissions!$B$2:$B$3000,$A10,Permissions!$R$2:$R$3000,"Yes") -> 0 | AZ10: =COUNTIFS(Permissions!$B$2:$B$3000,$A10,Permissions!$R$2:$R$3000,"Yes") -> 0 | BA10: =SUMIFS(Permissions!$M$2:$M$3000,Permissions!$B$2:$B$3000,$A10,Permissions!$R$2:$R$3000,"Yes") -> 0 | BB10: =SUMIFS(Permissions!$O$2:$O$3000,Permissions!$B$2:$B$3000,$A10,Permissions!$R$2:$R$3000,"Yes") -> 0 | BC10: =IF(AND(AM10>0,AR10>=AM10,AP10=0),"Finished",IF(AR10>0,"Partly built",IF(AM10>0,"Consented – not built","No consent"))) -> No consent | BD10: =IF(AND(R10<>"",AM10>1.1*R10),"Consented above capacity",IF(AND(LEFT(B10,8)="Planning",AZ10=0),"Consent parcel with no permission",IF(COUNTIF($A$2:$A$3000,$A10)>1,"Duplicate parcel_id","")))
A11: CITY-14 | B11: Council audit | C11: City | D11: Caherdavin | E11: City neighbourhood | F11: 1 | G11: Inside catchment | H11: 14 | I11: Caherdavin | J11: LIMERICK CITY NORTH LEA-7 | K11: Northside | L11: Council | M11: Exist Resi | N11: Infill | O11: 45+ | P11: 0.654 | Q11: 2.014 | R11: 30 | S11: Council estimate (area × density band) | T11: 22 | X11: City suburbs | Y11: 34 | Z11: 34 homes/ha = median of 39 permitted Limerick schemes of 10+ homes in city suburbs; applied to developable for density_estimate_units only | AB11: 18 | AC11: 18 | AD11: Complete/Commenced | AE11: Reduced Area | AF11: 2026-10-11 | AH11: =IF(R11="",AM11,R11) -> 30 | AI11: =SUMIFS(Permissions!$G$2:$G$3000,Permissions!$B$2:$B$3000,$A11,Permissions!$I$2:$I$3000,"Complete",Permissions!$R$2:$R$3000,"Yes") -> 0 | AJ11: =SUMIFS(Permissions!$G$2:$G$3000,Permissions!$B$2:$B$3000,$A11,Permissions!$I$2:$I$3000,"Under construction",Permissions!$R$2:$R$3000,"Yes") -> 0 | AK11: =SUMIFS(Permissions!$G$2:$G$3000,Permissions!$B$2:$B$3000,$A11,Permissions!$I$2:$I$3000,"Permitted – not started",Permissions!$R$2:$R$3000,"Yes") -> 0 | AL11: =SUMIFS(Permissions!$G$2:$G$3000,Permissions!$B$2:$B$3000,$A11,Permissions!$I$2:$I$3000,"Stalled",Permissions!$R$2:$R$3000,"Yes") -> 0 | AM11: =AI11+AJ11+AK11+AL11 -> 0 | AN11: =SUMIFS(Permissions!$G$2:$G$3000,Permissions!$B$2:$B$3000,$A11,Permissions!$I$2:$I$3000,"Expired – not started",Permissions!$R$2:$R$3000,"Yes") -> 0 | AO11: =SUMIFS(Permissions!$G$2:$G$3000,Permissions!$B$2:$B$3000,$A11,Permissions!$I$2:$I$3000,"In planning",Permissions!$R$2:$R$3000,"Yes") -> 0 | AP11: =IF(R11="",0,MAX(R11-AM11,0)) -> 30 | AQ11: =AM11+AP11 -> 30 | AR11: =SUMIFS(Permissions!$L$2:$L$3000,Permissions!$B$2:$B$3000,$A11,Permissions!$R$2:$R$3000,"Yes",Permissions!$I$2:$I$3000,"<>Expired – not started",Permissions!$I$2:$I$3000,"<>In planning") -> 0 | AS11: =AQ11-AR11 -> 30 | AT11: =SUMIFS(Permissions!$AJ$2:$AJ$3000,Permissions!$B$2:$B$3000,$A11,Permissions!$R$2:$R$3000,"Yes") -> 0 | AU11: =SUMIFS(Permissions!$AK$2:$AK$3000,Permissions!$B$2:$B$3000,$A11,Permissions!$R$2:$R$3000,"Yes") -> 0 | AV11: =SUMIFS(Permissions!$AL$2:$AL$3000,Permissions!$B$2:$B$3000,$A11,Permissions!$R$2:$R$3000,"Yes") -> 0 | AW11: =SUMIFS(Permissions!$AM$2:$AM$3000,Permissions!$B$2:$B$3000,$A11,Permissions!$R$2:$R$3000,"Yes") -> 0 | AX11: =SUMIFS(Permissions!$AN$2:$AN$3000,Permissions!$B$2:$B$3000,$A11,Permissions!$R$2:$R$3000,"Yes") -> 0 | AY11: =SUMIFS(Permissions!$AO$2:$AO$3000,Permissions!$B$2:$B$3000,$A11,Permissions!$R$2:$R$3000,"Yes") -> 0 | AZ11: =COUNTIFS(Permissions!$B$2:$B$3000,$A11,Permissions!$R$2:$R$3000,"Yes") -> 0 | BA11: =SUMIFS(Permissions!$M$2:$M$3000,Permissions!$B$2:$B$3000,$A11,Permissions!$R$2:$R$3000,"Yes") -> 0 | BB11: =SUMIFS(Permissions!$O$2:$O$3000,Permissions!$B$2:$B$3000,$A11,Permissions!$R$2:$R$3000,"Yes") -> 0 | BC11: =IF(AND(AM11>0,AR11>=AM11,AP11=0),"Finished",IF(AR11>0,"Partly built",IF(AM11>0,"Consented – not built","No consent"))) -> No consent | BD11: =IF(AND(R11<>"",AM11>1.1*R11),"Consented above capacity",IF(AND(LEFT(B11,8)="Planning",AZ11=0),"Consent parcel with no permission",IF(COUNTIF($A$2:$A$3000,$A11)>1,"Duplicate parcel_id","")))
A12: CITY-15 | B12: Council audit | C12: City | D12: Caherdavin | E12: City neighbourhood | F12: 1 | G12: Inside catchment | H12: 15 | I12: Caherdavin | J12: LIMERICK CITY NORTH LEA-7 | K12: Northside | L12: Council | M12: New Resi | N12: Infill | O12: 45+ | P12: 3.003 | Q12: 3.003 | R12: 135 | S12: Council estimate (area × density band) | T12: 102 | X12: City suburbs | Y12: 34 | Z12: 34 homes/ha = median of 39 permitted Limerick schemes of 10+ homes in city suburbs; applied to developable for density_estimate_units only | AB12: 4 | AC12: 4 | AD12: Undeveloped/Permission Sought | AE12: Unchanged | AF12: 2026-10-11 | AH12: =IF(R12="",AM12,R12) -> 135 | AI12: =SUMIFS(Permissions!$G$2:$G$3000,Permissions!$B$2:$B$3000,$A12,Permissions!$I$2:$I$3000,"Complete",Permissions!$R$2:$R$3000,"Yes") -> 0 | AJ12: =SUMIFS(Permissions!$G$2:$G$3000,Permissions!$B$2:$B$3000,$A12,Permissions!$I$2:$I$3000,"Under construction",Permissions!$R$2:$R$3000,"Yes") -> 0 | AK12: =SUMIFS(Permissions!$G$2:$G$3000,Permissions!$B$2:$B$3000,$A12,Permissions!$I$2:$I$3000,"Permitted – not started",Permissions!$R$2:$R$3000,"Yes") -> 0 | AL12: =SUMIFS(Permissions!$G$2:$G$3000,Permissions!$B$2:$B$3000,$A12,Permissions!$I$2:$I$3000,"Stalled",Permissions!$R$2:$R$3000,"Yes") -> 0 | AM12: =AI12+AJ12+AK12+AL12 -> 0 | AN12: =SUMIFS(Permissions!$G$2:$G$3000,Permissions!$B$2:$B$3000,$A12,Permissions!$I$2:$I$3000,"Expired – not started",Permissions!$R$2:$R$3000,"Yes") -> 0 | AO12: =SUMIFS(Permissions!$G$2:$G$3000,Permissions!$B$2:$B$3000,$A12,Permissions!$I$2:$I$3000,"In planning",Permissions!$R$2:$R$3000,"Yes") -> 0 | AP12: =IF(R12="",0,MAX(R12-AM12,0)) -> 135 | AQ12: =AM12+AP12 -> 135 | AR12: =SUMIFS(Permissions!$L$2:$L$3000,Permissions!$B$2:$B$3000,$A12,Permissions!$R$2:$R$3000,"Yes",Permissions!$I$2:$I$3000,"<>Expired – not started",Permissions!$I$2:$I$3000,"<>In planning") -> 0 | AS12: =AQ12-AR12 -> 135 | AT12: =SUMIFS(Permissions!$AJ$2:$AJ$3000,Permissions!$B$2:$B$3000,$A12,Permissions!$R$2:$R$3000,"Yes") -> 0 | AU12: =SUMIFS(Permissions!$AK$2:$AK$3000,Permissions!$B$2:$B$3000,$A12,Permissions!$R$2:$R$3000,"Yes") -> 0 | AV12: =SUMIFS(Permissions!$AL$2:$AL$3000,Permissions!$B$2:$B$3000,$A12,Permissions!$R$2:$R$3000,"Yes") -> 0 | AW12: =SUMIFS(Permissions!$AM$2:$AM$3000,Permissions!$B$2:$B$3000,$A12,Permissions!$R$2:$R$3000,"Yes") -> 0 | AX12: =SUMIFS(Permissions!$AN$2:$AN$3000,Permissions!$B$2:$B$3000,$A12,Permissions!$R$2:$R$3000,"Yes") -> 0 | AY12: =SUMIFS(Permissions!$AO$2:$AO$3000,Permissions!$B$2:$B$3000,$A12,Permissions!$R$2:$R$3000,"Yes") -> 0 | AZ12: =COUNTIFS(Permissions!$B$2:$B$3000,$A12,Permissions!$R$2:$R$3000,"Yes") -> 0 | BA12: =SUMIFS(Permissions!$M$2:$M$3000,Permissions!$B$2:$B$3000,$A12,Permissions!$R$2:$R$3000,"Yes") -> 0 | BB12: =SUMIFS(Permissions!$O$2:$O$3000,Permissions!$B$2:$B$3000,$A12,Permissions!$R$2:$R$3000,"Yes") -> 0 | BC12: =IF(AND(AM12>0,AR12>=AM12,AP12=0),"Finished",IF(AR12>0,"Partly built",IF(AM12>0,"Consented – not built","No consent"))) -> No consent | BD12: =IF(AND(R12<>"",AM12>1.1*R12),"Consented above capacity",IF(AND(LEFT(B12,8)="Planning",AZ12=0),"Consent parcel with no permission",IF(COUNTIF($A$2:$A$3000,$A12)>1,"Duplicate parcel_id","")))
A13: CITY-16 | B13: Council audit | C13: City | D13: Caherdavin | E13: City neighbourhood | F13: 1 | G13: Inside catchment | H13: 16 | I13: Caherdavin | J13: LIMERICK CITY NORTH LEA-7 | K13: Northside | L13: Council | M13: Exist Resi | N13: Infill | O13: 45+ | P13: 0.436 | Q13: 0.436 | R13: 20 | S13: Council estimate (area × density band) | T13: 15 | X13: City suburbs | Y13: 34 | Z13: 34 homes/ha = median of 39 permitted Limerick schemes of 10+ homes in city suburbs; applied to developable for density_estimate_units only | AB13: 0 | AC13: 0 | AD13: Undeveloped/Permission Sought | AE13: Unchanged | AF13: 2026-10-11 | AH13: =IF(R13="",AM13,R13) -> 20 | AI13: =SUMIFS(Permissions!$G$2:$G$3000,Permissions!$B$2:$B$3000,$A13,Permissions!$I$2:$I$3000,"Complete",Permissions!$R$2:$R$3000,"Yes") -> 0 | AJ13: =SUMIFS(Permissions!$G$2:$G$3000,Permissions!$B$2:$B$3000,$A13,Permissions!$I$2:$I$3000,"Under construction",Permissions!$R$2:$R$3000,"Yes") -> 0 | AK13: =SUMIFS(Permissions!$G$2:$G$3000,Permissions!$B$2:$B$3000,$A13,Permissions!$I$2:$I$3000,"Permitted – not started",Permissions!$R$2:$R$3000,"Yes") -> 0 | AL13: =SUMIFS(Permissions!$G$2:$G$3000,Permissions!$B$2:$B$3000,$A13,Permissions!$I$2:$I$3000,"Stalled",Permissions!$R$2:$R$3000,"Yes") -> 0 | AM13: =AI13+AJ13+AK13+AL13 -> 0 | AN13: =SUMIFS(Permissions!$G$2:$G$3000,Permissions!$B$2:$B$3000,$A13,Permissions!$I$2:$I$3000,"Expired – not started",Permissions!$R$2:$R$3000,"Yes") -> 0 | AO13: =SUMIFS(Permissions!$G$2:$G$3000,Permissions!$B$2:$B$3000,$A13,Permissions!$I$2:$I$3000,"In planning",Permissions!$R$2:$R$3000,"Yes") -> 0 | AP13: =IF(R13="",0,MAX(R13-AM13,0)) -> 20 | AQ13: =AM13+AP13 -> 20 | AR13: =SUMIFS(Permissions!$L$2:$L$3000,Permissions!$B$2:$B$3000,$A13,Permissions!$R$2:$R$3000,"Yes",Permissions!$I$2:$I$3000,"<>Expired – not started",Permissions!$I$2:$I$3000,"<>In planning") -> 0 | AS13: =AQ13-AR13 -> 20 | AT13: =SUMIFS(Permissions!$AJ$2:$AJ$3000,Permissions!$B$2:$B$3000,$A13,Permissions!$R$2:$R$3000,"Yes") -> 0 | AU13: =SUMIFS(Permissions!$AK$2:$AK$3000,Permissions!$B$2:$B$3000,$A13,Permissions!$R$2:$R$3000,"Yes") -> 0 | AV13: =SUMIFS(Permissions!$AL$2:$AL$3000,Permissions!$B$2:$B$3000,$A13,Permissions!$R$2:$R$3000,"Yes") -> 0 | AW13: =SUMIFS(Permissions!$AM$2:$AM$3000,Permissions!$B$2:$B$3000,$A13,Permissions!$R$2:$R$3000,"Yes") -> 0 | AX13: =SUMIFS(Permissions!$AN$2:$AN$3000,Permissions!$B$2:$B$3000,$A13,Permissions!$R$2:$R$3000,"Yes") -> 0 | AY13: =SUMIFS(Permissions!$AO$2:$AO$3000,Permissions!$B$2:$B$3000,$A13,Permissions!$R$2:$R$3000,"Yes") -> 0 | AZ13: =COUNTIFS(Permissions!$B$2:$B$3000,$A13,Permissions!$R$2:$R$3000,"Yes") -> 0 | BA13: =SUMIFS(Permissions!$M$2:$M$3000,Permissions!$B$2:$B$3000,$A13,Permissions!$R$2:$R$3000,"Yes") -> 0 | BB13: =SUMIFS(Permissions!$O$2:$O$3000,Permissions!$B$2:$B$3000,$A13,Permissions!$R$2:$R$3000,"Yes") -> 0 | BC13: =IF(AND(AM13>0,AR13>=AM13,AP13=0),"Finished",IF(AR13>0,"Partly built",IF(AM13>0,"Consented – not built","No consent"))) -> No consent | BD13: =IF(AND(R13<>"",AM13>1.1*R13),"Consented above capacity",IF(AND(LEFT(B13,8)="Planning",AZ13=0),"Consent parcel with no permission",IF(COUNTIF($A$2:$A$3000,$A13)>1,"Duplicate parcel_id","")))
A14: CITY-164 | B14: Council audit | C14: City | D14: Caherdavin | E14: City neighbourhood | F14: 1 | G14: Inside catchment | H14: 164 | I14: Caherdavin | J14: LIMERICK CITY NORTH LEA-7 | L14: Unknown | P14: 5.112 | Q14: 5.11 | R14: 179 | S14: Council estimate (area × density band) | T14: 174 | X14: City suburbs | Y14: 34 | Z14: 34 homes/ha = median of 39 permitted Limerick schemes of 10+ homes in city suburbs; applied to developable for density_estimate_units only | AB14: 0 | AC14: 0 | AE14: Addition | AF14: 2026-10-11 | AH14: =IF(R14="",AM14,R14) -> 179 | AI14: =SUMIFS(Permissions!$G$2:$G$3000,Permissions!$B$2:$B$3000,$A14,Permissions!$I$2:$I$3000,"Complete",Permissions!$R$2:$R$3000,"Yes") -> 0 | AJ14: =SUMIFS(Permissions!$G$2:$G$3000,Permissions!$B$2:$B$3000,$A14,Permissions!$I$2:$I$3000,"Under construction",Permissions!$R$2:$R$3000,"Yes") -> 0 | AK14: =SUMIFS(Permissions!$G$2:$G$3000,Permissions!$B$2:$B$3000,$A14,Permissions!$I$2:$I$3000,"Permitted – not started",Permissions!$R$2:$R$3000,"Yes") -> 0 | AL14: =SUMIFS(Permissions!$G$2:$G$3000,Permissions!$B$2:$B$3000,$A14,Permissions!$I$2:$I$3000,"Stalled",Permissions!$R$2:$R$3000,"Yes") -> 0 | AM14: =AI14+AJ14+AK14+AL14 -> 0 | AN14: =SUMIFS(Permissions!$G$2:$G$3000,Permissions!$B$2:$B$3000,$A14,Permissions!$I$2:$I$3000,"Expired – not started",Permissions!$R$2:$R$3000,"Yes") -> 0 | AO14: =SUMIFS(Permissions!$G$2:$G$3000,Permissions!$B$2:$B$3000,$A14,Permissions!$I$2:$I$3000,"In planning",Permissions!$R$2:$R$3000,"Yes") -> 0 | AP14: =IF(R14="",0,MAX(R14-AM14,0)) -> 179 | AQ14: =AM14+AP14 -> 179 | AR14: =SUMIFS(Permissions!$L$2:$L$3000,Permissions!$B$2:$B$3000,$A14,Permissions!$R$2:$R$3000,"Yes",Permissions!$I$2:$I$3000,"<>Expired – not started",Permissions!$I$2:$I$3000,"<>In planning") -> 0 | AS14: =AQ14-AR14 -> 179 | AT14: =SUMIFS(Permissions!$AJ$2:$AJ$3000,Permissions!$B$2:$B$3000,$A14,Permissions!$R$2:$R$3000,"Yes") -> 0 | AU14: =SUMIFS(Permissions!$AK$2:$AK$3000,Permissions!$B$2:$B$3000,$A14,Permissions!$R$2:$R$3000,"Yes") -> 0 | AV14: =SUMIFS(Permissions!$AL$2:$AL$3000,Permissions!$B$2:$B$3000,$A14,Permissions!$R$2:$R$3000,"Yes") -> 0 | AW14: =SUMIFS(Permissions!$AM$2:$AM$3000,Permissions!$B$2:$B$3000,$A14,Permissions!$R$2:$R$3000,"Yes") -> 0 | AX14: =SUMIFS(Permissions!$AN$2:$AN$3000,Permissions!$B$2:$B$3000,$A14,Permissions!$R$2:$R$3000,"Yes") -> 0 | AY14: =SUMIFS(Permissions!$AO$2:$AO$3000,Permissions!$B$2:$B$3000,$A14,Permissions!$R$2:$R$3000,"Yes") -> 0 | AZ14: =COUNTIFS(Permissions!$B$2:$B$3000,$A14,Permissions!$R$2:$R$3000,"Yes") -> 0 | BA14: =SUMIFS(Permissions!$M$2:$M$3000,Permissions!$B$2:$B$3000,$A14,Permissions!$R$2:$R$3000,"Yes") -> 0 | BB14: =SUMIFS(Permissions!$O$2:$O$3000,Permissions!$B$2:$B$3000,$A14,Permissions!$R$2:$R$3000,"Yes") -> 0 | BC14: =IF(AND(AM14>0,AR14>=AM14,AP14=0),"Finished",IF(AR14>0,"Partly built",IF(AM14>0,"Consented – not built","No consent"))) -> No consent | BD14: =IF(AND(R14<>"",AM14>1.1*R14),"Consented above capacity",IF(AND(LEFT(B14,8)="Planning",AZ14=0),"Consent parcel with no permission",IF(COUNTIF($A$2:$A$3000,$A14)>1,"Duplicate parcel_id","")))
A15: CITY-20 | B15: Council audit | C15: City | D15: Caherdavin | E15: City neighbourhood | F15: 1 | G15: Inside catchment | H15: 20 | I15: Caherdavin | J15: LIMERICK CITY NORTH LEA-7 | K15: Northside | L15: Private | M15: Mixed Use | N15: Infill | O15: 45+ | P15: 0.641 | Q15: 0.641 | R15: 29 | S15: Council estimate (area × density band) | T15: 22 | X15: City suburbs | Y15: 34 | Z15: 34 homes/ha = median of 39 permitted Limerick schemes of 10+ homes in city suburbs; applied to developable for density_estimate_units only | AB15: 0 | AC15: 0 | AD15: Undeveloped/Permission Sought | AE15: Unchanged | AF15: 2026-10-11 | AH15: =IF(R15="",AM15,R15) -> 29 | AI15: =SUMIFS(Permissions!$G$2:$G$3000,Permissions!$B$2:$B$3000,$A15,Permissions!$I$2:$I$3000,"Complete",Permissions!$R$2:$R$3000,"Yes") -> 0 | AJ15: =SUMIFS(Permissions!$G$2:$G$3000,Permissions!$B$2:$B$3000,$A15,Permissions!$I$2:$I$3000,"Under construction",Permissions!$R$2:$R$3000,"Yes") -> 0 | AK15: =SUMIFS(Permissions!$G$2:$G$3000,Permissions!$B$2:$B$3000,$A15,Permissions!$I$2:$I$3000,"Permitted – not started",Permissions!$R$2:$R$3000,"Yes") -> 0 | AL15: =SUMIFS(Permissions!$G$2:$G$3000,Permissions!$B$2:$B$3000,$A15,Permissions!$I$2:$I$3000,"Stalled",Permissions!$R$2:$R$3000,"Yes") -> 0 | AM15: =AI15+AJ15+AK15+AL15 -> 0 | AN15: =SUMIFS(Permissions!$G$2:$G$3000,Permissions!$B$2:$B$3000,$A15,Permissions!$I$2:$I$3000,"Expired – not started",Permissions!$R$2:$R$3000,"Yes") -> 0 | AO15: =SUMIFS(Permissions!$G$2:$G$3000,Permissions!$B$2:$B$3000,$A15,Permissions!$I$2:$I$3000,"In planning",Permissions!$R$2:$R$3000,"Yes") -> 0 | AP15: =IF(R15="",0,MAX(R15-AM15,0)) -> 29 | AQ15: =AM15+AP15 -> 29 | AR15: =SUMIFS(Permissions!$L$2:$L$3000,Permissions!$B$2:$B$3000,$A15,Permissions!$R$2:$R$3000,"Yes",Permissions!$I$2:$I$3000,"<>Expired – not started",Permissions!$I$2:$I$3000,"<>In planning") -> 0 | AS15: =AQ15-AR15 -> 29 | AT15: =SUMIFS(Permissions!$AJ$2:$AJ$3000,Permissions!$B$2:$B$3000,$A15,Permissions!$R$2:$R$3000,"Yes") -> 0 | AU15: =SUMIFS(Permissions!$AK$2:$AK$3000,Permissions!$B$2:$B$3000,$A15,Permissions!$R$2:$R$3000,"Yes") -> 0 | AV15: =SUMIFS(Permissions!$AL$2:$AL$3000,Permissions!$B$2:$B$3000,$A15,Permissions!$R$2:$R$3000,"Yes") -> 0 | AW15: =SUMIFS(Permissions!$AM$2:$AM$3000,Permissions!$B$2:$B$3000,$A15,Permissions!$R$2:$R$3000,"Yes") -> 0 | AX15: =SUMIFS(Permissions!$AN$2:$AN$3000,Permissions!$B$2:$B$3000,$A15,Permissions!$R$2:$R$3000,"Yes") -> 0 | AY15: =SUMIFS(Permissions!$AO$2:$AO$3000,Permissions!$B$2:$B$3000,$A15,Permissions!$R$2:$R$3000,"Yes") -> 0 | AZ15: =COUNTIFS(Permissions!$B$2:$B$3000,$A15,Permissions!$R$2:$R$3000,"Yes") -> 0 | BA15: =SUMIFS(Permissions!$M$2:$M$3000,Permissions!$B$2:$B$3000,$A15,Permissions!$R$2:$R$3000,"Yes") -> 0 | BB15: =SUMIFS(Permissions!$O$2:$O$3000,Permissions!$B$2:$B$3000,$A15,Permissions!$R$2:$R$3000,"Yes") -> 0 | BC15: =IF(AND(AM15>0,AR15>=AM15,AP15=0),"Finished",IF(AR15>0,"Partly built",IF(AM15>0,"Consented – not built","No consent"))) -> No consent | BD15: =IF(AND(R15<>"",AM15>1.1*R15),"Consented above capacity",IF(AND(LEFT(B15,8)="Planning",AZ15=0),"Consent parcel with no permission",IF(COUNTIF($A$2:$A$3000,$A15)>1,"Duplicate parcel_id","")))
A16: CITY-21 | B16: Council audit | C16: City | D16: Caherdavin | E16: City neighbourhood | F16: 1 | G16: Inside catchment | H16: 21 | I16: Caherdavin | J16: LIMERICK CITY NORTH LEA-7 | K16: Northside | L16: Private | M16: New Resi | N16: Brownfield | O16: 45+ | P16: 0.172 | Q16: 0.173 | R16: 31 | S16: Council estimate (area × density band) | T16: 6 | X16: City suburbs | Y16: 34 | Z16: 34 homes/ha = median of 39 permitted Limerick schemes of 10+ homes in city suburbs; applied to developable for density_estimate_units only | AB16: 0 | AC16: 0 | AD16: Permission Granted | AE16: Unchanged | AF16: 2026-10-11 | AH16: =IF(R16="",AM16,R16) -> 31 | AI16: =SUMIFS(Permissions!$G$2:$G$3000,Permissions!$B$2:$B$3000,$A16,Permissions!$I$2:$I$3000,"Complete",Permissions!$R$2:$R$3000,"Yes") -> 0 | AJ16: =SUMIFS(Permissions!$G$2:$G$3000,Permissions!$B$2:$B$3000,$A16,Permissions!$I$2:$I$3000,"Under construction",Permissions!$R$2:$R$3000,"Yes") -> 0 | AK16: =SUMIFS(Permissions!$G$2:$G$3000,Permissions!$B$2:$B$3000,$A16,Permissions!$I$2:$I$3000,"Permitted – not started",Permissions!$R$2:$R$3000,"Yes") -> 0 | AL16: =SUMIFS(Permissions!$G$2:$G$3000,Permissions!$B$2:$B$3000,$A16,Permissions!$I$2:$I$3000,"Stalled",Permissions!$R$2:$R$3000,"Yes") -> 31 | AM16: =AI16+AJ16+AK16+AL16 -> 31 | AN16: =SUMIFS(Permissions!$G$2:$G$3000,Permissions!$B$2:$B$3000,$A16,Permissions!$I$2:$I$3000,"Expired – not started",Permissions!$R$2:$R$3000,"Yes") -> 0 | AO16: =SUMIFS(Permissions!$G$2:$G$3000,Permissions!$B$2:$B$3000,$A16,Permissions!$I$2:$I$3000,"In planning",Permissions!$R$2:$R$3000,"Yes") -> 0 | AP16: =IF(R16="",0,MAX(R16-AM16,0)) -> 0 | AQ16: =AM16+AP16 -> 31 | AR16: =SUMIFS(Permissions!$L$2:$L$3000,Permissions!$B$2:$B$3000,$A16,Permissions!$R$2:$R$3000,"Yes",Permissions!$I$2:$I$3000,"<>Expired – not started",Permissions!$I$2:$I$3000,"<>In planning") -> 0 | AS16: =AQ16-AR16 -> 31 | AT16: =SUMIFS(Permissions!$AJ$2:$AJ$3000,Permissions!$B$2:$B$3000,$A16,Permissions!$R$2:$R$3000,"Yes") -> 0 | AU16: =SUMIFS(Permissions!$AK$2:$AK$3000,Permissions!$B$2:$B$3000,$A16,Permissions!$R$2:$R$3000,"Yes") -> 0 | AV16: =SUMIFS(Permissions!$AL$2:$AL$3000,Permissions!$B$2:$B$3000,$A16,Permissions!$R$2:$R$3000,"Yes") -> 0 | AW16: =SUMIFS(Permissions!$AM$2:$AM$3000,Permissions!$B$2:$B$3000,$A16,Permissions!$R$2:$R$3000,"Yes") -> 0 | AX16: =SUMIFS(Permissions!$AN$2:$AN$3000,Permissions!$B$2:$B$3000,$A16,Permissions!$R$2:$R$3000,"Yes") -> 0 | AY16: =SUMIFS(Permissions!$AO$2:$AO$3000,Permissions!$B$2:$B$3000,$A16,Permissions!$R$2:$R$3000,"Yes") -> 0 | AZ16: =COUNTIFS(Permissions!$B$2:$B$3000,$A16,Permissions!$R$2:$R$3000,"Yes") -> 1 | BA16: =SUMIFS(Permissions!$M$2:$M$3000,Permissions!$B$2:$B$3000,$A16,Permissions!$R$2:$R$3000,"Yes") -> 0 | BB16: =SUMIFS(Permissions!$O$2:$O$3000,Permissions!$B$2:$B$3000,$A16,Permissions!$R$2:$R$3000,"Yes") -> 0 | BC16: =IF(AND(AM16>0,AR16>=AM16,AP16=0),"Finished",IF(AR16>0,"Partly built",IF(AM16>0,"Consented – not built","No consent"))) -> Consented – not built | BD16: =IF(AND(R16<>"",AM16>1.1*R16),"Consented above capacity",IF(AND(LEFT(B16,8)="Planning",AZ16=0),"Consent parcel with no permission",IF(COUNTIF($A$2:$A$3000,$A16)>1,"Duplicate parcel_id","")))
A17: CITY-24 | B17: Council audit | C17: City | D17: Caherdavin | E17: City neighbourhood | F17: 1 | G17: Inside catchment | H17: 24 | I17: Caherdavin | J17: LIMERICK CITY NORTH LEA-7 | K17: Northside | L17: Unknown | M17: New Resi | N17: Infill | O17: 45+ | P17: 0.249 | Q17: 0.249 | R17: 46 | S17: Council estimate (area × density band) | T17: 8 | X17: City suburbs | Y17: 34 | Z17: 34 homes/ha = median of 39 permitted Limerick schemes of 10+ homes in city suburbs; applied to developable for density_estimate_units only | AB17: 0 | AC17: 0 | AD17: Permission Granted | AE17: Unchanged | AF17: 2026-10-11 | AH17: =IF(R17="",AM17,R17) -> 46 | AI17: =SUMIFS(Permissions!$G$2:$G$3000,Permissions!$B$2:$B$3000,$A17,Permissions!$I$2:$I$3000,"Complete",Permissions!$R$2:$R$3000,"Yes") -> 0 | AJ17: =SUMIFS(Permissions!$G$2:$G$3000,Permissions!$B$2:$B$3000,$A17,Permissions!$I$2:$I$3000,"Under construction",Permissions!$R$2:$R$3000,"Yes") -> 0 | AK17: =SUMIFS(Permissions!$G$2:$G$3000,Permissions!$B$2:$B$3000,$A17,Permissions!$I$2:$I$3000,"Permitted – not started",Permissions!$R$2:$R$3000,"Yes") -> 46 | AL17: =SUMIFS(Permissions!$G$2:$G$3000,Permissions!$B$2:$B$3000,$A17,Permissions!$I$2:$I$3000,"Stalled",Permissions!$R$2:$R$3000,"Yes") -> 0 | AM17: =AI17+AJ17+AK17+AL17 -> 46 | AN17: =SUMIFS(Permissions!$G$2:$G$3000,Permissions!$B$2:$B$3000,$A17,Permissions!$I$2:$I$3000,"Expired – not started",Permissions!$R$2:$R$3000,"Yes") -> 0 | AO17: =SUMIFS(Permissions!$G$2:$G$3000,Permissions!$B$2:$B$3000,$A17,Permissions!$I$2:$I$3000,"In planning",Permissions!$R$2:$R$3000,"Yes") -> 0 | AP17: =IF(R17="",0,MAX(R17-AM17,0)) -> 0 | AQ17: =AM17+AP17 -> 46 | AR17: =SUMIFS(Permissions!$L$2:$L$3000,Permissions!$B$2:$B$3000,$A17,Permissions!$R$2:$R$3000,"Yes",Permissions!$I$2:$I$3000,"<>Expired – not started",Permissions!$I$2:$I$3000,"<>In planning") -> 0 | AS17: =AQ17-AR17 -> 46 | AT17: =SUMIFS(Permissions!$AJ$2:$AJ$3000,Permissions!$B$2:$B$3000,$A17,Permissions!$R$2:$R$3000,"Yes") -> 0 | AU17: =SUMIFS(Permissions!$AK$2:$AK$3000,Permissions!$B$2:$B$3000,$A17,Permissions!$R$2:$R$3000,"Yes") -> 0 | AV17: =SUMIFS(Permissions!$AL$2:$AL$3000,Permissions!$B$2:$B$3000,$A17,Permissions!$R$2:$R$3000,"Yes") -> 19.4 | AW17: =SUMIFS(Permissions!$AM$2:$AM$3000,Permissions!$B$2:$B$3000,$A17,Permissions!$R$2:$R$3000,"Yes") -> 26.6 | AX17: =SUMIFS(Permissions!$AN$2:$AN$3000,Permissions!$B$2:$B$3000,$A17,Permissions!$R$2:$R$3000,"Yes") -> 0 | AY17: =SUMIFS(Permissions!$AO$2:$AO$3000,Permissions!$B$2:$B$3000,$A17,Permissions!$R$2:$R$3000,"Yes") -> 0 | AZ17: =COUNTIFS(Permissions!$B$2:$B$3000,$A17,Permissions!$R$2:$R$3000,"Yes") -> 1 | BA17: =SUMIFS(Permissions!$M$2:$M$3000,Permissions!$B$2:$B$3000,$A17,Permissions!$R$2:$R$3000,"Yes") -> 0 | BB17: =SUMIFS(Permissions!$O$2:$O$3000,Permissions!$B$2:$B$3000,$A17,Permissions!$R$2:$R$3000,"Yes") -> 0 | BC17: =IF(AND(AM17>0,AR17>=AM17,AP17=0),"Finished",IF(AR17>0,"Partly built",IF(AM17>0,"Consented – not built","No consent"))) -> Consented – not built | BD17: =IF(AND(R17<>"",AM17>1.1*R17),"Consented above capacity",IF(AND(LEFT(B17,8)="Planning",AZ17=0),"Consent parcel with no permission",IF(COUNTIF($A$2:$A$3000,$A17)>1,"Duplicate parcel_id","")))
A18: CITY-25 | B18: Council audit | C18: City | D18: Caherdavin | E18: City neighbourhood | F18: 1 | G18: Inside catchment | H18: 25 | I18: Caherdavin | J18: LIMERICK CITY NORTH LEA-7 | K18: Northside | L18: Council | M18: Exist Resi | N18: Infill | O18: 45+ | P18: 0.125 | Q18: 0.125 | R18: 6 | S18: Council estimate (area × density band) | T18: 4 | X18: City suburbs | Y18: 34 | Z18: 34 homes/ha = median of 39 permitted Limerick schemes of 10+ homes in city suburbs; applied to developable for density_estimate_units only | AB18: 0 | AC18: 0 | AD18: Undeveloped/Permission Sought | AE18: Unchanged | AF18: 2026-10-11 | AH18: =IF(R18="",AM18,R18) -> 6 | AI18: =SUMIFS(Permissions!$G$2:$G$3000,Permissions!$B$2:$B$3000,$A18,Permissions!$I$2:$I$3000,"Complete",Permissions!$R$2:$R$3000,"Yes") -> 0 | AJ18: =SUMIFS(Permissions!$G$2:$G$3000,Permissions!$B$2:$B$3000,$A18,Permissions!$I$2:$I$3000,"Under construction",Permissions!$R$2:$R$3000,"Yes") -> 0 | AK18: =SUMIFS(Permissions!$G$2:$G$3000,Permissions!$B$2:$B$3000,$A18,Permissions!$I$2:$I$3000,"Permitted – not started",Permissions!$R$2:$R$3000,"Yes") -> 0 | AL18: =SUMIFS(Permissions!$G$2:$G$3000,Permissions!$B$2:$B$3000,$A18,Permissions!$I$2:$I$3000,"Stalled",Permissions!$R$2:$R$3000,"Yes") -> 0 | AM18: =AI18+AJ18+AK18+AL18 -> 0 | AN18: =SUMIFS(Permissions!$G$2:$G$3000,Permissions!$B$2:$B$3000,$A18,Permissions!$I$2:$I$3000,"Expired – not started",Permissions!$R$2:$R$3000,"Yes") -> 0 | AO18: =SUMIFS(Permissions!$G$2:$G$3000,Permissions!$B$2:$B$3000,$A18,Permissions!$I$2:$I$3000,"In planning",Permissions!$R$2:$R$3000,"Yes") -> 6 | AP18: =IF(R18="",0,MAX(R18-AM18,0)) -> 6 | AQ18: =AM18+AP18 -> 6 | AR18: =SUMIFS(Permissions!$L$2:$L$3000,Permissions!$B$2:$B$3000,$A18,Permissions!$R$2:$R$3000,"Yes",Permissions!$I$2:$I$3000,"<>Expired – not started",Permissions!$I$2:$I$3000,"<>In planning") -> 0 | AS18: =AQ18-AR18 -> 6 | AT18: =SUMIFS(Permissions!$AJ$2:$AJ$3000,Permissions!$B$2:$B$3000,$A18,Permissions!$R$2:$R$3000,"Yes") -> 0 | AU18: =SUMIFS(Permissions!$AK$2:$AK$3000,Permissions!$B$2:$B$3000,$A18,Permissions!$R$2:$R$3000,"Yes") -> 0 | AV18: =SUMIFS(Permissions!$AL$2:$AL$3000,Permissions!$B$2:$B$3000,$A18,Permissions!$R$2:$R$3000,"Yes") -> 0 | AW18: =SUMIFS(Permissions!$AM$2:$AM$3000,Permissions!$B$2:$B$3000,$A18,Permissions!$R$2:$R$3000,"Yes") -> 0 | AX18: =SUMIFS(Permissions!$AN$2:$AN$3000,Permissions!$B$2:$B$3000,$A18,Permissions!$R$2:$R$3000,"Yes") -> 0 | AY18: =SUMIFS(Permissions!$AO$2:$AO$3000,Permissions!$B$2:$B$3000,$A18,Permissions!$R$2:$R$3000,"Yes") -> 0 | AZ18: =COUNTIFS(Permissions!$B$2:$B$3000,$A18,Permissions!$R$2:$R$3000,"Yes") -> 1 | BA18: =SUMIFS(Permissions!$M$2:$M$3000,Permissions!$B$2:$B$3000,$A18,Permissions!$R$2:$R$3000,"Yes") -> 0 | BB18: =SUMIFS(Permissions!$O$2:$O$3000,Permissions!$B$2:$B$3000,$A18,Permissions!$R$2:$R$3000,"Yes") -> 0 | BC18: =IF(AND(AM18>0,AR18>=AM18,AP18=0),"Finished",IF(AR18>0,"Partly built",IF(AM18>0,"Consented – not built","No consent"))) -> No consent | BD18: =IF(AND(R18<>"",AM18>1.1*R18),"Consented above capacity",IF(AND(LEFT(B18,8)="Planning",AZ18=0),"Consent parcel with no permission",IF(COUNTIF($A$2:$A$3000,$A18)>1,"Duplicate parcel_id","")))
A19: CITY-3 | B19: Council audit | C19: City | D19: Caherdavin | E19: City neighbourhood | F19: 1 | G19: Inside catchment | H19: 3 | I19: Caherdavin | J19: LIMERICK CITY NORTH LEA-7 | K19: Northside | L19: Private | M19: New Resi | N19: Brownfield | O19: 45+ | P19: 2.013 | Q19: 2.012 | R19: 343 | S19: Council estimate (area × density band) | T19: 68 | X19: City suburbs | Y19: 34 | Z19: 34 homes/ha = median of 39 permitted Limerick schemes of 10+ homes in city suburbs; applied to developable for density_estimate_units only | AB19: 157 | AC19: 95 | AD19: Permission Granted | AE19: Unchanged | AF19: 2026-10-11 | AH19: =IF(R19="",AM19,R19) -> 343 | AI19: =SUMIFS(Permissions!$G$2:$G$3000,Permissions!$B$2:$B$3000,$A19,Permissions!$I$2:$I$3000,"Complete",Permissions!$R$2:$R$3000,"Yes") -> 65 | AJ19: =SUMIFS(Permissions!$G$2:$G$3000,Permissions!$B$2:$B$3000,$A19,Permissions!$I$2:$I$3000,"Under construction",Permissions!$R$2:$R$3000,"Yes") -> 167 | AK19: =SUMIFS(Permissions!$G$2:$G$3000,Permissions!$B$2:$B$3000,$A19,Permissions!$I$2:$I$3000,"Permitted – not started",Permissions!$R$2:$R$3000,"Yes") -> 0 | AL19: =SUMIFS(Permissions!$G$2:$G$3000,Permissions!$B$2:$B$3000,$A19,Permissions!$I$2:$I$3000,"Stalled",Permissions!$R$2:$R$3000,"Yes") -> 0 | AM19: =AI19+AJ19+AK19+AL19 -> 232 | AN19: =SUMIFS(Permissions!$G$2:$G$3000,Permissions!$B$2:$B$3000,$A19,Permissions!$I$2:$I$3000,"Expired – not started",Permissions!$R$2:$R$3000,"Yes") -> 0 | AO19: =SUMIFS(Permissions!$G$2:$G$3000,Permissions!$B$2:$B$3000,$A19,Permissions!$I$2:$I$3000,"In planning",Permissions!$R$2:$R$3000,"Yes") -> 0 | AP19: =IF(R19="",0,MAX(R19-AM19,0)) -> 111 | AQ19: =AM19+AP19 -> 343 | AR19: =SUMIFS(Permissions!$L$2:$L$3000,Permissions!$B$2:$B$3000,$A19,Permissions!$R$2:$R$3000,"Yes",Permissions!$I$2:$I$3000,"<>Expired – not started",Permissions!$I$2:$I$3000,"<>In planning") -> 65 | AS19: =AQ19-AR19 -> 278 | AT19: =SUMIFS(Permissions!$AJ$2:$AJ$3000,Permissions!$B$2:$B$3000,$A19,Permissions!$R$2:$R$3000,"Yes") -> 17.4 | AU19: =SUMIFS(Permissions!$AK$2:$AK$3000,Permissions!$B$2:$B$3000,$A19,Permissions!$R$2:$R$3000,"Yes") -> 74.9 | AV19: =SUMIFS(Permissions!$AL$2:$AL$3000,Permissions!$B$2:$B$3000,$A19,Permissions!$R$2:$R$3000,"Yes") -> 74.6 | AW19: =SUMIFS(Permissions!$AM$2:$AM$3000,Permissions!$B$2:$B$3000,$A19,Permissions!$R$2:$R$3000,"Yes") -> 0 | AX19: =SUMIFS(Permissions!$AN$2:$AN$3000,Permissions!$B$2:$B$3000,$A19,Permissions!$R$2:$R$3000,"Yes") -> 0 | AY19: =SUMIFS(Permissions!$AO$2:$AO$3000,Permissions!$B$2:$B$3000,$A19,Permissions!$R$2:$R$3000,"Yes") -> 0.1 | AZ19: =COUNTIFS(Permissions!$B$2:$B$3000,$A19,Permissions!$R$2:$R$3000,"Yes") -> 2 | BA19: =SUMIFS(Permissions!$M$2:$M$3000,Permissions!$B$2:$B$3000,$A19,Permissions!$R$2:$R$3000,"Yes") -> 0 | BB19: =SUMIFS(Permissions!$O$2:$O$3000,Permissions!$B$2:$B$3000,$A19,Permissions!$R$2:$R$3000,"Yes") -> 0 | BC19: =IF(AND(AM19>0,AR19>=AM19,AP19=0),"Finished",IF(AR19>0,"Partly built",IF(AM19>0,"Consented – not built","No consent"))) -> Partly built | BD19: =IF(AND(R19<>"",AM19>1.1*R19),"Consented above capacity",IF(AND(LEFT(B19,8)="Planning",AZ19=0),"Consent parcel with no permission",IF(COUNTIF($A$2:$A$3000,$A19)>1,"Duplicate parcel_id","")))
A20: CITY-5 | B20: Council audit | C20: City | D20: Caherdavin | E20: City neighbourhood | F20: 1 | G20: Inside catchment | H20: 5 | I20: Caherdavin | J20: LIMERICK CITY NORTH LEA-7 | K20: Northside | L20: Unknown | M20: New Resi | N20: Greenfield | O20: 35+ | P20: 2.729 | Q20: 2.729 | R20: 99 | S20: Council estimate (area × density band) | T20: 93 | X20: City suburbs | Y20: 34 | Z20: 34 homes/ha = median of 39 permitted Limerick schemes of 10+ homes in city suburbs; applied to developable for density_estimate_units only | AB20: 0 | AC20: 0 | AD20: Permission Granted | AE20: Unchanged | AF20: 2026-10-11 | AH20: =IF(R20="",AM20,R20) -> 99 | AI20: =SUMIFS(Permissions!$G$2:$G$3000,Permissions!$B$2:$B$3000,$A20,Permissions!$I$2:$I$3000,"Complete",Permissions!$R$2:$R$3000,"Yes") -> 0 | AJ20: =SUMIFS(Permissions!$G$2:$G$3000,Permissions!$B$2:$B$3000,$A20,Permissions!$I$2:$I$3000,"Under construction",Permissions!$R$2:$R$3000,"Yes") -> 99 | AK20: =SUMIFS(Permissions!$G$2:$G$3000,Permissions!$B$2:$B$3000,$A20,Permissions!$I$2:$I$3000,"Permitted – not started",Permissions!$R$2:$R$3000,"Yes") -> 0 | AL20: =SUMIFS(Permissions!$G$2:$G$3000,Permissions!$B$2:$B$3000,$A20,Permissions!$I$2:$I$3000,"Stalled",Permissions!$R$2:$R$3000,"Yes") -> 0 | AM20: =AI20+AJ20+AK20+AL20 -> 99 | AN20: =SUMIFS(Permissions!$G$2:$G$3000,Permissions!$B$2:$B$3000,$A20,Permissions!$I$2:$I$3000,"Expired – not started",Permissions!$R$2:$R$3000,"Yes") -> 0 | AO20: =SUMIFS(Permissions!$G$2:$G$3000,Permissions!$B$2:$B$3000,$A20,Permissions!$I$2:$I$3000,"In planning",Permissions!$R$2:$R$3000,"Yes") -> 0 | AP20: =IF(R20="",0,MAX(R20-AM20,0)) -> 0 | AQ20: =AM20+AP20 -> 99 | AR20: =SUMIFS(Permissions!$L$2:$L$3000,Permissions!$B$2:$B$3000,$A20,Permissions!$R$2:$R$3000,"Yes",Permissions!$I$2:$I$3000,"<>Expired – not started",Permissions!$I$2:$I$3000,"<>In planning") -> 0 | AS20: =AQ20-AR20 -> 99 | AT20: =SUMIFS(Permissions!$AJ$2:$AJ$3000,Permissions!$B$2:$B$3000,$A20,Permissions!$R$2:$R$3000,"Yes") -> 13 | AU20: =SUMIFS(Permissions!$AK$2:$AK$3000,Permissions!$B$2:$B$3000,$A20,Permissions!$R$2:$R$3000,"Yes") -> 55.8 | AV20: =SUMIFS(Permissions!$AL$2:$AL$3000,Permissions!$B$2:$B$3000,$A20,Permissions!$R$2:$R$3000,"Yes") -> 30.2 | AW20: =SUMIFS(Permissions!$AM$2:$AM$3000,Permissions!$B$2:$B$3000,$A20,Permissions!$R$2:$R$3000,"Yes") -> 0 | AX20: =SUMIFS(Permissions!$AN$2:$AN$3000,Permissions!$B$2:$B$3000,$A20,Permissions!$R$2:$R$3000,"Yes") -> 0 | AY20: =SUMIFS(Permissions!$AO$2:$AO$3000,Permissions!$B$2:$B$3000,$A20,Permissions!$R$2:$R$3000,"Yes") -> 0 | AZ20: =COUNTIFS(Permissions!$B$2:$B$3000,$A20,Permissions!$R$2:$R$3000,"Yes") -> 1 | BA20: =SUMIFS(Permissions!$M$2:$M$3000,Permissions!$B$2:$B$3000,$A20,Permissions!$R$2:$R$3000,"Yes") -> 0 | BB20: =SUMIFS(Permissions!$O$2:$O$3000,Permissions!$B$2:$B$3000,$A20,Permissions!$R$2:$R$3000,"Yes") -> 0 | BC20: =IF(AND(AM20>0,AR20>=AM20,AP20=0),"Finished",IF(AR20>0,"Partly built",IF(AM20>0,"Consented – not built","No consent"))) -> Consented – not built | BD20: =IF(AND(R20<>"",AM20>1.1*R20),"Consented above capacity",IF(AND(LEFT(B20,8)="Planning",AZ20=0),"Consent parcel with no permission",IF(COUNTIF($A$2:$A$3000,$A20)>1,"Duplicate parcel_id","")))
A21: CITY-6 | B21: Council audit | C21: City | D21: Caherdavin | E21: City neighbourhood | F21: 1 | G21: Inside catchment | H21: 6 | I21: Caherdavin | J21: LIMERICK CITY NORTH LEA-7 | K21: Northside | L21: Unknown | M21: Local Centre | N21: Greenfield | O21: 35+ | P21: 0.162 | Q21: 0.651 | R21: 12 | S21: Council estimate (area × density band) | T21: 6 | X21: City suburbs | Y21: 34 | Z21: 34 homes/ha = median of 39 permitted Limerick schemes of 10+ homes in city suburbs; applied to developable for density_estimate_units only | AB21: 0 | AC21: 0 | AD21: Permission Granted | AE21: Unchanged | AF21: 2026-10-11 | AH21: =IF(R21="",AM21,R21) -> 12 | AI21: =SUMIFS(Permissions!$G$2:$G$3000,Permissions!$B$2:$B$3000,$A21,Permissions!$I$2:$I$3000,"Complete",Permissions!$R$2:$R$3000,"Yes") -> 0 | AJ21: =SUMIFS(Permissions!$G$2:$G$3000,Permissions!$B$2:$B$3000,$A21,Permissions!$I$2:$I$3000,"Under construction",Permissions!$R$2:$R$3000,"Yes") -> 0 | AK21: =SUMIFS(Permissions!$G$2:$G$3000,Permissions!$B$2:$B$3000,$A21,Permissions!$I$2:$I$3000,"Permitted – not started",Permissions!$R$2:$R$3000,"Yes") -> 12 | AL21: =SUMIFS(Permissions!$G$2:$G$3000,Permissions!$B$2:$B$3000,$A21,Permissions!$I$2:$I$3000,"Stalled",Permissions!$R$2:$R$3000,"Yes") -> 0 | AM21: =AI21+AJ21+AK21+AL21 -> 12 | AN21: =SUMIFS(Permissions!$G$2:$G$3000,Permissions!$B$2:$B$3000,$A21,Permissions!$I$2:$I$3000,"Expired – not started",Permissions!$R$2:$R$3000,"Yes") -> 0 | AO21: =SUMIFS(Permissions!$G$2:$G$3000,Permissions!$B$2:$B$3000,$A21,Permissions!$I$2:$I$3000,"In planning",Permissions!$R$2:$R$3000,"Yes") -> 0 | AP21: =IF(R21="",0,MAX(R21-AM21,0)) -> 0 | AQ21: =AM21+AP21 -> 12 | AR21: =SUMIFS(Permissions!$L$2:$L$3000,Permissions!$B$2:$B$3000,$A21,Permissions!$R$2:$R$3000,"Yes",Permissions!$I$2:$I$3000,"<>Expired – not started",Permissions!$I$2:$I$3000,"<>In planning") -> 0 | AS21: =AQ21-AR21 -> 12 | AT21: =SUMIFS(Permissions!$AJ$2:$AJ$3000,Permissions!$B$2:$B$3000,$A21,Permissions!$R$2:$R$3000,"Yes") -> 0 | AU21: =SUMIFS(Permissions!$AK$2:$AK$3000,Permissions!$B$2:$B$3000,$A21,Permissions!$R$2:$R$3000,"Yes") -> 0 | AV21: =SUMIFS(Permissions!$AL$2:$AL$3000,Permissions!$B$2:$B$3000,$A21,Permissions!$R$2:$R$3000,"Yes") -> 7 | AW21: =SUMIFS(Permissions!$AM$2:$AM$3000,Permissions!$B$2:$B$3000,$A21,Permissions!$R$2:$R$3000,"Yes") -> 5 | AX21: =SUMIFS(Permissions!$AN$2:$AN$3000,Permissions!$B$2:$B$3000,$A21,Permissions!$R$2:$R$3000,"Yes") -> 0 | AY21: =SUMIFS(Permissions!$AO$2:$AO$3000,Permissions!$B$2:$B$3000,$A21,Permissions!$R$2:$R$3000,"Yes") -> 0 | AZ21: =COUNTIFS(Permissions!$B$2:$B$3000,$A21,Permissions!$R$2:$R$3000,"Yes") -> 1 | BA21: =SUMIFS(Permissions!$M$2:$M$3000,Permissions!$B$2:$B$3000,$A21,Permissions!$R$2:$R$3000,"Yes") -> 0 | BB21: =SUMIFS(Permissions!$O$2:$O$3000,Permissions!$B$2:$B$3000,$A21,Permissions!$R$2:$R$3000,"Yes") -> 0 | BC21: =IF(AND(AM21>0,AR21>=AM21,AP21=0),"Finished",IF(AR21>0,"Partly built",IF(AM21>0,"Consented – not built","No consent"))) -> Consented – not built | BD21: =IF(AND(R21<>"",AM21>1.1*R21),"Consented above capacity",IF(AND(LEFT(B21,8)="Planning",AZ21=0),"Consent parcel with no permission",IF(COUNTIF($A$2:$A$3000,$A21)>1,"Duplicate parcel_id","")))
A22: CITY-7 | B22: Council audit | C22: City | D22: Caherdavin | E22: City neighbourhood | F22: 1 | G22: Inside catchment | H22: 7 | I22: Caherdavin | J22: LIMERICK CITY NORTH LEA-7 | K22: Northside | L22: Unknown | M22: New Resi | N22: Greenfield | O22: 35+ | P22: 11.8 | Q22: 11.8 | R22: 413 | S22: Council estimate (area × density band) | T22: 401 | X22: City suburbs | Y22: 34 | Z22: 34 homes/ha = median of 39 permitted Limerick schemes of 10+ homes in city suburbs; applied to developable for density_estimate_units only | AB22: 0 | AC22: 0 | AD22: Permission Granted | AE22: Unchanged | AF22: 2026-10-11 | AH22: =IF(R22="",AM22,R22) -> 413 | AI22: =SUMIFS(Permissions!$G$2:$G$3000,Permissions!$B$2:$B$3000,$A22,Permissions!$I$2:$I$3000,"Complete",Permissions!$R$2:$R$3000,"Yes") -> 0 | AJ22: =SUMIFS(Permissions!$G$2:$G$3000,Permissions!$B$2:$B$3000,$A22,Permissions!$I$2:$I$3000,"Under construction",Permissions!$R$2:$R$3000,"Yes") -> 0 | AK22: =SUMIFS(Permissions!$G$2:$G$3000,Permissions!$B$2:$B$3000,$A22,Permissions!$I$2:$I$3000,"Permitted – not started",Permissions!$R$2:$R$3000,"Yes") -> 251 | AL22: =SUMIFS(Permissions!$G$2:$G$3000,Permissions!$B$2:$B$3000,$A22,Permissions!$I$2:$I$3000,"Stalled",Permissions!$R$2:$R$3000,"Yes") -> 0 | AM22: =AI22+AJ22+AK22+AL22 -> 251 | AN22: =SUMIFS(Permissions!$G$2:$G$3000,Permissions!$B$2:$B$3000,$A22,Permissions!$I$2:$I$3000,"Expired – not started",Permissions!$R$2:$R$3000,"Yes") -> 0 | AO22: =SUMIFS(Permissions!$G$2:$G$3000,Permissions!$B$2:$B$3000,$A22,Permissions!$I$2:$I$3000,"In planning",Permissions!$R$2:$R$3000,"Yes") -> 0 | AP22: =IF(R22="",0,MAX(R22-AM22,0)) -> 162 | AQ22: =AM22+AP22 -> 413 | AR22: =SUMIFS(Permissions!$L$2:$L$3000,Permissions!$B$2:$B$3000,$A22,Permissions!$R$2:$R$3000,"Yes",Permissions!$I$2:$I$3000,"<>Expired – not started",Permissions!$I$2:$I$3000,"<>In planning") -> 0 | AS22: =AQ22-AR22 -> 413 | AT22: =SUMIFS(Permissions!$AJ$2:$AJ$3000,Permissions!$B$2:$B$3000,$A22,Permissions!$R$2:$R$3000,"Yes") -> 0 | AU22: =SUMIFS(Permissions!$AK$2:$AK$3000,Permissions!$B$2:$B$3000,$A22,Permissions!$R$2:$R$3000,"Yes") -> 0 | AV22: =SUMIFS(Permissions!$AL$2:$AL$3000,Permissions!$B$2:$B$3000,$A22,Permissions!$R$2:$R$3000,"Yes") -> 71 | AW22: =SUMIFS(Permissions!$AM$2:$AM$3000,Permissions!$B$2:$B$3000,$A22,Permissions!$R$2:$R$3000,"Yes") -> 137.4 | AX22: =SUMIFS(Permissions!$AN$2:$AN$3000,Permissions!$B$2:$B$3000,$A22,Permissions!$R$2:$R$3000,"Yes") -> 42.6 | AY22: =SUMIFS(Permissions!$AO$2:$AO$3000,Permissions!$B$2:$B$3000,$A22,Permissions!$R$2:$R$3000,"Yes") -> 0 | AZ22: =COUNTIFS(Permissions!$B$2:$B$3000,$A22,Permissions!$R$2:$R$3000,"Yes") -> 3 | BA22: =SUMIFS(Permissions!$M$2:$M$3000,Permissions!$B$2:$B$3000,$A22,Permissions!$R$2:$R$3000,"Yes") -> 0 | BB22: =SUMIFS(Permissions!$O$2:$O$3000,Permissions!$B$2:$B$3000,$A22,Permissions!$R$2:$R$3000,"Yes") -> 0 | BC22: =IF(AND(AM22>0,AR22>=AM22,AP22=0),"Finished",IF(AR22>0,"Partly built",IF(AM22>0,"Consented – not built","No consent"))) -> Consented – not built | BD22: =IF(AND(R22<>"",AM22>1.1*R22),"Consented above capacity",IF(AND(LEFT(B22,8)="Planning",AZ22=0),"Consent parcel with no permission",IF(COUNTIF($A$2:$A$3000,$A22)>1,"Duplicate parcel_id","")))
A23: CITY-8 | B23: Council audit | C23: City | D23: Caherdavin | E23: City neighbourhood | F23: 1 | G23: Inside catchment | H23: 8 | I23: Caherdavin | J23: LIMERICK CITY NORTH LEA-7 | K23: Northside | L23: Unknown | M23: New Resi | N23: Greenfield | O23: 35+ | P23: 2.772 | Q23: 2.771 | R23: 97 | S23: Council estimate (area × density band) | T23: 94 | X23: City suburbs | Y23: 34 | Z23: 34 homes/ha = median of 39 permitted Limerick schemes of 10+ homes in city suburbs; applied to developable for density_estimate_units only | AB23: 0 | AC23: 0 | AD23: Permission Granted | AE23: Unchanged | AF23: 2026-10-11 | AH23: =IF(R23="",AM23,R23) -> 97 | AI23: =SUMIFS(Permissions!$G$2:$G$3000,Permissions!$B$2:$B$3000,$A23,Permissions!$I$2:$I$3000,"Complete",Permissions!$R$2:$R$3000,"Yes") -> 0 | AJ23: =SUMIFS(Permissions!$G$2:$G$3000,Permissions!$B$2:$B$3000,$A23,Permissions!$I$2:$I$3000,"Under construction",Permissions!$R$2:$R$3000,"Yes") -> 0 | AK23: =SUMIFS(Permissions!$G$2:$G$3000,Permissions!$B$2:$B$3000,$A23,Permissions!$I$2:$I$3000,"Permitted – not started",Permissions!$R$2:$R$3000,"Yes") -> 86 | AL23: =SUMIFS(Permissions!$G$2:$G$3000,Permissions!$B$2:$B$3000,$A23,Permissions!$I$2:$I$3000,"Stalled",Permissions!$R$2:$R$3000,"Yes") -> 0 | AM23: =AI23+AJ23+AK23+AL23 -> 86 | AN23: =SUMIFS(Permissions!$G$2:$G$3000,Permissions!$B$2:$B$3000,$A23,Permissions!$I$2:$I$3000,"Expired – not started",Permissions!$R$2:$R$3000,"Yes") -> 0 | AO23: =SUMIFS(Permissions!$G$2:$G$3000,Permissions!$B$2:$B$3000,$A23,Permissions!$I$2:$I$3000,"In planning",Permissions!$R$2:$R$3000,"Yes") -> 0 | AP23: =IF(R23="",0,MAX(R23-AM23,0)) -> 11 | AQ23: =AM23+AP23 -> 97 | AR23: =SUMIFS(Permissions!$L$2:$L$3000,Permissions!$B$2:$B$3000,$A23,Permissions!$R$2:$R$3000,"Yes",Permissions!$I$2:$I$3000,"<>Expired – not started",Permissions!$I$2:$I$3000,"<>In planning") -> 0 | AS23: =AQ23-AR23 -> 97 | AT23: =SUMIFS(Permissions!$AJ$2:$AJ$3000,Permissions!$B$2:$B$3000,$A23,Permissions!$R$2:$R$3000,"Yes") -> 0 | AU23: =SUMIFS(Permissions!$AK$2:$AK$3000,Permissions!$B$2:$B$3000,$A23,Permissions!$R$2:$R$3000,"Yes") -> 0 | AV23: =SUMIFS(Permissions!$AL$2:$AL$3000,Permissions!$B$2:$B$3000,$A23,Permissions!$R$2:$R$3000,"Yes") -> 27.2 | AW23: =SUMIFS(Permissions!$AM$2:$AM$3000,Permissions!$B$2:$B$3000,$A23,Permissions!$R$2:$R$3000,"Yes") -> 56.4 | AX23: =SUMIFS(Permissions!$AN$2:$AN$3000,Permissions!$B$2:$B$3000,$A23,Permissions!$R$2:$R$3000,"Yes") -> 2.4 | AY23: =SUMIFS(Permissions!$AO$2:$AO$3000,Permissions!$B$2:$B$3000,$A23,Permissions!$R$2:$R$3000,"Yes") -> 0 | AZ23: =COUNTIFS(Permissions!$B$2:$B$3000,$A23,Permissions!$R$2:$R$3000,"Yes") -> 1 | BA23: =SUMIFS(Permissions!$M$2:$M$3000,Permissions!$B$2:$B$3000,$A23,Permissions!$R$2:$R$3000,"Yes") -> 0 | BB23: =SUMIFS(Permissions!$O$2:$O$3000,Permissions!$B$2:$B$3000,$A23,Permissions!$R$2:$R$3000,"Yes") -> 0 | BC23: =IF(AND(AM23>0,AR23>=AM23,AP23=0),"Finished",IF(AR23>0,"Partly built",IF(AM23>0,"Consented – not built","No consent"))) -> Consented – not built | BD23: =IF(AND(R23<>"",AM23>1.1*R23),"Consented above capacity",IF(AND(LEFT(B23,8)="Planning",AZ23=0),"Consent parcel with no permission",IF(COUNTIF($A$2:$A$3000,$A23)>1,"Duplicate parcel_id","")))
A24: CITY-9 | B24: Council audit | C24: City | D24: Caherdavin | E24: City neighbourhood | F24: 1 | G24: Inside catchment | H24: 9 | I24: Caherdavin | J24: LIMERICK CITY NORTH LEA-7 | K24: Northside | L24: Council | M24: Exist Resi | N24: Infill | O24: 45+ | P24: 1.07 | Q24: 1.071 | R24: 48 | S24: Council estimate (area × density band) | T24: 36 | X24: City suburbs | Y24: 34 | Z24: 34 homes/ha = median of 39 permitted Limerick schemes of 10+ homes in city suburbs; applied to developable for density_estimate_units only | AB24: 0 | AC24: 0 | AD24: Undeveloped/Permission Sought | AE24: Unchanged | AF24: 2026-10-11 | AH24: =IF(R24="",AM24,R24) -> 48 | AI24: =SUMIFS(Permissions!$G$2:$G$3000,Permissions!$B$2:$B$3000,$A24,Permissions!$I$2:$I$3000,"Complete",Permissions!$R$2:$R$3000,"Yes") -> 0 | AJ24: =SUMIFS(Permissions!$G$2:$G$3000,Permissions!$B$2:$B$3000,$A24,Permissions!$I$2:$I$3000,"Under construction",Permissions!$R$2:$R$3000,"Yes") -> 0 | AK24: =SUMIFS(Permissions!$G$2:$G$3000,Permissions!$B$2:$B$3000,$A24,Permissions!$I$2:$I$3000,"Permitted – not started",Permissions!$R$2:$R$3000,"Yes") -> 0 | AL24: =SUMIFS(Permissions!$G$2:$G$3000,Permissions!$B$2:$B$3000,$A24,Permissions!$I$2:$I$3000,"Stalled",Permissions!$R$2:$R$3000,"Yes") -> 0 | AM24: =AI24+AJ24+AK24+AL24 -> 0 | AN24: =SUMIFS(Permissions!$G$2:$G$3000,Permissions!$B$2:$B$3000,$A24,Permissions!$I$2:$I$3000,"Expired – not started",Permissions!$R$2:$R$3000,"Yes") -> 0 | AO24: =SUMIFS(Permissions!$G$2:$G$3000,Permissions!$B$2:$B$3000,$A24,Permissions!$I$2:$I$3000,"In planning",Permissions!$R$2:$R$3000,"Yes") -> 0 | AP24: =IF(R24="",0,MAX(R24-AM24,0)) -> 48 | AQ24: =AM24+AP24 -> 48 | AR24: =SUMIFS(Permissions!$L$2:$L$3000,Permissions!$B$2:$B$3000,$A24,Permissions!$R$2:$R$3000,"Yes",Permissions!$I$2:$I$3000,"<>Expired – not started",Permissions!$I$2:$I$3000,"<>In planning") -> 0 | AS24: =AQ24-AR24 -> 48 | AT24: =SUMIFS(Permissions!$AJ$2:$AJ$3000,Permissions!$B$2:$B$3000,$A24,Permissions!$R$2:$R$3000,"Yes") -> 0 | AU24: =SUMIFS(Permissions!$AK$2:$AK$3000,Permissions!$B$2:$B$3000,$A24,Permissions!$R$2:$R$3000,"Yes") -> 0 | AV24: =SUMIFS(Permissions!$AL$2:$AL$3000,Permissions!$B$2:$B$3000,$A24,Permissions!$R$2:$R$3000,"Yes") -> 0 | AW24: =SUMIFS(Permissions!$AM$2:$AM$3000,Permissions!$B$2:$B$3000,$A24,Permissions!$R$2:$R$3000,"Yes") -> 0 | AX24: =SUMIFS(Permissions!$AN$2:$AN$3000,Permissions!$B$2:$B$3000,$A24,Permissions!$R$2:$R$3000,"Yes") -> 0 | AY24: =SUMIFS(Permissions!$AO$2:$AO$3000,Permissions!$B$2:$B$3000,$A24,Permissions!$R$2:$R$3000,"Yes") -> 0 | AZ24: =COUNTIFS(Permissions!$B$2:$B$3000,$A24,Permissions!$R$2:$R$3000,"Yes") -> 0 | BA24: =SUMIFS(Permissions!$M$2:$M$3000,Permissions!$B$2:$B$3000,$A24,Permissions!$R$2:$R$3000,"Yes") -> 0 | BB24: =SUMIFS(Permissions!$O$2:$O$3000,Permissions!$B$2:$B$3000,$A24,Permissions!$R$2:$R$3000,"Yes") -> 0 | BC24: =IF(AND(AM24>0,AR24>=AM24,AP24=0),"Finished",IF(AR24>0,"Partly built",IF(AM24>0,"Consented – not built","No consent"))) -> No consent | BD24: =IF(AND(R24<>"",AM24>1.1*R24),"Consented above capacity",IF(AND(LEFT(B24,8)="Planning",AZ24=0),"Consent parcel with no permission",IF(COUNTIF($A$2:$A$3000,$A24)>1,"Duplicate parcel_id","")))
A25: CITY-159 | B25: Council audit | C25: City | D25: Castletroy/Annacotty | E25: City neighbourhood | F25: 1 | G25: Inside catchment | H25: 159 | I25: Castletroy/Annacotty | J25: LIMERICK CITY EAST LEA-7 | K25: Castletroy | L25: Private | M25: New Resi | N25: Greenfield | O25: 0.145 in 45+ 2.589 in 35+ | P25: 2.734 | Q25: 2.733 | R25: 97 | S25: Council estimate (area × density band) | T25: 93 | X25: City suburbs | Y25: 34 | Z25: 34 homes/ha = median of 39 permitted Limerick schemes of 10+ homes in city suburbs; applied to developable for density_estimate_units only | AB25: 0 | AC25: 0 | AD25: Undeveloped/Permission Sought | AE25: Unchanged | AF25: 2026-10-11 | AH25: =IF(R25="",AM25,R25) -> 97 | AI25: =SUMIFS(Permissions!$G$2:$G$3000,Permissions!$B$2:$B$3000,$A25,Permissions!$I$2:$I$3000,"Complete",Permissions!$R$2:$R$3000,"Yes") -> 0 | AJ25: =SUMIFS(Permissions!$G$2:$G$3000,Permissions!$B$2:$B$3000,$A25,Permissions!$I$2:$I$3000,"Under construction",Permissions!$R$2:$R$3000,"Yes") -> 0 | AK25: =SUMIFS(Permissions!$G$2:$G$3000,Permissions!$B$2:$B$3000,$A25,Permissions!$I$2:$I$3000,"Permitted – not started",Permissions!$R$2:$R$3000,"Yes") -> 0 | AL25: =SUMIFS(Permissions!$G$2:$G$3000,Permissions!$B$2:$B$3000,$A25,Permissions!$I$2:$I$3000,"Stalled",Permissions!$R$2:$R$3000,"Yes") -> 0 | AM25: =AI25+AJ25+AK25+AL25 -> 0 | AN25: =SUMIFS(Permissions!$G$2:$G$3000,Permissions!$B$2:$B$3000,$A25,Permissions!$I$2:$I$3000,"Expired – not started",Permissions!$R$2:$R$3000,"Yes") -> 0 | AO25: =SUMIFS(Permissions!$G$2:$G$3000,Permissions!$B$2:$B$3000,$A25,Permissions!$I$2:$I$3000,"In planning",Permissions!$R$2:$R$3000,"Yes") -> 0 | AP25: =IF(R25="",0,MAX(R25-AM25,0)) -> 97 | AQ25: =AM25+AP25 -> 97 | AR25: =SUMIFS(Permissions!$L$2:$L$3000,Permissions!$B$2:$B$3000,$A25,Permissions!$R$2:$R$3000,"Yes",Permissions!$I$2:$I$3000,"<>Expired – not started",Permissions!$I$2:$I$3000,"<>In planning") -> 0 | AS25: =AQ25-AR25 -> 97 | AT25: =SUMIFS(Permissions!$AJ$2:$AJ$3000,Permissions!$B$2:$B$3000,$A25,Permissions!$R$2:$R$3000,"Yes") -> 0 | AU25: =SUMIFS(Permissions!$AK$2:$AK$3000,Permissions!$B$2:$B$3000,$A25,Permissions!$R$2:$R$3000,"Yes") -> 0 | AV25: =SUMIFS(Permissions!$AL$2:$AL$3000,Permissions!$B$2:$B$3000,$A25,Permissions!$R$2:$R$3000,"Yes") -> 0 | AW25: =SUMIFS(Permissions!$AM$2:$AM$3000,Permissions!$B$2:$B$3000,$A25,Permissions!$R$2:$R$3000,"Yes") -> 0 | AX25: =SUMIFS(Permissions!$AN$2:$AN$3000,Permissions!$B$2:$B$3000,$A25,Permissions!$R$2:$R$3000,"Yes") -> 0 | AY25: =SUMIFS(Permissions!$AO$2:$AO$3000,Permissions!$B$2:$B$3000,$A25,Permissions!$R$2:$R$3000,"Yes") -> 0 | AZ25: =COUNTIFS(Permissions!$B$2:$B$3000,$A25,Permissions!$R$2:$R$3000,"Yes") -> 0 | BA25: =SUMIFS(Permissions!$M$2:$M$3000,Permissions!$B$2:$B$3000,$A25,Permissions!$R$2:$R$3000,"Yes") -> 0 | BB25: =SUMIFS(Permissions!$O$2:$O$3000,Permissions!$B$2:$B$3000,$A25,Permissions!$R$2:$R$3000,"Yes") -> 0 | BC25: =IF(AND(AM25>0,AR25>=AM25,AP25=0),"Finished",IF(AR25>0,"Partly built",IF(AM25>0,"Consented – not built","No consent"))) -> No consent | BD25: =IF(AND(R25<>"",AM25>1.1*R25),"Consented above capacity",IF(AND(LEFT(B25,8)="Planning",AZ25=0),"Consent parcel with no permission",IF(COUNTIF($A$2:$A$3000,$A25)>1,"Duplicate parcel_id","")))
A26: CITY-53 | B26: Council audit | C26: City | D26: Castletroy/Annacotty | E26: City neighbourhood | F26: 1 | G26: Inside catchment | H26: 53 | I26: Castletroy/Annacotty | J26: LIMERICK CITY EAST LEA-7 | K26: Castletroy | L26: Private | M26: New Resi | N26: Infill | O26: 45+ | P26: 2.401 | Q26: 2.401 | R26: 108 | S26: Council estimate (area × density band) | T26: 82 | X26: City suburbs | Y26: 34 | Z26: 34 homes/ha = median of 39 permitted Limerick schemes of 10+ homes in city suburbs; applied to developable for density_estimate_units only | AB26: 0 | AC26: 0 | AD26: Permission Granted | AE26: Unchanged | AF26: 2026-10-11 | AH26: =IF(R26="",AM26,R26) -> 108 | AI26: =SUMIFS(Permissions!$G$2:$G$3000,Permissions!$B$2:$B$3000,$A26,Permissions!$I$2:$I$3000,"Complete",Permissions!$R$2:$R$3000,"Yes") -> 0 | AJ26: =SUMIFS(Permissions!$G$2:$G$3000,Permissions!$B$2:$B$3000,$A26,Permissions!$I$2:$I$3000,"Under construction",Permissions!$R$2:$R$3000,"Yes") -> 0 | AK26: =SUMIFS(Permissions!$G$2:$G$3000,Permissions!$B$2:$B$3000,$A26,Permissions!$I$2:$I$3000,"Permitted – not started",Permissions!$R$2:$R$3000,"Yes") -> 196 | AL26: =SUMIFS(Permissions!$G$2:$G$3000,Permissions!$B$2:$B$3000,$A26,Permissions!$I$2:$I$3000,"Stalled",Permissions!$R$2:$R$3000,"Yes") -> 0 | AM26: =AI26+AJ26+AK26+AL26 -> 196 | AN26: =SUMIFS(Permissions!$G$2:$G$3000,Permissions!$B$2:$B$3000,$A26,Permissions!$I$2:$I$3000,"Expired – not started",Permissions!$R$2:$R$3000,"Yes") -> 0 | AO26: =SUMIFS(Permissions!$G$2:$G$3000,Permissions!$B$2:$B$3000,$A26,Permissions!$I$2:$I$3000,"In planning",Permissions!$R$2:$R$3000,"Yes") -> 0 | AP26: =IF(R26="",0,MAX(R26-AM26,0)) -> 0 | AQ26: =AM26+AP26 -> 196 | AR26: =SUMIFS(Permissions!$L$2:$L$3000,Permissions!$B$2:$B$3000,$A26,Permissions!$R$2:$R$3000,"Yes",Permissions!$I$2:$I$3000,"<>Expired – not started",Permissions!$I$2:$I$3000,"<>In planning") -> 0 | AS26: =AQ26-AR26 -> 196 | AT26: =SUMIFS(Permissions!$AJ$2:$AJ$3000,Permissions!$B$2:$B$3000,$A26,Permissions!$R$2:$R$3000,"Yes") -> 0 | AU26: =SUMIFS(Permissions!$AK$2:$AK$3000,Permissions!$B$2:$B$3000,$A26,Permissions!$R$2:$R$3000,"Yes") -> 0 | AV26: =SUMIFS(Permissions!$AL$2:$AL$3000,Permissions!$B$2:$B$3000,$A26,Permissions!$R$2:$R$3000,"Yes") -> 0 | AW26: =SUMIFS(Permissions!$AM$2:$AM$3000,Permissions!$B$2:$B$3000,$A26,Permissions!$R$2:$R$3000,"Yes") -> 196 | AX26: =SUMIFS(Permissions!$AN$2:$AN$3000,Permissions!$B$2:$B$3000,$A26,Permissions!$R$2:$R$3000,"Yes") -> 0 | AY26: =SUMIFS(Permissions!$AO$2:$AO$3000,Permissions!$B$2:$B$3000,$A26,Permissions!$R$2:$R$3000,"Yes") -> 0 | AZ26: =COUNTIFS(Permissions!$B$2:$B$3000,$A26,Permissions!$R$2:$R$3000,"Yes") -> 1 | BA26: =SUMIFS(Permissions!$M$2:$M$3000,Permissions!$B$2:$B$3000,$A26,Permissions!$R$2:$R$3000,"Yes") -> 0 | BB26: =SUMIFS(Permissions!$O$2:$O$3000,Permissions!$B$2:$B$3000,$A26,Permissions!$R$2:$R$3000,"Yes") -> 0 | BC26: =IF(AND(AM26>0,AR26>=AM26,AP26=0),"Finished",IF(AR26>0,"Partly built",IF(AM26>0,"Consented – not built","No consent"))) -> Consented – not built | BD26: =IF(AND(R26<>"",AM26>1.1*R26),"Consented above capacity",IF(AND(LEFT(B26,8)="Planning",AZ26=0),"Consent parcel with no permission",IF(COUNTIF($A$2:$A$3000,$A26)>1,"Duplicate parcel_id",""))) -> Consented above capacity
... A40: CITY-72 | B40: Council audit | C40: City | D40: Castletroy/Annacotty | E40: City neighbourhood | F40: 1 | G40: Inside catchment | H40: 72 | I40: Castletroy/Annacotty | J40: LIMERICK CITY EAST LEA-7 | K40: Castletroy | L40: Private | M40: Mixed Use | N40: Greenfield | O40: 45+ | P40: 4.8 | Q40: 16.047 | R40: 216 | S40: Council estimate (area × density band) | T40: 163 | X40: City suburbs | Y40: 34 | Z40: 34 homes/ha = median of 39 permitted Limerick schemes of 10+ homes in city suburbs; applied to developable for density_estimate_units only | AB40: 0 | AC40: 0 | AD40: Permission Granted | AE40: Reduced Area | AF40: 2026-10-11 | AH40: =IF(R40="",AM40,R40) -> 216 | AI40: =SUMIFS(Permissions!$G$2:$G$3000,Permissions!$B$2:$B$3000,$A40,Permissions!$I$2:$I$3000,"Complete",Permissions!$R$2:$R$3000,"Yes") -> 0 | AJ40: =SUMIFS(Permissions!$G$2:$G$3000,Permissions!$B$2:$B$3000,$A40,Permissions!$I$2:$I$3000,"Under construction",Permissions!$R$2:$R$3000,"Yes") -> 48 | AK40: =SUMIFS(Permissions!$G$2:$G$3000,Permissions!$B$2:$B$3000,$A40,Permissions!$I$2:$I$3000,"Permitted – not started",Permissions!$R$2:$R$3000,"Yes") -> 212 | AL40: =SUMIFS(Permissions!$G$2:$G$3000,Permissions!$B$2:$B$3000,$A40,Permissions!$I$2:$I$3000,"Stalled",Permissions!$R$2:$R$3000,"Yes") -> 0 | AM40: =AI40+AJ40+AK40+AL40 -> 260 | AN40: =SUMIFS(Permissions!$G$2:$G$3000,Permissions!$B$2:$B$3000,$A40,Permissions!$I$2:$I$3000,"Expired – not started",Permissions!$R$2:$R$3000,"Yes") -> 0 | AO40: =SUMIFS(Permissions!$G$2:$G$3000,Permissions!$B$2:$B$3000,$A40,Permissions!$I$2:$I$3000,"In planning",Permissions!$R$2:$R$3000,"Yes") -> 0 | AP40: =IF(R40="",0,MAX(R40-AM40,0)) -> 0 | AQ40: =AM40+AP40 -> 260 | AR40: =SUMIFS(Permissions!$L$2:$L$3000,Permissions!$B$2:$B$3000,$A40,Permissions!$R$2:$R$3000,"Yes",Permissions!$I$2:$I$3000,"<>Expired – not started",Permissions!$I$2:$I$3000,"<>In planning") -> 0 | AS40: =AQ40-AR40 -> 260 | AT40: =SUMIFS(Permissions!$AJ$2:$AJ$3000,Permissions!$B$2:$B$3000,$A40,Permissions!$R$2:$R$3000,"Yes") -> 11.2 | AU40: =SUMIFS(Permissions!$AK$2:$AK$3000,Permissions!$B$2:$B$3000,$A40,Permissions!$R$2:$R$3000,"Yes") -> 36.8 | AV40: =SUMIFS(Permissions!$AL$2:$AL$3000,Permissions!$B$2:$B$3000,$A40,Permissions!$R$2:$R$3000,"Yes") -> 0 | AW40: =SUMIFS(Permissions!$AM$2:$AM$3000,Permissions!$B$2:$B$3000,$A40,Permissions!$R$2:$R$3000,"Yes") -> 36.4 | AX40: =SUMIFS(Permissions!$AN$2:$AN$3000,Permissions!$B$2:$B$3000,$A40,Permissions!$R$2:$R$3000,"Yes") -> 65.9 | AY40: =SUMIFS(Permissions!$AO$2:$AO$3000,Permissions!$B$2:$B$3000,$A40,Permissions!$R$2:$R$3000,"Yes") -> 109.7 | AZ40: =COUNTIFS(Permissions!$B$2:$B$3000,$A40,Permissions!$R$2:$R$3000,"Yes") -> 2 | BA40: =SUMIFS(Permissions!$M$2:$M$3000,Permissions!$B$2:$B$3000,$A40,Permissions!$R$2:$R$3000,"Yes") -> 0 | BB40: =SUMIFS(Permissions!$O$2:$O$3000,Permissions!$B$2:$B$3000,$A40,Permissions!$R$2:$R$3000,"Yes") -> 0 | BC40: =IF(AND(AM40>0,AR40>=AM40,AP40=0),"Finished",IF(AR40>0,"Partly built",IF(AM40>0,"Consented – not built","No consent"))) -> Consented – not built | BD40: =IF(AND(R40<>"",AM40>1.1*R40),"Consented above capacity",IF(AND(LEFT(B40,8)="Planning",AZ40=0),"Consent parcel with no permission",IF(COUNTIF($A$2:$A$3000,$A40)>1,"Duplicate parcel_id",""))) -> Consented above capacity
A41: CITY-101 | B41: Council audit | C41: City | D41: City Centre | E41: City neighbourhood | F41: 1 | G41: Inside catchment | H41: 101 | I41: City Centre | J41: LIMERICK CITY WEST LEA-7 | K41: City Centre | L41: Private | M41: City C | N41: Brownfield | O41: 100+ | P41: 0.157 | Q41: 0.158 | R41: 16 | S41: Council estimate (area × density band) | T41: 16 | X41: City centre | Y41: 101 | Z41: 101 homes/ha = median of 6 permitted Limerick schemes of 10+ homes in city centre; applied to developable for density_estimate_units only | AB41: 31 | AC41: 0 | AE41: Unchanged | AF41: 2026-10-11 | AH41: =IF(R41="",AM41,R41) -> 16 | AI41: =SUMIFS(Permissions!$G$2:$G$3000,Permissions!$B$2:$B$3000,$A41,Permissions!$I$2:$I$3000,"Complete",Permissions!$R$2:$R$3000,"Yes") -> 0 | AJ41: =SUMIFS(Permissions!$G$2:$G$3000,Permissions!$B$2:$B$3000,$A41,Permissions!$I$2:$I$3000,"Under construction",Permissions!$R$2:$R$3000,"Yes") -> 0 | AK41: =SUMIFS(Permissions!$G$2:$G$3000,Permissions!$B$2:$B$3000,$A41,Permissions!$I$2:$I$3000,"Permitted – not started",Permissions!$R$2:$R$3000,"Yes") -> 0 | AL41: =SUMIFS(Permissions!$G$2:$G$3000,Permissions!$B$2:$B$3000,$A41,Permissions!$I$2:$I$3000,"Stalled",Permissions!$R$2:$R$3000,"Yes") -> 0 | AM41: =AI41+AJ41+AK41+AL41 -> 0 | AN41: =SUMIFS(Permissions!$G$2:$G$3000,Permissions!$B$2:$B$3000,$A41,Permissions!$I$2:$I$3000,"Expired – not started",Permissions!$R$2:$R$3000,"Yes") -> 8 | AO41: =SUMIFS(Permissions!$G$2:$G$3000,Permissions!$B$2:$B$3000,$A41,Permissions!$I$2:$I$3000,"In planning",Permissions!$R$2:$R$3000,"Yes") -> 0 | AP41: =IF(R41="",0,MAX(R41-AM41,0)) -> 16 | AQ41: =AM41+AP41 -> 16 | AR41: =SUMIFS(Permissions!$L$2:$L$3000,Permissions!$B$2:$B$3000,$A41,Permissions!$R$2:$R$3000,"Yes",Permissions!$I$2:$I$3000,"<>Expired – not started",Permissions!$I$2:$I$3000,"<>In planning") -> 0 | AS41: =AQ41-AR41 -> 16 | AT41: =SUMIFS(Permissions!$AJ$2:$AJ$3000,Permissions!$B$2:$B$3000,$A41,Permissions!$R$2:$R$3000,"Yes") -> 0 | AU41: =SUMIFS(Permissions!$AK$2:$AK$3000,Permissions!$B$2:$B$3000,$A41,Permissions!$R$2:$R$3000,"Yes") -> 0 | AV41: =SUMIFS(Permissions!$AL$2:$AL$3000,Permissions!$B$2:$B$3000,$A41,Permissions!$R$2:$R$3000,"Yes") -> 0 | AW41: =SUMIFS(Permissions!$AM$2:$AM$3000,Permissions!$B$2:$B$3000,$A41,Permissions!$R$2:$R$3000,"Yes") -> 0 | AX41: =SUMIFS(Permissions!$AN$2:$AN$3000,Permissions!$B$2:$B$3000,$A41,Permissions!$R$2:$R$3000,"Yes") -> 0 | AY41: =SUMIFS(Permissions!$AO$2:$AO$3000,Permissions!$B$2:$B$3000,$A41,Permissions!$R$2:$R$3000,"Yes") -> 0 | AZ41: =COUNTIFS(Permissions!$B$2:$B$3000,$A41,Permissions!$R$2:$R$3000,"Yes") -> 1 | BA41: =SUMIFS(Permissions!$M$2:$M$3000,Permissions!$B$2:$B$3000,$A41,Permissions!$R$2:$R$3000,"Yes") -> 0 | BB41: =SUMIFS(Permissions!$O$2:$O$3000,Permissions!$B$2:$B$3000,$A41,Permissions!$R$2:$R$3000,"Yes") -> 0 | BC41: =IF(AND(AM41>0,AR41>=AM41,AP41=0),"Finished",IF(AR41>0,"Partly built",IF(AM41>0,"Consented – not built","No consent"))) -> No consent | BD41: =IF(AND(R41<>"",AM41>1.1*R41),"Consented above capacity",IF(AND(LEFT(B41,8)="Planning",AZ41=0),"Consent parcel with no permission",IF(COUNTIF($A$2:$A$3000,$A41)>1,"Duplicate parcel_id","")))
A42: CITY-102 | B42: Council audit | C42: City | D42: City Centre | E42: City neighbourhood | F42: 1 | G42: Inside catchment | H42: 102 | I42: City Centre | J42: LIMERICK CITY NORTH LEA-7 | K42: City Centre | L42: Private | M42: City C | N42: Infill | O42: 100+ | P42: 0.118 | Q42: 0.13 | R42: 12 | S42: Estimate (council audit recorded no capacity): developable area x density | T42: 12 | X42: City centre | Y42: 101 | Z42: 101 homes/ha = median of 6 permitted Limerick schemes of 10+ homes in city centre; developable share 0.91 where none recorded | AB42: 0 | AC42: 0 | AD42: Undeveloped/Permission Sought | AE42: Unchanged | AF42: 2026-10-11 | AH42: =IF(R42="",AM42,R42) -> 12 | AI42: =SUMIFS(Permissions!$G$2:$G$3000,Permissions!$B$2:$B$3000,$A42,Permissions!$I$2:$I$3000,"Complete",Permissions!$R$2:$R$3000,"Yes") -> 0 | AJ42: =SUMIFS(Permissions!$G$2:$G$3000,Permissions!$B$2:$B$3000,$A42,Permissions!$I$2:$I$3000,"Under construction",Permissions!$R$2:$R$3000,"Yes") -> 0 | AK42: =SUMIFS(Permissions!$G$2:$G$3000,Permissions!$B$2:$B$3000,$A42,Permissions!$I$2:$I$3000,"Permitted – not started",Permissions!$R$2:$R$3000,"Yes") -> 0 | AL42: =SUMIFS(Permissions!$G$2:$G$3000,Permissions!$B$2:$B$3000,$A42,Permissions!$I$2:$I$3000,"Stalled",Permissions!$R$2:$R$3000,"Yes") -> 0 | AM42: =AI42+AJ42+AK42+AL42 -> 0 | AN42: =SUMIFS(Permissions!$G$2:$G$3000,Permissions!$B$2:$B$3000,$A42,Permissions!$I$2:$I$3000,"Expired – not started",Permissions!$R$2:$R$3000,"Yes") -> 0 | AO42: =SUMIFS(Permissions!$G$2:$G$3000,Permissions!$B$2:$B$3000,$A42,Permissions!$I$2:$I$3000,"In planning",Permissions!$R$2:$R$3000,"Yes") -> 0 | AP42: =IF(R42="",0,MAX(R42-AM42,0)) -> 12 | AQ42: =AM42+AP42 -> 12 | AR42: =SUMIFS(Permissions!$L$2:$L$3000,Permissions!$B$2:$B$3000,$A42,Permissions!$R$2:$R$3000,"Yes",Permissions!$I$2:$I$3000,"<>Expired – not started",Permissions!$I$2:$I$3000,"<>In planning") -> 0 | AS42: =AQ42-AR42 -> 12 | AT42: =SUMIFS(Permissions!$AJ$2:$AJ$3000,Permissions!$B$2:$B$3000,$A42,Permissions!$R$2:$R$3000,"Yes") -> 0 | AU42: =SUMIFS(Permissions!$AK$2:$AK$3000,Permissions!$B$2:$B$3000,$A42,Permissions!$R$2:$R$3000,"Yes") -> 0 | AV42: =SUMIFS(Permissions!$AL$2:$AL$3000,Permissions!$B$2:$B$3000,$A42,Permissions!$R$2:$R$3000,"Yes") -> 0 | AW42: =SUMIFS(Permissions!$AM$2:$AM$3000,Permissions!$B$2:$B$3000,$A42,Permissions!$R$2:$R$3000,"Yes") -> 0 | AX42: =SUMIFS(Permissions!$AN$2:$AN$3000,Permissions!$B$2:$B$3000,$A42,Permissions!$R$2:$R$3000,"Yes") -> 0 | AY42: =SUMIFS(Permissions!$AO$2:$AO$3000,Permissions!$B$2:$B$3000,$A42,Permissions!$R$2:$R$3000,"Yes") -> 0 | AZ42: =COUNTIFS(Permissions!$B$2:$B$3000,$A42,Permissions!$R$2:$R$3000,"Yes") -> 0 | BA42: =SUMIFS(Permissions!$M$2:$M$3000,Permissions!$B$2:$B$3000,$A42,Permissions!$R$2:$R$3000,"Yes") -> 0 | BB42: =SUMIFS(Permissions!$O$2:$O$3000,Permissions!$B$2:$B$3000,$A42,Permissions!$R$2:$R$3000,"Yes") -> 0 | BC42: =IF(AND(AM42>0,AR42>=AM42,AP42=0),"Finished",IF(AR42>0,"Partly built",IF(AM42>0,"Consented – not built","No consent"))) -> No consent | BD42: =IF(AND(R42<>"",AM42>1.1*R42),"Consented above capacity",IF(AND(LEFT(B42,8)="Planning",AZ42=0),"Consent parcel with no permission",IF(COUNTIF($A$2:$A$3000,$A42)>1,"Duplicate parcel_id","")))
A43: CITY-104 | B43: Council audit | C43: City | D43: City Centre | E43: City neighbourhood | F43: 1 | G43: Inside catchment | H43: 104 | I43: City Centre | J43: LIMERICK CITY NORTH LEA-7 | K43: City Centre | L43: Private | M43: City C | N43: Infill | O43: 100+ | P43: 0.068 | Q43: 0.075 | R43: 7 | S43: Estimate (council audit recorded no capacity): developable area x density | T43: 7 | X43: City centre | Y43: 101 | Z43: 101 homes/ha = median of 6 permitted Limerick schemes of 10+ homes in city centre; developable share 0.91 where none recorded | AB43: 0 | AC43: 0 | AD43: Undeveloped/Permission Sought | AE43: Unchanged | AF43: 2026-10-11 | AH43: =IF(R43="",AM43,R43) -> 7 | AI43: =SUMIFS(Permissions!$G$2:$G$3000,Permissions!$B$2:$B$3000,$A43,Permissions!$I$2:$I$3000,"Complete",Permissions!$R$2:$R$3000,"Yes") -> 0 | AJ43: =SUMIFS(Permissions!$G$2:$G$3000,Permissions!$B$2:$B$3000,$A43,Permissions!$I$2:$I$3000,"Under construction",Permissions!$R$2:$R$3000,"Yes") -> 0 | AK43: =SUMIFS(Permissions!$G$2:$G$3000,Permissions!$B$2:$B$3000,$A43,Permissions!$I$2:$I$3000,"Permitted – not started",Permissions!$R$2:$R$3000,"Yes") -> 0 | AL43: =SUMIFS(Permissions!$G$2:$G$3000,Permissions!$B$2:$B$3000,$A43,Permissions!$I$2:$I$3000,"Stalled",Permissions!$R$2:$R$3000,"Yes") -> 0 | AM43: =AI43+AJ43+AK43+AL43 -> 0 | AN43: =SUMIFS(Permissions!$G$2:$G$3000,Permissions!$B$2:$B$3000,$A43,Permissions!$I$2:$I$3000,"Expired – not started",Permissions!$R$2:$R$3000,"Yes") -> 0 | AO43: =SUMIFS(Permissions!$G$2:$G$3000,Permissions!$B$2:$B$3000,$A43,Permissions!$I$2:$I$3000,"In planning",Permissions!$R$2:$R$3000,"Yes") -> 0 | AP43: =IF(R43="",0,MAX(R43-AM43,0)) -> 7 | AQ43: =AM43+AP43 -> 7 | AR43: =SUMIFS(Permissions!$L$2:$L$3000,Permissions!$B$2:$B$3000,$A43,Permissions!$R$2:$R$3000,"Yes",Permissions!$I$2:$I$3000,"<>Expired – not started",Permissions!$I$2:$I$3000,"<>In planning") -> 0 | AS43: =AQ43-AR43 -> 7 | AT43: =SUMIFS(Permissions!$AJ$2:$AJ$3000,Permissions!$B$2:$B$3000,$A43,Permissions!$R$2:$R$3000,"Yes") -> 0 | AU43: =SUMIFS(Permissions!$AK$2:$AK$3000,Permissions!$B$2:$B$3000,$A43,Permissions!$R$2:$R$3000,"Yes") -> 0 | AV43: =SUMIFS(Permissions!$AL$2:$AL$3000,Permissions!$B$2:$B$3000,$A43,Permissions!$R$2:$R$3000,"Yes") -> 0 | AW43: =SUMIFS(Permissions!$AM$2:$AM$3000,Permissions!$B$2:$B$3000,$A43,Permissions!$R$2:$R$3000,"Yes") -> 0 | AX43: =SUMIFS(Permissions!$AN$2:$AN$3000,Permissions!$B$2:$B$3000,$A43,Permissions!$R$2:$R$3000,"Yes") -> 0 | AY43: =SUMIFS(Permissions!$AO$2:$AO$3000,Permissions!$B$2:$B$3000,$A43,Permissions!$R$2:$R$3000,"Yes") -> 0 | AZ43: =COUNTIFS(Permissions!$B$2:$B$3000,$A43,Permissions!$R$2:$R$3000,"Yes") -> 0 | BA43: =SUMIFS(Permissions!$M$2:$M$3000,Permissions!$B$2:$B$3000,$A43,Permissions!$R$2:$R$3000,"Yes") -> 0 | BB43: =SUMIFS(Permissions!$O$2:$O$3000,Permissions!$B$2:$B$3000,$A43,Permissions!$R$2:$R$3000,"Yes") -> 0 | BC43: =IF(AND(AM43>0,AR43>=AM43,AP43=0),"Finished",IF(AR43>0,"Partly built",IF(AM43>0,"Consented – not built","No consent"))) -> No consent | BD43: =IF(AND(R43<>"",AM43>1.1*R43),"Consented above capacity",IF(AND(LEFT(B43,8)="Planning",AZ43=0),"Consent parcel with no permission",IF(COUNTIF($A$2:$A$3000,$A43)>1,"Duplicate parcel_id","")))
A44: CITY-105 | B44: Council audit | C44: City | D44: City Centre | E44: City neighbourhood | F44: 1 | G44: Inside catchment | H44: 105 | I44: City Centre | J44: LIMERICK CITY EAST LEA-7 | K44: City Centre | L44: Private | M44: City C | N44: Infill | O44: 100+ | P44: 0.192 | Q44: 0.211 | R44: 19 | S44: Estimate (council audit recorded no capacity): developable area x density | T44: 19 | X44: City centre | Y44: 101 | Z44: 101 homes/ha = median of 6 permitted Limerick schemes of 10+ homes in city centre; developable share 0.91 where none recorded | AB44: 0 | AC44: 0 | AD44: Undeveloped/Permission Sought | AE44: Unchanged | AF44: 2026-10-11 | AH44: =IF(R44="",AM44,R44) -> 19 | AI44: =SUMIFS(Permissions!$G$2:$G$3000,Permissions!$B$2:$B$3000,$A44,Permissions!$I$2:$I$3000,"Complete",Permissions!$R$2:$R$3000,"Yes") -> 0 | AJ44: =SUMIFS(Permissions!$G$2:$G$3000,Permissions!$B$2:$B$3000,$A44,Permissions!$I$2:$I$3000,"Under construction",Permissions!$R$2:$R$3000,"Yes") -> 0 | AK44: =SUMIFS(Permissions!$G$2:$G$3000,Permissions!$B$2:$B$3000,$A44,Permissions!$I$2:$I$3000,"Permitted – not started",Permissions!$R$2:$R$3000,"Yes") -> 0 | AL44: =SUMIFS(Permissions!$G$2:$G$3000,Permissions!$B$2:$B$3000,$A44,Permissions!$I$2:$I$3000,"Stalled",Permissions!$R$2:$R$3000,"Yes") -> 0 | AM44: =AI44+AJ44+AK44+AL44 -> 0 | AN44: =SUMIFS(Permissions!$G$2:$G$3000,Permissions!$B$2:$B$3000,$A44,Permissions!$I$2:$I$3000,"Expired – not started",Permissions!$R$2:$R$3000,"Yes") -> 0 | AO44: =SUMIFS(Permissions!$G$2:$G$3000,Permissions!$B$2:$B$3000,$A44,Permissions!$I$2:$I$3000,"In planning",Permissions!$R$2:$R$3000,"Yes") -> 0 | AP44: =IF(R44="",0,MAX(R44-AM44,0)) -> 19 | AQ44: =AM44+AP44 -> 19 | AR44: =SUMIFS(Permissions!$L$2:$L$3000,Permissions!$B$2:$B$3000,$A44,Permissions!$R$2:$R$3000,"Yes",Permissions!$I$2:$I$3000,"<>Expired – not started",Permissions!$I$2:$I$3000,"<>In planning") -> 0 | AS44: =AQ44-AR44 -> 19 | AT44: =SUMIFS(Permissions!$AJ$2:$AJ$3000,Permissions!$B$2:$B$3000,$A44,Permissions!$R$2:$R$3000,"Yes") -> 0 | AU44: =SUMIFS(Permissions!$AK$2:$AK$3000,Permissions!$B$2:$B$3000,$A44,Permissions!$R$2:$R$3000,"Yes") -> 0 | AV44: =SUMIFS(Permissions!$AL$2:$AL$3000,Permissions!$B$2:$B$3000,$A44,Permissions!$R$2:$R$3000,"Yes") -> 0 | AW44: =SUMIFS(Permissions!$AM$2:$AM$3000,Permissions!$B$2:$B$3000,$A44,Permissions!$R$2:$R$3000,"Yes") -> 0 | AX44: =SUMIFS(Permissions!$AN$2:$AN$3000,Permissions!$B$2:$B$3000,$A44,Permissions!$R$2:$R$3000,"Yes") -> 0 | AY44: =SUMIFS(Permissions!$AO$2:$AO$3000,Permissions!$B$2:$B$3000,$A44,Permissions!$R$2:$R$3000,"Yes") -> 0 | AZ44: =COUNTIFS(Permissions!$B$2:$B$3000,$A44,Permissions!$R$2:$R$3000,"Yes") -> 0 | BA44: =SUMIFS(Permissions!$M$2:$M$3000,Permissions!$B$2:$B$3000,$A44,Permissions!$R$2:$R$3000,"Yes") -> 0 | BB44: =SUMIFS(Permissions!$O$2:$O$3000,Permissions!$B$2:$B$3000,$A44,Permissions!$R$2:$R$3000,"Yes") -> 0 | BC44: =IF(AND(AM44>0,AR44>=AM44,AP44=0),"Finished",IF(AR44>0,"Partly built",IF(AM44>0,"Consented – not built","No consent"))) -> No consent | BD44: =IF(AND(R44<>"",AM44>1.1*R44),"Consented above capacity",IF(AND(LEFT(B44,8)="Planning",AZ44=0),"Consent parcel with no permission",IF(COUNTIF($A$2:$A$3000,$A44)>1,"Duplicate parcel_id","")))
A45: CITY-106 | B45: Council audit | C45: City | D45: City Centre | E45: City neighbourhood | F45: 1 | G45: Inside catchment | H45: 106 | I45: City Centre | J45: LIMERICK CITY WEST LEA-7 | K45: City Centre | L45: Council | M45: Exist Resi | N45: Brownfield | O45: 45+ | P45: 0.14 | Q45: 0.141 | R45: 36 | S45: Council estimate (area × density band) | T45: 14 | X45: City centre | Y45: 101 | Z45: 101 homes/ha = median of 6 permitted Limerick schemes of 10+ homes in city centre; applied to developable for density_estimate_units only | AB45: 0 | AC45: 0 | AD45: Permission Granted | AE45: Unchanged | AF45: 2026-10-11 | AH45: =IF(R45="",AM45,R45) -> 36 | AI45: =SUMIFS(Permissions!$G$2:$G$3000,Permissions!$B$2:$B$3000,$A45,Permissions!$I$2:$I$3000,"Complete",Permissions!$R$2:$R$3000,"Yes") -> 0 | AJ45: =SUMIFS(Permissions!$G$2:$G$3000,Permissions!$B$2:$B$3000,$A45,Permissions!$I$2:$I$3000,"Under construction",Permissions!$R$2:$R$3000,"Yes") -> 36 | AK45: =SUMIFS(Permissions!$G$2:$G$3000,Permissions!$B$2:$B$3000,$A45,Permissions!$I$2:$I$3000,"Permitted – not started",Permissions!$R$2:$R$3000,"Yes") -> 0 | AL45: =SUMIFS(Permissions!$G$2:$G$3000,Permissions!$B$2:$B$3000,$A45,Permissions!$I$2:$I$3000,"Stalled",Permissions!$R$2:$R$3000,"Yes") -> 0 | AM45: =AI45+AJ45+AK45+AL45 -> 36 | AN45: =SUMIFS(Permissions!$G$2:$G$3000,Permissions!$B$2:$B$3000,$A45,Permissions!$I$2:$I$3000,"Expired – not started",Permissions!$R$2:$R$3000,"Yes") -> 0 | AO45: =SUMIFS(Permissions!$G$2:$G$3000,Permissions!$B$2:$B$3000,$A45,Permissions!$I$2:$I$3000,"In planning",Permissions!$R$2:$R$3000,"Yes") -> 0 | AP45: =IF(R45="",0,MAX(R45-AM45,0)) -> 0 | AQ45: =AM45+AP45 -> 36 | AR45: =SUMIFS(Permissions!$L$2:$L$3000,Permissions!$B$2:$B$3000,$A45,Permissions!$R$2:$R$3000,"Yes",Permissions!$I$2:$I$3000,"<>Expired – not started",Permissions!$I$2:$I$3000,"<>In planning") -> 0 | AS45: =AQ45-AR45 -> 36 | AT45: =SUMIFS(Permissions!$AJ$2:$AJ$3000,Permissions!$B$2:$B$3000,$A45,Permissions!$R$2:$R$3000,"Yes") -> 8.4 | AU45: =SUMIFS(Permissions!$AK$2:$AK$3000,Permissions!$B$2:$B$3000,$A45,Permissions!$R$2:$R$3000,"Yes") -> 27.6 | AV45: =SUMIFS(Permissions!$AL$2:$AL$3000,Permissions!$B$2:$B$3000,$A45,Permissions!$R$2:$R$3000,"Yes") -> 0 | AW45: =SUMIFS(Permissions!$AM$2:$AM$3000,Permissions!$B$2:$B$3000,$A45,Permissions!$R$2:$R$3000,"Yes") -> 0 | AX45: =SUMIFS(Permissions!$AN$2:$AN$3000,Permissions!$B$2:$B$3000,$A45,Permissions!$R$2:$R$3000,"Yes") -> 0 | AY45: =SUMIFS(Permissions!$AO$2:$AO$3000,Permissions!$B$2:$B$3000,$A45,Permissions!$R$2:$R$3000,"Yes") -> 0 | AZ45: =COUNTIFS(Permissions!$B$2:$B$3000,$A45,Permissions!$R$2:$R$3000,"Yes") -> 1 | BA45: =SUMIFS(Permissions!$M$2:$M$3000,Permissions!$B$2:$B$3000,$A45,Permissions!$R$2:$R$3000,"Yes") -> 0 | BB45: =SUMIFS(Permissions!$O$2:$O$3000,Permissions!$B$2:$B$3000,$A45,Permissions!$R$2:$R$3000,"Yes") -> 0 | BC45: =IF(AND(AM45>0,AR45>=AM45,AP45=0),"Finished",IF(AR45>0,"Partly built",IF(AM45>0,"Consented – not built","No consent"))) -> Consented – not built | BD45: =IF(AND(R45<>"",AM45>1.1*R45),"Consented above capacity",IF(AND(LEFT(B45,8)="Planning",AZ45=0),"Consent parcel with no permission",IF(COUNTIF($A$2:$A$3000,$A45)>1,"Duplicate parcel_id","")))
A46: CITY-107 | B46: Council audit | C46: City | D46: City Centre | E46: City neighbourhood | F46: 0.62 | G46: Inside catchment | H46: 107 | I46: City Centre | J46: LIMERICK CITY EAST LEA-7 | K46: City Centre | L46: Council | M46: City C | N46: Brownfield | O46: 100+ | P46: 68.48 | Q46: 68.509 | R46: 2500 | S46: Council estimate (area × density band) | T46: 2328 | X46: City suburbs | Y46: 34 | Z46: 34 homes/ha = median of 39 permitted Limerick schemes of 10+ homes in city suburbs; applied to developable for density_estimate_units only | AB46: 285 | AC46: 19 | AD46: Undeveloped/Permission Sought | AE46: Unchanged | AF46: 2026-10-11 | AH46: =IF(R46="",AM46,R46) -> 2500 | AI46: =SUMIFS(Permissions!$G$2:$G$3000,Permissions!$B$2:$B$3000,$A46,Permissions!$I$2:$I$3000,"Complete",Permissions!$R$2:$R$3000,"Yes") -> 11 | AJ46: =SUMIFS(Permissions!$G$2:$G$3000,Permissions!$B$2:$B$3000,$A46,Permissions!$I$2:$I$3000,"Under construction",Permissions!$R$2:$R$3000,"Yes") -> 0 | AK46: =SUMIFS(Permissions!$G$2:$G$3000,Permissions!$B$2:$B$3000,$A46,Permissions!$I$2:$I$3000,"Permitted – not started",Permissions!$R$2:$R$3000,"Yes") -> 0 | AL46: =SUMIFS(Permissions!$G$2:$G$3000,Permissions!$B$2:$B$3000,$A46,Permissions!$I$2:$I$3000,"Stalled",Permissions!$R$2:$R$3000,"Yes") -> 0 | AM46: =AI46+AJ46+AK46+AL46 -> 11 | AN46: =SUMIFS(Permissions!$G$2:$G$3000,Permissions!$B$2:$B$3000,$A46,Permissions!$I$2:$I$3000,"Expired – not started",Permissions!$R$2:$R$3000,"Yes") -> 0 | AO46: =SUMIFS(Permissions!$G$2:$G$3000,Permissions!$B$2:$B$3000,$A46,Permissions!$I$2:$I$3000,"In planning",Permissions!$R$2:$R$3000,"Yes") -> 4 | AP46: =IF(R46="",0,MAX(R46-AM46,0)) -> 2489 | AQ46: =AM46+AP46 -> 2500 | AR46: =SUMIFS(Permissions!$L$2:$L$3000,Permissions!$B$2:$B$3000,$A46,Permissions!$R$2:$R$3000,"Yes",Permissions!$I$2:$I$3000,"<>Expired – not started",Permissions!$I$2:$I$3000,"<>In planning") -> 11 | AS46: =AQ46-AR46 -> 2489 | AT46: =SUMIFS(Permissions!$AJ$2:$AJ$3000,Permissions!$B$2:$B$3000,$A46,Permissions!$R$2:$R$3000,"Yes") -> 0 | AU46: =SUMIFS(Permissions!$AK$2:$AK$3000,Permissions!$B$2:$B$3000,$A46,Permissions!$R$2:$R$3000,"Yes") -> 0 | AV46: =SUMIFS(Permissions!$AL$2:$AL$3000,Permissions!$B$2:$B$3000,$A46,Permissions!$R$2:$R$3000,"Yes") -> 0 | AW46: =SUMIFS(Permissions!$AM$2:$AM$3000,Permissions!$B$2:$B$3000,$A46,Permissions!$R$2:$R$3000,"Yes") -> 0 | AX46: =SUMIFS(Permissions!$AN$2:$AN$3000,Permissions!$B$2:$B$3000,$A46,Permissions!$R$2:$R$3000,"Yes") -> 0 | AY46: =SUMIFS(Permissions!$AO$2:$AO$3000,Permissions!$B$2:$B$3000,$A46,Permissions!$R$2:$R$3000,"Yes") -> 0 | AZ46: =COUNTIFS(Permissions!$B$2:$B$3000,$A46,Permissions!$R$2:$R$3000,"Yes") -> 2 | BA46: =SUMIFS(Permissions!$M$2:$M$3000,Permissions!$B$2:$B$3000,$A46,Permissions!$R$2:$R$3000,"Yes") -> 11 | BB46: =SUMIFS(Permissions!$O$2:$O$3000,Permissions!$B$2:$B$3000,$A46,Permissions!$R$2:$R$3000,"Yes") -> 0 | BC46: =IF(AND(AM46>0,AR46>=AM46,AP46=0),"Finished",IF(AR46>0,"Partly built",IF(AM46>0,"Consented – not built","No consent"))) -> Partly built | BD46: =IF(AND(R46<>"",AM46>1.1*R46),"Consented above capacity",IF(AND(LEFT(B46,8)="Planning",AZ46=0),"Consent parcel with no permission",IF(COUNTIF($A$2:$A$3000,$A46)>1,"Duplicate parcel_id","")))
A47: CITY-108 | B47: Council audit | C47: City | D47: City Centre | E47: City neighbourhood | F47: 1 | G47: Inside catchment | H47: 108 | I47: City Centre | J47: LIMERICK CITY NORTH LEA-7 | K47: City Centre | L47: Private | M47: New Resi | N47: Infill | O47: 45+ | P47: 0.297 | Q47: 0.297 | R47: 13 | S47: Council estimate (area × density band) | T47: 30 | X47: City centre | Y47: 101 | Z47: 101 homes/ha = median of 6 permitted Limerick schemes of 10+ homes in city centre; applied to developable for density_estimate_units only | AB47: 0 | AC47: 0 | AD47: Undeveloped/Permission Sought | AE47: Unchanged | AF47: 2026-10-11 | AH47: =IF(R47="",AM47,R47) -> 13 | AI47: =SUMIFS(Permissions!$G$2:$G$3000,Permissions!$B$2:$B$3000,$A47,Permissions!$I$2:$I$3000,"Complete",Permissions!$R$2:$R$3000,"Yes") -> 0 | AJ47: =SUMIFS(Permissions!$G$2:$G$3000,Permissions!$B$2:$B$3000,$A47,Permissions!$I$2:$I$3000,"Under construction",Permissions!$R$2:$R$3000,"Yes") -> 0 | AK47: =SUMIFS(Permissions!$G$2:$G$3000,Permissions!$B$2:$B$3000,$A47,Permissions!$I$2:$I$3000,"Permitted – not started",Permissions!$R$2:$R$3000,"Yes") -> 0 | AL47: =SUMIFS(Permissions!$G$2:$G$3000,Permissions!$B$2:$B$3000,$A47,Permissions!$I$2:$I$3000,"Stalled",Permissions!$R$2:$R$3000,"Yes") -> 0 | AM47: =AI47+AJ47+AK47+AL47 -> 0 | AN47: =SUMIFS(Permissions!$G$2:$G$3000,Permissions!$B$2:$B$3000,$A47,Permissions!$I$2:$I$3000,"Expired – not started",Permissions!$R$2:$R$3000,"Yes") -> 0 | AO47: =SUMIFS(Permissions!$G$2:$G$3000,Permissions!$B$2:$B$3000,$A47,Permissions!$I$2:$I$3000,"In planning",Permissions!$R$2:$R$3000,"Yes") -> 0 | AP47: =IF(R47="",0,MAX(R47-AM47,0)) -> 13 | AQ47: =AM47+AP47 -> 13 | AR47: =SUMIFS(Permissions!$L$2:$L$3000,Permissions!$B$2:$B$3000,$A47,Permissions!$R$2:$R$3000,"Yes",Permissions!$I$2:$I$3000,"<>Expired – not started",Permissions!$I$2:$I$3000,"<>In planning") -> 0 | AS47: =AQ47-AR47 -> 13 | AT47: =SUMIFS(Permissions!$AJ$2:$AJ$3000,Permissions!$B$2:$B$3000,$A47,Permissions!$R$2:$R$3000,"Yes") -> 0 | AU47: =SUMIFS(Permissions!$AK$2:$AK$3000,Permissions!$B$2:$B$3000,$A47,Permissions!$R$2:$R$3000,"Yes") -> 0 | AV47: =SUMIFS(Permissions!$AL$2:$AL$3000,Permissions!$B$2:$B$3000,$A47,Permissions!$R$2:$R$3000,"Yes") -> 0 | AW47: =SUMIFS(Permissions!$AM$2:$AM$3000,Permissions!$B$2:$B$3000,$A47,Permissions!$R$2:$R$3000,"Yes") -> 0 | AX47: =SUMIFS(Permissions!$AN$2:$AN$3000,Permissions!$B$2:$B$3000,$A47,Permissions!$R$2:$R$3000,"Yes") -> 0 | AY47: =SUMIFS(Permissions!$AO$2:$AO$3000,Permissions!$B$2:$B$3000,$A47,Permissions!$R$2:$R$3000,"Yes") -> 0 | AZ47: =COUNTIFS(Permissions!$B$2:$B$3000,$A47,Permissions!$R$2:$R$3000,"Yes") -> 0 | BA47: =SUMIFS(Permissions!$M$2:$M$3000,Permissions!$B$2:$B$3000,$A47,Permissions!$R$2:$R$3000,"Yes") -> 0 | BB47: =SUMIFS(Permissions!$O$2:$O$3000,Permissions!$B$2:$B$3000,$A47,Permissions!$R$2:$R$3000,"Yes") -> 0 | BC47: =IF(AND(AM47>0,AR47>=AM47,AP47=0),"Finished",IF(AR47>0,"Partly built",IF(AM47>0,"Consented – not built","No consent"))) -> No consent | BD47: =IF(AND(R47<>"",AM47>1.1*R47),"Consented above capacity",IF(AND(LEFT(B47,8)="Planning",AZ47=0),"Consent parcel with no permission",IF(COUNTIF($A$2:$A$3000,$A47)>1,"Duplicate parcel_id","")))
A48: CITY-162 | B48: Council audit | C48: City | D48: City Centre | E48: City neighbourhood | F48: 1 | G48: Inside catchment | H48: 162 | I48: City Centre | J48: LIMERICK CITY WEST LEA-7 | L48: Unknown | P48: 1.391 | Q48: 1.39 | R48: 139 | S48: Council estimate (area × density band) | T48: 140 | X48: City centre | Y48: 101 | Z48: 101 homes/ha = median of 6 permitted Limerick schemes of 10+ homes in city centre; applied to developable for density_estimate_units only | AB48: 0 | AC48: 0 | AE48: Addition | AF48: 2026-10-11 | AH48: =IF(R48="",AM48,R48) -> 139 | AI48: =SUMIFS(Permissions!$G$2:$G$3000,Permissions!$B$2:$B$3000,$A48,Permissions!$I$2:$I$3000,"Complete",Permissions!$R$2:$R$3000,"Yes") -> 0 | AJ48: =SUMIFS(Permissions!$G$2:$G$3000,Permissions!$B$2:$B$3000,$A48,Permissions!$I$2:$I$3000,"Under construction",Permissions!$R$2:$R$3000,"Yes") -> 0 | AK48: =SUMIFS(Permissions!$G$2:$G$3000,Permissions!$B$2:$B$3000,$A48,Permissions!$I$2:$I$3000,"Permitted – not started",Permissions!$R$2:$R$3000,"Yes") -> 0 | AL48: =SUMIFS(Permissions!$G$2:$G$3000,Permissions!$B$2:$B$3000,$A48,Permissions!$I$2:$I$3000,"Stalled",Permissions!$R$2:$R$3000,"Yes") -> 0 | AM48: =AI48+AJ48+AK48+AL48 -> 0 | AN48: =SUMIFS(Permissions!$G$2:$G$3000,Permissions!$B$2:$B$3000,$A48,Permissions!$I$2:$I$3000,"Expired – not started",Permissions!$R$2:$R$3000,"Yes") -> 0 | AO48: =SUMIFS(Permissions!$G$2:$G$3000,Permissions!$B$2:$B$3000,$A48,Permissions!$I$2:$I$3000,"In planning",Permissions!$R$2:$R$3000,"Yes") -> 0 | AP48: =IF(R48="",0,MAX(R48-AM48,0)) -> 139 | AQ48: =AM48+AP48 -> 139 | AR48: =SUMIFS(Permissions!$L$2:$L$3000,Permissions!$B$2:$B$3000,$A48,Permissions!$R$2:$R$3000,"Yes",Permissions!$I$2:$I$3000,"<>Expired – not started",Permissions!$I$2:$I$3000,"<>In planning") -> 0 | AS48: =AQ48-AR48 -> 139 | AT48: =SUMIFS(Permissions!$AJ$2:$AJ$3000,Permissions!$B$2:$B$3000,$A48,Permissions!$R$2:$R$3000,"Yes") -> 0 | AU48: =SUMIFS(Permissions!$AK$2:$AK$3000,Permissions!$B$2:$B$3000,$A48,Permissions!$R$2:$R$3000,"Yes") -> 0 | AV48: =SUMIFS(Permissions!$AL$2:$AL$3000,Permissions!$B$2:$B$3000,$A48,Permissions!$R$2:$R$3000,"Yes") -> 0 | AW48: =SUMIFS(Permissions!$AM$2:$AM$3000,Permissions!$B$2:$B$3000,$A48,Permissions!$R$2:$R$3000,"Yes") -> 0 | AX48: =SUMIFS(Permissions!$AN$2:$AN$3000,Permissions!$B$2:$B$3000,$A48,Permissions!$R$2:$R$3000,"Yes") -> 0 | AY48: =SUMIFS(Permissions!$AO$2:$AO$3000,Permissions!$B$2:$B$3000,$A48,Permissions!$R$2:$R$3000,"Yes") -> 0 | AZ48: =COUNTIFS(Permissions!$B$2:$B$3000,$A48,Permissions!$R$2:$R$3000,"Yes") -> 0 | BA48: =SUMIFS(Permissions!$M$2:$M$3000,Permissions!$B$2:$B$3000,$A48,Permissions!$R$2:$R$3000,"Yes") -> 0 | BB48: =SUMIFS(Permissions!$O$2:$O$3000,Permissions!$B$2:$B$3000,$A48,Permissions!$R$2:$R$3000,"Yes") -> 0 | BC48: =IF(AND(AM48>0,AR48>=AM48,AP48=0),"Finished",IF(AR48>0,"Partly built",IF(AM48>0,"Consented – not built","No consent"))) -> No consent | BD48: =IF(AND(R48<>"",AM48>1.1*R48),"Consented above capacity",IF(AND(LEFT(B48,8)="Planning",AZ48=0),"Consent parcel with no permission",IF(COUNTIF($A$2:$A$3000,$A48)>1,"Duplicate parcel_id","")))
A49: CITY-163 | B49: Council audit | C49: City | D49: City Centre | E49: City neighbourhood | F49: 1 | G49: Inside catchment | H49: 163 | I49: City Centre | J49: LIMERICK CITY WEST LEA-7 | L49: Unknown | P49: 0.567 | Q49: 0.567 | R49: 20 | S49: Council estimate (area × density band) | T49: 57 | X49: City centre | Y49: 101 | Z49: 101 homes/ha = median of 6 permitted Limerick schemes of 10+ homes in city centre; applied to developable for density_estimate_units only | AB49: 1 | AC49: 0 | AE49: Addition | AF49: 2026-10-11 | AH49: =IF(R49="",AM49,R49) -> 20 | AI49: =SUMIFS(Permissions!$G$2:$G$3000,Permissions!$B$2:$B$3000,$A49,Permissions!$I$2:$I$3000,"Complete",Permissions!$R$2:$R$3000,"Yes") -> 0 | AJ49: =SUMIFS(Permissions!$G$2:$G$3000,Permissions!$B$2:$B$3000,$A49,Permissions!$I$2:$I$3000,"Under construction",Permissions!$R$2:$R$3000,"Yes") -> 0 | AK49: =SUMIFS(Permissions!$G$2:$G$3000,Permissions!$B$2:$B$3000,$A49,Permissions!$I$2:$I$3000,"Permitted – not started",Permissions!$R$2:$R$3000,"Yes") -> 0 | AL49: =SUMIFS(Permissions!$G$2:$G$3000,Permissions!$B$2:$B$3000,$A49,Permissions!$I$2:$I$3000,"Stalled",Permissions!$R$2:$R$3000,"Yes") -> 0 | AM49: =AI49+AJ49+AK49+AL49 -> 0 | AN49: =SUMIFS(Permissions!$G$2:$G$3000,Permissions!$B$2:$B$3000,$A49,Permissions!$I$2:$I$3000,"Expired – not started",Permissions!$R$2:$R$3000,"Yes") -> 0 | AO49: =SUMIFS(Permissions!$G$2:$G$3000,Permissions!$B$2:$B$3000,$A49,Permissions!$I$2:$I$3000,"In planning",Permissions!$R$2:$R$3000,"Yes") -> 0 | AP49: =IF(R49="",0,MAX(R49-AM49,0)) -> 20 | AQ49: =AM49+AP49 -> 20 | AR49: =SUMIFS(Permissions!$L$2:$L$3000,Permissions!$B$2:$B$3000,$A49,Permissions!$R$2:$R$3000,"Yes",Permissions!$I$2:$I$3000,"<>Expired – not started",Permissions!$I$2:$I$3000,"<>In planning") -> 0 | AS49: =AQ49-AR49 -> 20 | AT49: =SUMIFS(Permissions!$AJ$2:$AJ$3000,Permissions!$B$2:$B$3000,$A49,Permissions!$R$2:$R$3000,"Yes") -> 0 | AU49: =SUMIFS(Permissions!$AK$2:$AK$3000,Permissions!$B$2:$B$3000,$A49,Permissions!$R$2:$R$3000,"Yes") -> 0 | AV49: =SUMIFS(Permissions!$AL$2:$AL$3000,Permissions!$B$2:$B$3000,$A49,Permissions!$R$2:$R$3000,"Yes") -> 0 | AW49: =SUMIFS(Permissions!$AM$2:$AM$3000,Permissions!$B$2:$B$3000,$A49,Permissions!$R$2:$R$3000,"Yes") -> 0 | AX49: =SUMIFS(Permissions!$AN$2:$AN$3000,Permissions!$B$2:$B$3000,$A49,Permissions!$R$2:$R$3000,"Yes") -> 0 | AY49: =SUMIFS(Permissions!$AO$2:$AO$3000,Permissions!$B$2:$B$3000,$A49,Permissions!$R$2:$R$3000,"Yes") -> 0 | AZ49: =COUNTIFS(Permissions!$B$2:$B$3000,$A49,Permissions!$R$2:$R$3000,"Yes") -> 0 | BA49: =SUMIFS(Permissions!$M$2:$M$3000,Permissions!$B$2:$B$3000,$A49,Permissions!$R$2:$R$3000,"Yes") -> 0 | BB49: =SUMIFS(Permissions!$O$2:$O$3000,Permissions!$B$2:$B$3000,$A49,Permissions!$R$2:$R$3000,"Yes") -> 0 | BC49: =IF(AND(AM49>0,AR49>=AM49,AP49=0),"Finished",IF(AR49>0,"Partly built",IF(AM49>0,"Consented – not built","No consent"))) -> No consent | BD49: =IF(AND(R49<>"",AM49>1.1*R49),"Consented above capacity",IF(AND(LEFT(B49,8)="Planning",AZ49=0),"Consent parcel with no permission",IF(COUNTIF($A$2:$A$3000,$A49)>1,"Duplicate parcel_id","")))
A50: CITY-22 | B50: Council audit | C50: City | D50: City Centre | E50: City neighbourhood | F50: 1 | G50: Inside catchment | H50: 22 | I50: City Centre | J50: LIMERICK CITY NORTH LEA-7 | K50: Northside | L50: Council | M50: City C | N50: Brownfield | O50: 100+ | P50: 3.919 | Q50: 3.918 | R50: 500 | S50: Council estimate (area × density band) | T50: 396 | X50: City centre | Y50: 101 | Z50: 101 homes/ha = median of 6 permitted Limerick schemes of 10+ homes in city centre; applied to developable for density_estimate_units only | AB50: 2 | AC50: 0 | AD50: Undeveloped/Permission Sought | AE50: Unchanged | AF50: 2026-10-11 | AH50: =IF(R50="",AM50,R50) -> 500 | AI50: =SUMIFS(Permissions!$G$2:$G$3000,Permissions!$B$2:$B$3000,$A50,Permissions!$I$2:$I$3000,"Complete",Permissions!$R$2:$R$3000,"Yes") -> 0 | AJ50: =SUMIFS(Permissions!$G$2:$G$3000,Permissions!$B$2:$B$3000,$A50,Permissions!$I$2:$I$3000,"Under construction",Permissions!$R$2:$R$3000,"Yes") -> 0 | AK50: =SUMIFS(Permissions!$G$2:$G$3000,Permissions!$B$2:$B$3000,$A50,Permissions!$I$2:$I$3000,"Permitted – not started",Permissions!$R$2:$R$3000,"Yes") -> 0 | AL50: =SUMIFS(Permissions!$G$2:$G$3000,Permissions!$B$2:$B$3000,$A50,Permissions!$I$2:$I$3000,"Stalled",Permissions!$R$2:$R$3000,"Yes") -> 0 | AM50: =AI50+AJ50+AK50+AL50 -> 0 | AN50: =SUMIFS(Permissions!$G$2:$G$3000,Permissions!$B$2:$B$3000,$A50,Permissions!$I$2:$I$3000,"Expired – not started",Permissions!$R$2:$R$3000,"Yes") -> 0 | AO50: =SUMIFS(Permissions!$G$2:$G$3000,Permissions!$B$2:$B$3000,$A50,Permissions!$I$2:$I$3000,"In planning",Permissions!$R$2:$R$3000,"Yes") -> 0 | AP50: =IF(R50="",0,MAX(R50-AM50,0)) -> 500 | AQ50: =AM50+AP50 -> 500 | AR50: =SUMIFS(Permissions!$L$2:$L$3000,Permissions!$B$2:$B$3000,$A50,Permissions!$R$2:$R$3000,"Yes",Permissions!$I$2:$I$3000,"<>Expired – not started",Permissions!$I$2:$I$3000,"<>In planning") -> 0 | AS50: =AQ50-AR50 -> 500 | AT50: =SUMIFS(Permissions!$AJ$2:$AJ$3000,Permissions!$B$2:$B$3000,$A50,Permissions!$R$2:$R$3000,"Yes") -> 0 | AU50: =SUMIFS(Permissions!$AK$2:$AK$3000,Permissions!$B$2:$B$3000,$A50,Permissions!$R$2:$R$3000,"Yes") -> 0 | AV50: =SUMIFS(Permissions!$AL$2:$AL$3000,Permissions!$B$2:$B$3000,$A50,Permissions!$R$2:$R$3000,"Yes") -> 0 | AW50: =SUMIFS(Permissions!$AM$2:$AM$3000,Permissions!$B$2:$B$3000,$A50,Permissions!$R$2:$R$3000,"Yes") -> 0 | AX50: =SUMIFS(Permissions!$AN$2:$AN$3000,Permissions!$B$2:$B$3000,$A50,Permissions!$R$2:$R$3000,"Yes") -> 0 | AY50: =SUMIFS(Permissions!$AO$2:$AO$3000,Permissions!$B$2:$B$3000,$A50,Permissions!$R$2:$R$3000,"Yes") -> 0 | AZ50: =COUNTIFS(Permissions!$B$2:$B$3000,$A50,Permissions!$R$2:$R$3000,"Yes") -> 0 | BA50: =SUMIFS(Permissions!$M$2:$M$3000,Permissions!$B$2:$B$3000,$A50,Permissions!$R$2:$R$3000,"Yes") -> 0 | BB50: =SUMIFS(Permissions!$O$2:$O$3000,Permissions!$B$2:$B$3000,$A50,Permissions!$R$2:$R$3000,"Yes") -> 0 | BC50: =IF(AND(AM50>0,AR50>=AM50,AP50=0),"Finished",IF(AR50>0,"Partly built",IF(AM50>0,"Consented – not built","No consent"))) -> No consent | BD50: =IF(AND(R50<>"",AM50>1.1*R50),"Consented above capacity",IF(AND(LEFT(B50,8)="Planning",AZ50=0),"Consent parcel with no permission",IF(COUNTIF($A$2:$A$3000,$A50)>1,"Duplicate parcel_id","")))
A51: CITY-23 | B51: Council audit | C51: City | D51: City Centre | E51: City neighbourhood | F51: 1 | G51: Inside catchment | H51: 23 | I51: City Centre | J51: LIMERICK CITY NORTH LEA-7 | K51: Northside | L51: Council | M51: New Resi | N51: Infill | O51: 45+ | P51: 0.148 | Q51: 0.148 | R51: 7 | S51: Council estimate (area × density band) | T51: 15 | X51: City centre | Y51: 101 | Z51: 101 homes/ha = median of 6 permitted Limerick schemes of 10+ homes in city centre; applied to developable for density_estimate_units only | AB51: 0 | AC51: 0 | AD51: Undeveloped/Permission Sought | AE51: Unchanged | AF51: 2026-10-11 | AH51: =IF(R51="",AM51,R51) -> 7 | AI51: =SUMIFS(Permissions!$G$2:$G$3000,Permissions!$B$2:$B$3000,$A51,Permissions!$I$2:$I$3000,"Complete",Permissions!$R$2:$R$3000,"Yes") -> 0 | AJ51: =SUMIFS(Permissions!$G$2:$G$3000,Permissions!$B$2:$B$3000,$A51,Permissions!$I$2:$I$3000,"Under construction",Permissions!$R$2:$R$3000,"Yes") -> 0 | AK51: =SUMIFS(Permissions!$G$2:$G$3000,Permissions!$B$2:$B$3000,$A51,Permissions!$I$2:$I$3000,"Permitted – not started",Permissions!$R$2:$R$3000,"Yes") -> 0 | AL51: =SUMIFS(Permissions!$G$2:$G$3000,Permissions!$B$2:$B$3000,$A51,Permissions!$I$2:$I$3000,"Stalled",Permissions!$R$2:$R$3000,"Yes") -> 0 | AM51: =AI51+AJ51+AK51+AL51 -> 0 | AN51: =SUMIFS(Permissions!$G$2:$G$3000,Permissions!$B$2:$B$3000,$A51,Permissions!$I$2:$I$3000,"Expired – not started",Permissions!$R$2:$R$3000,"Yes") -> 0 | AO51: =SUMIFS(Permissions!$G$2:$G$3000,Permissions!$B$2:$B$3000,$A51,Permissions!$I$2:$I$3000,"In planning",Permissions!$R$2:$R$3000,"Yes") -> 0 | AP51: =IF(R51="",0,MAX(R51-AM51,0)) -> 7 | AQ51: =AM51+AP51 -> 7 | AR51: =SUMIFS(Permissions!$L$2:$L$3000,Permissions!$B$2:$B$3000,$A51,Permissions!$R$2:$R$3000,"Yes",Permissions!$I$2:$I$3000,"<>Expired – not started",Permissions!$I$2:$I$3000,"<>In planning") -> 0 | AS51: =AQ51-AR51 -> 7 | AT51: =SUMIFS(Permissions!$AJ$2:$AJ$3000,Permissions!$B$2:$B$3000,$A51,Permissions!$R$2:$R$3000,"Yes") -> 0 | AU51: =SUMIFS(Permissions!$AK$2:$AK$3000,Permissions!$B$2:$B$3000,$A51,Permissions!$R$2:$R$3000,"Yes") -> 0 | AV51: =SUMIFS(Permissions!$AL$2:$AL$3000,Permissions!$B$2:$B$3000,$A51,Permissions!$R$2:$R$3000,"Yes") -> 0 | AW51: =SUMIFS(Permissions!$AM$2:$AM$3000,Permissions!$B$2:$B$3000,$A51,Permissions!$R$2:$R$3000,"Yes") -> 0 | AX51: =SUMIFS(Permissions!$AN$2:$AN$3000,Permissions!$B$2:$B$3000,$A51,Permissions!$R$2:$R$3000,"Yes") -> 0 | AY51: =SUMIFS(Permissions!$AO$2:$AO$3000,Permissions!$B$2:$B$3000,$A51,Permissions!$R$2:$R$3000,"Yes") -> 0 | AZ51: =COUNTIFS(Permissions!$B$2:$B$3000,$A51,Permissions!$R$2:$R$3000,"Yes") -> 0 | BA51: =SUMIFS(Permissions!$M$2:$M$3000,Permissions!$B$2:$B$3000,$A51,Permissions!$R$2:$R$3000,"Yes") -> 0 | BB51: =SUMIFS(Permissions!$O$2:$O$3000,Permissions!$B$2:$B$3000,$A51,Permissions!$R$2:$R$3000,"Yes") -> 0 | BC51: =IF(AND(AM51>0,AR51>=AM51,AP51=0),"Finished",IF(AR51>0,"Partly built",IF(AM51>0,"Consented – not built","No consent"))) -> No consent | BD51: =IF(AND(R51<>"",AM51>1.1*R51),"Consented above capacity",IF(AND(LEFT(B51,8)="Planning",AZ51=0),"Consent parcel with no permission",IF(COUNTIF($A$2:$A$3000,$A51)>1,"Duplicate parcel_id","")))
A52: CITY-86 | B52: Council audit | C52: City | D52: City Centre | E52: City neighbourhood | F52: 1 | G52: Inside catchment | H52: 86 | I52: City Centre | J52: LIMERICK CITY WEST LEA-7 | K52: City Centre | L52: Private | M52: City C | N52: Brownfield | O52: 100+ | P52: 0.676 | Q52: 0.676 | R52: 68 | S52: Council estimate (area × density band) | T52: 68 | X52: City centre | Y52: 101 | Z52: 101 homes/ha = median of 6 permitted Limerick schemes of 10+ homes in city centre; applied to developable for density_estimate_units only | AB52: 11 | AC52: 0 | AD52: Undeveloped/Permission Sought | AE52: Unchanged | AF52: 2026-10-11 | AH52: =IF(R52="",AM52,R52) -> 68 | AI52: =SUMIFS(Permissions!$G$2:$G$3000,Permissions!$B$2:$B$3000,$A52,Permissions!$I$2:$I$3000,"Complete",Permissions!$R$2:$R$3000,"Yes") -> 0 | AJ52: =SUMIFS(Permissions!$G$2:$G$3000,Permissions!$B$2:$B$3000,$A52,Permissions!$I$2:$I$3000,"Under construction",Permissions!$R$2:$R$3000,"Yes") -> 0 | AK52: =SUMIFS(Permissions!$G$2:$G$3000,Permissions!$B$2:$B$3000,$A52,Permissions!$I$2:$I$3000,"Permitted – not started",Permissions!$R$2:$R$3000,"Yes") -> 0 | AL52: =SUMIFS(Permissions!$G$2:$G$3000,Permissions!$B$2:$B$3000,$A52,Permissions!$I$2:$I$3000,"Stalled",Permissions!$R$2:$R$3000,"Yes") -> 0 | AM52: =AI52+AJ52+AK52+AL52 -> 0 | AN52: =SUMIFS(Permissions!$G$2:$G$3000,Permissions!$B$2:$B$3000,$A52,Permissions!$I$2:$I$3000,"Expired – not started",Permissions!$R$2:$R$3000,"Yes") -> 0 | AO52: =SUMIFS(Permissions!$G$2:$G$3000,Permissions!$B$2:$B$3000,$A52,Permissions!$I$2:$I$3000,"In planning",Permissions!$R$2:$R$3000,"Yes") -> 0 | AP52: =IF(R52="",0,MAX(R52-AM52,0)) -> 68 | AQ52: =AM52+AP52 -> 68 | AR52: =SUMIFS(Permissions!$L$2:$L$3000,Permissions!$B$2:$B$3000,$A52,Permissions!$R$2:$R$3000,"Yes",Permissions!$I$2:$I$3000,"<>Expired – not started",Permissions!$I$2:$I$3000,"<>In planning") -> 0 | AS52: =AQ52-AR52 -> 68 | AT52: =SUMIFS(Permissions!$AJ$2:$AJ$3000,Permissions!$B$2:$B$3000,$A52,Permissions!$R$2:$R$3000,"Yes") -> 0 | AU52: =SUMIFS(Permissions!$AK$2:$AK$3000,Permissions!$B$2:$B$3000,$A52,Permissions!$R$2:$R$3000,"Yes") -> 0 | AV52: =SUMIFS(Permissions!$AL$2:$AL$3000,Permissions!$B$2:$B$3000,$A52,Permissions!$R$2:$R$3000,"Yes") -> 0 | AW52: =SUMIFS(Permissions!$AM$2:$AM$3000,Permissions!$B$2:$B$3000,$A52,Permissions!$R$2:$R$3000,"Yes") -> 0 | AX52: =SUMIFS(Permissions!$AN$2:$AN$3000,Permissions!$B$2:$B$3000,$A52,Permissions!$R$2:$R$3000,"Yes") -> 0 | AY52: =SUMIFS(Permissions!$AO$2:$AO$3000,Permissions!$B$2:$B$3000,$A52,Permissions!$R$2:$R$3000,"Yes") -> 0 | AZ52: =COUNTIFS(Permissions!$B$2:$B$3000,$A52,Permissions!$R$2:$R$3000,"Yes") -> 0 | BA52: =SUMIFS(Permissions!$M$2:$M$3000,Permissions!$B$2:$B$3000,$A52,Permissions!$R$2:$R$3000,"Yes") -> 0 | BB52: =SUMIFS(Permissions!$O$2:$O$3000,Permissions!$B$2:$B$3000,$A52,Permissions!$R$2:$R$3000,"Yes") -> 0 | BC52: =IF(AND(AM52>0,AR52>=AM52,AP52=0),"Finished",IF(AR52>0,"Partly built",IF(AM52>0,"Consented – not built","No consent"))) -> No consent | BD52: =IF(AND(R52<>"",AM52>1.1*R52),"Consented above capacity",IF(AND(LEFT(B52,8)="Planning",AZ52=0),"Consent parcel with no permission",IF(COUNTIF($A$2:$A$3000,$A52)>1,"Duplicate parcel_id","")))
A53: CITY-87 | B53: Council audit | C53: City | D53: City Centre | E53: City neighbourhood | F53: 1 | G53: Inside catchment | H53: 87 | I53: City Centre | J53: LIMERICK CITY WEST LEA-7 | K53: City Centre | L53: Private | M53: City C | N53: Brownfield | O53: 100+ | P53: 0.136 | Q53: 0.137 | R53: 14 | S53: Council estimate (area × density band) | T53: 14 | X53: City centre | Y53: 101 | Z53: 101 homes/ha = median of 6 permitted Limerick schemes of 10+ homes in city centre; applied to developable for density_estimate_units only | AB53: 0 | AC53: 0 | AD53: Undeveloped/Permission Sought | AE53: Unchanged | AF53: 2026-10-11 | AH53: =IF(R53="",AM53,R53) -> 14 | AI53: =SUMIFS(Permissions!$G$2:$G$3000,Permissions!$B$2:$B$3000,$A53,Permissions!$I$2:$I$3000,"Complete",Permissions!$R$2:$R$3000,"Yes") -> 0 | AJ53: =SUMIFS(Permissions!$G$2:$G$3000,Permissions!$B$2:$B$3000,$A53,Permissions!$I$2:$I$3000,"Under construction",Permissions!$R$2:$R$3000,"Yes") -> 0 | AK53: =SUMIFS(Permissions!$G$2:$G$3000,Permissions!$B$2:$B$3000,$A53,Permissions!$I$2:$I$3000,"Permitted – not started",Permissions!$R$2:$R$3000,"Yes") -> 0 | AL53: =SUMIFS(Permissions!$G$2:$G$3000,Permissions!$B$2:$B$3000,$A53,Permissions!$I$2:$I$3000,"Stalled",Permissions!$R$2:$R$3000,"Yes") -> 0 | AM53: =AI53+AJ53+AK53+AL53 -> 0 | AN53: =SUMIFS(Permissions!$G$2:$G$3000,Permissions!$B$2:$B$3000,$A53,Permissions!$I$2:$I$3000,"Expired – not started",Permissions!$R$2:$R$3000,"Yes") -> 0 | AO53: =SUMIFS(Permissions!$G$2:$G$3000,Permissions!$B$2:$B$3000,$A53,Permissions!$I$2:$I$3000,"In planning",Permissions!$R$2:$R$3000,"Yes") -> 0 | AP53: =IF(R53="",0,MAX(R53-AM53,0)) -> 14 | AQ53: =AM53+AP53 -> 14 | AR53: =SUMIFS(Permissions!$L$2:$L$3000,Permissions!$B$2:$B$3000,$A53,Permissions!$R$2:$R$3000,"Yes",Permissions!$I$2:$I$3000,"<>Expired – not started",Permissions!$I$2:$I$3000,"<>In planning") -> 0 | AS53: =AQ53-AR53 -> 14 | AT53: =SUMIFS(Permissions!$AJ$2:$AJ$3000,Permissions!$B$2:$B$3000,$A53,Permissions!$R$2:$R$3000,"Yes") -> 0 | AU53: =SUMIFS(Permissions!$AK$2:$AK$3000,Permissions!$B$2:$B$3000,$A53,Permissions!$R$2:$R$3000,"Yes") -> 0 | AV53: =SUMIFS(Permissions!$AL$2:$AL$3000,Permissions!$B$2:$B$3000,$A53,Permissions!$R$2:$R$3000,"Yes") -> 0 | AW53: =SUMIFS(Permissions!$AM$2:$AM$3000,Permissions!$B$2:$B$3000,$A53,Permissions!$R$2:$R$3000,"Yes") -> 0 | AX53: =SUMIFS(Permissions!$AN$2:$AN$3000,Permissions!$B$2:$B$3000,$A53,Permissions!$R$2:$R$3000,"Yes") -> 0 | AY53: =SUMIFS(Permissions!$AO$2:$AO$3000,Permissions!$B$2:$B$3000,$A53,Permissions!$R$2:$R$3000,"Yes") -> 0 | AZ53: =COUNTIFS(Permissions!$B$2:$B$3000,$A53,Permissions!$R$2:$R$3000,"Yes") -> 0 | BA53: =SUMIFS(Permissions!$M$2:$M$3000,Permissions!$B$2:$B$3000,$A53,Permissions!$R$2:$R$3000,"Yes") -> 0 | BB53: =SUMIFS(Permissions!$O$2:$O$3000,Permissions!$B$2:$B$3000,$A53,Permissions!$R$2:$R$3000,"Yes") -> 0 | BC53: =IF(AND(AM53>0,AR53>=AM53,AP53=0),"Finished",IF(AR53>0,"Partly built",IF(AM53>0,"Consented – not built","No consent"))) -> No consent | BD53: =IF(AND(R53<>"",AM53>1.1*R53),"Consented above capacity",IF(AND(LEFT(B53,8)="Planning",AZ53=0),"Consent parcel with no permission",IF(COUNTIF($A$2:$A$3000,$A53)>1,"Duplicate parcel_id","")))
A54: CITY-88 | B54: Council audit | C54: City | D54: City Centre | E54: City neighbourhood | F54: 1 | G54: Inside catchment | H54: 88 | I54: City Centre | J54: LIMERICK CITY WEST LEA-7 | K54: City Centre | L54: Unknown | M54: City Centre | N54: Brownfield | O54: 100+ | P54: 0.348 | Q54: 0.349 | R54: 35 | S54: Council estimate (area × density band) | T54: 35 | X54: City centre | Y54: 101 | Z54: 101 homes/ha = median of 6 permitted Limerick schemes of 10+ homes in city centre; applied to developable for density_estimate_units only | AB54: 9 | AC54: 0 | AD54: Undeveloped/Permission Sought | AE54: Unchanged | AF54: 2026-10-11 | AH54: =IF(R54="",AM54,R54) -> 35 | AI54: =SUMIFS(Permissions!$G$2:$G$3000,Permissions!$B$2:$B$3000,$A54,Permissions!$I$2:$I$3000,"Complete",Permissions!$R$2:$R$3000,"Yes") -> 0 | AJ54: =SUMIFS(Permissions!$G$2:$G$3000,Permissions!$B$2:$B$3000,$A54,Permissions!$I$2:$I$3000,"Under construction",Permissions!$R$2:$R$3000,"Yes") -> 0 | AK54: =SUMIFS(Permissions!$G$2:$G$3000,Permissions!$B$2:$B$3000,$A54,Permissions!$I$2:$I$3000,"Permitted – not started",Permissions!$R$2:$R$3000,"Yes") -> 0 | AL54: =SUMIFS(Permissions!$G$2:$G$3000,Permissions!$B$2:$B$3000,$A54,Permissions!$I$2:$I$3000,"Stalled",Permissions!$R$2:$R$3000,"Yes") -> 0 | AM54: =AI54+AJ54+AK54+AL54 -> 0 | AN54: =SUMIFS(Permissions!$G$2:$G$3000,Permissions!$B$2:$B$3000,$A54,Permissions!$I$2:$I$3000,"Expired – not started",Permissions!$R$2:$R$3000,"Yes") -> 0 | AO54: =SUMIFS(Permissions!$G$2:$G$3000,Permissions!$B$2:$B$3000,$A54,Permissions!$I$2:$I$3000,"In planning",Permissions!$R$2:$R$3000,"Yes") -> 0 | AP54: =IF(R54="",0,MAX(R54-AM54,0)) -> 35 | AQ54: =AM54+AP54 -> 35 | AR54: =SUMIFS(Permissions!$L$2:$L$3000,Permissions!$B$2:$B$3000,$A54,Permissions!$R$2:$R$3000,"Yes",Permissions!$I$2:$I$3000,"<>Expired – not started",Permissions!$I$2:$I$3000,"<>In planning") -> 0 | AS54: =AQ54-AR54 -> 35 | AT54: =SUMIFS(Permissions!$AJ$2:$AJ$3000,Permissions!$B$2:$B$3000,$A54,Permissions!$R$2:$R$3000,"Yes") -> 0 | AU54: =SUMIFS(Permissions!$AK$2:$AK$3000,Permissions!$B$2:$B$3000,$A54,Permissions!$R$2:$R$3000,"Yes") -> 0 | AV54: =SUMIFS(Permissions!$AL$2:$AL$3000,Permissions!$B$2:$B$3000,$A54,Permissions!$R$2:$R$3000,"Yes") -> 0 | AW54: =SUMIFS(Permissions!$AM$2:$AM$3000,Permissions!$B$2:$B$3000,$A54,Permissions!$R$2:$R$3000,"Yes") -> 0 | AX54: =SUMIFS(Permissions!$AN$2:$AN$3000,Permissions!$B$2:$B$3000,$A54,Permissions!$R$2:$R$3000,"Yes") -> 0 | AY54: =SUMIFS(Permissions!$AO$2:$AO$3000,Permissions!$B$2:$B$3000,$A54,Permissions!$R$2:$R$3000,"Yes") -> 0 | AZ54: =COUNTIFS(Permissions!$B$2:$B$3000,$A54,Permissions!$R$2:$R$3000,"Yes") -> 0 | BA54: =SUMIFS(Permissions!$M$2:$M$3000,Permissions!$B$2:$B$3000,$A54,Permissions!$R$2:$R$3000,"Yes") -> 0 | BB54: =SUMIFS(Permissions!$O$2:$O$3000,Permissions!$B$2:$B$3000,$A54,Permissions!$R$2:$R$3000,"Yes") -> 0 | BC54: =IF(AND(AM54>0,AR54>=AM54,AP54=0),"Finished",IF(AR54>0,"Partly built",IF(AM54>0,"Consented – not built","No consent"))) -> No consent | BD54: =IF(AND(R54<>"",AM54>1.1*R54),"Consented above capacity",IF(AND(LEFT(B54,8)="Planning",AZ54=0),"Consent parcel with no permission",IF(COUNTIF($A$2:$A$3000,$A54)>1,"Duplicate parcel_id","")))
A55: CITY-89 | B55: Council audit | C55: City | D55: City Centre | E55: City neighbourhood | F55: 1 | G55: Inside catchment | H55: 89 | I55: City Centre | J55: LIMERICK CITY WEST LEA-7 | K55: City Centre | L55: Private | M55: City C | N55: Infill | O55: 100+ | P55: 0.082 | Q55: 0.09 | R55: 8 | S55: Estimate (council audit recorded no capacity): developable area x density | T55: 8 | X55: City centre | Y55: 101 | Z55: 101 homes/ha = median of 6 permitted Limerick schemes of 10+ homes in city centre; developable share 0.91 where none recorded | AB55: 0 | AC55: 0 | AD55: Undeveloped/Permission Sought | AE55: Unchanged | AF55: 2026-10-11 | AH55: =IF(R55="",AM55,R55) -> 8 | AI55: =SUMIFS(Permissions!$G$2:$G$3000,Permissions!$B$2:$B$3000,$A55,Permissions!$I$2:$I$3000,"Complete",Permissions!$R$2:$R$3000,"Yes") -> 0 | AJ55: =SUMIFS(Permissions!$G$2:$G$3000,Permissions!$B$2:$B$3000,$A55,Permissions!$I$2:$I$3000,"Under construction",Permissions!$R$2:$R$3000,"Yes") -> 0 | AK55: =SUMIFS(Permissions!$G$2:$G$3000,Permissions!$B$2:$B$3000,$A55,Permissions!$I$2:$I$3000,"Permitted – not started",Permissions!$R$2:$R$3000,"Yes") -> 0 | AL55: =SUMIFS(Permissions!$G$2:$G$3000,Permissions!$B$2:$B$3000,$A55,Permissions!$I$2:$I$3000,"Stalled",Permissions!$R$2:$R$3000,"Yes") -> 0 | AM55: =AI55+AJ55+AK55+AL55 -> 0 | AN55: =SUMIFS(Permissions!$G$2:$G$3000,Permissions!$B$2:$B$3000,$A55,Permissions!$I$2:$I$3000,"Expired – not started",Permissions!$R$2:$R$3000,"Yes") -> 0 | AO55: =SUMIFS(Permissions!$G$2:$G$3000,Permissions!$B$2:$B$3000,$A55,Permissions!$I$2:$I$3000,"In planning",Permissions!$R$2:$R$3000,"Yes") -> 0 | AP55: =IF(R55="",0,MAX(R55-AM55,0)) -> 8 | AQ55: =AM55+AP55 -> 8 | AR55: =SUMIFS(Permissions!$L$2:$L$3000,Permissions!$B$2:$B$3000,$A55,Permissions!$R$2:$R$3000,"Yes",Permissions!$I$2:$I$3000,"<>Expired – not started",Permissions!$I$2:$I$3000,"<>In planning") -> 0 | AS55: =AQ55-AR55 -> 8 | AT55: =SUMIFS(Permissions!$AJ$2:$AJ$3000,Permissions!$B$2:$B$3000,$A55,Permissions!$R$2:$R$3000,"Yes") -> 0 | AU55: =SUMIFS(Permissions!$AK$2:$AK$3000,Permissions!$B$2:$B$3000,$A55,Permissions!$R$2:$R$3000,"Yes") -> 0 | AV55: =SUMIFS(Permissions!$AL$2:$AL$3000,Permissions!$B$2:$B$3000,$A55,Permissions!$R$2:$R$3000,"Yes") -> 0 | AW55: =SUMIFS(Permissions!$AM$2:$AM$3000,Permissions!$B$2:$B$3000,$A55,Permissions!$R$2:$R$3000,"Yes") -> 0 | AX55: =SUMIFS(Permissions!$AN$2:$AN$3000,Permissions!$B$2:$B$3000,$A55,Permissions!$R$2:$R$3000,"Yes") -> 0 | AY55: =SUMIFS(Permissions!$AO$2:$AO$3000,Permissions!$B$2:$B$3000,$A55,Permissions!$R$2:$R$3000,"Yes") -> 0 | AZ55: =COUNTIFS(Permissions!$B$2:$B$3000,$A55,Permissions!$R$2:$R$3000,"Yes") -> 0 | BA55: =SUMIFS(Permissions!$M$2:$M$3000,Permissions!$B$2:$B$3000,$A55,Permissions!$R$2:$R$3000,"Yes") -> 0 | BB55: =SUMIFS(Permissions!$O$2:$O$3000,Permissions!$B$2:$B$3000,$A55,Permissions!$R$2:$R$3000,"Yes") -> 0 | BC55: =IF(AND(AM55>0,AR55>=AM55,AP55=0),"Finished",IF(AR55>0,"Partly built",IF(AM55>0,"Consented – not built","No consent"))) -> No consent | BD55: =IF(AND(R55<>"",AM55>1.1*R55),"Consented above capacity",IF(AND(LEFT(B55,8)="Planning",AZ55=0),"Consent parcel with no permission",IF(COUNTIF($A$2:$A$3000,$A55)>1,"Duplicate parcel_id","")))
A56: CITY-91 | B56: Council audit | C56: City | D56: City Centre | E56: City neighbourhood | F56: 1 | G56: Inside catchment | H56: 91 | I56: City Centre | J56: LIMERICK CITY WEST LEA-7 | K56: Dock Rd | L56: Council | M56: City C | N56: Brownfield | O56: 100+ | P56: 1.38 | Q56: 1.38 | R56: 285 | S56: Council estimate (area × density band) | T56: 139 | X56: City centre | Y56: 101 | Z56: 101 homes/ha = median of 6 permitted Limerick schemes of 10+ homes in city centre; applied to developable for density_estimate_units only | AB56: 0 | AC56: 0 | AD56: Undeveloped/Permission Sought | AE56: Unchanged | AF56: 2026-10-11 | AH56: =IF(R56="",AM56,R56) -> 285 | AI56: =SUMIFS(Permissions!$G$2:$G$3000,Permissions!$B$2:$B$3000,$A56,Permissions!$I$2:$I$3000,"Complete",Permissions!$R$2:$R$3000,"Yes") -> 0 | AJ56: =SUMIFS(Permissions!$G$2:$G$3000,Permissions!$B$2:$B$3000,$A56,Permissions!$I$2:$I$3000,"Under construction",Permissions!$R$2:$R$3000,"Yes") -> 0 | AK56: =SUMIFS(Permissions!$G$2:$G$3000,Permissions!$B$2:$B$3000,$A56,Permissions!$I$2:$I$3000,"Permitted – not started",Permissions!$R$2:$R$3000,"Yes") -> 285 | AL56: =SUMIFS(Permissions!$G$2:$G$3000,Permissions!$B$2:$B$3000,$A56,Permissions!$I$2:$I$3000,"Stalled",Permissions!$R$2:$R$3000,"Yes") -> 0 | AM56: =AI56+AJ56+AK56+AL56 -> 285 | AN56: =SUMIFS(Permissions!$G$2:$G$3000,Permissions!$B$2:$B$3000,$A56,Permissions!$I$2:$I$3000,"Expired – not started",Permissions!$R$2:$R$3000,"Yes") -> 0 | AO56: =SUMIFS(Permissions!$G$2:$G$3000,Permissions!$B$2:$B$3000,$A56,Permissions!$I$2:$I$3000,"In planning",Permissions!$R$2:$R$3000,"Yes") -> 0 | AP56: =IF(R56="",0,MAX(R56-AM56,0)) -> 0 | AQ56: =AM56+AP56 -> 285 | AR56: =SUMIFS(Permissions!$L$2:$L$3000,Permissions!$B$2:$B$3000,$A56,Permissions!$R$2:$R$3000,"Yes",Permissions!$I$2:$I$3000,"<>Expired – not started",Permissions!$I$2:$I$3000,"<>In planning") -> 0 | AS56: =AQ56-AR56 -> 285 | AT56: =SUMIFS(Permissions!$AJ$2:$AJ$3000,Permissions!$B$2:$B$3000,$A56,Permissions!$R$2:$R$3000,"Yes") -> 0 | AU56: =SUMIFS(Permissions!$AK$2:$AK$3000,Permissions!$B$2:$B$3000,$A56,Permissions!$R$2:$R$3000,"Yes") -> 0 | AV56: =SUMIFS(Permissions!$AL$2:$AL$3000,Permissions!$B$2:$B$3000,$A56,Permissions!$R$2:$R$3000,"Yes") -> 10.1 | AW56: =SUMIFS(Permissions!$AM$2:$AM$3000,Permissions!$B$2:$B$3000,$A56,Permissions!$R$2:$R$3000,"Yes") -> 61 | AX56: =SUMIFS(Permissions!$AN$2:$AN$3000,Permissions!$B$2:$B$3000,$A56,Permissions!$R$2:$R$3000,"Yes") -> 61 | AY56: =SUMIFS(Permissions!$AO$2:$AO$3000,Permissions!$B$2:$B$3000,$A56,Permissions!$R$2:$R$3000,"Yes") -> 152.9 | AZ56: =COUNTIFS(Permissions!$B$2:$B$3000,$A56,Permissions!$R$2:$R$3000,"Yes") -> 1 | BA56: =SUMIFS(Permissions!$M$2:$M$3000,Permissions!$B$2:$B$3000,$A56,Permissions!$R$2:$R$3000,"Yes") -> 0 | BB56: =SUMIFS(Permissions!$O$2:$O$3000,Permissions!$B$2:$B$3000,$A56,Permissions!$R$2:$R$3000,"Yes") -> 0 | BC56: =IF(AND(AM56>0,AR56>=AM56,AP56=0),"Finished",IF(AR56>0,"Partly built",IF(AM56>0,"Consented – not built","No consent"))) -> Consented – not built | BD56: =IF(AND(R56<>"",AM56>1.1*R56),"Consented above capacity",IF(AND(LEFT(B56,8)="Planning",AZ56=0),"Consent parcel with no permission",IF(COUNTIF($A$2:$A$3000,$A56)>1,"Duplicate parcel_id","")))
A57: CITY-92 | B57: Council audit | C57: City | D57: City Centre | E57: City neighbourhood | F57: 1 | G57: Inside catchment | H57: 92 | I57: City Centre | J57: LIMERICK CITY WEST LEA-7 | K57: City Centre | L57: Private | M57: City C | N57: Infill | O57: 100+ | P57: 0.072 | Q57: 0.079 | R57: 7 | S57: Estimate (council audit recorded no capacity): developable area x density | T57: 7 | X57: City centre | Y57: 101 | Z57: 101 homes/ha = median of 6 permitted Limerick schemes of 10+ homes in city centre; developable share 0.91 where none recorded | AB57: 0 | AC57: 0 | AD57: Undeveloped/Permission Sought | AE57: Unchanged | AF57: 2026-10-11 | AH57: =IF(R57="",AM57,R57) -> 7 | AI57: =SUMIFS(Permissions!$G$2:$G$3000,Permissions!$B$2:$B$3000,$A57,Permissions!$I$2:$I$3000,"Complete",Permissions!$R$2:$R$3000,"Yes") -> 0 | AJ57: =SUMIFS(Permissions!$G$2:$G$3000,Permissions!$B$2:$B$3000,$A57,Permissions!$I$2:$I$3000,"Under construction",Permissions!$R$2:$R$3000,"Yes") -> 0 | AK57: =SUMIFS(Permissions!$G$2:$G$3000,Permissions!$B$2:$B$3000,$A57,Permissions!$I$2:$I$3000,"Permitted – not started",Permissions!$R$2:$R$3000,"Yes") -> 0 | AL57: =SUMIFS(Permissions!$G$2:$G$3000,Permissions!$B$2:$B$3000,$A57,Permissions!$I$2:$I$3000,"Stalled",Permissions!$R$2:$R$3000,"Yes") -> 0 | AM57: =AI57+AJ57+AK57+AL57 -> 0 | AN57: =SUMIFS(Permissions!$G$2:$G$3000,Permissions!$B$2:$B$3000,$A57,Permissions!$I$2:$I$3000,"Expired – not started",Permissions!$R$2:$R$3000,"Yes") -> 0 | AO57: =SUMIFS(Permissions!$G$2:$G$3000,Permissions!$B$2:$B$3000,$A57,Permissions!$I$2:$I$3000,"In planning",Permissions!$R$2:$R$3000,"Yes") -> 0 | AP57: =IF(R57="",0,MAX(R57-AM57,0)) -> 7 | AQ57: =AM57+AP57 -> 7 | AR57: =SUMIFS(Permissions!$L$2:$L$3000,Permissions!$B$2:$B$3000,$A57,Permissions!$R$2:$R$3000,"Yes",Permissions!$I$2:$I$3000,"<>Expired – not started",Permissions!$I$2:$I$3000,"<>In planning") -> 0 | AS57: =AQ57-AR57 -> 7 | AT57: =SUMIFS(Permissions!$AJ$2:$AJ$3000,Permissions!$B$2:$B$3000,$A57,Permissions!$R$2:$R$3000,"Yes") -> 0 | AU57: =SUMIFS(Permissions!$AK$2:$AK$3000,Permissions!$B$2:$B$3000,$A57,Permissions!$R$2:$R$3000,"Yes") -> 0 | AV57: =SUMIFS(Permissions!$AL$2:$AL$3000,Permissions!$B$2:$B$3000,$A57,Permissions!$R$2:$R$3000,"Yes") -> 0 | AW57: =SUMIFS(Permissions!$AM$2:$AM$3000,Permissions!$B$2:$B$3000,$A57,Permissions!$R$2:$R$3000,"Yes") -> 0 | AX57: =SUMIFS(Permissions!$AN$2:$AN$3000,Permissions!$B$2:$B$3000,$A57,Permissions!$R$2:$R$3000,"Yes") -> 0 | AY57: =SUMIFS(Permissions!$AO$2:$AO$3000,Permissions!$B$2:$B$3000,$A57,Permissions!$R$2:$R$3000,"Yes") -> 0 | AZ57: =COUNTIFS(Permissions!$B$2:$B$3000,$A57,Permissions!$R$2:$R$3000,"Yes") -> 0 | BA57: =SUMIFS(Permissions!$M$2:$M$3000,Permissions!$B$2:$B$3000,$A57,Permissions!$R$2:$R$3000,"Yes") -> 0 | BB57: =SUMIFS(Permissions!$O$2:$O$3000,Permissions!$B$2:$B$3000,$A57,Permissions!$R$2:$R$3000,"Yes") -> 0 | BC57: =IF(AND(AM57>0,AR57>=AM57,AP57=0),"Finished",IF(AR57>0,"Partly built",IF(AM57>0,"Consented – not built","No consent"))) -> No consent | BD57: =IF(AND(R57<>"",AM57>1.1*R57),"Consented above capacity",IF(AND(LEFT(B57,8)="Planning",AZ57=0),"Consent parcel with no permission",IF(COUNTIF($A$2:$A$3000,$A57)>1,"Duplicate parcel_id","")))
A58: CITY-93 | B58: Council audit | C58: City | D58: City Centre | E58: City neighbourhood | F58: 1 | G58: Inside catchment | H58: 93 | I58: City Centre | J58: LIMERICK CITY WEST LEA-7 | K58: City Centre | L58: Private | M58: City C | N58: Infill | O58: 100+ | P58: 0.052 | Q58: 0.057 | R58: 5 | S58: Estimate (council audit recorded no capacity): developable area x density | T58: 5 | X58: City centre | Y58: 101 | Z58: 101 homes/ha = median of 6 permitted Limerick schemes of 10+ homes in city centre; developable share 0.91 where none recorded | AB58: 0 | AC58: 0 | AD58: Undeveloped/Permission Sought | AE58: Unchanged | AF58: 2026-10-11 | AH58: =IF(R58="",AM58,R58) -> 5 | AI58: =SUMIFS(Permissions!$G$2:$G$3000,Permissions!$B$2:$B$3000,$A58,Permissions!$I$2:$I$3000,"Complete",Permissions!$R$2:$R$3000,"Yes") -> 0 | AJ58: =SUMIFS(Permissions!$G$2:$G$3000,Permissions!$B$2:$B$3000,$A58,Permissions!$I$2:$I$3000,"Under construction",Permissions!$R$2:$R$3000,"Yes") -> 0 | AK58: =SUMIFS(Permissions!$G$2:$G$3000,Permissions!$B$2:$B$3000,$A58,Permissions!$I$2:$I$3000,"Permitted – not started",Permissions!$R$2:$R$3000,"Yes") -> 0 | AL58: =SUMIFS(Permissions!$G$2:$G$3000,Permissions!$B$2:$B$3000,$A58,Permissions!$I$2:$I$3000,"Stalled",Permissions!$R$2:$R$3000,"Yes") -> 0 | AM58: =AI58+AJ58+AK58+AL58 -> 0 | AN58: =SUMIFS(Permissions!$G$2:$G$3000,Permissions!$B$2:$B$3000,$A58,Permissions!$I$2:$I$3000,"Expired – not started",Permissions!$R$2:$R$3000,"Yes") -> 0 | AO58: =SUMIFS(Permissions!$G$2:$G$3000,Permissions!$B$2:$B$3000,$A58,Permissions!$I$2:$I$3000,"In planning",Permissions!$R$2:$R$3000,"Yes") -> 0 | AP58: =IF(R58="",0,MAX(R58-AM58,0)) -> 5 | AQ58: =AM58+AP58 -> 5 | AR58: =SUMIFS(Permissions!$L$2:$L$3000,Permissions!$B$2:$B$3000,$A58,Permissions!$R$2:$R$3000,"Yes",Permissions!$I$2:$I$3000,"<>Expired – not started",Permissions!$I$2:$I$3000,"<>In planning") -> 0 | AS58: =AQ58-AR58 -> 5 | AT58: =SUMIFS(Permissions!$AJ$2:$AJ$3000,Permissions!$B$2:$B$3000,$A58,Permissions!$R$2:$R$3000,"Yes") -> 0 | AU58: =SUMIFS(Permissions!$AK$2:$AK$3000,Permissions!$B$2:$B$3000,$A58,Permissions!$R$2:$R$3000,"Yes") -> 0 | AV58: =SUMIFS(Permissions!$AL$2:$AL$3000,Permissions!$B$2:$B$3000,$A58,Permissions!$R$2:$R$3000,"Yes") -> 0 | AW58: =SUMIFS(Permissions!$AM$2:$AM$3000,Permissions!$B$2:$B$3000,$A58,Permissions!$R$2:$R$3000,"Yes") -> 0 | AX58: =SUMIFS(Permissions!$AN$2:$AN$3000,Permissions!$B$2:$B$3000,$A58,Permissions!$R$2:$R$3000,"Yes") -> 0 | AY58: =SUMIFS(Permissions!$AO$2:$AO$3000,Permissions!$B$2:$B$3000,$A58,Permissions!$R$2:$R$3000,"Yes") -> 0 | AZ58: =COUNTIFS(Permissions!$B$2:$B$3000,$A58,Permissions!$R$2:$R$3000,"Yes") -> 0 | BA58: =SUMIFS(Permissions!$M$2:$M$3000,Permissions!$B$2:$B$3000,$A58,Permissions!$R$2:$R$3000,"Yes") -> 0 | BB58: =SUMIFS(Permissions!$O$2:$O$3000,Permissions!$B$2:$B$3000,$A58,Permissions!$R$2:$R$3000,"Yes") -> 0 | BC58: =IF(AND(AM58>0,AR58>=AM58,AP58=0),"Finished",IF(AR58>0,"Partly built",IF(AM58>0,"Consented – not built","No consent"))) -> No consent | BD58: =IF(AND(R58<>"",AM58>1.1*R58),"Consented above capacity",IF(AND(LEFT(B58,8)="Planning",AZ58=0),"Consent parcel with no permission",IF(COUNTIF($A$2:$A$3000,$A58)>1,"Duplicate parcel_id","")))
A59: CITY-95 | B59: Council audit | C59: City | D59: City Centre | E59: City neighbourhood | F59: 1 | G59: Inside catchment | H59: 95 | I59: City Centre | J59: LIMERICK CITY WEST LEA-7 | K59: City Centre | L59: Private | M59: City C | N59: Infill | O59: 100+ | P59: 0.095 | Q59: 0.104 | R59: 10 | S59: Estimate (council audit recorded no capacity): developable area x density | T59: 10 | X59: City centre | Y59: 101 | Z59: 101 homes/ha = median of 6 permitted Limerick schemes of 10+ homes in city centre; developable share 0.91 where none recorded | AB59: 0 | AC59: 0 | AD59: Undeveloped/Permission Sought | AE59: Unchanged | AF59: 2026-10-11 | AH59: =IF(R59="",AM59,R59) -> 10 | AI59: =SUMIFS(Permissions!$G$2:$G$3000,Permissions!$B$2:$B$3000,$A59,Permissions!$I$2:$I$3000,"Complete",Permissions!$R$2:$R$3000,"Yes") -> 0 | AJ59: =SUMIFS(Permissions!$G$2:$G$3000,Permissions!$B$2:$B$3000,$A59,Permissions!$I$2:$I$3000,"Under construction",Permissions!$R$2:$R$3000,"Yes") -> 0 | AK59: =SUMIFS(Permissions!$G$2:$G$3000,Permissions!$B$2:$B$3000,$A59,Permissions!$I$2:$I$3000,"Permitted – not started",Permissions!$R$2:$R$3000,"Yes") -> 0 | AL59: =SUMIFS(Permissions!$G$2:$G$3000,Permissions!$B$2:$B$3000,$A59,Permissions!$I$2:$I$3000,"Stalled",Permissions!$R$2:$R$3000,"Yes") -> 0 | AM59: =AI59+AJ59+AK59+AL59 -> 0 | AN59: =SUMIFS(Permissions!$G$2:$G$3000,Permissions!$B$2:$B$3000,$A59,Permissions!$I$2:$I$3000,"Expired – not started",Permissions!$R$2:$R$3000,"Yes") -> 0 | AO59: =SUMIFS(Permissions!$G$2:$G$3000,Permissions!$B$2:$B$3000,$A59,Permissions!$I$2:$I$3000,"In planning",Permissions!$R$2:$R$3000,"Yes") -> 0 | AP59: =IF(R59="",0,MAX(R59-AM59,0)) -> 10 | AQ59: =AM59+AP59 -> 10 | AR59: =SUMIFS(Permissions!$L$2:$L$3000,Permissions!$B$2:$B$3000,$A59,Permissions!$R$2:$R$3000,"Yes",Permissions!$I$2:$I$3000,"<>Expired – not started",Permissions!$I$2:$I$3000,"<>In planning") -> 0 | AS59: =AQ59-AR59 -> 10 | AT59: =SUMIFS(Permissions!$AJ$2:$AJ$3000,Permissions!$B$2:$B$3000,$A59,Permissions!$R$2:$R$3000,"Yes") -> 0 | AU59: =SUMIFS(Permissions!$AK$2:$AK$3000,Permissions!$B$2:$B$3000,$A59,Permissions!$R$2:$R$3000,"Yes") -> 0 | AV59: =SUMIFS(Permissions!$AL$2:$AL$3000,Permissions!$B$2:$B$3000,$A59,Permissions!$R$2:$R$3000,"Yes") -> 0 | AW59: =SUMIFS(Permissions!$AM$2:$AM$3000,Permissions!$B$2:$B$3000,$A59,Permissions!$R$2:$R$3000,"Yes") -> 0 | AX59: =SUMIFS(Permissions!$AN$2:$AN$3000,Permissions!$B$2:$B$3000,$A59,Permissions!$R$2:$R$3000,"Yes") -> 0 | AY59: =SUMIFS(Permissions!$AO$2:$AO$3000,Permissions!$B$2:$B$3000,$A59,Permissions!$R$2:$R$3000,"Yes") -> 0 | AZ59: =COUNTIFS(Permissions!$B$2:$B$3000,$A59,Permissions!$R$2:$R$3000,"Yes") -> 0 | BA59: =SUMIFS(Permissions!$M$2:$M$3000,Permissions!$B$2:$B$3000,$A59,Permissions!$R$2:$R$3000,"Yes") -> 0 | BB59: =SUMIFS(Permissions!$O$2:$O$3000,Permissions!$B$2:$B$3000,$A59,Permissions!$R$2:$R$3000,"Yes") -> 0 | BC59: =IF(AND(AM59>0,AR59>=AM59,AP59=0),"Finished",IF(AR59>0,"Partly built",IF(AM59>0,"Consented – not built","No consent"))) -> No consent | BD59: =IF(AND(R59<>"",AM59>1.1*R59),"Consented above capacity",IF(AND(LEFT(B59,8)="Planning",AZ59=0),"Consent parcel with no permission",IF(COUNTIF($A$2:$A$3000,$A59)>1,"Duplicate parcel_id","")))
A60: CITY-97 | B60: Council audit | C60: City | D60: City Centre | E60: City neighbourhood | F60: 1 | G60: Inside catchment | H60: 97 | I60: City Centre | J60: LIMERICK CITY WEST LEA-7 | K60: City Centre | L60: Private | M60: City C | N60: Infill | O60: 100+ | P60: 0.056 | Q60: 0.061 | R60: 6 | S60: Estimate (council audit recorded no capacity): developable area x density | T60: 6 | X60: City centre | Y60: 101 | Z60: 101 homes/ha = median of 6 permitted Limerick schemes of 10+ homes in city centre; developable share 0.91 where none recorded | AB60: 0 | AC60: 0 | AD60: Undeveloped/Permission Sought | AE60: Unchanged | AF60: 2026-10-11 | AH60: =IF(R60="",AM60,R60) -> 6 | AI60: =SUMIFS(Permissions!$G$2:$G$3000,Permissions!$B$2:$B$3000,$A60,Permissions!$I$2:$I$3000,"Complete",Permissions!$R$2:$R$3000,"Yes") -> 0 | AJ60: =SUMIFS(Permissions!$G$2:$G$3000,Permissions!$B$2:$B$3000,$A60,Permissions!$I$2:$I$3000,"Under construction",Permissions!$R$2:$R$3000,"Yes") -> 0 | AK60: =SUMIFS(Permissions!$G$2:$G$3000,Permissions!$B$2:$B$3000,$A60,Permissions!$I$2:$I$3000,"Permitted – not started",Permissions!$R$2:$R$3000,"Yes") -> 0 | AL60: =SUMIFS(Permissions!$G$2:$G$3000,Permissions!$B$2:$B$3000,$A60,Permissions!$I$2:$I$3000,"Stalled",Permissions!$R$2:$R$3000,"Yes") -> 0 | AM60: =AI60+AJ60+AK60+AL60 -> 0 | AN60: =SUMIFS(Permissions!$G$2:$G$3000,Permissions!$B$2:$B$3000,$A60,Permissions!$I$2:$I$3000,"Expired – not started",Permissions!$R$2:$R$3000,"Yes") -> 0 | AO60: =SUMIFS(Permissions!$G$2:$G$3000,Permissions!$B$2:$B$3000,$A60,Permissions!$I$2:$I$3000,"In planning",Permissions!$R$2:$R$3000,"Yes") -> 0 | AP60: =IF(R60="",0,MAX(R60-AM60,0)) -> 6 | AQ60: =AM60+AP60 -> 6 | AR60: =SUMIFS(Permissions!$L$2:$L$3000,Permissions!$B$2:$B$3000,$A60,Permissions!$R$2:$R$3000,"Yes",Permissions!$I$2:$I$3000,"<>Expired – not started",Permissions!$I$2:$I$3000,"<>In planning") -> 0 | AS60: =AQ60-AR60 -> 6 | AT60: =SUMIFS(Permissions!$AJ$2:$AJ$3000,Permissions!$B$2:$B$3000,$A60,Permissions!$R$2:$R$3000,"Yes") -> 0 | AU60: =SUMIFS(Permissions!$AK$2:$AK$3000,Permissions!$B$2:$B$3000,$A60,Permissions!$R$2:$R$3000,"Yes") -> 0 | AV60: =SUMIFS(Permissions!$AL$2:$AL$3000,Permissions!$B$2:$B$3000,$A60,Permissions!$R$2:$R$3000,"Yes") -> 0 | AW60: =SUMIFS(Permissions!$AM$2:$AM$3000,Permissions!$B$2:$B$3000,$A60,Permissions!$R$2:$R$3000,"Yes") -> 0 | AX60: =SUMIFS(Permissions!$AN$2:$AN$3000,Permissions!$B$2:$B$3000,$A60,Permissions!$R$2:$R$3000,"Yes") -> 0 | AY60: =SUMIFS(Permissions!$AO$2:$AO$3000,Permissions!$B$2:$B$3000,$A60,Permissions!$R$2:$R$3000,"Yes") -> 0 | AZ60: =COUNTIFS(Permissions!$B$2:$B$3000,$A60,Permissions!$R$2:$R$3000,"Yes") -> 0 | BA60: =SUMIFS(Permissions!$M$2:$M$3000,Permissions!$B$2:$B$3000,$A60,Permissions!$R$2:$R$3000,"Yes") -> 0 | BB60: =SUMIFS(Permissions!$O$2:$O$3000,Permissions!$B$2:$B$3000,$A60,Permissions!$R$2:$R$3000,"Yes") -> 0 | BC60: =IF(AND(AM60>0,AR60>=AM60,AP60=0),"Finished",IF(AR60>0,"Partly built",IF(AM60>0,"Consented – not built","No consent"))) -> No consent | BD60: =IF(AND(R60<>"",AM60>1.1*R60),"Consented above capacity",IF(AND(LEFT(B60,8)="Planning",AZ60=0),"Consent parcel with no permission",IF(COUNTIF($A$2:$A$3000,$A60)>1,"Duplicate parcel_id","")))
A61: CITY-99 | B61: Council audit | C61: City | D61: City Centre | E61: City neighbourhood | F61: 1 | G61: Inside catchment | H61: 99 | I61: City Centre | J61: LIMERICK CITY WEST LEA-7 | K61: City Centre | L61: Private | M61: City C | N61: Infill | O61: 100+ | P61: 0.059 | Q61: 0.065 | R61: 6 | S61: Estimate (council audit recorded no capacity): developable area x density | T61: 6 | X61: City centre | Y61: 101 | Z61: 101 homes/ha = median of 6 permitted Limerick schemes of 10+ homes in city centre; developable share 0.91 where none recorded | AB61: 0 | AC61: 0 | AD61: Undeveloped/Permission Sought | AE61: Unchanged | AF61: 2026-10-11 | AH61: =IF(R61="",AM61,R61) -> 6 | AI61: =SUMIFS(Permissions!$G$2:$G$3000,Permissions!$B$2:$B$3000,$A61,Permissions!$I$2:$I$3000,"Complete",Permissions!$R$2:$R$3000,"Yes") -> 0 | AJ61: =SUMIFS(Permissions!$G$2:$G$3000,Permissions!$B$2:$B$3000,$A61,Permissions!$I$2:$I$3000,"Under construction",Permissions!$R$2:$R$3000,"Yes") -> 0 | AK61: =SUMIFS(Permissions!$G$2:$G$3000,Permissions!$B$2:$B$3000,$A61,Permissions!$I$2:$I$3000,"Permitted – not started",Permissions!$R$2:$R$3000,"Yes") -> 0 | AL61: =SUMIFS(Permissions!$G$2:$G$3000,Permissions!$B$2:$B$3000,$A61,Permissions!$I$2:$I$3000,"Stalled",Permissions!$R$2:$R$3000,"Yes") -> 0 | AM61: =AI61+AJ61+AK61+AL61 -> 0 | AN61: =SUMIFS(Permissions!$G$2:$G$3000,Permissions!$B$2:$B$3000,$A61,Permissions!$I$2:$I$3000,"Expired – not started",Permissions!$R$2:$R$3000,"Yes") -> 0 | AO61: =SUMIFS(Permissions!$G$2:$G$3000,Permissions!$B$2:$B$3000,$A61,Permissions!$I$2:$I$3000,"In planning",Permissions!$R$2:$R$3000,"Yes") -> 0 | AP61: =IF(R61="",0,MAX(R61-AM61,0)) -> 6 | AQ61: =AM61+AP61 -> 6 | AR61: =SUMIFS(Permissions!$L$2:$L$3000,Permissions!$B$2:$B$3000,$A61,Permissions!$R$2:$R$3000,"Yes",Permissions!$I$2:$I$3000,"<>Expired – not started",Permissions!$I$2:$I$3000,"<>In planning") -> 0 | AS61: =AQ61-AR61 -> 6 | AT61: =SUMIFS(Permissions!$AJ$2:$AJ$3000,Permissions!$B$2:$B$3000,$A61,Permissions!$R$2:$R$3000,"Yes") -> 0 | AU61: =SUMIFS(Permissions!$AK$2:$AK$3000,Permissions!$B$2:$B$3000,$A61,Permissions!$R$2:$R$3000,"Yes") -> 0 | AV61: =SUMIFS(Permissions!$AL$2:$AL$3000,Permissions!$B$2:$B$3000,$A61,Permissions!$R$2:$R$3000,"Yes") -> 0 | AW61: =SUMIFS(Permissions!$AM$2:$AM$3000,Permissions!$B$2:$B$3000,$A61,Permissions!$R$2:$R$3000,"Yes") -> 0 | AX61: =SUMIFS(Permissions!$AN$2:$AN$3000,Permissions!$B$2:$B$3000,$A61,Permissions!$R$2:$R$3000,"Yes") -> 0 | AY61: =SUMIFS(Permissions!$AO$2:$AO$3000,Permissions!$B$2:$B$3000,$A61,Permissions!$R$2:$R$3000,"Yes") -> 0 | AZ61: =COUNTIFS(Permissions!$B$2:$B$3000,$A61,Permissions!$R$2:$R$3000,"Yes") -> 0 | BA61: =SUMIFS(Permissions!$M$2:$M$3000,Permissions!$B$2:$B$3000,$A61,Permissions!$R$2:$R$3000,"Yes") -> 0 | BB61: =SUMIFS(Permissions!$O$2:$O$3000,Permissions!$B$2:$B$3000,$A61,Permissions!$R$2:$R$3000,"Yes") -> 0 | BC61: =IF(AND(AM61>0,AR61>=AM61,AP61=0),"Finished",IF(AR61>0,"Partly built",IF(AM61>0,"Consented – not built","No consent"))) -> No consent | BD61: =IF(AND(R61<>"",AM61>1.1*R61),"Consented above capacity",IF(AND(LEFT(B61,8)="Planning",AZ61=0),"Consent parcel with no permission",IF(COUNTIF($A$2:$A$3000,$A61)>1,"Duplicate parcel_id","")))
... A91: CITY-160 | B91: Council audit | C91: City | D91: Dooradoyle | E91: City neighbourhood | F91: 1 | G91: Inside catchment | H91: 160 | I91: Dooradoyle | J91: LIMERICK CITY WEST LEA-7 | K91: Dooradoyle | L91: Private | M91: New Resi | N91: Greenfield | O91: 35+ | P91: 1.168 | Q91: 1.278 | R91: 41 | S91: Council estimate (area × density band) | T91: 40 | X91: City suburbs | Y91: 34 | Z91: 34 homes/ha = median of 39 permitted Limerick schemes of 10+ homes in city suburbs; applied to developable for density_estimate_units only | AB91: 0 | AC91: 0 | AD91: Undeveloped/Permission Sought | AE91: Unchanged | AF91: 2026-10-11 | AH91: =IF(R91="",AM91,R91) -> 41 | AI91: =SUMIFS(Permissions!$G$2:$G$3000,Permissions!$B$2:$B$3000,$A91,Permissions!$I$2:$I$3000,"Complete",Permissions!$R$2:$R$3000,"Yes") -> 0 | AJ91: =SUMIFS(Permissions!$G$2:$G$3000,Permissions!$B$2:$B$3000,$A91,Permissions!$I$2:$I$3000,"Under construction",Permissions!$R$2:$R$3000,"Yes") -> 0 | AK91: =SUMIFS(Permissions!$G$2:$G$3000,Permissions!$B$2:$B$3000,$A91,Permissions!$I$2:$I$3000,"Permitted – not started",Permissions!$R$2:$R$3000,"Yes") -> 0 | AL91: =SUMIFS(Permissions!$G$2:$G$3000,Permissions!$B$2:$B$3000,$A91,Permissions!$I$2:$I$3000,"Stalled",Permissions!$R$2:$R$3000,"Yes") -> 0 | AM91: =AI91+AJ91+AK91+AL91 -> 0 | AN91: =SUMIFS(Permissions!$G$2:$G$3000,Permissions!$B$2:$B$3000,$A91,Permissions!$I$2:$I$3000,"Expired – not started",Permissions!$R$2:$R$3000,"Yes") -> 0 | AO91: =SUMIFS(Permissions!$G$2:$G$3000,Permissions!$B$2:$B$3000,$A91,Permissions!$I$2:$I$3000,"In planning",Permissions!$R$2:$R$3000,"Yes") -> 0 | AP91: =IF(R91="",0,MAX(R91-AM91,0)) -> 41 | AQ91: =AM91+AP91 -> 41 | AR91: =SUMIFS(Permissions!$L$2:$L$3000,Permissions!$B$2:$B$3000,$A91,Permissions!$R$2:$R$3000,"Yes",Permissions!$I$2:$I$3000,"<>Expired – not started",Permissions!$I$2:$I$3000,"<>In planning") -> 0 | AS91: =AQ91-AR91 -> 41 | AT91: =SUMIFS(Permissions!$AJ$2:$AJ$3000,Permissions!$B$2:$B$3000,$A91,Permissions!$R$2:$R$3000,"Yes") -> 0 | AU91: =SUMIFS(Permissions!$AK$2:$AK$3000,Permissions!$B$2:$B$3000,$A91,Permissions!$R$2:$R$3000,"Yes") -> 0 | AV91: =SUMIFS(Permissions!$AL$2:$AL$3000,Permissions!$B$2:$B$3000,$A91,Permissions!$R$2:$R$3000,"Yes") -> 0 | AW91: =SUMIFS(Permissions!$AM$2:$AM$3000,Permissions!$B$2:$B$3000,$A91,Permissions!$R$2:$R$3000,"Yes") -> 0 | AX91: =SUMIFS(Permissions!$AN$2:$AN$3000,Permissions!$B$2:$B$3000,$A91,Permissions!$R$2:$R$3000,"Yes") -> 0 | AY91: =SUMIFS(Permissions!$AO$2:$AO$3000,Permissions!$B$2:$B$3000,$A91,Permissions!$R$2:$R$3000,"Yes") -> 0 | AZ91: =COUNTIFS(Permissions!$B$2:$B$3000,$A91,Permissions!$R$2:$R$3000,"Yes") -> 0 | BA91: =SUMIFS(Permissions!$M$2:$M$3000,Permissions!$B$2:$B$3000,$A91,Permissions!$R$2:$R$3000,"Yes") -> 0 | BB91: =SUMIFS(Permissions!$O$2:$O$3000,Permissions!$B$2:$B$3000,$A91,Permissions!$R$2:$R$3000,"Yes") -> 0 | BC91: =IF(AND(AM91>0,AR91>=AM91,AP91=0),"Finished",IF(AR91>0,"Partly built",IF(AM91>0,"Consented – not built","No consent"))) -> No consent | BD91: =IF(AND(R91<>"",AM91>1.1*R91),"Consented above capacity",IF(AND(LEFT(B91,8)="Planning",AZ91=0),"Consent parcel with no permission",IF(COUNTIF($A$2:$A$3000,$A91)>1,"Duplicate parcel_id","")))
A92: CITY-168 | B92: Council audit | C92: City | D92: Kings Island | E92: City neighbourhood | F92: 1 | G92: Inside catchment | H92: 168 | I92: Kings Island | J92: LIMERICK CITY NORTH LEA-7 | L92: Unknown | P92: 0.042 | Q92: 0.042 | R92: 1 | S92: Council estimate (area × density band) | T92: 1 | X92: City suburbs | Y92: 34 | Z92: 34 homes/ha = median of 39 permitted Limerick schemes of 10+ homes in city suburbs; applied to developable for density_estimate_units only | AB92: 0 | AC92: 0 | AE92: Addition | AF92: 2026-10-11 | AH92: =IF(R92="",AM92,R92) -> 1 | AI92: =SUMIFS(Permissions!$G$2:$G$3000,Permissions!$B$2:$B$3000,$A92,Permissions!$I$2:$I$3000,"Complete",Permissions!$R$2:$R$3000,"Yes") -> 0 | AJ92: =SUMIFS(Permissions!$G$2:$G$3000,Permissions!$B$2:$B$3000,$A92,Permissions!$I$2:$I$3000,"Under construction",Permissions!$R$2:$R$3000,"Yes") -> 0 | AK92: =SUMIFS(Permissions!$G$2:$G$3000,Permissions!$B$2:$B$3000,$A92,Permissions!$I$2:$I$3000,"Permitted – not started",Permissions!$R$2:$R$3000,"Yes") -> 0 | AL92: =SUMIFS(Permissions!$G$2:$G$3000,Permissions!$B$2:$B$3000,$A92,Permissions!$I$2:$I$3000,"Stalled",Permissions!$R$2:$R$3000,"Yes") -> 0 | AM92: =AI92+AJ92+AK92+AL92 -> 0 | AN92: =SUMIFS(Permissions!$G$2:$G$3000,Permissions!$B$2:$B$3000,$A92,Permissions!$I$2:$I$3000,"Expired – not started",Permissions!$R$2:$R$3000,"Yes") -> 0 | AO92: =SUMIFS(Permissions!$G$2:$G$3000,Permissions!$B$2:$B$3000,$A92,Permissions!$I$2:$I$3000,"In planning",Permissions!$R$2:$R$3000,"Yes") -> 0 | AP92: =IF(R92="",0,MAX(R92-AM92,0)) -> 1 | AQ92: =AM92+AP92 -> 1 | AR92: =SUMIFS(Permissions!$L$2:$L$3000,Permissions!$B$2:$B$3000,$A92,Permissions!$R$2:$R$3000,"Yes",Permissions!$I$2:$I$3000,"<>Expired – not started",Permissions!$I$2:$I$3000,"<>In planning") -> 0 | AS92: =AQ92-AR92 -> 1 | AT92: =SUMIFS(Permissions!$AJ$2:$AJ$3000,Permissions!$B$2:$B$3000,$A92,Permissions!$R$2:$R$3000,"Yes") -> 0 | AU92: =SUMIFS(Permissions!$AK$2:$AK$3000,Permissions!$B$2:$B$3000,$A92,Permissions!$R$2:$R$3000,"Yes") -> 0 | AV92: =SUMIFS(Permissions!$AL$2:$AL$3000,Permissions!$B$2:$B$3000,$A92,Permissions!$R$2:$R$3000,"Yes") -> 0 | AW92: =SUMIFS(Permissions!$AM$2:$AM$3000,Permissions!$B$2:$B$3000,$A92,Permissions!$R$2:$R$3000,"Yes") -> 0 | AX92: =SUMIFS(Permissions!$AN$2:$AN$3000,Permissions!$B$2:$B$3000,$A92,Permissions!$R$2:$R$3000,"Yes") -> 0 | AY92: =SUMIFS(Permissions!$AO$2:$AO$3000,Permissions!$B$2:$B$3000,$A92,Permissions!$R$2:$R$3000,"Yes") -> 0 | AZ92: =COUNTIFS(Permissions!$B$2:$B$3000,$A92,Permissions!$R$2:$R$3000,"Yes") -> 0 | BA92: =SUMIFS(Permissions!$M$2:$M$3000,Permissions!$B$2:$B$3000,$A92,Permissions!$R$2:$R$3000,"Yes") -> 0 | BB92: =SUMIFS(Permissions!$O$2:$O$3000,Permissions!$B$2:$B$3000,$A92,Permissions!$R$2:$R$3000,"Yes") -> 0 | BC92: =IF(AND(AM92>0,AR92>=AM92,AP92=0),"Finished",IF(AR92>0,"Partly built",IF(AM92>0,"Consented – not built","No consent"))) -> No consent | BD92: =IF(AND(R92<>"",AM92>1.1*R92),"Consented above capacity",IF(AND(LEFT(B92,8)="Planning",AZ92=0),"Consent parcel with no permission",IF(COUNTIF($A$2:$A$3000,$A92)>1,"Duplicate parcel_id","")))
